Workbook

Sheet 案件分流
A1: 事项 | B1: 业务日期 | C1: 条件初筛/历史判断 | D1: 产品与现金边界 | E1: 下一步与接口 | F1: 条/页定位
A2: F01 | B2: 2024-12-14 | C2: 12月14日不能仅据全国扩围新开户；先准备12月15日后核实 | D2: 无已缴事实，不追认1月缴费 | E2: 核实基本保险与开户条件后再按实际缴费取得凭证 | F2: S01一（一）；S02一/二；S05 F01
A3: F02 | B3: 2024-12-16 | C3: 参加基础条件满足；建议追加最多2000或延后 | D3: 年度剩余额度9000；家庭现金储备余量2000，不能照缴10000 | E3: 负责人复核现金需求，由家庭决定0–2000或暂缓；按实缴平台凭证办扣除 | F3: S01一（一）；S02一/二；S05 F02；S08
A4: F03 | B4: 2024-12-16 | C4: 当前缺基本养老保险参加条件，不能仅据扩围入制度 | D4: 不作缴费或退款承诺 | E4: 由家庭先向基本养老保险服务渠道核实自身参加情况 | F4: S01一（一）；S05 F03
A5: F04 | B5: 2025-08-25 | C5: 8月25日不能把尚未施行39号当当前直接领取依据 | D5: 窗口内12个月，但本通知9月1日才实施；不批准或演示已到账 | E5: 告知历史答复应待实施后按实际条件重新申请核实 | F5: S01四（一）；S03一（五）/七；S06 F04
A6: F05 | B6: 2025-09-05 | C6: 两年窗口12个月，失业路径初筛满足，尚待社保核实 | D6: 给定现金10000仅作附条件税300、净9700演示 | E6: 申请渠道/社保核实→平台状态→银行代扣→本人社保卡 | F6: S03一（五）/三；S02一/二；S06 F05
A7: F06 | B7: 2025-09-05 | C7: 窗口内11个月，未达失业路径12个月；历史总12笔不能算 | D7: 不给确定可领取/净到账额；无其他给定领取依据 | E7: 核查是否另有窗口内漏登领取月；没有就待达到条件 | F7: S03一（五）；S06 F06
A8: F07 | B8: 2025-09-05 | C8: 失业路径初筛满足，但不等于产品立即可取 | D8: 现金0；6000是基金快照且持有期未到，不演示5820到账 | E8: 产品运营核当前合同/特别提前办理安排/交易流程；再协调申请 | F8: S03一（五）/二；S04原PDF1/3/5页；S05 F07
A9: F08 | B9: 2025-09-05 | C9: 给定年龄条件有摘录支持；当前领取申请仍待核 | D9: 给定现金10000附条件税300、净9700，不是免税 | E9: 按社保核实/平台状态/银行代扣程序办理，不由顾问批准 | F9: S03一（一）/三；S02一/二；S05 F08
A10: F09 | B10: 2025-09-05 | C10: 无任何给定账户领取情形，满持有期不自动取得对外领取资格 | D10: 基金已满期可核交易开放/确认；赎回款不等于银行卡可用款 | E10: 先核基金正常赎回流程；住房资金需另评账户外合法流动性 | F10: S03一/二/三；S04原PDF1/3页；S05 F09
A11: F10 | B11: 2025-09-05 | C11: 失业初筛满足；现金与锁定基金必须分开 | D11: 现金4000附条件税120、净3880；基金8000不纳入当前演示 | E11: 先申请核实现金领取；产品运营另核未到期持仓安排 | F11: S03一（五）/二/三；S02一；S04原PDF1/3页；S05 F10
A12: F11 | B12: 2025-09-05 | C12: 当前低保事实支持领取初筛，待社保核实 | D12: 现金12000附条件税360、净11640；方式由本人选 | E12: 提供按月/分次/一次性及变更选择，按家庭需求确认后申请 | F12: S03一（六）/二/三；S02一；S05 F11
A13: F12 | B13: 2025-09-05 | C13: 非年龄路径返缴后回到缴存状态，须重新达到领取条件；当前无依据 | D13: 旧低保/旧领取状态不能沿用为本次批准 | E13: 社保接口核当前状态与资格；当前不递交虚假延续低保事实 | F13: S03四；S05 F12

Sheet 领取流水
A1: 流水ID | B1: 事项 | C1: 领取日 | D1: 领取月 | E1: 累计月数 | F1: 记录性质
A2: F04-U01 | B2: F04 | C2: 45550 | D2: 2024-09 | E2: 1 | F2: 题给已领取记录_非真实客户
A3: F04-U02 | B3: F04 | C3: 45580 | D3: 2024-10 | E3: 1 | F3: 题给已领取记录_非真实客户
A4: F04-U03 | B4: F04 | C4: 45611 | D4: 2024-11 | E4: 1 | F4: 题给已领取记录_非真实客户
A5: F04-U04 | B5: F04 | C5: 45641 | D5: 2024-12 | E5: 1 | F5: 题给已领取记录_非真实客户
A6: F04-U05 | B6: F04 | C6: 45672 | D6: 2025-01 | E6: 1 | F6: 题给已领取记录_非真实客户
A7: F04-U06 | B7: F04 | C7: 45703 | D7: 2025-02 | E7: 1 | F7: 题给已领取记录_非真实客户
A8: F04-U07 | B8: F04 | C8: 45731 | D8: 2025-03 | E8: 1 | F8: 题给已领取记录_非真实客户
A9: F04-U08 | B9: F04 | C9: 45762 | D9: 2025-04 | E9: 1 | F9: 题给已领取记录_非真实客户
A10: F04-U09 | B10: F04 | C10: 45792 | D10: 2025-05 | E10: 1 | F10: 题给已领取记录_非真实客户
A11: F04-U10 | B11: F04 | C11: 45823 | D11: 2025-06 | E11: 1 | F11: 题给已领取记录_非真实客户
A12: F04-U11 | B12: F04 | C12: 45853 | D12: 2025-07 | E12: 1 | F12: 题给已领取记录_非真实客户
A13: F04-U12 | B13: F04 | C13: 45884 | D13: 2025-08 | E13: 1 | F13: 题给已领取记录_非真实客户
... A61: F10-U12 | B61: F10 | C61: 45884 | D61: 2025-08 | E61: 1 | F61: 题给已领取记录_非真实客户

Sheet 窗口复算
A1: 事项 | B1: 窗口起点（含） | C1: 窗口终点（不含） | D1: 窗口内月数公式 | E1: 路径检查 | F1: 需注意的排除
A2: F04 | B2: 45163 | C2: 45894 | D2: =SUMIFS(领取流水!$E$2:$E$61,领取流水!$B$2:$B$61,A2,领取流水!$C$2:$C$61,">="&B2,领取流水!$C$2:$C$61,"<"&C2) -> 12 | E2: =IF(D2>=12,"月数达到，仍须核实施行及申请","月数不足") -> 月数达到，仍须核实施行及申请 | F2: 无窗口外记录
A3: F05 | B3: 45174 | C3: 45905 | D3: =SUMIFS(领取流水!$E$2:$E$61,领取流水!$B$2:$B$61,A3,领取流水!$C$2:$C$61,">="&B3,领取流水!$C$2:$C$61,"<"&C3) -> 12 | E3: =IF(D3>=12,"月数达到，仍须核实施行及申请","月数不足") -> 月数达到，仍须核实施行及申请 | F3: 无窗口外记录
A4: F06 | B4: 45174 | C4: 45905 | D4: =SUMIFS(领取流水!$E$2:$E$61,领取流水!$B$2:$B$61,A4,领取流水!$C$2:$C$61,">="&B4,领取流水!$C$2:$C$61,"<"&C4) -> 11 | E4: =IF(D4>=12,"月数达到，仍须核实施行及申请","月数不足") -> 月数不足 | F4: F06-U01
A5: F07 | B5: 45174 | C5: 45905 | D5: =SUMIFS(领取流水!$E$2:$E$61,领取流水!$B$2:$B$61,A5,领取流水!$C$2:$C$61,">="&B5,领取流水!$C$2:$C$61,"<"&C5) -> 12 | E5: =IF(D5>=12,"月数达到，仍须核实施行及申请","月数不足") -> 月数达到，仍须核实施行及申请 | F5: 无窗口外记录
A6: F10 | B6: 45174 | C6: 45905 | D6: =SUMIFS(领取流水!$E$2:$E$61,领取流水!$B$2:$B$61,A6,领取流水!$C$2:$C$61,">="&B6,领取流水!$C$2:$C$61,"<"&C6) -> 12 | E6: =IF(D6>=12,"月数达到，仍须核实施行及申请","月数不足") -> 月数达到，仍须核实施行及申请 | F6: 无窗口外记录

Sheet F02缴费规划
A1: F02年度实缴 | B1: 年度限额 | C1: 年度剩余 | D1: 账户外流动现金 | E1: 家庭最低储备 | F1: 储备以上余量 | G1: 原拟追加 | H1: 建议追加上限 | I1: 上限与储备勾稽
A2: 3000 | B2: 12000 | C2: =MAX(0,B2-A2) -> 9000 | D2: 20000 | E2: 18000 | F2: =MAX(0,D2-E2) -> 2000 | G2: 10000 | H2: =MIN(C2,F2) -> 2000 | I2: =IF(AND(H2<=C2,D2-H2>=E2),0,1) -> 0

Sheet 附条件现金演示
A1: 事项 | B1: 给定现金本金 | C1: 演示税率 | D1: 附条件税额 | E1: 附条件净额 | F1: 说明
A2: F05 | B2: 10000 | C2: 0.03 | D2: =ROUND(B2*C2,2) -> 300 | E2: =B2-D2 -> 9700 | F2: 待社保核实/平台状态/银行实际办理；不含基金估值，不是已到账
A3: F08 | B3: 10000 | C3: 0.03 | D3: =ROUND(B3*C3,2) -> 300 | E3: =B3-D3 -> 9700 | F3: 待社保核实/平台状态/银行实际办理；不含基金估值，不是已到账
A4: F10 | B4: 4000 | C4: 0.03 | D4: =ROUND(B4*C4,2) -> 120 | E4: =B4-D4 -> 3880 | F4: 待社保核实/平台状态/银行实际办理；不含基金估值，不是已到账
A5: F11 | B5: 12000 | C5: 0.03 | D5: =ROUND(B5*C5,2) -> 360 | E5: =B5-D5 -> 11640 | F5: 待社保核实/平台状态/银行实际办理；不含基金估值，不是已到账

Sheet 规则与D0更正
A1: 事项 | B1: 依据 | C1: 正确规则 | D1: 影响事项 | E1: D0应纠正/边界
A2: 扩围 | B2: S01一（一） | C2: 2024-12-15起，参加两类基本养老保险的劳动者均可参加 | D2: F01/F02/F03 | E2: 成文12-10/网页12-12/扩围12-15不是同一天
A3: 税收 | B3: S02一/二 | C3: 2024-01-01全国递延纳税；实际缴费按12000/年限额据实扣除；平台凭证 | D3: F01/F02 | E3: 税收起点不创造实际开户/缴费；扣除额不是退款额
A4: 领取新情形 | B4: S01四（一）；S03一/七 | C4: 2024原则写具体办法另定；39号2025-09-01实施 | D4: F04/F05 | E4: 成文2025-07-13不等于8月已可按本通知办理
A5: 失业窗口 | B5: S03一（五） | C5: 申请日前2年领取失业保险金累计达到12个月 | D5: F04–F07/F10 | E5: 不按历史总笔数，F06旧1笔在窗口外
A6: 领取程序 | B6: S03三；S02二 | C6: 社保核实→平台领取状态→银行代扣税→本人社保卡银行账户 | D6: F05/F08/F10/F11 | E6: 顾问初筛不能批准、确认已到账或替本人选方式
A7: 已购买产品 | B7: S03二；S04原PDF1/3/5页 | C7: 账户具领取条件，产品仍遵循相关规定；每份至少一年；赎回费0 | D7: F07/F09/F10 | E7: 0费不消除持有期；满期不等于账户可对外领
A8: 名称/风险 | B8: S04原PDF5/6页 | C8: 可能损失本金，养老名称不保证收益或退休收入 | D8: 全部 | E8: 稳健/养老不等于保本；0赎回费不代表全部费用0
A9: 非年龄路径返缴 | B9: S03四 | C9: 再次缴费恢复缴存状态，需重新达到领取条件 | D9: F12 | E9: 历史低保与旧领取状态不能永久沿用
A10: 领取方式 | B10: S03二 | C10: 可按月、分次、一次性并按需变更 | D10: F11 | E10: 让家庭选择，非顾问替选或限制只有按月
A11: 7天冷静期 | B11: S04并未提供统一7天权利；S08待核 | C11: 核具体销售文件/渠道/撤单时限；当前不宣传确定天数 | D11: 全部，尤其F07 | E11: 当前资料不足不等于一切产品绝无冷静/提前办理安排
A12: 家庭流动性 | B12: S05 F02；S08约定 | C12: 家庭储备为客户偏好，建议追加≤年度余额及账户外储备余量 | D12: F02 | E12: 可延后或更审慎，不用税惠驱动耗尽应急金
