Workbook

Sheet 来源记录
A1: 指标 | B1: 经济财年 | C1: 原始USD | D1: USD million | E1: start | F1: end | G1: accn | H1: filed | I1: JSON数组索引
A2: 净利润 | B2: 2022 | C2: 99803000000 | D2: =C2/1000000 | E2: 2021-09-26 | F2: 2022-09-24 | G2: 0000320193-24-000123 | H2: 2024-11-01 | I2: 296
A3: 净利润 | B3: 2023 | C3: 96995000000 | D3: =C3/1000000 | E3: 2022-09-25 | F3: 2023-09-30 | G3: 0000320193-24-000123 | H3: 2024-11-01 | I3: 308
A4: 净利润 | B4: 2024 | C4: 93736000000 | D4: =C4/1000000 | E4: 2023-10-01 | F4: 2024-09-28 | G4: 0000320193-24-000123 | H4: 2024-11-01 | I4: 320
A5: 经营现金流 | B5: 2022 | C5: 122151000000 | D5: =C5/1000000 | E5: 2021-09-26 | F5: 2022-09-24 | G5: 0000320193-24-000123 | H5: 2024-11-01 | I5: 106
A6: 经营现金流 | B6: 2023 | C6: 110543000000 | D6: =C6/1000000 | E6: 2022-09-25 | F6: 2023-09-30 | G6: 0000320193-24-000123 | H6: 2024-11-01 | I6: 114
A7: 经营现金流 | B7: 2024 | C7: 118254000000 | D7: =C7/1000000 | E7: 2023-10-01 | F7: 2024-09-28 | G7: 0000320193-24-000123 | H7: 2024-11-01 | I7: 122
A8: 折旧摊销 | B8: 2022 | C8: 11104000000 | D8: =C8/1000000 | E8: 2021-09-26 | F8: 2022-09-24 | G8: 0000320193-24-000123 | H8: 2024-11-01 | I8: 47
A9: 折旧摊销 | B9: 2023 | C9: 11519000000 | D9: =C9/1000000 | E9: 2022-09-25 | F9: 2023-09-30 | G9: 0000320193-24-000123 | H9: 2024-11-01 | I9: 55
A10: 折旧摊销 | B10: 2024 | C10: 11445000000 | D10: =C10/1000000 | E10: 2023-10-01 | F10: 2024-09-28 | G10: 0000320193-24-000123 | H10: 2024-11-01 | I10: 63
A11: 股份报酬 | B11: 2022 | C11: 9038000000 | D11: =C11/1000000 | E11: 2021-09-26 | F11: 2022-09-24 | G11: 0000320193-24-000123 | H11: 2024-11-01 | I11: 152
A12: 股份报酬 | B12: 2023 | C12: 10833000000 | D12: =C12/1000000 | E12: 2022-09-25 | F12: 2023-09-30 | G12: 0000320193-24-000123 | H12: 2024-11-01 | I12: 160
A13: 股份报酬 | B13: 2024 | C13: 11688000000 | D13: =C13/1000000 | E13: 2023-10-01 | F13: 2024-09-28 | G13: 0000320193-24-000123 | H13: 2024-11-01 | I13: 168
... A28: 税前利润 | B28: 2024 | C28: 123485000000 | D28: =C28/1000000 | E28: 2023-10-01 | F28: 2024-09-28 | G28: 0000320193-24-000123 | H28: 2024-11-01 | I28: 158

Sheet 指标字典
A1: 来源记录中的指标 | B1: 别名 | C1: SEC us-gaap tag | D1: 原始单位
A2: 净利润 | B2: NI | C2: NetIncomeLoss | D2: USD
A3: 经营现金流 | B3: CFO | C3: NetCashProvidedByUsedInOperatingActivities | D3: USD
A4: 折旧摊销 | B4: DA | C4: DepreciationDepletionAndAmortization | D4: USD
A5: 股份报酬 | B5: SBC | C5: ShareBasedCompensation | D5: USD
A6: 购建固定资产支付 | B6: CAPEX | C6: PaymentsToAcquirePropertyPlantAndEquipment | D6: USD
A7: 普通股回购支付 | B7: BUYBACK | C7: PaymentsForRepurchaseOfCommonStock | D7: USD
A8: 股息支付 | B8: DIV | C8: PaymentsOfDividends | D8: USD
A9: 所得税费用 | B9: TAX | C9: IncomeTaxExpenseBenefit | D9: USD
A10: 税前利润 | B10: PRETAX | C10: IncomeLossFromContinuingOperationsBeforeIncomeTaxesExtraordinaryItemsNoncontrollingInterest | D10: USD

Sheet 指标复算
A1: 指标与单位 | B1: FY2022 | C1: FY2023 | D1: FY2024
A2: NI / USD million | B2: ='来源记录'!D2 | C2: ='来源记录'!D3 | D2: ='来源记录'!D4
A3: CFO / USD million | B3: ='来源记录'!D5 | C3: ='来源记录'!D6 | D3: ='来源记录'!D7
A4: D&A / USD million | B4: ='来源记录'!D8 | C4: ='来源记录'!D9 | D4: ='来源记录'!D10
A5: SBC / USD million | B5: ='来源记录'!D11 | C5: ='来源记录'!D12 | D5: ='来源记录'!D13
A6: CFO-NI / USD million | B6: =B3-B2 | C6: =C3-C2 | D6: =D3-D2
A7: D&A+SBC / USD million | B7: =B4+B5 | C7: =C4+C5 | D7: =D4+D5
A8: 残差（非全部营运资本）/ USD million | B8: =B6-B7 | C8: =C6-C7 | D8: =D6-D7
A9: CFO/NI / 倍 | B9: =ROUND(B3/B2,4) | C9: =ROUND(C3/C2,4) | D9: =ROUND(D3/D2,4)
A10: 含首尾期间天数 / 天 | B10: 364 | C10: 371 | D10: 364
A11: CFO/天 / USD million | B11: =ROUND(B3/B10,4) | C11: =ROUND(C3/C10,4) | D11: =ROUND(D3/D10,4)
A12: CAPEX / USD million | B12: ='来源记录'!D14 | C12: ='来源记录'!D15 | D12: ='来源记录'!D16
A13: FCF / USD million | B13: =B3-B12 | C13: =C3-C12 | D13: =D3-D12
A14: 回购 / USD million | B14: ='来源记录'!D17 | C14: ='来源记录'!D18 | D14: ='来源记录'!D19
A15: 股息 / USD million | B15: ='来源记录'!D20 | C15: ='来源记录'!D21 | D15: ='来源记录'!D22
A16: 资本回报 / USD million | B16: =B14+B15 | C16: =C14+C15 | D16: =D14+D15
A17: FCF/资本回报 / 倍 | B17: =ROUND(B13/B16,4) | C17: =ROUND(C13/C16,4) | D17: =ROUND(D13/D16,4)
A18: FCF-资本回报 / USD million | B18: =B13-B16 | C18: =C13-C16 | D18: =D13-D16
A19: 税前利润 / USD million | B19: ='来源记录'!D26 | C19: ='来源记录'!D27 | D19: ='来源记录'!D28
A20: 所得税费用 / USD million | B20: ='来源记录'!D23 | C20: ='来源记录'!D24 | D20: ='来源记录'!D25
A21: ETR / 比例 | B21: =ROUND(B20/B19,4) | C21: =ROUND(C20/C19,4) | D21: =ROUND(D20/D19,4)
A22: 税前-税费-NI复核 / USD million | B22: =B19-B20-B2 | C22: =C19-C20-C2 | D22: =D19-D20-D2

Sheet 年度比较
A1: 变化与单位 | B1: FY2023 vs FY2022 | C1: FY2024 vs FY2023
A2: NI同比 / 比例 | B2: =ROUND('指标复算'!C2/'指标复算'!B2-1,4) | C2: =ROUND('指标复算'!D2/'指标复算'!C2-1,4)
A3: CFO同比 / 比例 | B3: =ROUND('指标复算'!C3/'指标复算'!B3-1,4) | C3: =ROUND('指标复算'!D3/'指标复算'!C3-1,4)
A4: CFO/天同比 / 比例 | B4: =ROUND('指标复算'!C11/'指标复算'!B11-1,4) | C4: =ROUND('指标复算'!D11/'指标复算'!C11-1,4)
A5: FCF同比 / 比例 | B5: =ROUND('指标复算'!C13/'指标复算'!B13-1,4) | C5: =ROUND('指标复算'!D13/'指标复算'!C13-1,4)
A6: 资本回报同比 / 比例 | B6: =ROUND('指标复算'!C16/'指标复算'!B16-1,4) | C6: =ROUND('指标复算'!D16/'指标复算'!C16-1,4)
A7: 税前利润同比 / 比例 | B7: =ROUND('指标复算'!C19/'指标复算'!B19-1,4) | C7: =ROUND('指标复算'!D19/'指标复算'!C19-1,4)
A8: 所得税费用同比 / 比例 | B8: =ROUND('指标复算'!C20/'指标复算'!B20-1,4) | C8: =ROUND('指标复算'!D20/'指标复算'!C20-1,4)
A9: CFO增量 / USD million | B9: ='指标复算'!C3-'指标复算'!B3 | C9: ='指标复算'!D3-'指标复算'!C3
A10: NI增量 / USD million | B10: ='指标复算'!C2-'指标复算'!B2 | C10: ='指标复算'!D2-'指标复算'!C2
A11: 税前增量-税费增量 / USD million | B11: =('指标复算'!C19-'指标复算'!B19)-('指标复算'!C20-'指标复算'!B20) | C11: =('指标复算'!D19-'指标复算'!C19)-('指标复算'!D20-'指标复算'!C20)

Sheet 静态压力
A1: 指标与单位 | B1: 2024基准 | C1: 规划压力假设
A2: CFO / USD million | B2: ='指标复算'!D3 | C2: =ROUND(B2*0.9,4)
A3: CAPEX / USD million | B3: ='指标复算'!D12 | C3: =ROUND(B3*1.2,4)
A4: FCF / USD million | B4: =B2-B3 | C4: =C2-C3
A5: 股息 / USD million | B5: ='指标复算'!D15 | C5: =B5
A6: 回购 / USD million | B6: ='指标复算'!D14 | C6: =B6
A7: 资本回报 / USD million | B7: =B5+B6 | C7: =C5+C6
A8: 覆盖率 / 倍 | B8: =ROUND(B4/B7,4) | C8: =ROUND(C4/C7,4)
A9: FCF-回报 / USD million | B9: =B4-B7 | C9: =C4-C7
A10: 非负余额的最大回购 / USD million | B10: =MAX(0,B4-B5) | C10: =MAX(0,C4-C5)
A11: 相对2024回购所需减少额 / USD million | B11: =MAX(0,B6-B10) | C11: =MAX(0,B6-C10)

Sheet 决策与待补
A1: 问题 | B1: 观察/判断 | C1: 限制 | D1: 动作
A2: 时间选择 | B2: filed不晚于2024-11-01，统一2024 accn，按start/end区分三个财年 | C2: 2026快照包含未来记录；fy=2024不意味着每条都是2024经济期间 | D2: 保留JSON路径、索引和筛选记录
A3: 现金质量 | B3: 2024 CFO上升但NI下降，转换比上升不能等于盈利全面改善 | C3: 部分来自分母下降；税前/税费拆解只是会计关系，不能编原因 | D3: 索取税务和现金流附注
A4: 残差 | B4: 分别为2206、-8804、1385 USD million | C4: 排除D&A/SBC后的余项含其他调节，不可称全部营运资本 | D4: 取得完整CFO调节项目后细分
A5: 资本回报 | B5: 2024 FCF108807、回报110183、差额-1376；压力差额-15090.8 | C5: 余额小于0不等于资不抵债，也不证明公司借款来源 | D5: 静态压力最大回购79858.2；提交经理作为讨论约束，非批准
A6: 期间与单位 | B6: 2022/24各364天、2023为371天；金额百万美元，ETR用比例 | C6: 天数标准化是本委托诊断，不是现金流重述；费用非现金税 | D6: 原数、公式、单位与memo一致
A7: 完整性 | B7: API不是10-K全文或历史API原样，缺完整债务与现金信息 | C7: 不能据当前快照补编2024已知税务原因、现金储备或审计意见 | D7: 索取已披露原文和可动用现金、债务到期、回报政策
