Workbook

Sheet Data_Source
A1: FY23-FY25 Segment Financial Data (Recast Basis)
A2: Source: S01_FY25_公开分部表.docx | Unit: USD Millions
A3: Note: S01 states 'We have recast certain prior period amounts to conform to the way we internally manage and monitor our business.'
A5: Revenue (USD Millions)
A6: Division | B6: FY23 | C6: FY24 | D6: FY25
A7: Productivity and Business Processes | B7: 94151 | C7: 106820 | D7: 120810
A8: Intelligent Cloud | B8: 72944 | C8: 87464 | D8: 106265
A9: More Personal Computing | B9: 44820 | C9: 50838 | D9: 54649
A11: Operating Income (USD Millions)
A12: Division | B12: FY23 | C12: FY24 | D12: FY25
A13: Productivity and Business Processes | B13: 50074 | C13: 59661 | D13: 69773
A14: Intelligent Cloud | B14: 28411 | C14: 37813 | D14: 44589
A15: More Personal Computing | B15: 10038 | C15: 11959 | D15: 14166

Sheet Assumptions
A1: FY26 Budget Allocation Assumptions
A2: Source: internal_budget_proposals.csv
A4: Budget Parameter | B4: Value | C4: Unit / Note
A5: Total Incremental Budget | B5: 5000 | C5: USD Millions
A6: Number of Divisions to Select | B6: 2 | C6: count
A7: Minimum Allocation per Division | B7: 1000 | C7: USD Millions
A8: Maximum Allocation (% of Request) | B8: 0.8 | C8: percentage
A10: Internal Budget Proposals (FY26)
A11: Division | B11: Requested Incremental Budget (USD M) | C11: Marginal OI Conversion Rate
A12: Productivity and Business Processes | B12: 3000 | C12: 0.25
A13: Intelligent Cloud | B13: 4000 | C13: 0.35
A14: More Personal Computing | B14: 2000 | C14: 0.15

Sheet Analysis
A1: FY23-FY25 Financial Performance Analysis
A2: CAGR and Operating Margin calculations based on S01 recast data only
A4: Division | B4: FY23 Revenue (USD M) | C4: FY25 Revenue (USD M) | D4: Revenue CAGR (FY23 to FY25) | E4: FY25 Operating Income (USD M) | F4: FY25 OI Margin
A5: Productivity and Business Processes | B5: =Data_Source!B7 | C5: =Data_Source!D7 | D5: =(C5/B5)^(1/2)-1 | E5: =Data_Source!D13 | F5: =E5/C5
A6: Intelligent Cloud | B6: =Data_Source!B8 | C6: =Data_Source!D8 | D6: =(C6/B6)^(1/2)-1 | E6: =Data_Source!D14 | F6: =E6/C6
A7: More Personal Computing | B7: =Data_Source!B9 | C7: =Data_Source!D9 | D7: =(C7/B7)^(1/2)-1 | E7: =Data_Source!D15 | F7: =E7/C7
A9: Marginal OI Conversion Rate Ranking (Descending)
A10: Rank | B10: Division | C10: Marginal OI Conversion Rate | D10: Requested Budget (USD M) | E10: Max Allocation 80% Cap (USD M)
A11: 1 | B11: Intelligent Cloud | C11: =Assumptions!C13 | D11: =Assumptions!B13 | E11: =D11*Assumptions!B8
A12: 2 | B12: Productivity and Business Processes | C12: =Assumptions!C12 | D12: =Assumptions!B12 | E12: =D12*Assumptions!B8
A13: 3 | B13: More Personal Computing | C13: =Assumptions!C14 | D13: =Assumptions!B14 | E13: =D13*Assumptions!B8

Sheet Allocation_Model
A1: FY26 Incremental Budget Allocation Model
A2: Logic: Prioritize highest marginal OI conversion rate; allocate up to 80% of request, then remainder to 2nd highest
A4: Parameter | B4: Value | C4: Source
A5: Total Budget (USD M) | B5: =Assumptions!B5 | C5: Assumptions!B5
A6: Divisions to Select | B6: =Assumptions!B6 | C6: Assumptions!B6
A7: Min per Division (USD M) | B7: =Assumptions!B7 | C7: Assumptions!B7
A8: Max % of Request | B8: =Assumptions!B8 | C8: Assumptions!B8
A10: Rank | B10: Division | C10: Marginal Rate | D10: Requested (USD M) | E10: 80% Cap (USD M) | F10: Allocated (USD M) | G10: Expected Marginal OI (USD M)
A11: =Analysis!A11 | B11: =Analysis!B11 | C11: =Analysis!C11 | D11: =Analysis!D11 | E11: =Analysis!E11 | F11: =MIN(B5, E11) | G11: =F11*C11
A12: =Analysis!A12 | B12: =Analysis!B12 | C12: =Analysis!C12 | D12: =Analysis!D12 | E12: =Analysis!E12 | F12: =MIN(B5-F11, E12) | G12: =F12*C12
A13: =Analysis!A13 | B13: =Analysis!B13 | C13: =Analysis!C13 | D13: =Analysis!D13 | E13: =Analysis!E13 | F13: 0 | G13: =F13*C13
A15: Validation Checks
A16: Total Allocated (USD M) | B16: =SUM(F11:F13) | C16: Must equal Total Budget (B5)
A17: Budget Match? | B17: =IF(B16=B5,"YES","NO - MISMATCH!")
A18: Selected Count | B18: =COUNTIF(F11:F13,">0") | C18: Must equal 2
A19: Min Allocation Check (>= 1,000) | B19: =IF(AND(F11>=B7,F12>=B7),"PASS","FAIL") | C19: All selected divisions >= Min
A20: Max Cap Check (<= 80% Request) | B20: =IF(AND(F11<=E11,F12<=E12),"PASS","FAIL") | C20: All selected divisions <= 80% cap

Sheet Results_Summary
A1: Final FY26 Incremental Budget Allocation Results
A2: Unit: USD Millions
A4: Division | B4: Allocated Budget (USD M) | C4: Marginal OI Conversion Rate | D4: Expected Marginal OI (USD M)
A5: =Allocation_Model!B11 | B5: =Allocation_Model!F11 | C5: =Allocation_Model!C11 | D5: =Allocation_Model!G11
A6: =Allocation_Model!B12 | B6: =Allocation_Model!F12 | C6: =Allocation_Model!C12 | D6: =Allocation_Model!G12
A7: Total | B7: =SUM(B5:B6) | D7: =SUM(D5:D6)
