Workbook

Sheet 使用说明
A1: 项目 | B1: 解释
A2: 业务基准 | B2: 2025-08-05 09:00 Asia/Shanghai
A3: 期间/单位 | B3: 截至6月30日的整财年；百万美元。页名Q4不改变年度表头。
A4: 主口径 | B4: FY25表中FY24比较期与FY25，均为同一披露版本。
A5: 诊断差定义 | B5: 错误同比-正确同比；乘100后为百分点，不是百分比增长。
A6: 历史保留 | B6: 旧FY24作为历史记录和纠错诊断，不作现时主结论。
A7: 归因限制 | B7: 公开表只称recast以符合内部管理监控方式；不能识别具体产品划转、汇率、并购或有机增长。
A8: 精度 | B8: 原数百万美元整数；公式全精度；显示同比百分数和差值百分点均2位小数。
A9: 审批/交付状态 | B9: 销售较新建议未批准；本工作包为研究草稿，不是已发送邮件或投资建议。

Sheet 披露数据
A1: 披露版本 | B1: 财年截至日期 | C1: 分部 | D1: 财年 | E1: 收入（百万美元） | F1: 营业利润（百万美元） | G1: 来源定位
A2: FY25 | B2: 2025-06-30 | C2: Productivity and Business Processes | D2: 2025 | E2: 120810 | F2: 69773 | G2: S01 / Revenue和Operating Income / Productivity and Business Processes / 2025列
A3: FY25 | B3: 2024-06-30 | C3: Productivity and Business Processes | D3: 2024 | E3: 106820 | F3: 59661 | G3: S01 / Revenue和Operating Income / Productivity and Business Processes / 2024列
A4: FY25 | B4: 2023-06-30 | C4: Productivity and Business Processes | D4: 2023 | E4: 94151 | F4: 50074 | G4: S01 / Revenue和Operating Income / Productivity and Business Processes / 2023列
A5: FY25 | B5: 2025-06-30 | C5: Intelligent Cloud | D5: 2025 | E5: 106265 | F5: 44589 | G5: S01 / Revenue和Operating Income / Intelligent Cloud / 2025列
A6: FY25 | B6: 2024-06-30 | C6: Intelligent Cloud | D6: 2024 | E6: 87464 | F6: 37813 | G6: S01 / Revenue和Operating Income / Intelligent Cloud / 2024列
A7: FY25 | B7: 2023-06-30 | C7: Intelligent Cloud | D7: 2023 | E7: 72944 | F7: 28411 | G7: S01 / Revenue和Operating Income / Intelligent Cloud / 2023列
A8: FY25 | B8: 2025-06-30 | C8: More Personal Computing | D8: 2025 | E8: 54649 | F8: 14166 | G8: S01 / Revenue和Operating Income / More Personal Computing / 2025列
A9: FY25 | B9: 2024-06-30 | C9: More Personal Computing | D9: 2024 | E9: 50838 | F9: 11959 | G9: S01 / Revenue和Operating Income / More Personal Computing / 2024列
A10: FY25 | B10: 2023-06-30 | C10: More Personal Computing | D10: 2023 | E10: 44820 | F10: 10038 | G10: S01 / Revenue和Operating Income / More Personal Computing / 2023列
A11: FY25 | B11: 2025-06-30 | C11: Total | D11: 2025 | E11: 281724 | F11: 128528 | G11: S01 / Revenue和Operating Income / Total / 2025列
A12: FY25 | B12: 2024-06-30 | C12: Total | D12: 2024 | E12: 245122 | F12: 109433 | G12: S01 / Revenue和Operating Income / Total / 2024列
A13: FY25 | B13: 2023-06-30 | C13: Total | D13: 2023 | E13: 211915 | F13: 88523 | G13: S01 / Revenue和Operating Income / Total / 2023列
... A25: FY24 | B25: 2022-06-30 | C25: Total | D25: 2022 | E25: 198270 | F25: 83383 | G25: S02 / Revenue和Operating Income / Total / 2022列

Sheet FY24桥接
A1: 分部 | B1: FY24旧收入 | C1: FY24重述收入 | D1: 收入重述差（新减旧） | E1: FY24旧营业利润 | F1: FY24重述营业利润 | G1: 利润重述差（新减旧）
A2: Productivity and Business Processes | B2: =披露数据!E14 -> 77728 | C2: =披露数据!E3 -> 106820 | D2: =C2-B2 -> 29092 | E2: =披露数据!F14 -> 40540 | F2: =披露数据!F3 -> 59661 | G2: =F2-E2 -> 19121
A3: Intelligent Cloud | B3: =披露数据!E17 -> 105362 | C3: =披露数据!E6 -> 87464 | D3: =C3-B3 -> -17898 | E3: =披露数据!F17 -> 49584 | F3: =披露数据!F6 -> 37813 | G3: =F3-E3 -> -11771
A4: More Personal Computing | B4: =披露数据!E20 -> 62032 | C4: =披露数据!E9 -> 50838 | D4: =C4-B4 -> -11194 | E4: =披露数据!F20 -> 19309 | F4: =披露数据!F9 -> 11959 | G4: =F4-E4 -> -7350
A5: Total | B5: =披露数据!E23 -> 245122 | C5: =披露数据!E12 -> 245122 | D5: =C5-B5 -> 0 | E5: =披露数据!F23 -> 109433 | F5: =披露数据!F12 -> 109433 | G5: =F5-E5 -> 0

Sheet FY25同比
A1: 分部 | B1: FY25收入 | C1: FY24重述收入 | D1: 正确收入同比 | E1: FY24旧收入 | F1: 误用旧基数收入同比（诊断） | G1: 收入误差（百分点） | H1: FY25营业利润 | I1: FY24重述营业利润 | J1: 正确利润同比 | K1: FY24旧营业利润 | L1: 误用旧基数利润同比（诊断） | M1: 利润误差（百分点）
A2: Productivity and Business Processes | B2: =披露数据!E2 -> 120810 | C2: =披露数据!E3 -> 106820 | D2: =B2/C2-1 -> 0.13096798 | E2: =披露数据!E14 -> 77728 | F2: =B2/E2-1 -> 0.55426616 | G2: =(F2-D2)*100 -> 42.329818 | H2: =披露数据!F2 -> 69773 | I2: =披露数据!F3 -> 59661 | J2: =H2/I2-1 -> 0.16949096 | K2: =披露数据!F14 -> 40540 | L2: =H2/K2-1 -> 0.72109028 | M2: =(L2-J2)*100 -> 55.159932
A3: Intelligent Cloud | B3: =披露数据!E5 -> 106265 | C3: =披露数据!E6 -> 87464 | D3: =B3/C3-1 -> 0.21495701 | E3: =披露数据!E17 -> 105362 | F3: =B3/E3-1 -> 0.0085704523 | G3: =(F3-D3)*100 -> -20.638656 | H3: =披露数据!F5 -> 44589 | I3: =披露数据!F6 -> 37813 | J3: =H3/I3-1 -> 0.17919763 | K3: =披露数据!F17 -> 49584 | L3: =H3/K3-1 -> -0.10073814 | M3: =(L3-J3)*100 -> -27.993577
A4: More Personal Computing | B4: =披露数据!E8 -> 54649 | C4: =披露数据!E9 -> 50838 | D4: =B4/C4-1 -> 0.07496361 | E4: =披露数据!E20 -> 62032 | F4: =B4/E4-1 -> -0.11901922 | G4: =(F4-D4)*100 -> -19.398283 | H4: =披露数据!F8 -> 14166 | I4: =披露数据!F9 -> 11959 | J4: =H4/I4-1 -> 0.1845472 | K4: =披露数据!F20 -> 19309 | L4: =H4/K4-1 -> -0.26635248 | M4: =(L4-J4)*100 -> -45.089968
A5: Total | B5: =披露数据!E11 -> 281724 | C5: =披露数据!E12 -> 245122 | D5: =B5/C5-1 -> 0.14932156 | E5: =披露数据!E23 -> 245122 | F5: =B5/E5-1 -> 0.14932156 | G5: =(F5-D5)*100 -> 0 | H5: =披露数据!F11 -> 128528 | I5: =披露数据!F12 -> 109433 | J5: =H5/I5-1 -> 0.17449033 | K5: =披露数据!F23 -> 109433 | L5: =H5/K5-1 -> 0.17449033 | M5: =(L5-J5)*100 -> 0

Sheet 勾稽
A1: 检查 | B1: 收入 | C1: 营业利润 | D1: 预期
A2: FY24分部重述差合计 | B2: =SUM(FY24桥接!D2:D4) -> 0 | C2: =SUM(FY24桥接!G2:G4) -> 0 | D2: 0
A3: FY24合并总额重述差 | B3: =FY24桥接!D5 -> 0 | C3: =FY24桥接!G5 -> 0 | D3: 0
A4: FY25分部和与合并数之差 | B4: =SUM(FY25同比!B2:B4)-FY25同比!B5 -> 0 | C4: =SUM(FY25同比!H2:H4)-FY25同比!H5 -> 0 | D4: 0
