Workbook

Sheet Policy
A1: Parameter | B1: Approved value
A2: year_days | B2: 360
A3: budget | B3: 100000
A4: fleet_limit | B4: 4
A5: stress_demand_percent | B5: 80
A6: stress_age_periods | B6: 4
A7: stress_cycle_days | B7: 10
A8: minimum_stress_net | B8: 50000
A9: max_per_option | B9: 3
A10: version | B10: V2

Sheet Rates
A1: Cargo | B1: Base | C1: days1 | D1: days2 duration
A2: Coal | B2: 5916 | C2: 7 | D2: 255
A3: Goods | B3: 6144 | C3: 5 | D3: 28
A4: Mail | B4: 4550 | C4: 20 | D4: 90
A5: Passengers | B5: 3185 | C5: 0 | D5: 24

Sheet Routes
A1: ID | B1: Cargo | C1: x1 | D1: y1 | E1: x2 | F1: y2 | G1: Travelled tiles | H1: Station wait | I1: Age periods | J1: Cycle days | K1: Capacity | L1: Demand | M1: Purchase | N1: Annual running | O1: Exclusive group
A2: C1 | B2: Coal | C2: 20 | D2: 20 | E2: 160 | F2: 80 | G2: 280 | H2: 12 | I2: 28 | J2: 90 | K2: 120 | L2: 1200 | M2: 22000 | N2: 7000 | O2: coal
A3: G1 | B3: Goods | C3: 40 | D3: 60 | E3: 240 | F3: 160 | G3: 420 | H3: 4 | I3: 18 | J3: 60 | K3: 80 | L3: 1600 | M3: 28000 | N3: 10000 | O3: goods
A4: G2 | B4: Goods | C4: 40 | D4: 60 | E4: 240 | F4: 160 | G4: 340 | H4: 8 | I4: 8 | J4: 40 | K4: 50 | L4: 1600 | M4: 45000 | N4: 18000 | O4: goods
A5: P1 | B5: Passengers | C5: 15 | D5: 15 | E5: 115 | F5: 75 | G5: 240 | H5: 6 | I5: 12 | J5: 48 | K5: 100 | L5: 2050 | M5: 20000 | N5: 8000 | O5: passengers
A6: P2 | B6: Passengers | C6: 15 | D6: 15 | E6: 115 | F6: 75 | G6: 180 | H6: 4 | I6: 6 | J6: 30 | K6: 70 | L6: 2050 | M6: 30000 | N6: 12000 | O6: passengers
A7: M1 | B7: Mail | C7: 80 | D7: 10 | E7: 200 | F7: 130 | G7: 310 | H7: 12 | I7: 24 | J7: 90 | K7: 60 | L7: 677 | M7: 25000 | N7: 6000 | O7: mail

Sheet Options
A1: ID | B1: Vehicles | C1: Cargo | D1: Rate | E1: days1 | F1: days2 | G1: Pay distance | H1: Age | I1: Cycles/year | J1: Capacity | K1: Demand | L1: Trips | M1: Delivered | N1: Time factor | O1: Revenue | P1: Purchase | Q1: Running | R1: Base net | S1: Stress age | T1: Stress cycles | U1: Stress demand | V1: Stress units | W1: Stress factor | X1: Stress revenue | Y1: Stress net
A2: C1 | B2: 1 | C2: Coal | D2: =Rates!B2 | E2: =Rates!C2 | F2: =Rates!D2 | G2: =ABS(Routes!C2-Routes!E2)+ABS(Routes!D2-Routes!F2) | H2: =Routes!I2 | I2: =INT(Policy!B2/Routes!J2) | J2: =Routes!K2 | K2: =Routes!L2 | L2: =B2*I2 | M2: =MIN(K2,J2*L2) | N2: =MAX(31,255-MAX(0,H2-E2)-MAX(0,H2-E2-F2)) | O2: =INT(J2*D2*G2*N2/2097152)*INT(M2/J2)+INT(MOD(M2,J2)*D2*G2*N2/2097152) | P2: =B2*Routes!M2 | Q2: =B2*Routes!N2 | R2: =O2-P2-Q2 | S2: =H2+Policy!B6 | T2: =INT(Policy!B2/(Routes!J2+Policy!B7)) | U2: =INT(K2*Policy!B5/100) | V2: =MIN(U2,B2*T2*J2) | W2: =MAX(31,255-MAX(0,S2-E2)-MAX(0,S2-E2-F2)) | X2: =INT(J2*D2*G2*W2/2097152)*INT(V2/J2)+INT(MOD(V2,J2)*D2*G2*W2/2097152) | Y2: =X2-P2-Q2
A3: C1 | B3: 2 | C3: Coal | D3: =Rates!B2 | E3: =Rates!C2 | F3: =Rates!D2 | G3: =ABS(Routes!C2-Routes!E2)+ABS(Routes!D2-Routes!F2) | H3: =Routes!I2 | I3: =INT(Policy!B2/Routes!J2) | J3: =Routes!K2 | K3: =Routes!L2 | L3: =B3*I3 | M3: =MIN(K3,J3*L3) | N3: =MAX(31,255-MAX(0,H3-E3)-MAX(0,H3-E3-F3)) | O3: =INT(J3*D3*G3*N3/2097152)*INT(M3/J3)+INT(MOD(M3,J3)*D3*G3*N3/2097152) | P3: =B3*Routes!M2 | Q3: =B3*Routes!N2 | R3: =O3-P3-Q3 | S3: =H3+Policy!B6 | T3: =INT(Policy!B2/(Routes!J2+Policy!B7)) | U3: =INT(K3*Policy!B5/100) | V3: =MIN(U3,B3*T3*J3) | W3: =MAX(31,255-MAX(0,S3-E3)-MAX(0,S3-E3-F3)) | X3: =INT(J3*D3*G3*W3/2097152)*INT(V3/J3)+INT(MOD(V3,J3)*D3*G3*W3/2097152) | Y3: =X3-P3-Q3
A4: C1 | B4: 3 | C4: Coal | D4: =Rates!B2 | E4: =Rates!C2 | F4: =Rates!D2 | G4: =ABS(Routes!C2-Routes!E2)+ABS(Routes!D2-Routes!F2) | H4: =Routes!I2 | I4: =INT(Policy!B2/Routes!J2) | J4: =Routes!K2 | K4: =Routes!L2 | L4: =B4*I4 | M4: =MIN(K4,J4*L4) | N4: =MAX(31,255-MAX(0,H4-E4)-MAX(0,H4-E4-F4)) | O4: =INT(J4*D4*G4*N4/2097152)*INT(M4/J4)+INT(MOD(M4,J4)*D4*G4*N4/2097152) | P4: =B4*Routes!M2 | Q4: =B4*Routes!N2 | R4: =O4-P4-Q4 | S4: =H4+Policy!B6 | T4: =INT(Policy!B2/(Routes!J2+Policy!B7)) | U4: =INT(K4*Policy!B5/100) | V4: =MIN(U4,B4*T4*J4) | W4: =MAX(31,255-MAX(0,S4-E4)-MAX(0,S4-E4-F4)) | X4: =INT(J4*D4*G4*W4/2097152)*INT(V4/J4)+INT(MOD(V4,J4)*D4*G4*W4/2097152) | Y4: =X4-P4-Q4
A5: G1 | B5: 1 | C5: Goods | D5: =Rates!B3 | E5: =Rates!C3 | F5: =Rates!D3 | G5: =ABS(Routes!C3-Routes!E3)+ABS(Routes!D3-Routes!F3) | H5: =Routes!I3 | I5: =INT(Policy!B2/Routes!J3) | J5: =Routes!K3 | K5: =Routes!L3 | L5: =B5*I5 | M5: =MIN(K5,J5*L5) | N5: =MAX(31,255-MAX(0,H5-E5)-MAX(0,H5-E5-F5)) | O5: =INT(J5*D5*G5*N5/2097152)*INT(M5/J5)+INT(MOD(M5,J5)*D5*G5*N5/2097152) | P5: =B5*Routes!M3 | Q5: =B5*Routes!N3 | R5: =O5-P5-Q5 | S5: =H5+Policy!B6 | T5: =INT(Policy!B2/(Routes!J3+Policy!B7)) | U5: =INT(K5*Policy!B5/100) | V5: =MIN(U5,B5*T5*J5) | W5: =MAX(31,255-MAX(0,S5-E5)-MAX(0,S5-E5-F5)) | X5: =INT(J5*D5*G5*W5/2097152)*INT(V5/J5)+INT(MOD(V5,J5)*D5*G5*W5/2097152) | Y5: =X5-P5-Q5
A6: G1 | B6: 2 | C6: Goods | D6: =Rates!B3 | E6: =Rates!C3 | F6: =Rates!D3 | G6: =ABS(Routes!C3-Routes!E3)+ABS(Routes!D3-Routes!F3) | H6: =Routes!I3 | I6: =INT(Policy!B2/Routes!J3) | J6: =Routes!K3 | K6: =Routes!L3 | L6: =B6*I6 | M6: =MIN(K6,J6*L6) | N6: =MAX(31,255-MAX(0,H6-E6)-MAX(0,H6-E6-F6)) | O6: =INT(J6*D6*G6*N6/2097152)*INT(M6/J6)+INT(MOD(M6,J6)*D6*G6*N6/2097152) | P6: =B6*Routes!M3 | Q6: =B6*Routes!N3 | R6: =O6-P6-Q6 | S6: =H6+Policy!B6 | T6: =INT(Policy!B2/(Routes!J3+Policy!B7)) | U6: =INT(K6*Policy!B5/100) | V6: =MIN(U6,B6*T6*J6) | W6: =MAX(31,255-MAX(0,S6-E6)-MAX(0,S6-E6-F6)) | X6: =INT(J6*D6*G6*W6/2097152)*INT(V6/J6)+INT(MOD(V6,J6)*D6*G6*W6/2097152) | Y6: =X6-P6-Q6
A7: G1 | B7: 3 | C7: Goods | D7: =Rates!B3 | E7: =Rates!C3 | F7: =Rates!D3 | G7: =ABS(Routes!C3-Routes!E3)+ABS(Routes!D3-Routes!F3) | H7: =Routes!I3 | I7: =INT(Policy!B2/Routes!J3) | J7: =Routes!K3 | K7: =Routes!L3 | L7: =B7*I7 | M7: =MIN(K7,J7*L7) | N7: =MAX(31,255-MAX(0,H7-E7)-MAX(0,H7-E7-F7)) | O7: =INT(J7*D7*G7*N7/2097152)*INT(M7/J7)+INT(MOD(M7,J7)*D7*G7*N7/2097152) | P7: =B7*Routes!M3 | Q7: =B7*Routes!N3 | R7: =O7-P7-Q7 | S7: =H7+Policy!B6 | T7: =INT(Policy!B2/(Routes!J3+Policy!B7)) | U7: =INT(K7*Policy!B5/100) | V7: =MIN(U7,B7*T7*J7) | W7: =MAX(31,255-MAX(0,S7-E7)-MAX(0,S7-E7-F7)) | X7: =INT(J7*D7*G7*W7/2097152)*INT(V7/J7)+INT(MOD(V7,J7)*D7*G7*W7/2097152) | Y7: =X7-P7-Q7
A8: G2 | B8: 1 | C8: Goods | D8: =Rates!B3 | E8: =Rates!C3 | F8: =Rates!D3 | G8: =ABS(Routes!C4-Routes!E4)+ABS(Routes!D4-Routes!F4) | H8: =Routes!I4 | I8: =INT(Policy!B2/Routes!J4) | J8: =Routes!K4 | K8: =Routes!L4 | L8: =B8*I8 | M8: =MIN(K8,J8*L8) | N8: =MAX(31,255-MAX(0,H8-E8)-MAX(0,H8-E8-F8)) | O8: =INT(J8*D8*G8*N8/2097152)*INT(M8/J8)+INT(MOD(M8,J8)*D8*G8*N8/2097152) | P8: =B8*Routes!M4 | Q8: =B8*Routes!N4 | R8: =O8-P8-Q8 | S8: =H8+Policy!B6 | T8: =INT(Policy!B2/(Routes!J4+Policy!B7)) | U8: =INT(K8*Policy!B5/100) | V8: =MIN(U8,B8*T8*J8) | W8: =MAX(31,255-MAX(0,S8-E8)-MAX(0,S8-E8-F8)) | X8: =INT(J8*D8*G8*W8/2097152)*INT(V8/J8)+INT(MOD(V8,J8)*D8*G8*W8/2097152) | Y8: =X8-P8-Q8
A9: G2 | B9: 2 | C9: Goods | D9: =Rates!B3 | E9: =Rates!C3 | F9: =Rates!D3 | G9: =ABS(Routes!C4-Routes!E4)+ABS(Routes!D4-Routes!F4) | H9: =Routes!I4 | I9: =INT(Policy!B2/Routes!J4) | J9: =Routes!K4 | K9: =Routes!L4 | L9: =B9*I9 | M9: =MIN(K9,J9*L9) | N9: =MAX(31,255-MAX(0,H9-E9)-MAX(0,H9-E9-F9)) | O9: =INT(J9*D9*G9*N9/2097152)*INT(M9/J9)+INT(MOD(M9,J9)*D9*G9*N9/2097152) | P9: =B9*Routes!M4 | Q9: =B9*Routes!N4 | R9: =O9-P9-Q9 | S9: =H9+Policy!B6 | T9: =INT(Policy!B2/(Routes!J4+Policy!B7)) | U9: =INT(K9*Policy!B5/100) | V9: =MIN(U9,B9*T9*J9) | W9: =MAX(31,255-MAX(0,S9-E9)-MAX(0,S9-E9-F9)) | X9: =INT(J9*D9*G9*W9/2097152)*INT(V9/J9)+INT(MOD(V9,J9)*D9*G9*W9/2097152) | Y9: =X9-P9-Q9
A10: G2 | B10: 3 | C10: Goods | D10: =Rates!B3 | E10: =Rates!C3 | F10: =Rates!D3 | G10: =ABS(Routes!C4-Routes!E4)+ABS(Routes!D4-Routes!F4) | H10: =Routes!I4 | I10: =INT(Policy!B2/Routes!J4) | J10: =Routes!K4 | K10: =Routes!L4 | L10: =B10*I10 | M10: =MIN(K10,J10*L10) | N10: =MAX(31,255-MAX(0,H10-E10)-MAX(0,H10-E10-F10)) | O10: =INT(J10*D10*G10*N10/2097152)*INT(M10/J10)+INT(MOD(M10,J10)*D10*G10*N10/2097152) | P10: =B10*Routes!M4 | Q10: =B10*Routes!N4 | R10: =O10-P10-Q10 | S10: =H10+Policy!B6 | T10: =INT(Policy!B2/(Routes!J4+Policy!B7)) | U10: =INT(K10*Policy!B5/100) | V10: =MIN(U10,B10*T10*J10) | W10: =MAX(31,255-MAX(0,S10-E10)-MAX(0,S10-E10-F10)) | X10: =INT(J10*D10*G10*W10/2097152)*INT(V10/J10)+INT(MOD(V10,J10)*D10*G10*W10/2097152) | Y10: =X10-P10-Q10
A11: P1 | B11: 1 | C11: Passengers | D11: =Rates!B5 | E11: =Rates!C5 | F11: =Rates!D5 | G11: =ABS(Routes!C5-Routes!E5)+ABS(Routes!D5-Routes!F5) | H11: =Routes!I5 | I11: =INT(Policy!B2/Routes!J5) | J11: =Routes!K5 | K11: =Routes!L5 | L11: =B11*I11 | M11: =MIN(K11,J11*L11) | N11: =MAX(31,255-MAX(0,H11-E11)-MAX(0,H11-E11-F11)) | O11: =INT(J11*D11*G11*N11/2097152)*INT(M11/J11)+INT(MOD(M11,J11)*D11*G11*N11/2097152) | P11: =B11*Routes!M5 | Q11: =B11*Routes!N5 | R11: =O11-P11-Q11 | S11: =H11+Policy!B6 | T11: =INT(Policy!B2/(Routes!J5+Policy!B7)) | U11: =INT(K11*Policy!B5/100) | V11: =MIN(U11,B11*T11*J11) | W11: =MAX(31,255-MAX(0,S11-E11)-MAX(0,S11-E11-F11)) | X11: =INT(J11*D11*G11*W11/2097152)*INT(V11/J11)+INT(MOD(V11,J11)*D11*G11*W11/2097152) | Y11: =X11-P11-Q11
A12: P1 | B12: 2 | C12: Passengers | D12: =Rates!B5 | E12: =Rates!C5 | F12: =Rates!D5 | G12: =ABS(Routes!C5-Routes!E5)+ABS(Routes!D5-Routes!F5) | H12: =Routes!I5 | I12: =INT(Policy!B2/Routes!J5) | J12: =Routes!K5 | K12: =Routes!L5 | L12: =B12*I12 | M12: =MIN(K12,J12*L12) | N12: =MAX(31,255-MAX(0,H12-E12)-MAX(0,H12-E12-F12)) | O12: =INT(J12*D12*G12*N12/2097152)*INT(M12/J12)+INT(MOD(M12,J12)*D12*G12*N12/2097152) | P12: =B12*Routes!M5 | Q12: =B12*Routes!N5 | R12: =O12-P12-Q12 | S12: =H12+Policy!B6 | T12: =INT(Policy!B2/(Routes!J5+Policy!B7)) | U12: =INT(K12*Policy!B5/100) | V12: =MIN(U12,B12*T12*J12) | W12: =MAX(31,255-MAX(0,S12-E12)-MAX(0,S12-E12-F12)) | X12: =INT(J12*D12*G12*W12/2097152)*INT(V12/J12)+INT(MOD(V12,J12)*D12*G12*W12/2097152) | Y12: =X12-P12-Q12
A13: P1 | B13: 3 | C13: Passengers | D13: =Rates!B5 | E13: =Rates!C5 | F13: =Rates!D5 | G13: =ABS(Routes!C5-Routes!E5)+ABS(Routes!D5-Routes!F5) | H13: =Routes!I5 | I13: =INT(Policy!B2/Routes!J5) | J13: =Routes!K5 | K13: =Routes!L5 | L13: =B13*I13 | M13: =MIN(K13,J13*L13) | N13: =MAX(31,255-MAX(0,H13-E13)-MAX(0,H13-E13-F13)) | O13: =INT(J13*D13*G13*N13/2097152)*INT(M13/J13)+INT(MOD(M13,J13)*D13*G13*N13/2097152) | P13: =B13*Routes!M5 | Q13: =B13*Routes!N5 | R13: =O13-P13-Q13 | S13: =H13+Policy!B6 | T13: =INT(Policy!B2/(Routes!J5+Policy!B7)) | U13: =INT(K13*Policy!B5/100) | V13: =MIN(U13,B13*T13*J13) | W13: =MAX(31,255-MAX(0,S13-E13)-MAX(0,S13-E13-F13)) | X13: =INT(J13*D13*G13*W13/2097152)*INT(V13/J13)+INT(MOD(V13,J13)*D13*G13*W13/2097152) | Y13: =X13-P13-Q13
A14: P2 | B14: 1 | C14: Passengers | D14: =Rates!B5 | E14: =Rates!C5 | F14: =Rates!D5 | G14: =ABS(Routes!C6-Routes!E6)+ABS(Routes!D6-Routes!F6) | H14: =Routes!I6 | I14: =INT(Policy!B2/Routes!J6) | J14: =Routes!K6 | K14: =Routes!L6 | L14: =B14*I14 | M14: =MIN(K14,J14*L14) | N14: =MAX(31,255-MAX(0,H14-E14)-MAX(0,H14-E14-F14)) | O14: =INT(J14*D14*G14*N14/2097152)*INT(M14/J14)+INT(MOD(M14,J14)*D14*G14*N14/2097152) | P14: =B14*Routes!M6 | Q14: =B14*Routes!N6 | R14: =O14-P14-Q14 | S14: =H14+Policy!B6 | T14: =INT(Policy!B2/(Routes!J6+Policy!B7)) | U14: =INT(K14*Policy!B5/100) | V14: =MIN(U14,B14*T14*J14) | W14: =MAX(31,255-MAX(0,S14-E14)-MAX(0,S14-E14-F14)) | X14: =INT(J14*D14*G14*W14/2097152)*INT(V14/J14)+INT(MOD(V14,J14)*D14*G14*W14/2097152) | Y14: =X14-P14-Q14
A15: P2 | B15: 2 | C15: Passengers | D15: =Rates!B5 | E15: =Rates!C5 | F15: =Rates!D5 | G15: =ABS(Routes!C6-Routes!E6)+ABS(Routes!D6-Routes!F6) | H15: =Routes!I6 | I15: =INT(Policy!B2/Routes!J6) | J15: =Routes!K6 | K15: =Routes!L6 | L15: =B15*I15 | M15: =MIN(K15,J15*L15) | N15: =MAX(31,255-MAX(0,H15-E15)-MAX(0,H15-E15-F15)) | O15: =INT(J15*D15*G15*N15/2097152)*INT(M15/J15)+INT(MOD(M15,J15)*D15*G15*N15/2097152) | P15: =B15*Routes!M6 | Q15: =B15*Routes!N6 | R15: =O15-P15-Q15 | S15: =H15+Policy!B6 | T15: =INT(Policy!B2/(Routes!J6+Policy!B7)) | U15: =INT(K15*Policy!B5/100) | V15: =MIN(U15,B15*T15*J15) | W15: =MAX(31,255-MAX(0,S15-E15)-MAX(0,S15-E15-F15)) | X15: =INT(J15*D15*G15*W15/2097152)*INT(V15/J15)+INT(MOD(V15,J15)*D15*G15*W15/2097152) | Y15: =X15-P15-Q15
A16: P2 | B16: 3 | C16: Passengers | D16: =Rates!B5 | E16: =Rates!C5 | F16: =Rates!D5 | G16: =ABS(Routes!C6-Routes!E6)+ABS(Routes!D6-Routes!F6) | H16: =Routes!I6 | I16: =INT(Policy!B2/Routes!J6) | J16: =Routes!K6 | K16: =Routes!L6 | L16: =B16*I16 | M16: =MIN(K16,J16*L16) | N16: =MAX(31,255-MAX(0,H16-E16)-MAX(0,H16-E16-F16)) | O16: =INT(J16*D16*G16*N16/2097152)*INT(M16/J16)+INT(MOD(M16,J16)*D16*G16*N16/2097152) | P16: =B16*Routes!M6 | Q16: =B16*Routes!N6 | R16: =O16-P16-Q16 | S16: =H16+Policy!B6 | T16: =INT(Policy!B2/(Routes!J6+Policy!B7)) | U16: =INT(K16*Policy!B5/100) | V16: =MIN(U16,B16*T16*J16) | W16: =MAX(31,255-MAX(0,S16-E16)-MAX(0,S16-E16-F16)) | X16: =INT(J16*D16*G16*W16/2097152)*INT(V16/J16)+INT(MOD(V16,J16)*D16*G16*W16/2097152) | Y16: =X16-P16-Q16
A17: M1 | B17: 1 | C17: Mail | D17: =Rates!B4 | E17: =Rates!C4 | F17: =Rates!D4 | G17: =ABS(Routes!C7-Routes!E7)+ABS(Routes!D7-Routes!F7) | H17: =Routes!I7 | I17: =INT(Policy!B2/Routes!J7) | J17: =Routes!K7 | K17: =Routes!L7 | L17: =B17*I17 | M17: =MIN(K17,J17*L17) | N17: =MAX(31,255-MAX(0,H17-E17)-MAX(0,H17-E17-F17)) | O17: =INT(J17*D17*G17*N17/2097152)*INT(M17/J17)+INT(MOD(M17,J17)*D17*G17*N17/2097152) | P17: =B17*Routes!M7 | Q17: =B17*Routes!N7 | R17: =O17-P17-Q17 | S17: =H17+Policy!B6 | T17: =INT(Policy!B2/(Routes!J7+Policy!B7)) | U17: =INT(K17*Policy!B5/100) | V17: =MIN(U17,B17*T17*J17) | W17: =MAX(31,255-MAX(0,S17-E17)-MAX(0,S17-E17-F17)) | X17: =INT(J17*D17*G17*W17/2097152)*INT(V17/J17)+INT(MOD(V17,J17)*D17*G17*W17/2097152) | Y17: =X17-P17-Q17
A18: M1 | B18: 2 | C18: Mail | D18: =Rates!B4 | E18: =Rates!C4 | F18: =Rates!D4 | G18: =ABS(Routes!C7-Routes!E7)+ABS(Routes!D7-Routes!F7) | H18: =Routes!I7 | I18: =INT(Policy!B2/Routes!J7) | J18: =Routes!K7 | K18: =Routes!L7 | L18: =B18*I18 | M18: =MIN(K18,J18*L18) | N18: =MAX(31,255-MAX(0,H18-E18)-MAX(0,H18-E18-F18)) | O18: =INT(J18*D18*G18*N18/2097152)*INT(M18/J18)+INT(MOD(M18,J18)*D18*G18*N18/2097152) | P18: =B18*Routes!M7 | Q18: =B18*Routes!N7 | R18: =O18-P18-Q18 | S18: =H18+Policy!B6 | T18: =INT(Policy!B2/(Routes!J7+Policy!B7)) | U18: =INT(K18*Policy!B5/100) | V18: =MIN(U18,B18*T18*J18) | W18: =MAX(31,255-MAX(0,S18-E18)-MAX(0,S18-E18-F18)) | X18: =INT(J18*D18*G18*W18/2097152)*INT(V18/J18)+INT(MOD(V18,J18)*D18*G18*W18/2097152) | Y18: =X18-P18-Q18
A19: M1 | B19: 3 | C19: Mail | D19: =Rates!B4 | E19: =Rates!C4 | F19: =Rates!D4 | G19: =ABS(Routes!C7-Routes!E7)+ABS(Routes!D7-Routes!F7) | H19: =Routes!I7 | I19: =INT(Policy!B2/Routes!J7) | J19: =Routes!K7 | K19: =Routes!L7 | L19: =B19*I19 | M19: =MIN(K19,J19*L19) | N19: =MAX(31,255-MAX(0,H19-E19)-MAX(0,H19-E19-F19)) | O19: =INT(J19*D19*G19*N19/2097152)*INT(M19/J19)+INT(MOD(M19,J19)*D19*G19*N19/2097152) | P19: =B19*Routes!M7 | Q19: =B19*Routes!N7 | R19: =O19-P19-Q19 | S19: =H19+Policy!B6 | T19: =INT(Policy!B2/(Routes!J7+Policy!B7)) | U19: =INT(K19*Policy!B5/100) | V19: =MIN(U19,B19*T19*J19) | W19: =MAX(31,255-MAX(0,S19-E19)-MAX(0,S19-E19-F19)) | X19: =INT(J19*D19*G19*W19/2097152)*INT(V19/J19)+INT(MOD(V19,J19)*D19*G19*W19/2097152) | Y19: =X19-P19-Q19

Sheet Selected
A1: ID | B1: Vehicles | C1: Purchase | D1: Base net | E1: Stress net | F1: Formula origin
A2: C1 | B2: 0 | C2: =0 | D2: =0 | E2: =0 | F2: not purchased
A3: G1 | B3: 3 | C3: =Options!P7 | D3: =Options!R7 | E3: =Options!Y7 | F3: Options row 7
A4: G2 | B4: 0 | C4: =0 | D4: =0 | E4: =0 | F4: not purchased
A5: P1 | B5: 0 | C5: =0 | D5: =0 | E5: =0 | F5: not purchased
A6: P2 | B6: 0 | C6: =0 | D6: =0 | E6: =0 | F6: not purchased
A7: M1 | B7: 0 | C7: =0 | D7: =0 | E7: =0 | F7: not purchased
A8: TOTAL | B8: =SUM(B2:B7) | C8: =SUM(C2:C7) | D8: =SUM(D2:D7) | E8: =SUM(E2:E7) | F8: First-year net deducts purchase and full-year running costs

Sheet Ranking
A1: Rank | B1: Fleet vector | C1: Purchase | D1: Base net | E1: Stress net
A2: 1 | B2: {"C1": 0, "G1": 3, "G2": 0, "M1": 0, "P1": 0, "P2": 0} | C2: 84000 | D2: 192270 | E2: 137010
A3: 2 | B3: {"C1": 2, "G1": 2, "G2": 0, "M1": 0, "P1": 0, "P2": 0} | C3: 100000 | D3: 196916 | E3: 126766
A4: 3 | B4: {"C1": 1, "G1": 2, "G2": 0, "M1": 0, "P1": 1, "P2": 0} | C4: 98000 | D4: 175876 | E4: 115895
A5: 4 | B5: {"C1": 1, "G1": 2, "G2": 0, "M1": 0, "P1": 0, "P2": 0} | C5: 78000 | D5: 162548 | E5: 109053

Sheet 基准对照
A1: 选项 | B1: 计费距离/格 | C1: 车辆数 | D1: 年循环/辆 | E1: 总循环 | F1: 交付量 | G1: 收入/英镑 | H1: 购车/英镑 | I1: 年运行费/英镑 | J1: 首年净现金/英镑
A2: =Options!A2 | B2: =Options!G2 | C2: =Options!B2 | D2: =Options!I2 | E2: =Options!L2 | F2: =Options!M2 | G2: =Options!O2 | H2: =Options!P2 | I2: =Options!Q2 | J2: =Options!R2
A3: =Options!A3 | B3: =Options!G3 | C3: =Options!B3 | D3: =Options!I3 | E3: =Options!L3 | F3: =Options!M3 | G3: =Options!O3 | H3: =Options!P3 | I3: =Options!Q3 | J3: =Options!R3
A4: =Options!A4 | B4: =Options!G4 | C4: =Options!B4 | D4: =Options!I4 | E4: =Options!L4 | F4: =Options!M4 | G4: =Options!O4 | H4: =Options!P4 | I4: =Options!Q4 | J4: =Options!R4
A5: =Options!A5 | B5: =Options!G5 | C5: =Options!B5 | D5: =Options!I5 | E5: =Options!L5 | F5: =Options!M5 | G5: =Options!O5 | H5: =Options!P5 | I5: =Options!Q5 | J5: =Options!R5
A6: =Options!A6 | B6: =Options!G6 | C6: =Options!B6 | D6: =Options!I6 | E6: =Options!L6 | F6: =Options!M6 | G6: =Options!O6 | H6: =Options!P6 | I6: =Options!Q6 | J6: =Options!R6
A7: =Options!A7 | B7: =Options!G7 | C7: =Options!B7 | D7: =Options!I7 | E7: =Options!L7 | F7: =Options!M7 | G7: =Options!O7 | H7: =Options!P7 | I7: =Options!Q7 | J7: =Options!R7
A8: =Options!A8 | B8: =Options!G8 | C8: =Options!B8 | D8: =Options!I8 | E8: =Options!L8 | F8: =Options!M8 | G8: =Options!O8 | H8: =Options!P8 | I8: =Options!Q8 | J8: =Options!R8
A9: =Options!A9 | B9: =Options!G9 | C9: =Options!B9 | D9: =Options!I9 | E9: =Options!L9 | F9: =Options!M9 | G9: =Options!O9 | H9: =Options!P9 | I9: =Options!Q9 | J9: =Options!R9
A10: =Options!A10 | B10: =Options!G10 | C10: =Options!B10 | D10: =Options!I10 | E10: =Options!L10 | F10: =Options!M10 | G10: =Options!O10 | H10: =Options!P10 | I10: =Options!Q10 | J10: =Options!R10
A11: =Options!A11 | B11: =Options!G11 | C11: =Options!B11 | D11: =Options!I11 | E11: =Options!L11 | F11: =Options!M11 | G11: =Options!O11 | H11: =Options!P11 | I11: =Options!Q11 | J11: =Options!R11
A12: =Options!A12 | B12: =Options!G12 | C12: =Options!B12 | D12: =Options!I12 | E12: =Options!L12 | F12: =Options!M12 | G12: =Options!O12 | H12: =Options!P12 | I12: =Options!Q12 | J12: =Options!R12
A13: =Options!A13 | B13: =Options!G13 | C13: =Options!B13 | D13: =Options!I13 | E13: =Options!L13 | F13: =Options!M13 | G13: =Options!O13 | H13: =Options!P13 | I13: =Options!Q13 | J13: =Options!R13
... A19: =Options!A19 | B19: =Options!G19 | C19: =Options!B19 | D19: =Options!I19 | E19: =Options!L19 | F19: =Options!M19 | G19: =Options!O19 | H19: =Options!P19 | I19: =Options!Q19 | J19: =Options!R19

Sheet 压力对照
A1: 选项 | B1: 计费距离/格 | C1: 车辆数 | D1: 老化/周期 | E1: 年循环/辆 | F1: 年度需求 | G1: 交付量 | H1: 收入/英镑 | I1: 购车/英镑 | J1: 首年净现金/英镑
A2: =Options!A2 | B2: =Options!G2 | C2: =Options!B2 | D2: =Options!S2 | E2: =Options!T2 | F2: =Options!U2 | G2: =Options!V2 | H2: =Options!X2 | I2: =Options!P2 | J2: =Options!Y2
A3: =Options!A3 | B3: =Options!G3 | C3: =Options!B3 | D3: =Options!S3 | E3: =Options!T3 | F3: =Options!U3 | G3: =Options!V3 | H3: =Options!X3 | I3: =Options!P3 | J3: =Options!Y3
A4: =Options!A4 | B4: =Options!G4 | C4: =Options!B4 | D4: =Options!S4 | E4: =Options!T4 | F4: =Options!U4 | G4: =Options!V4 | H4: =Options!X4 | I4: =Options!P4 | J4: =Options!Y4
A5: =Options!A5 | B5: =Options!G5 | C5: =Options!B5 | D5: =Options!S5 | E5: =Options!T5 | F5: =Options!U5 | G5: =Options!V5 | H5: =Options!X5 | I5: =Options!P5 | J5: =Options!Y5
A6: =Options!A6 | B6: =Options!G6 | C6: =Options!B6 | D6: =Options!S6 | E6: =Options!T6 | F6: =Options!U6 | G6: =Options!V6 | H6: =Options!X6 | I6: =Options!P6 | J6: =Options!Y6
A7: =Options!A7 | B7: =Options!G7 | C7: =Options!B7 | D7: =Options!S7 | E7: =Options!T7 | F7: =Options!U7 | G7: =Options!V7 | H7: =Options!X7 | I7: =Options!P7 | J7: =Options!Y7
A8: =Options!A8 | B8: =Options!G8 | C8: =Options!B8 | D8: =Options!S8 | E8: =Options!T8 | F8: =Options!U8 | G8: =Options!V8 | H8: =Options!X8 | I8: =Options!P8 | J8: =Options!Y8
A9: =Options!A9 | B9: =Options!G9 | C9: =Options!B9 | D9: =Options!S9 | E9: =Options!T9 | F9: =Options!U9 | G9: =Options!V9 | H9: =Options!X9 | I9: =Options!P9 | J9: =Options!Y9
A10: =Options!A10 | B10: =Options!G10 | C10: =Options!B10 | D10: =Options!S10 | E10: =Options!T10 | F10: =Options!U10 | G10: =Options!V10 | H10: =Options!X10 | I10: =Options!P10 | J10: =Options!Y10
A11: =Options!A11 | B11: =Options!G11 | C11: =Options!B11 | D11: =Options!S11 | E11: =Options!T11 | F11: =Options!U11 | G11: =Options!V11 | H11: =Options!X11 | I11: =Options!P11 | J11: =Options!Y11
A12: =Options!A12 | B12: =Options!G12 | C12: =Options!B12 | D12: =Options!S12 | E12: =Options!T12 | F12: =Options!U12 | G12: =Options!V12 | H12: =Options!X12 | I12: =Options!P12 | J12: =Options!Y12
A13: =Options!A13 | B13: =Options!G13 | C13: =Options!B13 | D13: =Options!S13 | E13: =Options!T13 | F13: =Options!U13 | G13: =Options!V13 | H13: =Options!X13 | I13: =Options!P13 | J13: =Options!Y13
... A19: =Options!A19 | B19: =Options!G19 | C19: =Options!B19 | D19: =Options!S19 | E19: =Options!T19 | F19: =Options!U19 | G19: =Options!V19 | H19: =Options!X19 | I19: =Options!P19 | J19: =Options!Y19
