Workbook

Sheet 口径说明
A1: 事项 | B1: 口径
A2: 基准 | B2: 2022-12-15 10:00 America/New_York；源报告October 2022，具体日未知
A3: 价格单位 | B3: S01两期均已是2021美元。主计算直接比，不再乘1.05976096。
A4: 统计范围 | B4: 12个指定州；全国行不参与州数、平均或排名。
A5: 分类 | B5: 近似单州90%检验；未发现显著差异≠证明变化为零；未做多重校正。
A6: 报告精度 | B6: 原始整数保留；计算全精度；美元2位、增长2位%、z3位。
A7: 数据边界 | B7: 回顾访问前12个月；权重基准不同；不代表同户追踪、个人收入、因果政策效果或州际生活成本已调整。
A8: 状态 | B8: 仅待审核研究包；未真实发布、拨款或完成外部联系。

Sheet 原始收入
A1: State | B1: 2019 estimate ($2021) | C1: MOE2019 | D1: 2021 estimate ($2021) | E1: MOE2021 | F1: 官方变化（%） | G1: 官方90%星号 | H1: 来源定位
A2: Arizona | B2: 65764 | C2: 472 | D2: 69056 | E2: 686 | F2: 5 | G2: * | H2: S01 / Table 1 / Arizona / 收入部分；原报告印刷页3
A3: California | B3: 85248 | C3: 332 | D3: 84907 | E3: 542 | F3: -0.4 | H3: S01 / Table 1 / California / 收入部分；原报告印刷页3
A4: Colorado | B4: 81737 | C4: 839 | D4: 82254 | E4: 791 | F4: 0.6 | H4: S01 / Table 1 / Colorado / 收入部分；原报告印刷页3
A5: Florida | B5: 62767 | C5: 469 | D5: 63062 | E5: 425 | F5: 0.5 | H5: S01 / Table 1 / Florida / 收入部分；原报告印刷页3
A6: Georgia | B6: 65684 | C6: 463 | D6: 66559 | E6: 712 | F6: 1.3 | G6: * | H6: S01 / Table 1 / Georgia / 收入部分；原报告印刷页3
A7: Illinois | B7: 73322 | C7: 620 | D7: 72205 | E7: 574 | F7: -1.5 | G7: * | H7: S01 / Table 1 / Illinois / 收入部分；原报告印刷页3
A8: New York | B8: 76418 | C8: 479 | D8: 74314 | E8: 613 | F8: -2.8 | G8: * | H8: S01 / Table 1 / New York / 收入部分；原报告印刷页3
A9: Ohio | B9: 62147 | C9: 597 | D9: 62262 | E9: 456 | F9: 0.2 | H9: S01 / Table 1 / Ohio / 收入部分；原报告印刷页3
A10: Pennsylvania | B10: 67256 | C10: 455 | D10: 68957 | E10: 505 | F10: 2.5 | G10: * | H10: S01 / Table 1 / Pennsylvania / 收入部分；原报告印刷页3
A11: Texas | B11: 67861 | C11: 530 | D11: 66963 | E11: 513 | F11: -1.3 | G11: * | H11: S01 / Table 1 / Texas / 收入部分；原报告印刷页3
A12: Virginia | B12: 81026 | C12: 893 | D12: 80963 | E12: 731 | F12: -0.1 | H12: S01 / Table 1 / Virginia / 收入部分；原报告印刷页3
A13: Washington | B13: 83390 | C13: 978 | D13: 84247 | E13: 844 | F13: 1 | H13: S01 / Table 1 / Washington / 收入部分；原报告印刷页3

Sheet 逐州分析
A1: State | B1: 2019 $2021 | C1: MOE19 | D1: 2021 $2021 | E1: MOE21 | F1: 差 $2021 | G1: 跨期变化率 | H1: SE19 | I1: SE21 | J1: 差90%MOE | K1: 差区间下限 | L1: 差区间上限 | M1: z（绝对值） | N1: 90%单州结论
A2: =原始收入!A2 -> Arizona | B2: =原始收入!B2 -> 65764 | C2: =原始收入!C2 -> 472 | D2: =原始收入!D2 -> 69056 | E2: =原始收入!E2 -> 686 | F2: =D2-B2 -> 3292 | G2: =D2/B2-1 -> 0.050057782 | H2: =C2/1.645 -> 286.93009 | I2: =E2/1.645 -> 417.02128 | J2: =SQRT(C2^2+E2^2) -> 832.69442 | K2: =F2-J2 -> 2459.3056 | L2: =F2+J2 -> 4124.6944 | M2: =ABS(F2)/SQRT(H2^2+I2^2) -> 6.5033941 | N2: =IF(M2>1.645,IF(F2>0,"显著上升","显著下降"),"未发现显著差异") -> 显著上升
A3: =原始收入!A3 -> California | B3: =原始收入!B3 -> 85248 | C3: =原始收入!C3 -> 332 | D3: =原始收入!D3 -> 84907 | E3: =原始收入!E3 -> 542 | F3: =D3-B3 -> -341 | G3: =D3/B3-1 -> -0.0040000938 | H3: =C3/1.645 -> 201.82371 | I3: =E3/1.645 -> 329.48328 | J3: =SQRT(C3^2+E3^2) -> 635.6005 | K3: =F3-J3 -> -976.6005 | L3: =F3+J3 -> 294.6005 | M3: =ABS(F3)/SQRT(H3^2+I3^2) -> 0.88254335 | N3: =IF(M3>1.645,IF(F3>0,"显著上升","显著下降"),"未发现显著差异") -> 未发现显著差异
A4: =原始收入!A4 -> Colorado | B4: =原始收入!B4 -> 81737 | C4: =原始收入!C4 -> 839 | D4: =原始收入!D4 -> 82254 | E4: =原始收入!E4 -> 791 | F4: =D4-B4 -> 517 | G4: =D4/B4-1 -> 0.0063251649 | H4: =C4/1.645 -> 510.0304 | I4: =E4/1.645 -> 480.85106 | J4: =SQRT(C4^2+E4^2) -> 1153.0837 | K4: =F4-J4 -> -636.08369 | L4: =F4+J4 -> 1670.0837 | M4: =ABS(F4)/SQRT(H4^2+I4^2) -> 0.73755704 | N4: =IF(M4>1.645,IF(F4>0,"显著上升","显著下降"),"未发现显著差异") -> 未发现显著差异
A5: =原始收入!A5 -> Florida | B5: =原始收入!B5 -> 62767 | C5: =原始收入!C5 -> 469 | D5: =原始收入!D5 -> 63062 | E5: =原始收入!E5 -> 425 | F5: =D5-B5 -> 295 | G5: =D5/B5-1 -> 0.0046999219 | H5: =C5/1.645 -> 285.10638 | I5: =E5/1.645 -> 258.35866 | J5: =SQRT(C5^2+E5^2) -> 632.91864 | K5: =F5-J5 -> -337.91864 | L5: =F5+J5 -> 927.91864 | M5: =ABS(F5)/SQRT(H5^2+I5^2) -> 0.76672572 | N5: =IF(M5>1.645,IF(F5>0,"显著上升","显著下降"),"未发现显著差异") -> 未发现显著差异
A6: =原始收入!A6 -> Georgia | B6: =原始收入!B6 -> 65684 | C6: =原始收入!C6 -> 463 | D6: =原始收入!D6 -> 66559 | E6: =原始收入!E6 -> 712 | F6: =D6-B6 -> 875 | G6: =D6/B6-1 -> 0.013321357 | H6: =C6/1.645 -> 281.45897 | I6: =E6/1.645 -> 432.82675 | J6: =SQRT(C6^2+E6^2) -> 849.30148 | K6: =F6-J6 -> 25.698522 | L6: =F6+J6 -> 1724.3015 | M6: =ABS(F6)/SQRT(H6^2+I6^2) -> 1.6947751 | N6: =IF(M6>1.645,IF(F6>0,"显著上升","显著下降"),"未发现显著差异") -> 显著上升
A7: =原始收入!A7 -> Illinois | B7: =原始收入!B7 -> 73322 | C7: =原始收入!C7 -> 620 | D7: =原始收入!D7 -> 72205 | E7: =原始收入!E7 -> 574 | F7: =D7-B7 -> -1117 | G7: =D7/B7-1 -> -0.015234173 | H7: =C7/1.645 -> 376.8997 | I7: =E7/1.645 -> 348.93617 | J7: =SQRT(C7^2+E7^2) -> 844.91183 | K7: =F7-J7 -> -1961.9118 | L7: =F7+J7 -> -272.08817 | M7: =ABS(F7)/SQRT(H7^2+I7^2) -> 2.1747417 | N7: =IF(M7>1.645,IF(F7>0,"显著上升","显著下降"),"未发现显著差异") -> 显著下降
A8: =原始收入!A8 -> New York | B8: =原始收入!B8 -> 76418 | C8: =原始收入!C8 -> 479 | D8: =原始收入!D8 -> 74314 | E8: =原始收入!E8 -> 613 | F8: =D8-B8 -> -2104 | G8: =D8/B8-1 -> -0.02753278 | H8: =C8/1.645 -> 291.18541 | I8: =E8/1.645 -> 372.64438 | J8: =SQRT(C8^2+E8^2) -> 777.95244 | K8: =F8-J8 -> -2881.9524 | L8: =F8+J8 -> -1326.0476 | M8: =ABS(F8)/SQRT(H8^2+I8^2) -> 4.4489609 | N8: =IF(M8>1.645,IF(F8>0,"显著上升","显著下降"),"未发现显著差异") -> 显著下降
A9: =原始收入!A9 -> Ohio | B9: =原始收入!B9 -> 62147 | C9: =原始收入!C9 -> 597 | D9: =原始收入!D9 -> 62262 | E9: =原始收入!E9 -> 456 | F9: =D9-B9 -> 115 | G9: =D9/B9-1 -> 0.0018504513 | H9: =C9/1.645 -> 362.91793 | I9: =E9/1.645 -> 277.20365 | J9: =SQRT(C9^2+E9^2) -> 751.22899 | K9: =F9-J9 -> -636.22899 | L9: =F9+J9 -> 866.22899 | M9: =ABS(F9)/SQRT(H9^2+I9^2) -> 0.25182069 | N9: =IF(M9>1.645,IF(F9>0,"显著上升","显著下降"),"未发现显著差异") -> 未发现显著差异
A10: =原始收入!A10 -> Pennsylvania | B10: =原始收入!B10 -> 67256 | C10: =原始收入!C10 -> 455 | D10: =原始收入!D10 -> 68957 | E10: =原始收入!E10 -> 505 | F10: =D10-B10 -> 1701 | G10: =D10/B10-1 -> 0.025291424 | H10: =C10/1.645 -> 276.59574 | I10: =E10/1.645 -> 306.99088 | J10: =SQRT(C10^2+E10^2) -> 679.7426 | K10: =F10-J10 -> 1021.2574 | L10: =F10+J10 -> 2380.7426 | M10: =ABS(F10)/SQRT(H10^2+I10^2) -> 4.1164773 | N10: =IF(M10>1.645,IF(F10>0,"显著上升","显著下降"),"未发现显著差异") -> 显著上升
A11: =原始收入!A11 -> Texas | B11: =原始收入!B11 -> 67861 | C11: =原始收入!C11 -> 530 | D11: =原始收入!D11 -> 66963 | E11: =原始收入!E11 -> 513 | F11: =D11-B11 -> -898 | G11: =D11/B11-1 -> -0.013232932 | H11: =C11/1.645 -> 322.18845 | I11: =E11/1.645 -> 311.8541 | J11: =SQRT(C11^2+E11^2) -> 737.61033 | K11: =F11-J11 -> -1635.6103 | L11: =F11+J11 -> -160.38967 | M11: =ABS(F11)/SQRT(H11^2+I11^2) -> 2.002697 | N11: =IF(M11>1.645,IF(F11>0,"显著上升","显著下降"),"未发现显著差异") -> 显著下降
A12: =原始收入!A12 -> Virginia | B12: =原始收入!B12 -> 81026 | C12: =原始收入!C12 -> 893 | D12: =原始收入!D12 -> 80963 | E12: =原始收入!E12 -> 731 | F12: =D12-B12 -> -63 | G12: =D12/B12-1 -> -0.0007775282 | H12: =C12/1.645 -> 542.85714 | I12: =E12/1.645 -> 444.3769 | J12: =SQRT(C12^2+E12^2) -> 1154.0407 | K12: =F12-J12 -> -1217.0407 | L12: =F12+J12 -> 1091.0407 | M12: =ABS(F12)/SQRT(H12^2+I12^2) -> 0.089801857 | N12: =IF(M12>1.645,IF(F12>0,"显著上升","显著下降"),"未发现显著差异") -> 未发现显著差异
A13: =原始收入!A13 -> Washington | B13: =原始收入!B13 -> 83390 | C13: =原始收入!C13 -> 978 | D13: =原始收入!D13 -> 84247 | E13: =原始收入!E13 -> 844 | F13: =D13-B13 -> 857 | G13: =D13/B13-1 -> 0.010277012 | H13: =C13/1.645 -> 594.52888 | I13: =E13/1.645 -> 513.06991 | J13: =SQRT(C13^2+E13^2) -> 1291.8282 | K13: =F13-J13 -> -434.82816 | L13: =F13+J13 -> 2148.8282 | M13: =ABS(F13)/SQRT(H13^2+I13^2) -> 1.0912945 | N13: =IF(M13>1.645,IF(F13>0,"显著上升","显著下降"),"未发现显著差异") -> 未发现显著差异

Sheet 旧稿审计
A1: State | B1: 旧稿错误增长 | C1: 正确跨期变化 | D1: 旧减新（百分点） | E1: 旧稿点值分类 | F1: 更正处理
A2: Arizona | B2: =原始收入!D2/(原始收入!B2*1.05976096)-1 -> -0.0091560059 | C2: =逐州分析!G2 -> 0.050057782 | D2: =(B2-C2)*100 -> -5.9213788 | E2: =IF(原始收入!D2>原始收入!B2,"改善","未改善") -> 改善 | F2: 拒绝再调通胀；以差异检验替代点值改善标签；不把审计旧值用于发布
A3: California | B3: =原始收入!D3/(原始收入!B3*1.05976096)-1 -> -0.060165505 | C3: =逐州分析!G3 -> -0.0040000938 | D3: =(B3-C3)*100 -> -5.6165412 | E3: =IF(原始收入!D3>原始收入!B3,"改善","未改善") -> 未改善 | F3: 拒绝再调通胀；以差异检验替代点值改善标签；不把审计旧值用于发布
A4: Colorado | B4: =原始收入!D4/(原始收入!B4*1.05976096)-1 -> -0.050422498 | C4: =逐州分析!G4 -> 0.0063251649 | D4: =(B4-C4)*100 -> -5.6747663 | E4: =IF(原始收入!D4>原始收入!B4,"改善","未改善") -> 改善 | F4: 拒绝再调通胀；以差异检验替代点值改善标签；不把审计旧值用于发布
A5: Florida | B5: =原始收入!D5/(原始收入!B5*1.05976096)-1 -> -0.051956092 | C5: =逐州分析!G5 -> 0.0046999219 | D5: =(B5-C5)*100 -> -5.6656014 | E5: =IF(原始收入!D5>原始收入!B5,"改善","未改善") -> 改善 | F5: 拒绝再调通胀；以差异检验替代点值改善标签；不把审计旧值用于发布
A6: Georgia | B6: =原始收入!D6/(原始收入!B6*1.05976096)-1 -> -0.043820828 | C6: =逐州分析!G6 -> 0.013321357 | D6: =(B6-C6)*100 -> -5.7142185 | E6: =IF(原始收入!D6>原始收入!B6,"改善","未改善") -> 改善 | F6: 拒绝再调通胀；以差异检验替代点值改善标签；不把审计旧值用于发布
A7: Illinois | B7: =原始收入!D7/(原始收入!B7*1.05976096)-1 -> -0.070766083 | C7: =逐州分析!G7 -> -0.015234173 | D7: =(B7-C7)*100 -> -5.5531911 | E7: =IF(原始收入!D7>原始收入!B7,"改善","未改善") -> 未改善 | F7: 拒绝再调通胀；以差异检验替代点值改善标签；不把审计旧值用于发布
A8: New York | B8: =原始收入!D8/(原始收入!B8*1.05976096)-1 -> -0.082371161 | C8: =逐州分析!G8 -> -0.02753278 | D8: =(B8-C8)*100 -> -5.483838 | E8: =IF(原始收入!D8>原始收入!B8,"改善","未改善") -> 未改善 | F8: 拒绝再调通胀；以差异检验替代点值改善标签；不把审计旧值用于发布
A9: Ohio | B9: =原始收入!D9/(原始收入!B9*1.05976096)-1 -> -0.054644878 | C9: =逐州分析!G9 -> 0.0018504513 | D9: =(B9-C9)*100 -> -5.649533 | E9: =IF(原始收入!D9>原始收入!B9,"改善","未改善") -> 改善 | F9: 拒绝再调通胀；以差异检验替代点值改善标签；不把审计旧值用于发布
A10: Pennsylvania | B10: =原始收入!D10/(原始收入!B10*1.05976096)-1 -> -0.032525765 | C10: =逐州分析!G10 -> 0.025291424 | D10: =(B10-C10)*100 -> -5.7817189 | E10: =IF(原始收入!D10>原始收入!B10,"改善","未改善") -> 改善 | F10: 拒绝再调通胀；以差异检验替代点值改善标签；不把审计旧值用于发布
A11: Texas | B11: =原始收入!D11/(原始收入!B11*1.05976096)-1 -> -0.068877695 | C11: =逐州分析!G11 -> -0.013232932 | D11: =(B11-C11)*100 -> -5.5644763 | E11: =IF(原始收入!D11>原始收入!B11,"改善","未改善") -> 未改善 | F11: 拒绝再调通胀；以差异检验替代点值改善标签；不把审计旧值用于发布
A12: Virginia | B12: =原始收入!D12/(原始收入!B12*1.05976096)-1 -> -0.057124663 | C12: =逐州分析!G12 -> -0.0007775282 | D12: =(B12-C12)*100 -> -5.6347135 | E12: =IF(原始收入!D12>原始收入!B12,"改善","未改善") -> 未改善 | F12: 拒绝再调通胀；以差异检验替代点值改善标签；不把审计旧值用于发布
A13: Washington | B13: =原始收入!D13/(原始收入!B13*1.05976096)-1 -> -0.0466935 | C13: =逐州分析!G13 -> 0.010277012 | D13: =(B13-C13)*100 -> -5.6970512 | E13: =IF(原始收入!D13>原始收入!B13,"改善","未改善") -> 改善 | F13: 拒绝再调通胀；以差异检验替代点值改善标签；不把审计旧值用于发布

Sheet 建议处置
A1: 建议 | B1: 处理 | C1: 依据 | D1: 下一步/责任
A2: 2020实验数据拼入序列 | B2: 不采纳；不插值、不补造2020常规收入 | C2: S01页1、S02 2021指南；方法/非应答差异 | D2: 研究负责人保留2019/2021断点并明确缺口原因
A3: 接入2017–2021五年产品 | B3: 不与1年拼接；不能称单年2021变化 | C3: S02第4章；1年/5年不同窗口；2015–2019与2017–2021又有3年重叠 | D3: 若另做小地域分析，另立一致5年产品设计并优先非重叠窗口
A4: 十二州中位数平均称全国并自动拨款 | B4: 不采纳；中位数不可按州简单平均代表全国，且收入不等于项目需求/效果 | C4: S03研究目标；S01全国中位数单独公布；没有成本、覆盖需求或效果资料 | D4: 项目负责人补项目成本、服务缺口、目标群体规模与效果证据；委员会另行确定分配标准
