Workbook

Sheet 取数台账
A1: ID | B1: 机构与模式 | C1: 原施工估算USD | D1: 修订总额或重设计特征USD | E1: 原设计USD | F1: 本次设计USD | G1: 其他USD | H1: 总报价USD | I1: 采用版本与边界
A2: P01 | B2: Army/新设计 | C2: 2000000 | D2: 0 | E2: 0 | F2: 190000 | G2: 40000 | H2: 230000 | I2: 输入P01；设计价含全部设计成本及利润，其他服务按给定分类排除本项上限。
A3: P02 | B3: Navy/新增工作 | C3: 3000000 | D3: 4000000 | E3: 180000 | F3: 240000 | G3: 40000 | H3: 460000 | I3: 4000000是修订总额，不再叠原3000000；设计要180000+240000。
A4: P03 | B4: Air Force/重设计 | C4: 5000000 | D4: 1000000 | E4: 350000 | F4: 260000 | G4: 60000 | H4: 670000 | I4: 原5000000+重设计特征1000000，原350000+重设计260000；不要仅检本次。
A5: P04 | B5: DLA/新设计 | C5: 1000000 | D5: 0 | E5: 0 | F5: 80000 | G5: 10000 | H5: 90000 | I5: 仅描述性取数，不授权DLA套本规则10%；其他适用法缺失。
A6: P05 | B6: NASA/新设计 | C6: 2000000 | D6: 0 | E6: 0 | F6: 160000 | G6: 20000 | H6: 180000 | I6: 民事机构不适用本规则；不能据此推定其应为6%或10%。
A7: P06 | B7: Army/补足请求 | C7: 2000000 | D7: 0 | E7: 120000 | F7: 80000 | G7: 30000 | H7: 230000 | I7: 提议设计总200000，原签设计120000仍有效；80000仅请求，不是已批准应收。
A8: P07 | B8: Navy/未分项 | C8: 1500000 | D8: 0 | E8: 0 | F8: 未知 | G8: 未知 | H8: 170000 | I8: 总价170000不等于设计价；需对方分项和支持文件，不自行估拆。
A9: P08 | B9: Air Force/新设计 | C9: 4000000 | D9: 0 | E9: 0 | F9: 410000 | G9: 10000 | H9: 420000 | I9: 09:40报价V2取代V1；10:10 V3截点后排除，09:20估算4200000未批，批准基准仍4000000。
A10: P09 | B10: Air Force/重设计 | C10: 2000000 | D10: 500000 | E10: 150000 | F10: 100000 | G10: 30000 | H10: 280000 | I10: 重设计合并分子和分母；准确等号可过，不用舍入先做阈值判定。

Sheet 费用复算
A1: ID | B1: 分母USD | C1: 设计合计USD | D1: 其他USD | E1: 本项上限USD | F1: 设计比率 | G1: 超限USD | H1: 测试结论
A2: P01 | B2: ='取数台账'!C2 | C2: ='取数台账'!E2+'取数台账'!F2 | D2: ='取数台账'!G2 | E2: =B2*10% | F2: =C2/B2 | G2: =MAX(C2-E2,0) | H2: 9.50%；设计未超，余量10000。总价230000/2000000=11.50%不是本项设计上限测试。
A3: P02 | B3: ='取数台账'!D3 | C3: ='取数台账'!E3+'取数台账'!F3 | D3: ='取数台账'!G3 | E3: =B3*10% | F3: =C3/B3 | G3: =MAX(C3-E3,0) | H3: 10.50%；超20000，先改设计价或取得合法已批准基准后重算，不仅算新增价。
A4: P03 | B4: ='取数台账'!C4+'取数台账'!D4 | C4: ='取数台账'!E4+'取数台账'!F4 | D4: ='取数台账'!G4 | E4: =B4*10% | F4: =C4/B4 | G4: =MAX(C4-E4,0) | H4: 10.166666...%；超10000；显示10.17%不是先舍入再决定。
A5: P04 | B5: ='取数台账'!C5 | C5: ='取数台账'!F5 | D5: ='取数台账'!G5 | E5: 本规则不适用 | F5: =C5/B5 | G5: 不判定 | H5: 描述性8%；DLA非三军事部门，不可据本规则批准10%上限或付款。
A6: P05 | B6: ='取数台账'!C6 | C6: ='取数台账'!F6 | D6: ='取数台账'!G6 | E6: 本规则不适用 | F6: =C6/B6 | G6: 不判定 | H6: 描述性8%；NASA为民事机构，需另核其规则，不推断6%或10%。
A7: P06 | B7: ='取数台账'!C7 | C7: ='取数台账'!E7+'取数台账'!F7 | D7: ='取数台账'!G7 | E7: =B7*10% | F7: =C7/B7 | G7: =MAX(C7-E7,0) | H7: 提议200000恰为10%，未超本项法定上限；原签设计120000不自动上调，80000不可直接开票。
A8: P07 | B8: ='取数台账'!C8 | C8: 未知 | D8: 未知 | E8: =B8*10% | F8: 待分项 | G8: 待分项 | H8: 设计上限150000；若可证设计≤150000则本项不过限，否则超；总170000不能单独决定。
A9: P08 | B9: ='取数台账'!C9 | C9: ='取数台账'!E9+'取数台账'!F9 | D9: ='取数台账'!G9 | E9: =B9*10% | F9: =C9/B9 | G9: =MAX(C9-E9,0) | H9: 10.25%；截点前V2超10000。未批4200000和未来V3不能用来过关。
A10: P09 | B10: ='取数台账'!C10+'取数台账'!D10 | C10: ='取数台账'!E10+'取数台账'!F10 | D10: ='取数台账'!G10 | E10: =B10*10% | F10: =C10/B10 | G10: =MAX(C10-E10,0) | H10: 10.00%恰等于上限，超限0；可继续谈判/签署流程，不等于已验收或应付款。

Sheet 规范与版本
A1: 项目 | B1: 结论 | C1: 依据与边界
A2: 时点 | B2: 2024-09-06 10:00 America/New_York；规则2024-06-27公布、2024-08-26生效。 | C2: RULE PDF1；不把公布日当生效，不判断生效前追溯或2026现行法。
A3: 主体与对象 | B3: 仅Army/Navy/Air Force特定设计服务的完整contract price(or fee)，不是所有DoD或政府，也不是只限制利润。 | C3: RULE PDF1范围说明、PDF3 236.606-70(a)、(c)。
A4: 修改计算 | B4: 新增工作用修订总施工估算；重设计用原估算+重设计特征估算，设计价均汇总原+新增/重设计。 | C4: RULE PDF3 (b)(1)、(b)(2)(i)-(iii)；其他服务排除本项，不等于免审。
A5: 上限非定价 | B5: 10%是上限，不是承诺费率或自动补款；报价需成本说明并协商，原合同调价依给定双方书面修改。 | C5: RULE PDF2；内部合同既定条件与签署/验收约定是演练事实，不称联邦法。
A6: P08选版 | B6: 已收到09:40 V2采用；10:10 V3在截点后排除；4200000预算草案未批，批准估算仍4000000。 | C6: 输入报价事件；版本日期、取得时刻与批准状态分别判断。
A7: 数值材料边界 | B7: 本题项目数据原创模拟，不是真实政府采购下载；PDF经济影响3.25%/5.42%及例子不是本项目费率。 | C7: 经济影响段数字不一致不用于项目复算；未核未附FAR全套或其他机构规则。

Sheet 合同处置
A1: ID | B1: 当前处理 | C1: 责任与动作 | D1: 关闭材料与依据
A2: P01 | B2: 费用测试可过，继续议价，不按10%顶格承诺。 | C2: 商务核设计与其他分类及成本说明，双方授权人协商。 | D2: 双方书面价款/范围后再按验收材料核票；RULE PDF3(a)(c)、合同既定条件。
A3: P02 | B3: 超20000，当前报价不得按合规价签。 | C3: 商务请对方改设计总价至≤400000或提供真实批准变更后重算。 | D3: 修订范围、批准总估算、设计价分项及重新测试；RULE PDF3(b)(1)。
A4: P03 | B4: 超10000，不能只让本次260000单独过关。 | C4: 商务核重设计特征估算与原价，重新议价。 | D4: 合并设计≤600000及分母6000000证据、双方书面修改；PDF3(b)(2)。
A5: P04 | B5: 本规则不适用；不下DLA法定上限结论。 | C5: 法务请求适用规则/合同条款，商务暂不依10%承诺。 | D5: 适用机构规则与合同文本后另审；其他项目可继续，不套回6%。
A6: P05 | B6: 本规则不适用；NASA另核。 | C6: 法务索取民事机构适用条款，保留描述性8%。 | D6: 适用规则、采购范围和合同文本，不用本规则批准付款。
A7: P06 | B7: 法定上限测试不超但80000非既定应收，暂停补差开票。 | C7: 商务告知原设计120000/其他30000保留；新价须双方授权人书面同意。 | D7: 双方修改与对应验收才进核票；当前均缺。不得擅填已签/已验收/已付。
A8: P07 | B8: 待分项，不能硬判全过或全超。 | C8: 商务向报价方索170000设计/其他拆分与分类支持。 | D8: 设计部分≤150000的可核证据或修价；有材料再测，不由财务估拆。
A9: P08 | B9: V2超10000，未批草案/未来V3不能关闭。 | C9: 商务保留报价事件，要求截点后新资料进入下一轮并重新冻结时点。 | D9: 真实批准估算或合规新报价及重算；不回填10:00包，也不把报价当已签。
A10: P09 | B10: 恰10%，费用测试通过，继续协商和书面修改。 | C10: 商务备齐重设计分子/分母，双方授权人签，指定人验收。 | D10: 设计250000/分母2500000；本项通过不替代合同和验收程序。

Sheet 条款审阅
A1: 条号 | B1: 问题与保留 | C1: 修订方向
A2: S1 | B2: 10%数字有范围；不可统一所有机构或作费率。 | C2: 限定三军事部门、特定设计服务；范围外另核，不推定6%或10%。
A3: S2 | B3: 应保留其他服务不受本项10%限制的意思；利润限定错误，其他费用仍需合同审核。 | C3: 全设计价含成本/间接费/利润；有依据的其他服务分项；不以移项规避。
A4: S3 | B4: 新增与重设计的分母、原设计价均错误。 | C4: 新增按修订总额，重设计加原估算与重设计特征估算；合并设计价复核。
A5: S4 | B5: 公布/生效和上限/应付款混同；原合同不自动补差。 | C5: 2024-08-26生效仅作为规则时点；调价经双方书面同意，不直接变原价。
A6: S5 | B6: 法务/项目经理越过授权及验收；不能邮件代全部凭证。 | C6: 双方授权人签范围/价格，指定验收人验收，财务凭材料核票，缺则留待补证。
A7: S6 | B7: 最新标记不能越过截点和批准条件，缺分项不能猜。 | C7: 记录收到时刻与批准状态；后到资料另轮复核，未分项先向报价方补证。
