Workbook

Sheet 来源台账
A1: 别名 | B1: 经济年 | C1: 原始USD | D1: USD百万 | E1: USD数组索引 | F1: 期间开始 | G1: 期间结束
A2: INC | B2: 2022 | C2: 72565000000 | D2: =C2/1000000 | E2: 199 | F2: 2022-01-01 | G2: 2022-12-31
A3: NII | B3: 2022 | C3: 52462000000 | D3: =C3/1000000 | E3: 199 | F3: 2022-01-01 | G3: 2022-12-31
A4: EXP | B4: 2022 | C4: 20103000000 | D4: =C4/1000000 | E4: 0 | F4: 2022-01-01 | G4: 2022-12-31
A5: DEP | B5: 2022 | C5: 4718000000 | D5: =C5/1000000 | E5: 199 | F5: 2022-01-01 | G5: 2022-12-31
A6: ST | B6: 2022 | C6: 6978000000 | D6: =C6/1000000 | E6: 199 | F6: 2022-01-01 | G6: 2022-12-31
A7: LT | B7: 2022 | C7: 6869000000 | D7: =C7/1000000 | E7: 199 | F7: 2022-01-01 | G7: 2022-12-31
A8: TRD | B8: 2022 | C8: 1538000000 | D8: =C8/1000000 | E8: 199 | F8: 2022-01-01 | G8: 2022-12-31
A9: CASH | B9: 2022 | C9: 18526000000 | D9: =C9/1000000 | E9: 56 | F9: 2022-01-01 | G9: 2022-12-31
A10: INC | B10: 2023 | C10: 130262000000 | D10: =C10/1000000 | E10: 211 | F10: 2023-01-01 | G10: 2023-12-31
A11: NII | B11: 2023 | C11: 56931000000 | D11: =C11/1000000 | E11: 211 | F11: 2023-01-01 | G11: 2023-12-31
A12: EXP | B12: 2023 | C12: 73331000000 | D12: =C12/1000000 | E12: 5 | F12: 2023-01-01 | G12: 2023-12-31
A13: DEP | B13: 2023 | C13: 26163000000 | D13: =C13/1000000 | E13: 211 | F13: 2023-01-01 | G13: 2023-12-31
... A25: CASH | B25: 2024 | C25: 89687000000 | D25: =C25/1000000 | E25: 60 | F25: 2024-01-01 | G25: 2024-12-31

Sheet 指标字典
A1: 别名 | B1: us-gaap标签 | C1: 字段定位与选择契约
A2: INC | B2: InterestAndDividendIncomeOperating | C2: SEC_companyfacts_70858.json；/facts/us-gaap/{标签}/units/USD/{索引}。索引见来源台账，零起始；单位USD。
A3: NII | B3: InterestIncomeExpenseNet | C3: 所有24条限定accn=0000070858-25-000139，form=10-K，filed=2025-02-25；逐经济年按start/end，不用fy代替。
A4: EXP | B4: InterestExpenseOperating | C4: EXP不要误用InterestExpense或CASH。USD百万=原USD/1000000。
A5: DEP | B5: InterestExpenseDeposits | C5: 与ST、LT、TRD组成所选总费用；金额组成不等于利率/业务量因果。
A6: ST | B6: InterestExpenseShortTermBorrowings | C6: 2022/2023/2024完整自然年，不混季度或其他accession比较值。
A7: LT | B7: InterestExpenseLongTermDebt | C7: 2026年当前API按历史filed筛选，不是2025-02-26历史API快照。
A8: TRD | B8: InterestExpenseTradingLiabilities | C8: frame可缺；不是必须按frame选年度。
A9: CASH | B9: InterestPaidNet | C9: 现金净付息不同权责EXP；差额不独自证明应计项目成因。

Sheet 年度桥接
A1: 指标/单位USD百万 | B1: 2022 | C1: 2023 | D1: 2024 | E1: 2022至2023增量 | F1: 2023至2024增量
A2: INC 利息及股息收入 | B2: ='来源台账'!D2 | C2: ='来源台账'!D10 | D2: ='来源台账'!D18 | E2: =C2-B2 | F2: =D2-C2
A3: EXP 权责利息费用 | B3: ='来源台账'!D4 | C3: ='来源台账'!D12 | D3: ='来源台账'!D20 | E3: =C3-B3 | F3: =D3-C3
A4: NII 净利息收入 | B4: ='来源台账'!D3 | C4: ='来源台账'!D11 | D4: ='来源台账'!D19 | E4: =C4-B4 | F4: =D4-C4
A5: DEP 存款利息费用 | B5: ='来源台账'!D5 | C5: ='来源台账'!D13 | D5: ='来源台账'!D21 | E5: =C5-B5 | F5: =D5-C5
A6: ST 短期借款利息费用 | B6: ='来源台账'!D6 | C6: ='来源台账'!D14 | D6: ='来源台账'!D22 | E6: =C6-B6 | F6: =D6-C6
A7: LT 长期债务利息费用 | B7: ='来源台账'!D7 | C7: ='来源台账'!D15 | D7: ='来源台账'!D23 | E7: =C7-B7 | F7: =D7-C7
A8: TRD 交易负债利息费用 | B8: ='来源台账'!D8 | C8: ='来源台账'!D16 | D8: ='来源台账'!D24 | E8: =C8-B8 | F8: =D8-C8
A9: CASH 现金净付息 | B9: ='来源台账'!D9 | C9: ='来源台账'!D17 | D9: ='来源台账'!D25 | E9: =C9-B9 | F9: =D9-C9
A10: 收入-费用-NII残差 | B10: =B2-B3-B4 | C10: =C2-C3-C4 | D10: =D2-D3-D4 | E10: =E2-E3-E4 | F10: =F2-F3-F4
A11: 四费用合计-EXP残差 | B11: =SUM(B5:B8)-B3 | C11: =SUM(C5:C8)-C3 | D11: =SUM(D5:D8)-D3 | E11: =SUM(E5:E8)-E3 | F11: =SUM(F5:F8)-F3
A12: 权责费用减现金净付息 | B12: =B3-B9 | C12: =C3-C9 | D12: =D3-D9 | E12: =C12-B12 | F12: =D12-C12
A13: 存款费用增量/总费用增量（%） | B13: 不适用 | C13: 不适用 | D13: 不适用 | E13: =E5/E3*100 | F13: =F5/F3*100
A14: 解释 | B14: 仅金额复算 | C14: 收入增57697，费用增53228，NII增4469 | D14: 收入增16345，费用增17216，NII减871 | E14: 存款增21445，占费用增量约40.29% | F14: 存款增12279，占费用增量约71.32%；不是NII跌幅因果贡献率

Sheet 发布关口
A1: 对象 | B1: 截点状态/依据 | C1: 下一动作与负责角色 | D1: 关闭证据或边界
A2: 主体差异 | B2: CIK=70858；companyfacts.entityName=BofA Finance LLC；submissions.name=BANK OF AMERICA CORP /DE/。名称差异未解决，不能改输入或推断更名。 | C2: 资料管理员取得原申报封面及报告范围交研究负责人核验；10:00起按V2增加数据负责人签字。 | D2: 同CIK和accession目录匹配不等于已确认主体范围；现无原10-K全文，不得说已读年报附注。
A3: 目标申报定位 | B3: history004索引526：10-K；accession 0000070858-25-000139；报告期2024-12-31；filingDate 2025-02-25。 | C3: acceptanceDateTime 2025-02-26T03:07:15Z = 2025-02-25 22:07:15 America/New_York，早于09:30截点。 | D3: 目录不同于全文。目标不在recent不等于未提交；申报日和UTC受理时间均保留，不互相改写。
A4: 当前政策 | B4: 2025-02-26 09:30 America/New_York适用V1；V2虽已发布，10:00才生效。 | C4: 不要把V2追溯生效；若流程跨10:00重新按V2检查新增签字依赖。 | D4: E04为09:40后到且无证明，不纳入截点已知；未来邮件或计划签字都不等于已闭环。
A5: 内部复核与正式流转 | B5: 24条数值台账可作为初步限定材料送同级复核；E02仅提出请求、尚无回签，未获内部正式流转批准。 | C5: 分析员提交台账及残差给同级复核者，标明主体待核与证据限度。 | D5: 同级复核签字且初步/范围标识具备后才内部正式流转；不把可复算说成已批准。
A6: 对外发布 | B6: 暂缓。主体/报告范围和其他关键解释缺口未关闭；E01没有研究负责人批准。 | C6: 资料管理员补原文，研究负责人核验适用范围并作最终批准；跨10:00时先取得V2数据负责人核验签字。 | D6: 未有原文核验及适用审批链就不外发；分析员无代批权，不造签字或发送证据。
A7: 净息差NIM | B7: 不可由NII除期末总资产替代；缺同口径平均生息资产及指标定义。 | C7: 资料管理员补平均生息资产口径和对应期间，交银行研究复核者核。 | D7: 分子/分母期间、范围和FTE选择对齐后才计算或比较；不输出虚构净息差排名。
A8: FTE调整 | B8: 当前选定值仅按原标签作金额核对，没有已核实FTE桥接。 | C8: 补GAAP到FTE调节表及定义，由银行研究复核者确认可比口径。 | D8: 原始数与调整项可追溯后才称FTE，不把已算NII直接贴FTE标签。
A9: 利率/业务量归因 | B9: 费用增量与NII金额桥接可复算；不能推出具体存款利率或数量因果。 | C9: 补rate/volume明细、平均余额及利率数据与分摊方法，研究复核者核验。 | D9: 71.32%仅为存款费用增量/总费用增量；不称NII下降中71.32%由存款利率造成。

Sheet 草案审阅
A1: ID | B1: 结论 | C1: 替换/保留要点
A2: D01 | B2: 退回修正 | C2: 保留两名称与同CIK；无法据此确认更名或主体范围，不能改原始输入；补原申报核验。
A3: D02 | B3: 退回修正 | C3: 经济年由start/end决定，目标10-K的fy2024含三年比较；按accession/form/期间/单位/filed筛选，不取最新回填。
A4: D03 | B4: 退回修正 | C4: 2024收入增16345，权责费用增17216，NII减871；现金净付息89687不是权责90547，差860，单位USD百万。
A5: D04 | B5: 退回修正 | C5: 没有同口径平均生息资产或FTE调节；不能用期末总资产计算净息差或直接给同行排名。
A6: D05 | B6: 退回修正 | C6: 存款费用增12279/总费用增17216=71.3232%左右；只反映费用增量组成，不是利率或NII跌幅因果贡献。
A7: D06 | B7: 退回修正 | C7: 09:30适用V1，V2 10:00后才生效；未来数据负责人签字不代现有研究负责人批准，分析员无代批。
A8: D07 | B8: 保留并限定 | C8: 初步台账可送复核；E02尚无回签，未获内部正式流转或外发批准；主体异常及其他缺口继续保留。
A9: D08 | B9: 退回修正 | C9: history004索引526定位目标10-K；filingDate 2025-02-25和acceptance 2025-02-26T03:07:15Z不冲突，NY为2月25日22:07:15。
