Workbook

Sheet 口径说明
A1: 项目 | B1: 口径与执行边界
A2: 目标/版本 | B2: R2 2026-10-21 08:00 chief_analyst approved；09:00 Asia/Shanghai基准；不采用未批准08:35营销建议
A3: 数据 | B3: World Bank WDI，单次真实冻结，数据集lastupdated=2026-10-08；不是国别发布日期或旧vintage。S01/S02可逐键追溯。
A4: 单位 | B4: C/D列为十亿美元；原始观测美元全精度。增长列3.42表示3.42%，不是3.42份额；差为百分点。
A5: 公式 | B5: 2020–2024同国相邻同口径比率×100；2019缺2018水平保留空值，官方2019增长可照录。2019指数基准100。
A6: 核对容差 | B6: 绝对差≤0.00001个百分点为团队约定，不是World Bank法定或官方精度标准。
A7: Skill执行 | B7: 实际运行wdi-series-reconcile；4候选入口适用性见备忘，JSON记录真实源/Skill哈希，不等于签名认证。
A8: 来源归属 | B8: World Bank WDI及其元数据所列国家官方统计、OECD和WB估计；保留原API与知识来源URL，非World Bank背书。
A9: 禁止推断 | B9: 现价美元同比不直接等于实际增长；CD/KD美元比值非国内通胀；GDP不证明福利/生活成本/投资回报；无第二官方快照不编造修订归因。
A10: 交接状态 | B10: 待首席分析师复核，外部发布/投资/进入市场均未获批准，未执行外部联系。

Sheet 指标字典
A1: indicator | B1: name | C1: price/unit | D1: source | E1: raw_api_unit | F1: reference_note
A2: NY.GDP.MKTP.CD | B2: GDP (current US$) | C2: current USD | D2: https://api.worldbank.org/v2/indicator/NY.GDP.MKTP.CD?source=2&format=json | F2: S02原定义/sourceNote；2010帮助页仅举例
A3: NY.GDP.MKTP.KD | B3: GDP (constant 2015 US$) | C3: constant 2015 USD | D3: https://api.worldbank.org/v2/indicator/NY.GDP.MKTP.KD?source=2&format=json | F3: S02原定义/sourceNote；2010帮助页仅举例
A4: NY.GDP.MKTP.KD.ZG | B4: GDP growth (annual %) | C4: percent | D4: https://api.worldbank.org/v2/indicator/NY.GDP.MKTP.KD.ZG?source=2&format=json | F4: S02原定义/sourceNote；2010帮助页仅举例

Sheet 原始观测
A1: country | B1: year | C1: indicator | D1: raw_value | E1: source_key | F1: snapshot_lastupdated
A2: BRA | B2: 2019 | C2: NY.GDP.MKTP.CD | D2: 1.8732882e+12 | E2: S01 raw API: countryiso3code/date/indicator.id | F2: 2026-10-08
A3: BRA | B3: 2019 | C3: NY.GDP.MKTP.KD | D3: 1.8196832e+12 | E3: S01 raw API: countryiso3code/date/indicator.id | F3: 2026-10-08
A4: BRA | B4: 2019 | C4: NY.GDP.MKTP.KD.ZG | D4: 1.2207778 | E4: S01 raw API: countryiso3code/date/indicator.id | F4: 2026-10-08
A5: BRA | B5: 2020 | C5: NY.GDP.MKTP.CD | D5: 1.4761072e+12 | E5: S01 raw API: countryiso3code/date/indicator.id | F5: 2026-10-08
A6: BRA | B6: 2020 | C6: NY.GDP.MKTP.KD | D6: 1.7600566e+12 | E6: S01 raw API: countryiso3code/date/indicator.id | F6: 2026-10-08
A7: BRA | B7: 2020 | C7: NY.GDP.MKTP.KD.ZG | D7: -3.2767588 | E7: S01 raw API: countryiso3code/date/indicator.id | F7: 2026-10-08
A8: BRA | B8: 2021 | C8: NY.GDP.MKTP.CD | D8: 1.6706474e+12 | E8: S01 raw API: countryiso3code/date/indicator.id | F8: 2026-10-08
A9: BRA | B9: 2021 | C9: NY.GDP.MKTP.KD | D9: 1.8438811e+12 | E9: S01 raw API: countryiso3code/date/indicator.id | F9: 2026-10-08
A10: BRA | B10: 2021 | C10: NY.GDP.MKTP.KD.ZG | D10: 4.7626044 | E10: S01 raw API: countryiso3code/date/indicator.id | F10: 2026-10-08
A11: BRA | B11: 2022 | C11: NY.GDP.MKTP.CD | D11: 1.9519239e+12 | E11: S01 raw API: countryiso3code/date/indicator.id | F11: 2026-10-08
A12: BRA | B12: 2022 | C12: NY.GDP.MKTP.KD | D12: 1.8995054e+12 | E12: S01 raw API: countryiso3code/date/indicator.id | F12: 2026-10-08
A13: BRA | B13: 2022 | C13: NY.GDP.MKTP.KD.ZG | D13: 3.0166944 | E13: S01 raw API: countryiso3code/date/indicator.id | F13: 2026-10-08
... A73: USA | B73: 2024 | C73: NY.GDP.MKTP.KD.ZG | D73: 2.7931872 | E73: S01 raw API: countryiso3code/date/indicator.id | F73: 2026-10-08

Sheet 年度分析
A1: country | B1: year | C1: current USD bn | D1: constant2015 USD bn | E1: official real growth % | F1: derived real growth % | G1: nominal USD growth % | H1: nominal minus real pp | I1: real index 2019=100 | J1: derived-official pp | K1: status
A2: BRA | B2: 2019 | C2: =原始观测!D2/1000000000 -> 1873.2882 | D2: =原始观测!D3/1000000000 -> 1819.6832 | E2: =原始观测!D4 -> 1.2207778 | I2: =D2/D2*100 -> 100 | K2: NO_2018_LEVEL
A3: BRA | B3: 2020 | C3: =原始观测!D5/1000000000 -> 1476.1072 | D3: =原始观测!D6/1000000000 -> 1760.0566 | E3: =原始观测!D7 -> -3.2767588 | F3: =(D3/D2-1)*100 -> -3.2767588 | G3: =(C3/C2-1)*100 -> -21.202342 | H3: =G3-F3 -> -17.925583 | I3: =D3/D2*100 -> 96.723241 | J3: =F3-E3 -> -8.8817842e-14 | K3: RECONCILED
A4: BRA | B4: 2021 | C4: =原始观测!D8/1000000000 -> 1670.6474 | D4: =原始观测!D9/1000000000 -> 1843.8811 | E4: =原始观测!D10 -> 4.7626044 | F4: =(D4/D3-1)*100 -> 4.7626044 | G4: =(C4/C3-1)*100 -> 13.179271 | H4: =G4-F4 -> 8.4166663 | I4: =D4/D2*100 -> 101.32979 | J4: =F4-E4 -> 3.0198066e-14 | K4: RECONCILED
A5: BRA | B5: 2022 | C5: =原始观测!D11/1000000000 -> 1951.9239 | D5: =原始观测!D12/1000000000 -> 1899.5054 | E5: =原始观测!D13 -> 3.0166944 | F5: =(D5/D4-1)*100 -> 3.0166944 | G5: =(C5/C4-1)*100 -> 16.83638 | H5: =G5-F5 -> 13.819686 | I5: =D5/D2*100 -> 104.3866 | J5: =F5-E5 -> 1.7719159e-13 | K5: RECONCILED
A6: BRA | B6: 2023 | C6: =原始观测!D14/1000000000 -> 2191.1318 | D6: =原始观测!D15/1000000000 -> 1961.0808 | E6: =原始观测!D16 -> 3.2416553 | F6: =(D6/D5-1)*100 -> 3.2416553 | G6: =(C6/C5-1)*100 -> 12.254977 | H6: =G6-F6 -> 9.0133213 | I6: =D6/D2*100 -> 107.77045 | J6: =F6-E6 -> 1.603162e-13 | K6: RECONCILED
A7: BRA | B7: 2024 | C7: =原始观测!D17/1000000000 -> 2185.8216 | D7: =原始观测!D18/1000000000 -> 2028.1363 | E7: =原始观测!D19 -> 3.4193152 | F7: =(D7/D6-1)*100 -> 3.4193152 | G7: =(C7/C6-1)*100 -> -0.24234759 | H7: =G7-F7 -> -3.6616628 | I7: =D7/D2*100 -> 111.45546 | J7: =F7-E7 -> -1.8296475e-13 | K7: RECONCILED
A8: GBR | B8: 2019 | C8: =原始观测!D20/1000000000 -> 2875.7101 | D8: =原始观测!D21/1000000000 -> 3189.2767 | E8: =原始观测!D22 -> 1.256299 | I8: =D8/D8*100 -> 100 | K8: NO_2018_LEVEL
A9: GBR | B9: 2020 | C9: =原始观测!D23/1000000000 -> 2724.0015 | D9: =原始观测!D24/1000000000 -> 2868.8215 | E9: =原始观测!D25 -> -10.047897 | F9: =(D9/D8-1)*100 -> -10.047897 | G9: =(C9/C8-1)*100 -> -5.275518 | H9: =G9-F9 -> 4.7723787 | I9: =D9/D8*100 -> 89.952103 | J9: =F9-E9 -> 1.1368684e-13 | K9: RECONCILED
A10: GBR | B10: 2021 | C10: =原始观测!D26/1000000000 -> 3194.5592 | D10: =原始观测!D27/1000000000 -> 3113.9081 | E10: =原始观测!D28 -> 8.5431118 | F10: =(D10/D9-1)*100 -> 8.5431118 | G10: =(C10/C9-1)*100 -> 17.274503 | H10: =G10-F10 -> 8.7313909 | I10: =D10/D8*100 -> 97.636812 | J10: =F10-E10 -> 4.6185278e-14 | K10: RECONCILED
A11: GBR | B11: 2022 | C11: =原始观测!D29/1000000000 -> 3181.2444 | D11: =原始观测!D30/1000000000 -> 3274.2652 | E11: =原始观测!D31 -> 5.1497039 | F11: =(D11/D10-1)*100 -> 5.1497039 | G11: =(C11/C10-1)*100 -> -0.41679736 | H11: =G11-F11 -> -5.5665012 | I11: =D11/D8*100 -> 102.66482 | J11: =F11-E11 -> -2.016165e-13 | K11: RECONCILED
A12: GBR | B12: 2023 | C12: =原始观测!D32/1000000000 -> 3420.7967 | D12: =原始观测!D33/1000000000 -> 3283.1597 | E12: =原始观测!D34 -> 0.27165005 | F12: =(D12/D11-1)*100 -> 0.27165005 | G12: =(C12/C11-1)*100 -> 7.5301447 | H12: =G12-F12 -> 7.2584947 | I12: =D12/D8*100 -> 102.94371 | J12: =F12-E12 -> 4.3576254e-14 | K12: RECONCILED
A13: GBR | B13: 2024 | C13: =原始观测!D35/1000000000 -> 3695.5395 | D13: =原始观测!D36/1000000000 -> 3318.627 | E13: =原始观测!D37 -> 1.0802772 | F13: =(D13/D12-1)*100 -> 1.0802772 | G13: =(C13/C12-1)*100 -> 8.0315461 | H13: =G13-F13 -> 6.9512689 | I13: =D13/D8*100 -> 104.05579 | J13: =F13-E13 -> 4.0856207e-14 | K13: RECONCILED
A14: JPN | B14: 2019 | C14: =原始观测!D38/1000000000 -> 5245.755 | D14: =原始观测!D39/1000000000 -> 4664.8125 | E14: =原始观测!D40 -> -0.30849692 | I14: =D14/D14*100 -> 100 | K14: NO_2018_LEVEL
A15: JPN | B15: 2020 | C15: =原始观测!D41/1000000000 -> 5189.1975 | D15: =原始观测!D42/1000000000 -> 4465.0056 | E15: =原始观测!D43 -> -4.2832794 | F15: =(D15/D14-1)*100 -> -4.2832794 | G15: =(C15/C14-1)*100 -> -1.0781567 | H15: =G15-F15 -> 3.2051228 | I15: =D15/D14*100 -> 95.716721 | J15: =F15-E15 -> 5.8619776e-14 | K15: RECONCILED
A16: JPN | B16: 2021 | C16: =原始观测!D44/1000000000 -> 5225.9335 | D16: =原始观测!D45/1000000000 -> 4624.1471 | E16: =原始观测!D46 -> 3.5641953 | F16: =(D16/D15-1)*100 -> 3.5641953 | G16: =(C16/C15-1)*100 -> 0.70793175 | H16: =G16-F16 -> -2.8562636 | I16: =D16/D14*100 -> 99.128251 | J16: =F16-E16 -> -4.9737992e-14 | K16: RECONCILED
A17: JPN | B17: 2022 | C17: =原始观测!D47/1000000000 -> 4447.9762 | D17: =原始观测!D48/1000000000 -> 4685.7244 | E17: =原始观测!D49 -> 1.3316475 | F17: =(D17/D16-1)*100 -> 1.3316475 | G17: =(C17/C16-1)*100 -> -14.886476 | H17: =G17-F17 -> -16.218123 | I17: =D17/D14*100 -> 100.44829 | J17: =F17-E17 -> 5.9952043e-14 | K17: RECONCILED
A18: JPN | B18: 2023 | C18: =原始观测!D50/1000000000 -> 4384.8543 | D18: =原始观测!D51/1000000000 -> 4719.4985 | E18: =原始观测!D52 -> 0.7207853 | F18: =(D18/D17-1)*100 -> 0.7207853 | G18: =(C18/C17-1)*100 -> -1.4191159 | H18: =G18-F18 -> -2.1399012 | I18: =D18/D14*100 -> 101.17231 | J18: =F18-E18 -> 2.7089442e-14 | K18: RECONCILED
A19: JPN | B19: 2024 | C19: =原始观测!D53/1000000000 -> 4190.0082 | D19: =原始观测!D54/1000000000 -> 4708.1677 | E19: =原始观测!D55 -> -0.24008424 | F19: =(D19/D18-1)*100 -> -0.24008424 | G19: =(C19/C18-1)*100 -> -4.4436159 | H19: =G19-F19 -> -4.2035317 | I19: =D19/D14*100 -> 100.92941 | J19: =F19-E19 -> 4.7128967e-14 | K19: RECONCILED
A20: USA | B20: 2019 | C20: =原始观测!D56/1000000000 -> 21539.982 | D20: =原始观测!D57/1000000000 -> 20159.639 | E20: =原始观测!D58 -> 2.5838253 | I20: =D20/D20*100 -> 100 | K20: NO_2018_LEVEL
A21: USA | B21: 2020 | C21: =原始观测!D59/1000000000 -> 21375.281 | D21: =原始观测!D60/1000000000 -> 19740.041 | E21: =原始观测!D61 -> -2.081376 | F21: =(D21/D20-1)*100 -> -2.081376 | G21: =(C21/C20-1)*100 -> -0.76462924 | H21: =G21-F21 -> 1.3167467 | I21: =D21/D20*100 -> 97.918624 | J21: =F21-E21 -> 3.1485925e-13 | K21: RECONCILED
A22: USA | B22: 2021 | C22: =原始观测!D62/1000000000 -> 23725.645 | D22: =原始观测!D63/1000000000 -> 20954.453 | E22: =原始观测!D64 -> 6.1520225 | F22: =(D22/D21-1)*100 -> 6.1520225 | G22: =(C22/C21-1)*100 -> 10.99571 | H22: =G22-F22 -> 4.8436879 | I22: =D22/D20*100 -> 103.9426 | J22: =F22-E22 -> -1.5898394e-13 | K22: RECONCILED
A23: USA | B23: 2022 | C23: =原始观测!D65/1000000000 -> 26054.614 | D23: =原始观测!D66/1000000000 -> 21483.388 | E23: =原始观测!D67 -> 2.5242139 | F23: =(D23/D22-1)*100 -> 2.5242139 | G23: =(C23/C22-1)*100 -> 9.8162516 | H23: =G23-F23 -> 7.2920377 | I23: =D23/D20*100 -> 106.56633 | J23: =F23-E23 -> -2.1538327e-13 | K23: RECONCILED
A24: USA | B24: 2023 | C24: =原始观测!D68/1000000000 -> 27811.517 | D24: =原始观测!D69/1000000000 -> 22113.789 | E24: =原始观测!D70 -> 2.9343632 | F24: =(D24/D23-1)*100 -> 2.9343632 | G24: =(C24/C23-1)*100 -> 6.743155 | H24: =G24-F24 -> 3.8087917 | I24: =D24/D20*100 -> 109.69338 | J24: =F24-E24 -> -9.0594199e-14 | K24: RECONCILED
A25: USA | B25: 2024 | C25: =原始观测!D71/1000000000 -> 29298.013 | D25: =原始观测!D72/1000000000 -> 22731.468 | E25: =原始观测!D73 -> 2.7931872 | F25: =(D25/D24-1)*100 -> 2.7931872 | G25: =(C25/C24-1)*100 -> 5.3448936 | H25: =G25-F25 -> 2.5517065 | I25: =D25/D20*100 -> 112.75732 | J25: =F25-E25 -> 1.9984014e-13 | K25: RECONCILED

Sheet 旧稿纠错
A1: country | B1: D0 numerator indicator | C1: D0 denominator indicator | D1: D0 growth % | E1: diagnosis | F1: correct real2024 % | G1: D0 minus correct pp | H1: action
A2: BRA | B2: NY.GDP.MKTP.KD | C2: NY.GDP.MKTP.CD | D2: -7.4388697 | E2: MIXED_PRICE_BASIS_INVALID | F2: =年度分析!F7 -> 3.4193152 | G2: =D2-F2 -> -10.858185 | H2: 撤回D0衰退/实际增长标签，替换同口径研究结论；不能称官方vintage修订
A3: GBR | B3: NY.GDP.MKTP.CD | C3: NY.GDP.MKTP.CD | D3: 8.0315461 | E3: NOMINAL_USD_NOT_REAL | F3: =年度分析!F13 -> 1.0802772 | G3: =D3-F3 -> 6.9512689 | H3: 撤回D0衰退/实际增长标签，替换同口径研究结论；不能称官方vintage修订
A4: JPN | B4: NY.GDP.MKTP.KD | C4: NY.GDP.MKTP.CD | D4: 7.373413 | E4: MIXED_PRICE_BASIS_INVALID | F4: =年度分析!F19 -> -0.24008424 | G4: =D4-F4 -> 7.6134972 | H4: 撤回D0衰退/实际增长标签，替换同口径研究结论；不能称官方vintage修订
A5: USA | B5: NY.GDP.MKTP.CD | C5: NY.GDP.MKTP.CD | D5: 5.3448936 | E5: NOMINAL_USD_NOT_REAL | F5: =年度分析!F25 -> 2.7931872 | G5: =D5-F5 -> 2.5517065 | H5: 撤回D0衰退/实际增长标签，替换同口径研究结论；不能称官方vintage修订

Sheet 2024补查
A1: country | B1: 2024 real growth % | C1: 2019→2024 real index | D1: real negative? | E1: next research action
A2: BRA | B2: =年度分析!F7 -> 3.4193152 | C2: =年度分析!I7 -> 111.45546 | D2: =IF(B2<0,"YES","NO") -> NO | E2: 保留实际增长描述，若旧稿误报负增长则更正；企业行动另需经营证据
A3: GBR | B3: =年度分析!F13 -> 1.0802772 | C3: =年度分析!I13 -> 104.05579 | D3: =IF(B3<0,"YES","NO") -> NO | E3: 保留实际增长描述，若旧稿误报负增长则更正；企业行动另需经营证据
A4: JPN | B4: =年度分析!F19 -> -0.24008424 | C4: =年度分析!I19 -> 100.92941 | D4: =IF(B4<0,"YES","NO") -> YES | E4: 实际负增长：补查国别行业构成/需求证据，暂不对外下公司决策
A5: USA | B5: =年度分析!F25 -> 2.7931872 | C5: =年度分析!I25 -> 112.75732 | D5: =IF(B5<0,"YES","NO") -> NO | E5: 保留实际增长描述，若旧稿误报负增长则更正；企业行动另需经营证据
