Workbook

Sheet Executive Summary
A1: Willowmere Components | Wholesale Rebate Review
A2: Frozen source snapshot: 27 February 2027 | Currency: EUR | Markets: France and Germany
A4: Selected headline treatment: calendar-date inclusive; includes return WHR-FR-008 timestamped exactly 2027-02-27T00:00:00Z.
A5: Alternate sensitivity: frozen-snapshot boundary treatment excludes only that exact-midnight return; all other source-record treatment is unchanged.
A7: Selected scenario - calendar-date inclusive (headline)
A8: Metric | B8: France | C8: Germany | D8: Combined
A9: Proposed rebate (%) | B9: =France!$E$3 -> 0.0735 | C9: =Germany!$E$3 -> 0.0735 | D9: =B9 -> 0.0735
A10: Net individual units | B10: =France!$B$10 -> 1208 | C10: =Germany!$B$10 -> 1140 | D10: =SUM(B10:C10) -> 2348
A11: Net sales (EUR) | B11: =France!$B$11 -> 28507.28 | C11: =Germany!$B$11 -> 28801.68 | D11: =SUM(B11:C11) -> 57308.96
A12: Net cost (EUR) | B12: =France!$B$12 -> 22398.08 | C12: =Germany!$B$12 -> 23048.52 | D12: =SUM(B12:C12) -> 45446.6
A13: Rebate value (EUR) | B13: =France!$B$13 -> 2095.2851 | C13: =Germany!$B$13 -> 2116.9235 | D13: =SUM(B13:C13) -> 4212.2086
A14: Contribution margin (EUR) | B14: =France!$B$14 -> 4013.9149 | C14: =Germany!$B$14 -> 3636.2365 | D14: =SUM(B14:C14) -> 7650.1514
A15: Contribution margin (%) | B15: =France!$B$15 -> 0.14080315 | C15: =Germany!$B$15 -> 0.12625085 | D15: =IFERROR(D14/D11,0) -> 0.13348962
A16: Commercial guardrail (CM %) | B16: =France!$B$16 -> 0.133 | C16: =Germany!$B$16 -> 0.133 | D16: =B16 -> 0.133
A17: Margin vs guardrail (pp) | B17: =France!$B$17 -> 0.78031534 | C17: =Germany!$B$17 -> -0.67491521 | D17: =(D15-D16)*100 -> 0.048962257
A18: Commercial defensibility | B18: =France!$B$18 -> Meets supplied guardrail | C18: =Germany!$B$18 -> Below supplied guardrail | D18: =IF(D15>=D16,"Meets supplied guardrail","Below supplied guardrail") -> Meets supplied guardrail
A21: Alternate sensitivity - frozen-snapshot boundary (midnight return excluded)
A22: Metric | B22: France | C22: Germany | D22: Combined
A23: Net individual units | B23: =France!$C$10 -> 1304 | C23: =Germany!$C$10 -> 1140 | D23: =SUM(B23:C23) -> 2444
A24: Net sales (EUR) | B24: =France!$C$11 -> 31560.08 | C24: =Germany!$C$11 -> 28801.68 | D24: =SUM(B24:C24) -> 60361.76
A25: Net cost (EUR) | B25: =France!$C$12 -> 24910.4 | C25: =Germany!$C$12 -> 23048.52 | D25: =SUM(B25:C25) -> 47958.92
A26: Rebate value (EUR) | B26: =France!$C$13 -> 2319.6659 | C26: =Germany!$C$13 -> 2116.9235 | D26: =SUM(B26:C26) -> 4436.5894
A27: Contribution margin (EUR) | B27: =France!$C$14 -> 4330.0141 | C27: =Germany!$C$14 -> 3636.2365 | D27: =SUM(B27:C27) -> 7966.2506
A28: Contribution margin (%) | B28: =France!$C$15 -> 0.13719909 | C28: =Germany!$C$15 -> 0.12625085 | D28: =IFERROR(D27/D24,0) -> 0.13197512
A29: Commercial guardrail (CM %) | B29: =France!$C$16 -> 0.133 | C29: =Germany!$C$16 -> 0.133 | D29: =B29 -> 0.133
A30: Margin vs guardrail (pp) | B30: =France!$C$17 -> 0.41990857 | C30: =Germany!$C$17 -> -0.67491521 | D30: =(D28-D29)*100 -> -0.1024878
A31: Commercial defensibility | B31: =France!$C$18 -> Meets supplied guardrail | C31: =Germany!$C$18 -> Below supplied guardrail | D31: =IF(D28>=D29,"Meets supplied guardrail","Below supplied guardrail") -> Below supplied guardrail
A32: Change in contribution margin % vs selected (pp) | B32: =(B28-B15)*100 -> -0.36040678 | C32: =(C28-C15)*100 -> 0 | D32: =(D28-D15)*100 -> -0.15145006
A35: =IF(D15>=D16,"Selected scenario conclusion: The proposed rebate is commercially defensible against the supplied guardrail on the selected calendar-date-inclusive basis.","Selected scenario conclusion: The proposed rebate is below the supplied guardrail on the selected calendar-date-inclusive basis and is not commercially defensible on that basis.") -> Selected scenario conclusion: The proposed rebate is commercially defensible against the supplied guardrail on the selected calendar-date-inclusive basis.
A38: This is an evidence-based guardrail comparison only. No supplier action, negotiation position, or sourcing recommendation is stated.

Sheet France
A1: France | Corrected Wholesale Rebate Detail
A2: Market: France | Currency: EUR | Commercial quantity basis: individual units
A3: Frozen snapshot cutoff | B3: ='Source Copy'!$D$7 -> 46445 | D3: Proposed rebate | E3: ='Source Copy'!$D$6 -> 0.0735 | G3: Commercial guardrail | H3: ='Source Copy'!$F$6 -> 0.133 | J3: Rate-card precision | K3: ='Source Copy'!$B$7 -> EUR 0.01 per individual unit
A4: Selected scenario (headline): calendar-date inclusive through 27 February 2027; includes return WHR-FR-008 at exactly 2027-02-27T00:00:00Z.
A5: Alternate sensitivity: frozen-snapshot boundary treatment excludes only that exact-midnight return; all other source-record treatment is unchanged.
A7: Scenario totals - traceable to the per-record detail below
A8: Metric | B8: Selected scenario | C8: Alternate sensitivity | D8: Audit expression
A9: Included source lines | B9: =COUNTIF($X$23:$X$32,"Include") -> 9 | C9: =COUNTIF($Y$23:$Y$32,"Include") -> 8 | D9: Count of Include flags in columns X / Y
A10: Net individual units | B10: =SUMIF($X$23:$X$32,"Include",$R$23:$R$32) -> 1208 | C10: =SUMIF($Y$23:$Y$32,"Include",$R$23:$R$32) -> 1304 | D10: SUMIF inclusion flag, signed individual units
A11: Net sales (EUR) | B11: =SUMIF($X$23:$X$32,"Include",$S$23:$S$32) -> 28507.28 | C11: =SUMIF($Y$23:$Y$32,"Include",$S$23:$S$32) -> 31560.08 | D11: SUMIF inclusion flag, signed gross sales
A12: Net cost (EUR) | B12: =SUMIF($X$23:$X$32,"Include",$T$23:$T$32) -> 22398.08 | C12: =SUMIF($Y$23:$Y$32,"Include",$T$23:$T$32) -> 24910.4 | D12: SUMIF inclusion flag, signed cost
A13: Rebate value (EUR) | B13: =SUMIF($X$23:$X$32,"Include",$U$23:$U$32) -> 2095.2851 | C13: =SUMIF($Y$23:$Y$32,"Include",$U$23:$U$32) -> 2319.6659 | D13: SUMIF inclusion flag, signed rebate
A14: Contribution margin (EUR) | B14: =SUMIF($X$23:$X$32,"Include",$V$23:$V$32) -> 4013.9149 | C14: =SUMIF($Y$23:$Y$32,"Include",$V$23:$V$32) -> 4330.0141 | D14: SUMIF inclusion flag, signed contribution
A15: Contribution margin (%) | B15: =IFERROR(B14/B11,0) -> 0.14080315 | C15: =IFERROR(C14/C11,0) -> 0.13719909 | D15: Contribution margin / net sales
A16: Commercial guardrail (CM %) | B16: =$H$3 -> 0.133 | C16: =$H$3 -> 0.133 | D16: Source Copy commercial CM guardrail
A17: Margin vs guardrail (pp) | B17: =(B15-B16)*100 -> 0.78031534 | C17: =(C15-C16)*100 -> 0.41990857 | D17: Contribution margin % less guardrail
A18: Commercial defensibility | B18: =IF(B15>=B16,"Meets supplied guardrail","Below supplied guardrail") -> Meets supplied guardrail | C18: =IF(C15>=C16,"Meets supplied guardrail","Below supplied guardrail") -> Meets supplied guardrail | D18: Evidence-only comparison; no action recommendation
A20: Detail rule: raw signed economics are shown for every source line; columns X and Y determine whether each line contributes to the selected or alternate totals.
A22: Source Record ID | B22: Original Account Key | C22: Normalized Account Key | D22: Market (map join) | E22: Original Timestamp Text | F22: Parsed Calculation Timestamp (UTC) | G22: Date Interpretation | H22: Event Type | I22: Product Code | J22: Shipment Reference | K22: Source Qty (packs) | L22: Source Pack Size (individual units/pack) | M22: Calculated Individual Units | N22: Source Unit Rate (EUR/individual unit) | O22: Commercial Unit Rate (EUR/individual unit) | P22: Source Unit Cost (EUR/individual unit) | Q22: Event Sign | R22: Signed Individual Units | S22: Signed Gross Sales (EUR) | T22: Signed Cost (EUR) | U22: Signed Rebate (EUR) | V22: Signed Contribution (EUR) | W22: Cutoff Classification | X22: Selected Inclusion | Y22: Alternate Inclusion | Z22: Record Treatment | AA22: Source Copy Cell
A23: ='Source Copy'!$A$19 -> WHR-FR-001 | B23: ='Source Copy'!$B$19 -> LA-FR | C23: =UPPER(TRIM(B23)) -> LA-FR | D23: =IFERROR(INDEX('Source Copy'!$B$12:$B$15,MATCH(C23,'Source Copy'!$A$12:$A$15,0)),"Unmapped") -> France | E23: ='Source Copy'!$C$19 -> 04/03/2026 08:15 | F23: 46085.344 | G23: Slash text interpreted as DD/MM/YYYY | H23: ='Source Copy'!$D$19 -> Sale | I23: ='Source Copy'!$E$19 -> QH-AR-10 | J23: ='Source Copy'!$J$19 -> FR-61084 | K23: ='Source Copy'!$F$19 -> 12 | L23: ='Source Copy'!$G$19 -> 24 | M23: =K23*L23 -> 288 | N23: ='Source Copy'!$H$19 -> 23.47 | O23: =ROUND(N23,2) -> 23.47 | P23: ='Source Copy'!$I$19 -> 18.15 | Q23: =IF(H23="Return",-1,1) -> 1 | R23: =M23*Q23 -> 288 | S23: =R23*O23 -> 6759.36 | T23: =R23*P23 -> 5227.2 | U23: =S23*$E$3 -> 496.81296 | V23: =S23-T23-U23 -> 1035.347 | W23: =IF(F23<DATE(YEAR($B$3),MONTH($B$3),DAY($B$3)),"Before snapshot date",IF(F23>DATE(YEAR($B$3),MONTH($B$3),DAY($B$3)),"After cutoff",IF(AND(H23="Return",F23=DATE(YEAR($B$3),MONTH($B$3),DAY($B$3))),"Exact-midnight return","Snapshot-date record"))) -> Before snapshot date | X23: =IF(OR(W23="Before snapshot date",W23="Exact-midnight return"),"Include","Exclude") -> Include | Y23: =IF(W23="Before snapshot date","Include","Exclude") -> Include | Z23: =IF(W23="After cutoff","Excluded in both: after cutoff",IF(W23="Exact-midnight return","Selected include / alternate exclude","Included in both scenarios")) -> Included in both scenarios | AA23: Source Copy!A19
A24: ='Source Copy'!$A$20 -> WHR-FR-002 | B24: ='Source Copy'!$B$20 -> la-fr | C24: =UPPER(TRIM(B24)) -> LA-FR | D24: =IFERROR(INDEX('Source Copy'!$B$12:$B$15,MATCH(C24,'Source Copy'!$A$12:$A$15,0)),"Unmapped") -> France | E24: ='Source Copy'!$C$20 -> 2026-11-18T09:40:00Z | F24: 46344.403 | G24: ISO UTC timestamp parsed | H24: ='Source Copy'!$D$20 -> Sale | I24: ='Source Copy'!$E$20 -> QH-AR-10 | J24: ='Source Copy'!$J$20 -> FR-61084 | K24: ='Source Copy'!$F$20 -> 8 | L24: ='Source Copy'!$G$20 -> 24 | M24: =K24*L24 -> 192 | N24: ='Source Copy'!$H$20 -> 23.47 | O24: =ROUND(N24,2) -> 23.47 | P24: ='Source Copy'!$I$20 -> 18.15 | Q24: =IF(H24="Return",-1,1) -> 1 | R24: =M24*Q24 -> 192 | S24: =R24*O24 -> 4506.24 | T24: =R24*P24 -> 3484.8 | U24: =S24*$E$3 -> 331.20864 | V24: =S24-T24-U24 -> 690.23136 | W24: =IF(F24<DATE(YEAR($B$3),MONTH($B$3),DAY($B$3)),"Before snapshot date",IF(F24>DATE(YEAR($B$3),MONTH($B$3),DAY($B$3)),"After cutoff",IF(AND(H24="Return",F24=DATE(YEAR($B$3),MONTH($B$3),DAY($B$3))),"Exact-midnight return","Snapshot-date record"))) -> Before snapshot date | X24: =IF(OR(W24="Before snapshot date",W24="Exact-midnight return"),"Include","Exclude") -> Include | Y24: =IF(W24="Before snapshot date","Include","Exclude") -> Include | Z24: =IF(W24="After cutoff","Excluded in both: after cutoff",IF(W24="Exact-midnight return","Selected include / alternate exclude","Included in both scenarios")) -> Included in both scenarios | AA24: Source Copy!A20
A25: ='Source Copy'!$A$21 -> WHR-FR-003 | B25: ='Source Copy'!$B$21 -> MV-FR | C25: =UPPER(TRIM(B25)) -> MV-FR | D25: =IFERROR(INDEX('Source Copy'!$B$12:$B$15,MATCH(C25,'Source Copy'!$A$12:$A$15,0)),"Unmapped") -> France | E25: ='Source Copy'!$C$21 -> 2026-12-05T14:05:00Z | F25: 46361.587 | G25: ISO UTC timestamp parsed | H25: ='Source Copy'!$D$21 -> Sale | I25: ='Source Copy'!$E$21 -> QH-PL-60 | J25: ='Source Copy'!$J$21 -> FR-61088 | K25: ='Source Copy'!$F$21 -> 15 | L25: ='Source Copy'!$G$21 -> 12 | M25: =K25*L25 -> 180 | N25: ='Source Copy'!$H$21 -> 31.8 | O25: =ROUND(N25,2) -> 31.8 | P25: ='Source Copy'!$I$21 -> 26.17 | Q25: =IF(H25="Return",-1,1) -> 1 | R25: =M25*Q25 -> 180 | S25: =R25*O25 -> 5724 | T25: =R25*P25 -> 4710.6 | U25: =S25*$E$3 -> 420.714 | V25: =S25-T25-U25 -> 592.686 | W25: =IF(F25<DATE(YEAR($B$3),MONTH($B$3),DAY($B$3)),"Before snapshot date",IF(F25>DATE(YEAR($B$3),MONTH($B$3),DAY($B$3)),"After cutoff",IF(AND(H25="Return",F25=DATE(YEAR($B$3),MONTH($B$3),DAY($B$3))),"Exact-midnight return","Snapshot-date record"))) -> Before snapshot date | X25: =IF(OR(W25="Before snapshot date",W25="Exact-midnight return"),"Include","Exclude") -> Include | Y25: =IF(W25="Before snapshot date","Include","Exclude") -> Include | Z25: =IF(W25="After cutoff","Excluded in both: after cutoff",IF(W25="Exact-midnight return","Selected include / alternate exclude","Included in both scenarios")) -> Included in both scenarios | AA25: Source Copy!A21
A26: ='Source Copy'!$A$22 -> WHR-FR-004 | B26: ='Source Copy'!$B$22 -> mv-fr | C26: =UPPER(TRIM(B26)) -> MV-FR | D26: =IFERROR(INDEX('Source Copy'!$B$12:$B$15,MATCH(C26,'Source Copy'!$A$12:$A$15,0)),"Unmapped") -> France | E26: ='Source Copy'!$C$22 -> 2027-01-11T11:25:00Z | F26: 46398.476 | G26: ISO UTC timestamp parsed | H26: ='Source Copy'!$D$22 -> Return | I26: ='Source Copy'!$E$22 -> QH-PL-60 | J26: ='Source Copy'!$J$22 -> FR-RMA-121 | K26: ='Source Copy'!$F$22 -> 2 | L26: ='Source Copy'!$G$22 -> 12 | M26: =K26*L26 -> 24 | N26: ='Source Copy'!$H$22 -> 31.8 | O26: =ROUND(N26,2) -> 31.8 | P26: ='Source Copy'!$I$22 -> 26.17 | Q26: =IF(H26="Return",-1,1) -> -1 | R26: =M26*Q26 -> -24 | S26: =R26*O26 -> -763.2 | T26: =R26*P26 -> -628.08 | U26: =S26*$E$3 -> -56.0952 | V26: =S26-T26-U26 -> -79.0248 | W26: =IF(F26<DATE(YEAR($B$3),MONTH($B$3),DAY($B$3)),"Before snapshot date",IF(F26>DATE(YEAR($B$3),MONTH($B$3),DAY($B$3)),"After cutoff",IF(AND(H26="Return",F26=DATE(YEAR($B$3),MONTH($B$3),DAY($B$3))),"Exact-midnight return","Snapshot-date record"))) -> Before snapshot date | X26: =IF(OR(W26="Before snapshot date",W26="Exact-midnight return"),"Include","Exclude") -> Include | Y26: =IF(W26="Before snapshot date","Include","Exclude") -> Include | Z26: =IF(W26="After cutoff","Excluded in both: after cutoff",IF(W26="Exact-midnight return","Selected include / alternate exclude","Included in both scenarios")) -> Included in both scenarios | AA26: Source Copy!A22
A27: ='Source Copy'!$A$23 -> WHR-FR-005 | B27: ='Source Copy'!$B$23 -> LA-FR | C27: =UPPER(TRIM(B27)) -> LA-FR | D27: =IFERROR(INDEX('Source Copy'!$B$12:$B$15,MATCH(C27,'Source Copy'!$A$12:$A$15,0)),"Unmapped") -> France | E27: ='Source Copy'!$C$23 -> 2027-02-08T08:10:00Z | F27: 46426.34 | G27: ISO UTC timestamp parsed | H27: ='Source Copy'!$D$23 -> Sale | I27: ='Source Copy'!$E$23 -> QH-AR-10 | J27: ='Source Copy'!$J$23 -> FR-61115 | K27: ='Source Copy'!$F$23 -> 10 | L27: ='Source Copy'!$G$23 -> 24 | M27: =K27*L27 -> 240 | N27: ='Source Copy'!$H$23 -> 23.47 | O27: =ROUND(N27,2) -> 23.47 | P27: ='Source Copy'!$I$23 -> 18.15 | Q27: =IF(H27="Return",-1,1) -> 1 | R27: =M27*Q27 -> 240 | S27: =R27*O27 -> 5632.8 | T27: =R27*P27 -> 4356 | U27: =S27*$E$3 -> 414.0108 | V27: =S27-T27-U27 -> 862.7892 | W27: =IF(F27<DATE(YEAR($B$3),MONTH($B$3),DAY($B$3)),"Before snapshot date",IF(F27>DATE(YEAR($B$3),MONTH($B$3),DAY($B$3)),"After cutoff",IF(AND(H27="Return",F27=DATE(YEAR($B$3),MONTH($B$3),DAY($B$3))),"Exact-midnight return","Snapshot-date record"))) -> Before snapshot date | X27: =IF(OR(W27="Before snapshot date",W27="Exact-midnight return"),"Include","Exclude") -> Include | Y27: =IF(W27="Before snapshot date","Include","Exclude") -> Include | Z27: =IF(W27="After cutoff","Excluded in both: after cutoff",IF(W27="Exact-midnight return","Selected include / alternate exclude","Included in both scenarios")) -> Included in both scenarios | AA27: Source Copy!A23
A28: ='Source Copy'!$A$24 -> WHR-FR-006 | B28: ='Source Copy'!$B$24 -> la-fr | C28: =UPPER(TRIM(B28)) -> LA-FR | D28: =IFERROR(INDEX('Source Copy'!$B$12:$B$15,MATCH(C28,'Source Copy'!$A$12:$A$15,0)),"Unmapped") -> France | E28: ='Source Copy'!$C$24 -> 2027-02-20T15:20:00Z | F28: 46438.639 | G28: ISO UTC timestamp parsed | H28: ='Source Copy'!$D$24 -> Sale | I28: ='Source Copy'!$E$24 -> QH-AR-10 | J28: ='Source Copy'!$J$24 -> FR-61120 | K28: ='Source Copy'!$F$24 -> 6 | L28: ='Source Copy'!$G$24 -> 24 | M28: =K28*L28 -> 144 | N28: ='Source Copy'!$H$24 -> 23.47 | O28: =ROUND(N28,2) -> 23.47 | P28: ='Source Copy'!$I$24 -> 18.15 | Q28: =IF(H28="Return",-1,1) -> 1 | R28: =M28*Q28 -> 144 | S28: =R28*O28 -> 3379.68 | T28: =R28*P28 -> 2613.6 | U28: =S28*$E$3 -> 248.40648 | V28: =S28-T28-U28 -> 517.67352 | W28: =IF(F28<DATE(YEAR($B$3),MONTH($B$3),DAY($B$3)),"Before snapshot date",IF(F28>DATE(YEAR($B$3),MONTH($B$3),DAY($B$3)),"After cutoff",IF(AND(H28="Return",F28=DATE(YEAR($B$3),MONTH($B$3),DAY($B$3))),"Exact-midnight return","Snapshot-date record"))) -> Before snapshot date | X28: =IF(OR(W28="Before snapshot date",W28="Exact-midnight return"),"Include","Exclude") -> Include | Y28: =IF(W28="Before snapshot date","Include","Exclude") -> Include | Z28: =IF(W28="After cutoff","Excluded in both: after cutoff",IF(W28="Exact-midnight return","Selected include / alternate exclude","Included in both scenarios")) -> Included in both scenarios | AA28: Source Copy!A24
A29: ='Source Copy'!$A$25 -> WHR-FR-007 | B29: ='Source Copy'!$B$25 -> MV-FR | C29: =UPPER(TRIM(B29)) -> MV-FR | D29: =IFERROR(INDEX('Source Copy'!$B$12:$B$15,MATCH(C29,'Source Copy'!$A$12:$A$15,0)),"Unmapped") -> France | E29: ='Source Copy'!$C$25 -> 2027-02-26T16:15:00Z | F29: 46444.677 | G29: ISO UTC timestamp parsed | H29: ='Source Copy'!$D$25 -> Sale | I29: ='Source Copy'!$E$25 -> QH-PL-60 | J29: ='Source Copy'!$J$25 -> FR-61127 | K29: ='Source Copy'!$F$25 -> 7 | L29: ='Source Copy'!$G$25 -> 12 | M29: =K29*L29 -> 84 | N29: ='Source Copy'!$H$25 -> 31.8 | O29: =ROUND(N29,2) -> 31.8 | P29: ='Source Copy'!$I$25 -> 26.17 | Q29: =IF(H29="Return",-1,1) -> 1 | R29: =M29*Q29 -> 84 | S29: =R29*O29 -> 2671.2 | T29: =R29*P29 -> 2198.28 | U29: =S29*$E$3 -> 196.3332 | V29: =S29-T29-U29 -> 276.5868 | W29: =IF(F29<DATE(YEAR($B$3),MONTH($B$3),DAY($B$3)),"Before snapshot date",IF(F29>DATE(YEAR($B$3),MONTH($B$3),DAY($B$3)),"After cutoff",IF(AND(H29="Return",F29=DATE(YEAR($B$3),MONTH($B$3),DAY($B$3))),"Exact-midnight return","Snapshot-date record"))) -> Before snapshot date | X29: =IF(OR(W29="Before snapshot date",W29="Exact-midnight return"),"Include","Exclude") -> Include | Y29: =IF(W29="Before snapshot date","Include","Exclude") -> Include | Z29: =IF(W29="After cutoff","Excluded in both: after cutoff",IF(W29="Exact-midnight return","Selected include / alternate exclude","Included in both scenarios")) -> Included in both scenarios | AA29: Source Copy!A25
A30: ='Source Copy'!$A$26 -> WHR-FR-008 | B30: ='Source Copy'!$B$26 -> mv-fr | C30: =UPPER(TRIM(B30)) -> MV-FR | D30: =IFERROR(INDEX('Source Copy'!$B$12:$B$15,MATCH(C30,'Source Copy'!$A$12:$A$15,0)),"Unmapped") -> France | E30: ='Source Copy'!$C$26 -> 2027-02-27T00:00:00Z | F30: 46445 | G30: ISO UTC timestamp parsed | H30: ='Source Copy'!$D$26 -> Return | I30: ='Source Copy'!$E$26 -> QH-PL-60 | J30: ='Source Copy'!$J$26 -> FR-RMA-131 | K30: ='Source Copy'!$F$26 -> 8 | L30: ='Source Copy'!$G$26 -> 12 | M30: =K30*L30 -> 96 | N30: ='Source Copy'!$H$26 -> 31.8 | O30: =ROUND(N30,2) -> 31.8 | P30: ='Source Copy'!$I$26 -> 26.17 | Q30: =IF(H30="Return",-1,1) -> -1 | R30: =M30*Q30 -> -96 | S30: =R30*O30 -> -3052.8 | T30: =R30*P30 -> -2512.32 | U30: =S30*$E$3 -> -224.3808 | V30: =S30-T30-U30 -> -316.0992 | W30: =IF(F30<DATE(YEAR($B$3),MONTH($B$3),DAY($B$3)),"Before snapshot date",IF(F30>DATE(YEAR($B$3),MONTH($B$3),DAY($B$3)),"After cutoff",IF(AND(H30="Return",F30=DATE(YEAR($B$3),MONTH($B$3),DAY($B$3))),"Exact-midnight return","Snapshot-date record"))) -> Exact-midnight return | X30: =IF(OR(W30="Before snapshot date",W30="Exact-midnight return"),"Include","Exclude") -> Include | Y30: =IF(W30="Before snapshot date","Include","Exclude") -> Exclude | Z30: =IF(W30="After cutoff","Excluded in both: after cutoff",IF(W30="Exact-midnight return","Selected include / alternate exclude","Included in both scenarios")) -> Selected include / alternate exclude | AA30: Source Copy!A26
A31: ='Source Copy'!$A$27 -> WHR-FR-009 | B31: ='Source Copy'!$B$27 -> LA-FR | C31: =UPPER(TRIM(B31)) -> LA-FR | D31: =IFERROR(INDEX('Source Copy'!$B$12:$B$15,MATCH(C31,'Source Copy'!$A$12:$A$15,0)),"Unmapped") -> France | E31: ='Source Copy'!$C$27 -> 2027-03-01T10:00:00Z | F31: 46447.417 | G31: ISO UTC timestamp parsed | H31: ='Source Copy'!$D$27 -> Sale | I31: ='Source Copy'!$E$27 -> QH-AR-10 | J31: ='Source Copy'!$J$27 -> FR-61144 | K31: ='Source Copy'!$F$27 -> 9 | L31: ='Source Copy'!$G$27 -> 24 | M31: =K31*L31 -> 216 | N31: ='Source Copy'!$H$27 -> 23.47 | O31: =ROUND(N31,2) -> 23.47 | P31: ='Source Copy'!$I$27 -> 18.15 | Q31: =IF(H31="Return",-1,1) -> 1 | R31: =M31*Q31 -> 216 | S31: =R31*O31 -> 5069.52 | T31: =R31*P31 -> 3920.4 | U31: =S31*$E$3 -> 372.60972 | V31: =S31-T31-U31 -> 776.51028 | W31: =IF(F31<DATE(YEAR($B$3),MONTH($B$3),DAY($B$3)),"Before snapshot date",IF(F31>DATE(YEAR($B$3),MONTH($B$3),DAY($B$3)),"After cutoff",IF(AND(H31="Return",F31=DATE(YEAR($B$3),MONTH($B$3),DAY($B$3))),"Exact-midnight return","Snapshot-date record"))) -> After cutoff | X31: =IF(OR(W31="Before snapshot date",W31="Exact-midnight return"),"Include","Exclude") -> Exclude | Y31: =IF(W31="Before snapshot date","Include","Exclude") -> Exclude | Z31: =IF(W31="After cutoff","Excluded in both: after cutoff",IF(W31="Exact-midnight return","Selected include / alternate exclude","Included in both scenarios")) -> Excluded in both: after cutoff | AA31: Source Copy!A27
A32: ='Source Copy'!$A$28 -> WHR-FR-010 | B32: ='Source Copy'!$B$28 -> la-fr | C32: =UPPER(TRIM(B32)) -> LA-FR | D32: =IFERROR(INDEX('Source Copy'!$B$12:$B$15,MATCH(C32,'Source Copy'!$A$12:$A$15,0)),"Unmapped") -> France | E32: ='Source Copy'!$C$28 -> 2027-02-14T13:45:00Z | F32: 46432.573 | G32: ISO UTC timestamp parsed | H32: ='Source Copy'!$D$28 -> Sale | I32: ='Source Copy'!$E$28 -> QH-MT-05 | J32: ='Source Copy'!$J$28 -> FR-61118 | K32: ='Source Copy'!$F$28 -> 20 | L32: ='Source Copy'!$G$28 -> 10 | M32: =K32*L32 -> 200 | N32: ='Source Copy'!$H$28 -> 18.25 | O32: =ROUND(N32,2) -> 18.25 | P32: ='Source Copy'!$I$28 -> 14.74 | Q32: =IF(H32="Return",-1,1) -> 1 | R32: =M32*Q32 -> 200 | S32: =R32*O32 -> 3650 | T32: =R32*P32 -> 2948 | U32: =S32*$E$3 -> 268.275 | V32: =S32-T32-U32 -> 433.725 | W32: =IF(F32<DATE(YEAR($B$3),MONTH($B$3),DAY($B$3)),"Before snapshot date",IF(F32>DATE(YEAR($B$3),MONTH($B$3),DAY($B$3)),"After cutoff",IF(AND(H32="Return",F32=DATE(YEAR($B$3),MONTH($B$3),DAY($B$3))),"Exact-midnight return","Snapshot-date record"))) -> Before snapshot date | X32: =IF(OR(W32="Before snapshot date",W32="Exact-midnight return"),"Include","Exclude") -> Include | Y32: =IF(W32="Before snapshot date","Include","Exclude") -> Include | Z32: =IF(W32="After cutoff","Excluded in both: after cutoff",IF(W32="Exact-midnight return","Selected include / alternate exclude","Included in both scenarios")) -> Included in both scenarios | AA32: Source Copy!A28

Sheet Germany
A1: Germany | Corrected Wholesale Rebate Detail
A2: Market: Germany | Currency: EUR | Commercial quantity basis: individual units
A3: Frozen snapshot cutoff | B3: ='Source Copy'!$D$7 -> 46445 | D3: Proposed rebate | E3: ='Source Copy'!$D$6 -> 0.0735 | G3: Commercial guardrail | H3: ='Source Copy'!$F$6 -> 0.133 | J3: Rate-card precision | K3: ='Source Copy'!$B$7 -> EUR 0.01 per individual unit
A4: Selected scenario (headline): calendar-date inclusive through 27 February 2027; includes return WHR-FR-008 at exactly 2027-02-27T00:00:00Z.
A5: Alternate sensitivity: frozen-snapshot boundary treatment excludes only that exact-midnight return; all other source-record treatment is unchanged.
A7: Scenario totals - traceable to the per-record detail below
A8: Metric | B8: Selected scenario | C8: Alternate sensitivity | D8: Audit expression
A9: Included source lines | B9: =COUNTIF($X$23:$X$32,"Include") -> 8 | C9: =COUNTIF($Y$23:$Y$32,"Include") -> 8 | D9: Count of Include flags in columns X / Y
A10: Net individual units | B10: =SUMIF($X$23:$X$32,"Include",$R$23:$R$32) -> 1140 | C10: =SUMIF($Y$23:$Y$32,"Include",$R$23:$R$32) -> 1140 | D10: SUMIF inclusion flag, signed individual units
A11: Net sales (EUR) | B11: =SUMIF($X$23:$X$32,"Include",$S$23:$S$32) -> 28801.68 | C11: =SUMIF($Y$23:$Y$32,"Include",$S$23:$S$32) -> 28801.68 | D11: SUMIF inclusion flag, signed gross sales
A12: Net cost (EUR) | B12: =SUMIF($X$23:$X$32,"Include",$T$23:$T$32) -> 23048.52 | C12: =SUMIF($Y$23:$Y$32,"Include",$T$23:$T$32) -> 23048.52 | D12: SUMIF inclusion flag, signed cost
A13: Rebate value (EUR) | B13: =SUMIF($X$23:$X$32,"Include",$U$23:$U$32) -> 2116.9235 | C13: =SUMIF($Y$23:$Y$32,"Include",$U$23:$U$32) -> 2116.9235 | D13: SUMIF inclusion flag, signed rebate
A14: Contribution margin (EUR) | B14: =SUMIF($X$23:$X$32,"Include",$V$23:$V$32) -> 3636.2365 | C14: =SUMIF($Y$23:$Y$32,"Include",$V$23:$V$32) -> 3636.2365 | D14: SUMIF inclusion flag, signed contribution
A15: Contribution margin (%) | B15: =IFERROR(B14/B11,0) -> 0.12625085 | C15: =IFERROR(C14/C11,0) -> 0.12625085 | D15: Contribution margin / net sales
A16: Commercial guardrail (CM %) | B16: =$H$3 -> 0.133 | C16: =$H$3 -> 0.133 | D16: Source Copy commercial CM guardrail
A17: Margin vs guardrail (pp) | B17: =(B15-B16)*100 -> -0.67491521 | C17: =(C15-C16)*100 -> -0.67491521 | D17: Contribution margin % less guardrail
A18: Commercial defensibility | B18: =IF(B15>=B16,"Meets supplied guardrail","Below supplied guardrail") -> Below supplied guardrail | C18: =IF(C15>=C16,"Meets supplied guardrail","Below supplied guardrail") -> Below supplied guardrail | D18: Evidence-only comparison; no action recommendation
A20: Detail rule: raw signed economics are shown for every source line; columns X and Y determine whether each line contributes to the selected or alternate totals.
A22: Source Record ID | B22: Original Account Key | C22: Normalized Account Key | D22: Market (map join) | E22: Original Timestamp Text | F22: Parsed Calculation Timestamp (UTC) | G22: Date Interpretation | H22: Event Type | I22: Product Code | J22: Shipment Reference | K22: Source Qty (packs) | L22: Source Pack Size (individual units/pack) | M22: Calculated Individual Units | N22: Source Unit Rate (EUR/individual unit) | O22: Commercial Unit Rate (EUR/individual unit) | P22: Source Unit Cost (EUR/individual unit) | Q22: Event Sign | R22: Signed Individual Units | S22: Signed Gross Sales (EUR) | T22: Signed Cost (EUR) | U22: Signed Rebate (EUR) | V22: Signed Contribution (EUR) | W22: Cutoff Classification | X22: Selected Inclusion | Y22: Alternate Inclusion | Z22: Record Treatment | AA22: Source Copy Cell
A23: ='Source Copy'!$A$29 -> WHR-DE-001 | B23: ='Source Copy'!$B$29 -> BR-DE | C23: =UPPER(TRIM(B23)) -> BR-DE | D23: =IFERROR(INDEX('Source Copy'!$B$12:$B$15,MATCH(C23,'Source Copy'!$A$12:$A$15,0)),"Unmapped") -> Germany | E23: ='Source Copy'!$C$29 -> 2026-10-10T07:30:00Z | F23: 46305.312 | G23: ISO UTC timestamp parsed | H23: ='Source Copy'!$D$29 -> Sale | I23: ='Source Copy'!$E$29 -> QH-AR-10 | J23: ='Source Copy'!$J$29 -> DE-44091 | K23: ='Source Copy'!$F$29 -> 10 | L23: ='Source Copy'!$G$29 -> 24 | M23: =K23*L23 -> 240 | N23: ='Source Copy'!$H$29 -> 23.47 | O23: =ROUND(N23,2) -> 23.47 | P23: ='Source Copy'!$I$29 -> 18.15 | Q23: =IF(H23="Return",-1,1) -> 1 | R23: =M23*Q23 -> 240 | S23: =R23*O23 -> 5632.8 | T23: =R23*P23 -> 4356 | U23: =S23*$E$3 -> 414.0108 | V23: =S23-T23-U23 -> 862.7892 | W23: =IF(F23<DATE(YEAR($B$3),MONTH($B$3),DAY($B$3)),"Before snapshot date",IF(F23>DATE(YEAR($B$3),MONTH($B$3),DAY($B$3)),"After cutoff",IF(AND(H23="Return",F23=DATE(YEAR($B$3),MONTH($B$3),DAY($B$3))),"Exact-midnight return","Snapshot-date record"))) -> Before snapshot date | X23: =IF(OR(W23="Before snapshot date",W23="Exact-midnight return"),"Include","Exclude") -> Include | Y23: =IF(W23="Before snapshot date","Include","Exclude") -> Include | Z23: =IF(W23="After cutoff","Excluded in both: after cutoff",IF(W23="Exact-midnight return","Selected include / alternate exclude","Included in both scenarios")) -> Included in both scenarios | AA23: Source Copy!A29
A24: ='Source Copy'!$A$30 -> WHR-DE-002 | B24: ='Source Copy'!$B$30 -> br-de | C24: =UPPER(TRIM(B24)) -> BR-DE | D24: =IFERROR(INDEX('Source Copy'!$B$12:$B$15,MATCH(C24,'Source Copy'!$A$12:$A$15,0)),"Unmapped") -> Germany | E24: ='Source Copy'!$C$30 -> 2026-11-26T10:45:00Z | F24: 46352.448 | G24: ISO UTC timestamp parsed | H24: ='Source Copy'!$D$30 -> Sale | I24: ='Source Copy'!$E$30 -> QH-AR-10 | J24: ='Source Copy'!$J$30 -> DE-44092 | K24: ='Source Copy'!$F$30 -> 7 | L24: ='Source Copy'!$G$30 -> 24 | M24: =K24*L24 -> 168 | N24: ='Source Copy'!$H$30 -> 23.47 | O24: =ROUND(N24,2) -> 23.47 | P24: ='Source Copy'!$I$30 -> 18.15 | Q24: =IF(H24="Return",-1,1) -> 1 | R24: =M24*Q24 -> 168 | S24: =R24*O24 -> 3942.96 | T24: =R24*P24 -> 3049.2 | U24: =S24*$E$3 -> 289.80756 | V24: =S24-T24-U24 -> 603.95244 | W24: =IF(F24<DATE(YEAR($B$3),MONTH($B$3),DAY($B$3)),"Before snapshot date",IF(F24>DATE(YEAR($B$3),MONTH($B$3),DAY($B$3)),"After cutoff",IF(AND(H24="Return",F24=DATE(YEAR($B$3),MONTH($B$3),DAY($B$3))),"Exact-midnight return","Snapshot-date record"))) -> Before snapshot date | X24: =IF(OR(W24="Before snapshot date",W24="Exact-midnight return"),"Include","Exclude") -> Include | Y24: =IF(W24="Before snapshot date","Include","Exclude") -> Include | Z24: =IF(W24="After cutoff","Excluded in both: after cutoff",IF(W24="Exact-midnight return","Selected include / alternate exclude","Included in both scenarios")) -> Included in both scenarios | AA24: Source Copy!A30
A25: ='Source Copy'!$A$31 -> WHR-DE-003 | B25: ='Source Copy'!$B$31 -> KS-DE | C25: =UPPER(TRIM(B25)) -> KS-DE | D25: =IFERROR(INDEX('Source Copy'!$B$12:$B$15,MATCH(C25,'Source Copy'!$A$12:$A$15,0)),"Unmapped") -> Germany | E25: ='Source Copy'!$C$31 -> 2026-12-22T12:00:00Z | F25: 46378.5 | G25: ISO UTC timestamp parsed | H25: ='Source Copy'!$D$31 -> Sale | I25: ='Source Copy'!$E$31 -> QH-PL-60 | J25: ='Source Copy'!$J$31 -> DE-44110 | K25: ='Source Copy'!$F$31 -> 18 | L25: ='Source Copy'!$G$31 -> 12 | M25: =K25*L25 -> 216 | N25: ='Source Copy'!$H$31 -> 31.8 | O25: =ROUND(N25,2) -> 31.8 | P25: ='Source Copy'!$I$31 -> 26.17 | Q25: =IF(H25="Return",-1,1) -> 1 | R25: =M25*Q25 -> 216 | S25: =R25*O25 -> 6868.8 | T25: =R25*P25 -> 5652.72 | U25: =S25*$E$3 -> 504.8568 | V25: =S25-T25-U25 -> 711.2232 | W25: =IF(F25<DATE(YEAR($B$3),MONTH($B$3),DAY($B$3)),"Before snapshot date",IF(F25>DATE(YEAR($B$3),MONTH($B$3),DAY($B$3)),"After cutoff",IF(AND(H25="Return",F25=DATE(YEAR($B$3),MONTH($B$3),DAY($B$3))),"Exact-midnight return","Snapshot-date record"))) -> Before snapshot date | X25: =IF(OR(W25="Before snapshot date",W25="Exact-midnight return"),"Include","Exclude") -> Include | Y25: =IF(W25="Before snapshot date","Include","Exclude") -> Include | Z25: =IF(W25="After cutoff","Excluded in both: after cutoff",IF(W25="Exact-midnight return","Selected include / alternate exclude","Included in both scenarios")) -> Included in both scenarios | AA25: Source Copy!A31
A26: ='Source Copy'!$A$32 -> WHR-DE-004 | B26: ='Source Copy'!$B$32 -> ks-de | C26: =UPPER(TRIM(B26)) -> KS-DE | D26: =IFERROR(INDEX('Source Copy'!$B$12:$B$15,MATCH(C26,'Source Copy'!$A$12:$A$15,0)),"Unmapped") -> Germany | E26: ='Source Copy'!$C$32 -> 2027-01-18T09:50:00Z | F26: 46405.41 | G26: ISO UTC timestamp parsed | H26: ='Source Copy'!$D$32 -> Return | I26: ='Source Copy'!$E$32 -> QH-PL-60 | J26: ='Source Copy'!$J$32 -> DE-RMA-061 | K26: ='Source Copy'!$F$32 -> 3 | L26: ='Source Copy'!$G$32 -> 12 | M26: =K26*L26 -> 36 | N26: ='Source Copy'!$H$32 -> 31.8 | O26: =ROUND(N26,2) -> 31.8 | P26: ='Source Copy'!$I$32 -> 26.17 | Q26: =IF(H26="Return",-1,1) -> -1 | R26: =M26*Q26 -> -36 | S26: =R26*O26 -> -1144.8 | T26: =R26*P26 -> -942.12 | U26: =S26*$E$3 -> -84.1428 | V26: =S26-T26-U26 -> -118.5372 | W26: =IF(F26<DATE(YEAR($B$3),MONTH($B$3),DAY($B$3)),"Before snapshot date",IF(F26>DATE(YEAR($B$3),MONTH($B$3),DAY($B$3)),"After cutoff",IF(AND(H26="Return",F26=DATE(YEAR($B$3),MONTH($B$3),DAY($B$3))),"Exact-midnight return","Snapshot-date record"))) -> Before snapshot date | X26: =IF(OR(W26="Before snapshot date",W26="Exact-midnight return"),"Include","Exclude") -> Include | Y26: =IF(W26="Before snapshot date","Include","Exclude") -> Include | Z26: =IF(W26="After cutoff","Excluded in both: after cutoff",IF(W26="Exact-midnight return","Selected include / alternate exclude","Included in both scenarios")) -> Included in both scenarios | AA26: Source Copy!A32
A27: ='Source Copy'!$A$33 -> WHR-DE-005 | B27: ='Source Copy'!$B$33 -> br-de | C27: =UPPER(TRIM(B27)) -> BR-DE | D27: =IFERROR(INDEX('Source Copy'!$B$12:$B$15,MATCH(C27,'Source Copy'!$A$12:$A$15,0)),"Unmapped") -> Germany | E27: ='Source Copy'!$C$33 -> 2027-02-05T17:25:00Z | F27: 46423.726 | G27: ISO UTC timestamp parsed | H27: ='Source Copy'!$D$33 -> Sale | I27: ='Source Copy'!$E$33 -> QH-MT-05 | J27: ='Source Copy'!$J$33 -> DE-44133 | K27: ='Source Copy'!$F$33 -> 24 | L27: ='Source Copy'!$G$33 -> 10 | M27: =K27*L27 -> 240 | N27: ='Source Copy'!$H$33 -> 18.25 | O27: =ROUND(N27,2) -> 18.25 | P27: ='Source Copy'!$I$33 -> 14.74 | Q27: =IF(H27="Return",-1,1) -> 1 | R27: =M27*Q27 -> 240 | S27: =R27*O27 -> 4380 | T27: =R27*P27 -> 3537.6 | U27: =S27*$E$3 -> 321.93 | V27: =S27-T27-U27 -> 520.47 | W27: =IF(F27<DATE(YEAR($B$3),MONTH($B$3),DAY($B$3)),"Before snapshot date",IF(F27>DATE(YEAR($B$3),MONTH($B$3),DAY($B$3)),"After cutoff",IF(AND(H27="Return",F27=DATE(YEAR($B$3),MONTH($B$3),DAY($B$3))),"Exact-midnight return","Snapshot-date record"))) -> Before snapshot date | X27: =IF(OR(W27="Before snapshot date",W27="Exact-midnight return"),"Include","Exclude") -> Include | Y27: =IF(W27="Before snapshot date","Include","Exclude") -> Include | Z27: =IF(W27="After cutoff","Excluded in both: after cutoff",IF(W27="Exact-midnight return","Selected include / alternate exclude","Included in both scenarios")) -> Included in both scenarios | AA27: Source Copy!A33
A28: ='Source Copy'!$A$34 -> WHR-DE-006 | B28: ='Source Copy'!$B$34 -> KS-DE | C28: =UPPER(TRIM(B28)) -> KS-DE | D28: =IFERROR(INDEX('Source Copy'!$B$12:$B$15,MATCH(C28,'Source Copy'!$A$12:$A$15,0)),"Unmapped") -> Germany | E28: ='Source Copy'!$C$34 -> 2027-02-23T10:15:00Z | F28: 46441.427 | G28: ISO UTC timestamp parsed | H28: ='Source Copy'!$D$34 -> Sale | I28: ='Source Copy'!$E$34 -> QH-PL-60 | J28: ='Source Copy'!$J$34 -> DE-44138 | K28: ='Source Copy'!$F$34 -> 8 | L28: ='Source Copy'!$G$34 -> 12 | M28: =K28*L28 -> 96 | N28: ='Source Copy'!$H$34 -> 31.8 | O28: =ROUND(N28,2) -> 31.8 | P28: ='Source Copy'!$I$34 -> 26.17 | Q28: =IF(H28="Return",-1,1) -> 1 | R28: =M28*Q28 -> 96 | S28: =R28*O28 -> 3052.8 | T28: =R28*P28 -> 2512.32 | U28: =S28*$E$3 -> 224.3808 | V28: =S28-T28-U28 -> 316.0992 | W28: =IF(F28<DATE(YEAR($B$3),MONTH($B$3),DAY($B$3)),"Before snapshot date",IF(F28>DATE(YEAR($B$3),MONTH($B$3),DAY($B$3)),"After cutoff",IF(AND(H28="Return",F28=DATE(YEAR($B$3),MONTH($B$3),DAY($B$3))),"Exact-midnight return","Snapshot-date record"))) -> Before snapshot date | X28: =IF(OR(W28="Before snapshot date",W28="Exact-midnight return"),"Include","Exclude") -> Include | Y28: =IF(W28="Before snapshot date","Include","Exclude") -> Include | Z28: =IF(W28="After cutoff","Excluded in both: after cutoff",IF(W28="Exact-midnight return","Selected include / alternate exclude","Included in both scenarios")) -> Included in both scenarios | AA28: Source Copy!A34
A29: ='Source Copy'!$A$35 -> WHR-DE-007 | B29: ='Source Copy'!$B$35 -> BR-DE | C29: =UPPER(TRIM(B29)) -> BR-DE | D29: =IFERROR(INDEX('Source Copy'!$B$12:$B$15,MATCH(C29,'Source Copy'!$A$12:$A$15,0)),"Unmapped") -> Germany | E29: ='Source Copy'!$C$35 -> 2027-02-26T22:59:00Z | F29: 46444.958 | G29: ISO UTC timestamp parsed | H29: ='Source Copy'!$D$35 -> Sale | I29: ='Source Copy'!$E$35 -> QH-AR-10 | J29: ='Source Copy'!$J$35 -> DE-44140 | K29: ='Source Copy'!$F$35 -> 4 | L29: ='Source Copy'!$G$35 -> 24 | M29: =K29*L29 -> 96 | N29: ='Source Copy'!$H$35 -> 23.47 | O29: =ROUND(N29,2) -> 23.47 | P29: ='Source Copy'!$I$35 -> 18.15 | Q29: =IF(H29="Return",-1,1) -> 1 | R29: =M29*Q29 -> 96 | S29: =R29*O29 -> 2253.12 | T29: =R29*P29 -> 1742.4 | U29: =S29*$E$3 -> 165.60432 | V29: =S29-T29-U29 -> 345.11568 | W29: =IF(F29<DATE(YEAR($B$3),MONTH($B$3),DAY($B$3)),"Before snapshot date",IF(F29>DATE(YEAR($B$3),MONTH($B$3),DAY($B$3)),"After cutoff",IF(AND(H29="Return",F29=DATE(YEAR($B$3),MONTH($B$3),DAY($B$3))),"Exact-midnight return","Snapshot-date record"))) -> Before snapshot date | X29: =IF(OR(W29="Before snapshot date",W29="Exact-midnight return"),"Include","Exclude") -> Include | Y29: =IF(W29="Before snapshot date","Include","Exclude") -> Include | Z29: =IF(W29="After cutoff","Excluded in both: after cutoff",IF(W29="Exact-midnight return","Selected include / alternate exclude","Included in both scenarios")) -> Included in both scenarios | AA29: Source Copy!A35
A30: ='Source Copy'!$A$36 -> WHR-DE-008 | B30: ='Source Copy'!$B$36 -> ks-de | C30: =UPPER(TRIM(B30)) -> KS-DE | D30: =IFERROR(INDEX('Source Copy'!$B$12:$B$15,MATCH(C30,'Source Copy'!$A$12:$A$15,0)),"Unmapped") -> Germany | E30: ='Source Copy'!$C$36 -> 2027-02-28T01:05:00Z | F30: 46446.045 | G30: ISO UTC timestamp parsed | H30: ='Source Copy'!$D$36 -> Return | I30: ='Source Copy'!$E$36 -> QH-MT-05 | J30: ='Source Copy'!$J$36 -> DE-RMA-068 | K30: ='Source Copy'!$F$36 -> 4 | L30: ='Source Copy'!$G$36 -> 10 | M30: =K30*L30 -> 40 | N30: ='Source Copy'!$H$36 -> 18.25 | O30: =ROUND(N30,2) -> 18.25 | P30: ='Source Copy'!$I$36 -> 14.74 | Q30: =IF(H30="Return",-1,1) -> -1 | R30: =M30*Q30 -> -40 | S30: =R30*O30 -> -730 | T30: =R30*P30 -> -589.6 | U30: =S30*$E$3 -> -53.655 | V30: =S30-T30-U30 -> -86.745 | W30: =IF(F30<DATE(YEAR($B$3),MONTH($B$3),DAY($B$3)),"Before snapshot date",IF(F30>DATE(YEAR($B$3),MONTH($B$3),DAY($B$3)),"After cutoff",IF(AND(H30="Return",F30=DATE(YEAR($B$3),MONTH($B$3),DAY($B$3))),"Exact-midnight return","Snapshot-date record"))) -> After cutoff | X30: =IF(OR(W30="Before snapshot date",W30="Exact-midnight return"),"Include","Exclude") -> Exclude | Y30: =IF(W30="Before snapshot date","Include","Exclude") -> Exclude | Z30: =IF(W30="After cutoff","Excluded in both: after cutoff",IF(W30="Exact-midnight return","Selected include / alternate exclude","Included in both scenarios")) -> Excluded in both: after cutoff | AA30: Source Copy!A36
A31: ='Source Copy'!$A$37 -> WHR-DE-009 | B31: ='Source Copy'!$B$37 -> BR-DE | C31: =UPPER(TRIM(B31)) -> BR-DE | D31: =IFERROR(INDEX('Source Copy'!$B$12:$B$15,MATCH(C31,'Source Copy'!$A$12:$A$15,0)),"Unmapped") -> Germany | E31: ='Source Copy'!$C$37 -> 2027-03-02T06:45:00Z | F31: 46448.281 | G31: ISO UTC timestamp parsed | H31: ='Source Copy'!$D$37 -> Sale | I31: ='Source Copy'!$E$37 -> QH-AR-10 | J31: ='Source Copy'!$J$37 -> DE-44152 | K31: ='Source Copy'!$F$37 -> 9 | L31: ='Source Copy'!$G$37 -> 24 | M31: =K31*L31 -> 216 | N31: ='Source Copy'!$H$37 -> 23.47 | O31: =ROUND(N31,2) -> 23.47 | P31: ='Source Copy'!$I$37 -> 18.15 | Q31: =IF(H31="Return",-1,1) -> 1 | R31: =M31*Q31 -> 216 | S31: =R31*O31 -> 5069.52 | T31: =R31*P31 -> 3920.4 | U31: =S31*$E$3 -> 372.60972 | V31: =S31-T31-U31 -> 776.51028 | W31: =IF(F31<DATE(YEAR($B$3),MONTH($B$3),DAY($B$3)),"Before snapshot date",IF(F31>DATE(YEAR($B$3),MONTH($B$3),DAY($B$3)),"After cutoff",IF(AND(H31="Return",F31=DATE(YEAR($B$3),MONTH($B$3),DAY($B$3))),"Exact-midnight return","Snapshot-date record"))) -> After cutoff | X31: =IF(OR(W31="Before snapshot date",W31="Exact-midnight return"),"Include","Exclude") -> Exclude | Y31: =IF(W31="Before snapshot date","Include","Exclude") -> Exclude | Z31: =IF(W31="After cutoff","Excluded in both: after cutoff",IF(W31="Exact-midnight return","Selected include / alternate exclude","Included in both scenarios")) -> Excluded in both: after cutoff | AA31: Source Copy!A37
A32: ='Source Copy'!$A$38 -> WHR-DE-010 | B32: ='Source Copy'!$B$38 -> KS-DE | C32: =UPPER(TRIM(B32)) -> KS-DE | D32: =IFERROR(INDEX('Source Copy'!$B$12:$B$15,MATCH(C32,'Source Copy'!$A$12:$A$15,0)),"Unmapped") -> Germany | E32: ='Source Copy'!$C$38 -> 2027-02-12T11:10:00Z | F32: 46430.465 | G32: ISO UTC timestamp parsed | H32: ='Source Copy'!$D$38 -> Sale | I32: ='Source Copy'!$E$38 -> QH-PL-60 | J32: ='Source Copy'!$J$38 -> DE-44135 | K32: ='Source Copy'!$F$38 -> 10 | L32: ='Source Copy'!$G$38 -> 12 | M32: =K32*L32 -> 120 | N32: ='Source Copy'!$H$38 -> 31.8 | O32: =ROUND(N32,2) -> 31.8 | P32: ='Source Copy'!$I$38 -> 26.17 | Q32: =IF(H32="Return",-1,1) -> 1 | R32: =M32*Q32 -> 120 | S32: =R32*O32 -> 3816 | T32: =R32*P32 -> 3140.4 | U32: =S32*$E$3 -> 280.476 | V32: =S32-T32-U32 -> 395.124 | W32: =IF(F32<DATE(YEAR($B$3),MONTH($B$3),DAY($B$3)),"Before snapshot date",IF(F32>DATE(YEAR($B$3),MONTH($B$3),DAY($B$3)),"After cutoff",IF(AND(H32="Return",F32=DATE(YEAR($B$3),MONTH($B$3),DAY($B$3))),"Exact-midnight return","Snapshot-date record"))) -> Before snapshot date | X32: =IF(OR(W32="Before snapshot date",W32="Exact-midnight return"),"Include","Exclude") -> Include | Y32: =IF(W32="Before snapshot date","Include","Exclude") -> Include | Z32: =IF(W32="After cutoff","Excluded in both: after cutoff",IF(W32="Exact-midnight return","Selected include / alternate exclude","Included in both scenarios")) -> Included in both scenarios | AA32: Source Copy!A38

Sheet Method
A1: Method and Assumption Register
A2: Corrected model basis | Frozen snapshot 27 February 2027 | Currency: EUR
A4: Source facts, interpretation, scenario choice, and calculation rules
A5: Topic | B5: Classification | C5: Source field / record | D5: Treatment used in the corrected model
A6: Source scope and markets | B6: Sourced fact | C6: Source Copy!D7; Customer map Source Copy!A12:D15 | D6: The frozen snapshot boundary is 27 February 2027. The supplied account map covers France and Germany; records are kept in separate country sheets after the account join.
A7: Proposal term and commercial guardrail | B7: Sourced fact | C7: Proposed rebate Source Copy!D6; guardrail Source Copy!F6; currency Source Copy!B6 | D7: The model applies the sourced proposed rebate of 7.35% to signed gross sales and compares each contribution-margin percentage with the sourced 13.3% guardrail. Currency is EUR.
A8: Account-key matching | B8: Analyst interpretation / correction | C8: Transaction Cust ID and Customer map Cust ID in Source Copy!A19:L38 | D8: For every transaction, the join key is TRIM(UPPER(original account key)): surrounding whitespace is removed and case is made consistent. The original account-key string remains visible next to the normalized key in each detail sheet.
A9: Mixed timestamp representations | B9: Analyst interpretation | C9: Transaction timestamp in Source Copy!A19:L38; affected record WHR-FR-001 | D9: ISO-form timestamps ending in Z are parsed as UTC. The slash-form text 04/03/2026 08:15 is genuinely ambiguous; it is read as DD/MM/YYYY (4 March 2026, 08:15). An MM/DD reading would be 3 April 2026, also before the cutoff, so the record is retained under either reading. Original text and parsed timestamp are both displayed.
A10: Cutoff and exact-midnight return | B10: Scenario choice | C10: Frozen snapshot date Source Copy!D7; WHR-FR-008 transaction timestamp 2027-02-27T00:00:00Z | D10: Selected scenario: interpret the stated snapshot date as calendar-date inclusive, so the return at exactly 00:00 on 27 February 2027 is included. Alternate sensitivity: interpret the frozen snapshot as a start-of-day boundary and exclude only that return. Later records are excluded in both scenarios. The source does not control this timestamp convention, so both treatments remain visible.
A11: Commercial quantity basis | B11: Sourced field plus calculated rule | C11: Qty Shipped, Pack size, and Shipment ref in Source Copy!A19:L38 | D11: Individual units are the commercial quantity basis: calculated individual units = source pack quantity multiplied by source pack size. Qty Shipped is packs, not individual units. Shipment references identify dispatches only and are not quantities sold; multiple lines sharing a shipment remain separate economic records.
A12: Unit-rate precision | B12: Sourced fact plus analyst correction | C12: Rate-card precision Source Copy!B7; Unit rate (EUR), including WHR-FR-002 and WHR-DE-002 | D12: The source rate-card convention is EUR 0.01 per individual unit. The commercial unit rate is ROUND(source unit rate, 2); therefore 23.4700003 is treated as EUR 23.47, the same commercial price as 23.47. Machine-level floating-point residue is not presented as a separate price or product.
A13: Returns and signs | B13: Calculated rule | C13: Event field in Source Copy!A19:L38; return IDs WHR-FR-004, WHR-FR-008, WHR-DE-004, WHR-DE-008 | D13: Sale events use sign +1 and Return events use sign -1. Returns reverse individual units, gross sales, cost, rebate value, and contribution; a source record remains one line and is never duplicated as a sale.
A14: Financial equations | B14: Calculated rule | C14: Visible country detail formulas and sourced rates/costs/proposal term | D14: Signed gross sales = signed individual units x commercial unit rate. Signed cost = signed individual units x source unit cost. Signed rebate = signed gross sales x proposed rebate. Contribution margin = net sales - net cost - rebate. Contribution margin % = contribution margin / net sales.
A15: Commercial defensibility comparison | B15: Calculated rule | C15: Sourced guardrail Source Copy!F6; Executive Summary selected table | D15: The result is commercially defensible only where the selected contribution-margin percentage is at or above the supplied commercial guardrail. The workbook reports that comparison as evidence and does not prescribe an action, negotiation position, or supplier choice.
A16: Data boundary | B16: Scope statement | C16: Supplied workbook only | D16: No external market information, rates, accounts, transactions, or financial values are introduced. Sourced facts, formulas, and analyst interpretation are distinguished in this register and in the detailed audit columns.

Sheet Change Log
A1: Change Log - Corrected Wholesale Rebate Model
A2: Corrections made to the existing model extract; supplied source material is retained unchanged on Source Copy.
A4: Correction record and source-to-output mapping
A5: Change ID | B5: Correction area | C5: Existing-model issue observed | D5: Corrected treatment | E5: Affected source field / record | F5: Output fields / impact
A6: CL-01 | B6: Snapshot cutoff and midnight return | C6: The existing extract says transactions before 27 Feb 2027 and does not make the exact boundary treatment auditable. | D6: Selected calendar-date-inclusive treatment includes the exact-midnight return; the alternate frozen-boundary sensitivity excludes only it. Post-cutoff records remain excluded. | E6: Frozen snapshot date Source Copy!D7; WHR-FR-008 Transaction timestamp = 2027-02-27T00:00:00Z | F6: France columns W:Y; France scenario totals; Executive Summary selected and alternate blocks.
A7: CL-02 | B7: Timestamp parsing | C7: The transaction timestamp column mixes ISO UTC text with one ambiguous slash-form value, with no calculation timestamp in the existing extract. | D7: Original timestamp text is retained. ISO values are parsed as UTC; 04/03/2026 08:15 is interpreted DD/MM/YYYY for calculation and disclosed as an ambiguity. | E7: Transaction timestamp in Source Copy!A19:L38; affected record WHR-FR-001 | F7: France and Germany columns E:G; Method mixed-timestamp register entry.
A8: CL-03 | B8: Account-key normalization and market assignment | C8: The existing extract presents raw account-key matching, while source transaction keys include case and surrounding-whitespace variants. | D8: Account join uses TRIM(UPPER(Cust ID)) against the supplied customer map. Original keys are retained and each normalized key maps to exactly one market. | E8: Cust ID in transaction detail and Customer map; examples WHR-FR-002, WHR-FR-010, WHR-DE-002, WHR-DE-006, WHR-DE-009. | F8: France/Germany columns B:D; country separation and all country totals.
A9: CL-04 | B9: Pack-to-unit quantity basis and shipment references | C9: The existing extract identifies Qty Shipped as its volume basis; a pack count or a distinct-shipment count is not an individual-unit sales basis. | D9: Calculated individual units = Qty Shipped packs x Pack size. Shipment refs are identifiers only; shared shipment FR-61084 remains two separate source lines. | E9: Qty Shipped, Pack size, Shipment ref in Source Copy!A19:L38; shared shipment rows WHR-FR-001 and WHR-FR-002. | F9: France/Germany columns J:M and R; scenario totals Net individual units.
A10: CL-05 | B10: Floating-point unit-rate precision | C10: The source unit-rate column includes a machine-residue representation next to a cents-level commercial rate. | D10: Commercial rate rounds to the supplied EUR 0.01 rate-card precision; 23.4700003 is treated as EUR 23.47, not a separate price. | E10: Rate-card precision Source Copy!B7; Unit rate (EUR) on WHR-FR-002 and WHR-DE-002. | F10: France/Germany columns N:O and signed gross-sales/rebate/contribution calculations.
A11: CL-06 | B11: Return signs and line-level economics | C11: The existing extract does not show signed return economics or a line-to-summary audit trail. | D11: Return events use a negative sign for units, sales, cost, rebate, and contribution. Each source record remains one economic line in its own normalized market. | E11: Event field in Source Copy!A19:L38; returns WHR-FR-004, WHR-FR-008, WHR-DE-004, WHR-DE-008. | F11: France/Germany columns Q:V and scenario inclusion columns W:Y; Executive Summary totals.

Sheet Source Copy
A1: Willowmere Components | Wholesale Rebate Review
A2: Frozen market snapshot - 27 February 2027 | Quillhaven Solutions
A4: Proposal & commercial terms | H4: Existing model extract
A5: Prepared by | B5: Lidia Sinclair | C5: Challenge logged | D5: 46449 | E5: Raised by | F5: Antoni Alcantara | H5: Basis | I5: Recorded value
A6: Currency | B6: EUR | C6: Proposed rebate | D6: 0.0735 | E6: Commercial CM guardrail | F6: 0.133 | H6: Filter note | I6: transactions before 27 Feb 2027
A7: Rate-card precision | B7: EUR 0.01 per individual unit | C7: Frozen snapshot date | D7: 46445 | E7: Export timestamp | F7: 2027-02-27 18:10 UTC | H7: Volume basis | I7: Qty Shipped
H8: Account lookup | I8: account key
H9: France CM % | I9: 0.141
A10: Customer map | H10: Germany CM % | I10: 0.128
A11: Cust ID | B11: Market | C11: customer_name | D11: Map Ref | H11: Combined CM % | I11: 0.135
A12: LA-FR | B12: France | C12: Lanterne Assemblage SAS | D12: MAP-FR-01 | H12: Review state | I12: Pending correction
A13: MV-FR | B13: France | C13: Montvarin Electrique | D13: MAP-FR-02
A14: BR-DE | B14: Germany | C14: Bredenau Werke GmbH | D14: MAP-DE-01
A15: KS-DE | B15: Germany | C15: Kestel Schalttechnik GmbH | D15: MAP-DE-02
A17: Transaction detail - ERP snapshot
A18: Record ID | B18: Cust ID | C18: Transaction timestamp | D18: Event | E18: Product code | F18: Qty Shipped | G18: Pack size | H18: Unit rate (EUR) | I18: Unit cost (EUR) | J18: Shipment ref | K18: Entered by | L18: Line memo
A19: WHR-FR-001 | B19: LA-FR | C19: 04/03/2026 08:15 | D19: Sale | E19: QH-AR-10 | F19: 12 | G19: 24 | H19: 23.47 | I19: 18.15 | J19: FR-61084 | K19: m.choi
A20: WHR-FR-002 | B20: la-fr | C20: 2026-11-18T09:40:00Z | D20: Sale | E20: QH-AR-10 | F20: 8 | G20: 24 | H20: 23.47 | I20: 18.15 | J20: FR-61084 | K20: m.choi | L20: repeat dispatch
A21: WHR-FR-003 | B21: MV-FR | C21: 2026-12-05T14:05:00Z | D21: Sale | E21: QH-PL-60 | F21: 15 | G21: 12 | H21: 31.8 | I21: 26.17 | J21: FR-61088 | K21: l.bertin
A22: WHR-FR-004 | B22: mv-fr | C22: 2027-01-11T11:25:00Z | D22: Return | E22: QH-PL-60 | F22: 2 | G22: 12 | H22: 31.8 | I22: 26.17 | J22: FR-RMA-121 | K22: l.bertin | L22: seal issue
A23: WHR-FR-005 | B23: LA-FR | C23: 2027-02-08T08:10:00Z | D23: Sale | E23: QH-AR-10 | F23: 10 | G23: 24 | H23: 23.47 | I23: 18.15 | J23: FR-61115 | K23: m.choi
A24: WHR-FR-006 | B24: la-fr | C24: 2027-02-20T15:20:00Z | D24: Sale | E24: QH-AR-10 | F24: 6 | G24: 24 | H24: 23.47 | I24: 18.15 | J24: FR-61120 | K24: m.choi
A25: WHR-FR-007 | B25: MV-FR | C25: 2027-02-26T16:15:00Z | D25: Sale | E25: QH-PL-60 | F25: 7 | G25: 12 | H25: 31.8 | I25: 26.17 | J25: FR-61127 | K25: l.bertin
A26: WHR-FR-008 | B26: mv-fr | C26: 2027-02-27T00:00:00Z | D26: Return | E26: QH-PL-60 | F26: 8 | G26: 12 | H26: 31.8 | I26: 26.17 | J26: FR-RMA-131 | K26: l.bertin
A27: WHR-FR-009 | B27: LA-FR | C27: 2027-03-01T10:00:00Z | D27: Sale | E27: QH-AR-10 | F27: 9 | G27: 24 | H27: 23.47 | I27: 18.15 | J27: FR-61144 | K27: m.choi | L27: late posting
A28: WHR-FR-010 | B28: la-fr | C28: 2027-02-14T13:45:00Z | D28: Sale | E28: QH-MT-05 | F28: 20 | G28: 10 | H28: 18.25 | I28: 14.74 | J28: FR-61118 | K28: p.doyle
A29: WHR-DE-001 | B29: BR-DE | C29: 2026-10-10T07:30:00Z | D29: Sale | E29: QH-AR-10 | F29: 10 | G29: 24 | H29: 23.47 | I29: 18.15 | J29: DE-44091 | K29: a.voss
A30: WHR-DE-002 | B30: br-de | C30: 2026-11-26T10:45:00Z | D30: Sale | E30: QH-AR-10 | F30: 7 | G30: 24 | H30: 23.47 | I30: 18.15 | J30: DE-44092 | K30: a.voss
A31: WHR-DE-003 | B31: KS-DE | C31: 2026-12-22T12:00:00Z | D31: Sale | E31: QH-PL-60 | F31: 18 | G31: 12 | H31: 31.8 | I31: 26.17 | J31: DE-44110 | K31: s.ahn
A32: WHR-DE-004 | B32: ks-de | C32: 2027-01-18T09:50:00Z | D32: Return | E32: QH-PL-60 | F32: 3 | G32: 12 | H32: 31.8 | I32: 26.17 | J32: DE-RMA-061 | K32: s.ahn
A33: WHR-DE-005 | B33: br-de | C33: 2027-02-05T17:25:00Z | D33: Sale | E33: QH-MT-05 | F33: 24 | G33: 10 | H33: 18.25 | I33: 14.74 | J33: DE-44133 | K33: a.voss
A34: WHR-DE-006 | B34: KS-DE | C34: 2027-02-23T10:15:00Z | D34: Sale | E34: QH-PL-60 | F34: 8 | G34: 12 | H34: 31.8 | I34: 26.17 | J34: DE-44138 | K34: s.ahn
A35: WHR-DE-007 | B35: BR-DE | C35: 2027-02-26T22:59:00Z | D35: Sale | E35: QH-AR-10 | F35: 4 | G35: 24 | H35: 23.47 | I35: 18.15 | J35: DE-44140 | K35: a.voss
A36: WHR-DE-008 | B36: ks-de | C36: 2027-02-28T01:05:00Z | D36: Return | E36: QH-MT-05 | F36: 4 | G36: 10 | H36: 18.25 | I36: 14.74 | J36: DE-RMA-068 | K36: s.ahn
A37: WHR-DE-009 | B37: BR-DE | C37: 2027-03-02T06:45:00Z | D37: Sale | E37: QH-AR-10 | F37: 9 | G37: 24 | H37: 23.47 | I37: 18.15 | J37: DE-44152 | K37: a.voss | L37: late posting
A38: WHR-DE-010 | B38: KS-DE | C38: 2027-02-12T11:10:00Z | D38: Sale | E38: QH-PL-60 | F38: 10 | G38: 12 | H38: 31.8 | I38: 26.17 | J38: DE-44135 | K38: s.ahn
A40: Export footer | B40: Wholesale Ledger v4.2 | snapshot generated 2027-02-27 18:10 UTC
A41: Line memo | B41: Some export memo fields are blank.
