Workbook

Sheet Decision Summary
A1: Inglewood Institute - Customer Case Response
A2: Prepared by Jelena Desrosiers | Pinehollow Energy, Commercial Equipment
A4: Case and Decision Control
A5: Customer | B5: Inglewood Institute | E5: Compliance reviewer | F5: Efua Calloway
A6: Case owner | B6: Jelena Desrosiers | E6: Approval authority | F6: Gitta Rutkowski, Operations Manager
A7: Jurisdiction | B7: England and Wales | E7: Currency | F7: GBP
A8: Freight snapshot | B8: 8 April 2030 | E8: Decision status | F8: PENDING GITTA RUTKOWSKI APPROVAL
A10: Approval Record - Complete Only After Decision
A11: Approver name | E11: Pending approval
A12: Approval decision | E12: Pending approval
A13: Approval date | E13: Pending approval
A14: Signature | E14: Pending approval
A16: Recommendation
A17: Recommend Gitta Rutkowski approve Option B - credit and replacement, subject to recorded approval.
A19: Confirmed replacement quantity | B19: ='Option Comparison'!C21 -> 27 | D19: individual stands | F19: Control | G19: Pending recorded approval
A20: Proposed cash credit | B20: ='Option Comparison'!C27 -> 398.82 | D20: GBP | F20: Control | G20: Pending recorded approval
A21: Replacement merchandise value | B21: ='Option Comparison'!C22 -> 2383.25 | D21: GBP | F21: Control | G21: Pending recorded approval
A22: Replacement freight borne by Pinehollow | B22: ='Option Comparison'!C24 -> 413.49 | D22: GBP | F22: Control | G22: Pending recorded approval
A23: Estimated Pinehollow outlay | B23: ='Option Comparison'!C30 -> 2294.31 | D23: GBP | F23: Control | G23: Pending recorded approval
A24: Incremental outlay versus Option A | B24: ='Option Comparison'!B32 -> 398.82 | D24: GBP | F24: Control | G24: Cash-credit increment
A26: Selected Interpretation and Review Rationale
A27: Selected merchandise-credit basis: eligible damaged individual stands. CT-7.1 ties a price adjustment to affected goods and final receiving evidence; REV-02 leaves both eligible-damage and normalised-invoiced readings open. This evidence-led reading credits only final eligible damage and avoids extending a damage-linked credit to accepted or unaffected units.
A29: Date treatment: the mixed receiving entry 06/04/30 is interpreted as 6 April 2030 (day/month/year), consistent with the England and Wales terms and the surrounding 5-7 April 2030 chronology.
A32: Tradeoffs and Release Control
A33: Service: restores 27 confirmed eligible damaged stands in one Friday 12 April 2030 consolidated release. Evidence: applies receiving-note overrides, corrected shipment routes, contracted per-stand pricing, and the 8 April 2030 snapshot. Cost: Option B adds £398.82 to Pinehollow outlay versus replacement only, matching the substantiated cash credit. Timing and control: Gitta's decision is due by 16:00 Thursday 11 April 2030; credit, customer communication, and release remain pending her recorded approval.
A37: Trace: INV-77421 / INV-77422; REC-9401 to REC-9404; FL-2030-4810 / FL-2030-4811; REV-01 to REV-06; CT-4.1, CT-4.2, CT-6.3, CT-7.1 and CT-8.2.

Sheet Reconciliation
A1: Evidence Reconciliation
A2: Source pack references retained; quantities compared in individual stands and freight counted once per shipment.
A4: A. Product Mapping and Quantity Reconciliation
A5: Source order / invoice line | B5: Product code | C5: PO / order label | D5: Invoice label | E5: Invoice qty | F5: Qty basis | G5: Pack size (stands) | H5: Normalised invoiced stands | I5: Receiving records / source trace
A6: PH-IO-2030-118 / INV-77421 line 10 | B6: MD-ALP-8 | C6: Atlas 8-stand carton | D6: MDS Atlas display stand pack | E6: 5 | F6: packs | G6: 8 | H6: =IF(F6="packs",E6*G6,E6) -> 40 | I6: SO-118 / Inv ln 10; REC-9401
A7: PH-IO-2030-118 / INV-77421 line 20 | B7: MD-VRT-1 | C7: Vertex single display stand | D7: Vertex modular display unit | E7: 27 | F7: individual stands | G7: 1 | H7: =IF(F7="packs",E7*G7,E7) -> 27 | I7: SO-118 / Inv ln 20; REC-9402
A8: PH-IO-2030-119 / INV-77422 line 10 | B8: MD-NEX-4 | C8: Nexus 4-stand kit | D8: Nexus display stand quad | E8: 6 | F8: packs | G8: 4 | H8: =IF(F8="packs",E8*G8,E8) -> 24 | I8: SO-119 / Inv ln 10; REC-9403, REC-9404
A10: B. Price Adjustment and Replacement Basis
A11: Product code | B11: Contract GBP / stand | C11: Billed GBP / stated basis | D11: Billed GBP / stand | E11: Positive difference GBP / stand | F11: Internal repl. cost GBP / stand | G11: Note-adjusted eligible damaged stands | H11: Replacement qty stands | I11: Selected credit qty stands | J11: Merchandise credit GBP | K11: Evidence / decision reference
A12: MD-ALP-8 | B12: 86.5 | C12: 795.2 | D12: =C12/Reconciliation!G6 -> 99.4 | E12: =MAX(D12-B12,0) -> 12.9 | F12: 54.25 | G12: 19 | H12: =G12 -> 19 | I12: =G12 -> 19 | J12: =ROUND(E12*I12,2) -> 245.1 | K12: CT-4.1 / CT-7.1 / REV-02; receiving-note basis
A13: MD-VRT-1 | B13: 104 | C13: 116.6 | D13: =C13/Reconciliation!G7 -> 116.6 | E13: =MAX(D13-B13,0) -> 12.6 | F13: 64 | G13: 5 | H13: =G13 -> 5 | I13: =G13 -> 5 | J13: =ROUND(E13*I13,2) -> 63 | K13: CT-4.1 / CT-7.1 / REV-02; receiving-note basis
A14: MD-NEX-4 | B14: 73.25 | C14: 321 | D14: =C14/Reconciliation!G8 -> 80.25 | E14: =MAX(D14-B14,0) -> 7 | F14: 43.75 | G14: 3 | H14: =G14 -> 3 | I14: =G14 -> 3 | J14: =ROUND(E14*I14,2) -> 21 | K14: CT-4.1 / CT-7.1 / REV-02; receiving-note basis
I16: Merchandise credit subtotal | J16: =SUM(J12:J14) -> 329.1
A18: C. Shipment Freight Reconciliation
A19: Shipment ID | B19: Invoice no. | C19: Source zone / service label | D19: Route-note resolution | E19: Contract merchandise value GBP | F19: Snapshot rate | G19: Allowed freight GBP | H19: Billed freight GBP | I19: Original freight overcharge credit GBP | J19: Count control | K19: Source evidence / note
A20: SHP-4810 | B20: INV-77421 | C20: London Inner / Priority 12 | D20: EM-2 East Midlands / EXP-12 | E20: 6268 | F20: 0.1735 | G20: =ROUND(E20*F20,2) -> 1087.5 | H20: 1130 | I20: =MAX(H20-G20,0) -> 42.5 | J20: One amount per shipment | K20: Freight ledger FL-2030-4810; FS-01; Scan exception: delivery route recorded as East Midlands (EM-2); use EM-2 with EXP-12.
A21: SHP-4811 | B21: INV-77422 | C21: Central South / Std service 48 | D21: NM-4 North Midlands / STD-48 | E21: 1758 | F21: 0.1125 | G21: =ROUND(E21*F21,2) -> 197.78 | H21: 225 | I21: =MAX(H21-G21,0) -> 27.22 | J21: One amount per shipment | K21: Freight ledger FL-2030-4811; FS-02; Manifest amendment: route confirmed North Midlands (NM-4); retain STD-48 service code.
H23: Original freight credit subtotal | I23: =SUM(I20:I21) -> 69.72
A25: D. Receiving Evidence Normalisation
A26: Receiving record | B26: Source date / time | C26: Normalised date / time | D26: Shipment ID | E26: Product code | F26: Recorded description | G26: Main damage qty / unit | H26: Main status | I26: Note-resolved remedy qty stands | J26: Final eligibility | K26: Note / evidence reference
A27: REC-9401 | B27: 2030-04-05 09:35 | C27: 05 Apr 2030 09:35 | D27: SHP-4810 | E27: MD-ALP-8 | F27: Atlas display carton | G27: 3 cartons | H27: Eligible replacement | I27: 19 | J27: Eligible - note override | K27: Dock recount: confirmed remedy quantity is 19 individual stands; one carton partly recoverable. [PHOTO-ING-05-1]
A28: REC-9402 | B28: 06/04/30 | C28: 06 Apr 2030 | D28: SHP-4810 | E28: MD-VRT-1 | F28: Vertex stand | G28: 5 individual stands | H28: Eligible replacement | I28: 5 | J28: Eligible | K28: Five individual stands crushed; customer held pending remedy. [PHOTO-ING-06-A to C]
A29: REC-9403 | B29: 2030-04-06 15:18 | C29: 06 Apr 2030 15:18 | D29: SHP-4811 | E29: MD-NEX-4 | F29: Nexus floor stand | G29: 4 individual stands | H29: Eligible replacement | I29: 0 | J29: Ineligible - accepted after inspection | K29: Accepted after inspection; cosmetic marks accepted by Inglewood. Do not replace or credit as damage. [REC-9403 follow-up]
A30: REC-9404 | B30: 2030-04-07 08:20 | C30: 07 Apr 2030 08:20 | D30: SHP-4811 | E30: MD-NEX-4 | F30: Nexus floor unit | G30: 3 individual stands | H30: Eligible replacement | I30: 3 | J30: Eligible | K30: Confirmed bent legs; eligible for replacement. [PHOTO-ING-07-2]
A32: Control note: all receiving-row notes have been applied before eligibility, replacement, or credit aggregation. REC-9402 is read as 6 April 2030 under the England and Wales date context.

Sheet Option Comparison
A1: Remedy Options
A2: Both options use the same note-adjusted replacement schedule and one consolidated replacement shipment.
A4: Replacement Schedule
A5: Product code | B5: Product / invoice label | C5: Eligible replacement qty stands | D5: Contract GBP / stand | E5: Replacement merchandise value GBP | F5: Internal repl. cost GBP / stand | G5: Estimated internal replacement cost GBP
A6: MD-ALP-8 | B6: MDS Atlas display stand pack | C6: =Reconciliation!H12 -> 19 | D6: =Reconciliation!B12 -> 86.5 | E6: =ROUND(C6*D6,2) -> 1643.5 | F6: =Reconciliation!F12 -> 54.25 | G6: =ROUND(C6*F6,2) -> 1030.75
A7: MD-VRT-1 | B7: Vertex modular display unit | C7: =Reconciliation!H13 -> 5 | D7: =Reconciliation!B13 -> 104 | E7: =ROUND(C7*D7,2) -> 520 | F7: =Reconciliation!F13 -> 64 | G7: =ROUND(C7*F7,2) -> 320
A8: MD-NEX-4 | B8: Nexus display stand quad | C8: =Reconciliation!H14 -> 3 | D8: =Reconciliation!B14 -> 73.25 | E8: =ROUND(C8*D8,2) -> 219.75 | F8: =Reconciliation!F14 -> 43.75 | G8: =ROUND(C8*F8,2) -> 131.25
B10: Total | C10: =SUM(C6:C8) -> 27 | E10: =SUM(E6:E8) -> 2383.25 | G10: =SUM(G6:G8) -> 1482
A12: Consolidated Replacement Freight Plan
A13: Release plan | B13: One consolidated shipment | D13: Source | E13: REV-03 / CT-6.3
A14: Route / service | B14: EM-2 / EXP-12 | D14: Snapshot line | E14: FS-01
A15: Snapshot date | B15: 8 April 2030 | D15: Tariff | E15: 0.1735
A16: Freight basis | B16: =E10 -> 2383.25 | D16: Replacement freight GBP | E16: =ROUND(B16*E15,2) -> 413.49
A19: Side-by-Side Remedy Comparison
A20: Metric | B20: Option A - Replacement only | C20: Option B - Credit and replacement | D20: Difference B - A
A21: Replacement quantity (individual stands) | B21: =C10 -> 27 | C21: =C10 -> 27 | D21: =C21-B21 -> 0
A22: Replacement merchandise value (GBP) | B22: =E10 -> 2383.25 | C22: =E10 -> 2383.25 | D22: =C22-B22 -> 0
A23: Replacement freight treatment | B23: Pinehollow bears one consolidated shipment | C23: Pinehollow bears one consolidated shipment | D23: No difference
A24: Replacement freight borne by Pinehollow (GBP) | B24: =E16 -> 413.49 | C24: =E16 -> 413.49 | D24: =C24-B24 -> 0
A25: Merchandise overcharge credit (GBP) | B25: 0 | C25: =Reconciliation!J16 -> 329.1 | D25: =C25-B25 -> 329.1
A26: Original freight overcharge credit (GBP) | B26: 0 | C26: =Reconciliation!I23 -> 69.72 | D26: =C26-B26 -> 69.72
A27: Cash credit (GBP) | B27: 0 | C27: =ROUND(C25+C26,2) -> 398.82 | D27: =C27-B27 -> 398.82
A28: Total customer remedy value (GBP) | B28: =ROUND(B22+B24+B27,2) -> 2796.74 | C28: =ROUND(C22+C24+C27,2) -> 3195.56 | D28: =C28-B28 -> 398.82
A29: Estimated internal replacement merchandise cost (GBP) | B29: =G10 -> 1482 | C29: =G10 -> 1482 | D29: =C29-B29 -> 0
A30: Estimated Pinehollow outlay (GBP) | B30: =ROUND(B29+B24+B27,2) -> 1895.49 | C30: =ROUND(C29+C24+C27,2) -> 2294.31 | D30: =C30-B30 -> 398.82
A32: Displayed outlay difference (Option B - Option A) | B32: =C30-B30 -> 398.82
A34: Recommendation: Option B is proposed because it restores confirmed damage and returns the supported merchandise and original-freight overcharges. Approval remains pending.

Sheet Customer Response
A1: Customer-Ready Revised Response
A2: Draft for release after approval - do not send while status is pending.
A4: To | B4: Efua Calloway, Compliance Reviewer
A5: From | B5: Jelena Desrosiers, Wholesale Account Representative, Pinehollow Energy
A6: Subject | B6: Revised proposed remedy - disputed modular display-stand order
A7: Status | B7: PENDING GITTA RUTKOWSKI APPROVAL
A10: Dear Efua,
A12: We have reconciled the affected lines in invoices INV-77421 and INV-77422 with receiving records REC-9401 to REC-9404. After applying the inspection notes, this confirms 27 eligible damaged individual stands: 19 MD-ALP-8; 5 MD-VRT-1; 3 MD-NEX-4.
A14: Subject to Gitta Rutkowski's approval, Pinehollow proposes one consolidated replacement release of 27 individual stands on Friday 12 April 2030. The replacement merchandise is valued at £2,383.25 at the contracted per-stand prices. Pinehollow would bear one consolidated replacement freight charge of £413.49, calculated using EM-2 / EXP-12 in the 8 April 2030 freight snapshot.
A16: Our review also substantiates merchandise and original-freight overcharges. Using the selected eligible damaged individual-stand credit basis, Pinehollow proposes a cash credit of £398.82, comprising £329.10 merchandise price adjustment and £69.72 original freight adjustment.
A18: The proposed outcome remains pending Gitta Rutkowski's approval. It is not yet authorized, issued, or released. Following recorded approval, we will confirm the credit, communicate the outcome, and proceed with the Friday release.
A20: Regards, Jelena Desrosiers Wholesale Account Representative Pinehollow Energy, Commercial Equipment
A23: Control reference: CT-8.2; REV-04; REV-05. Send only after the approval record is completed.

Sheet Action Register
A1: Approval and Release Action Register
A2: Execution sequence for the Thursday approval cutoff and Friday release. All unapproved actions remain on hold.
A4: Overall status | B4: PENDING GITTA RUTKOWSKI APPROVAL
A6: Action ID | B6: Next step | C6: Owner / operating function | D6: Due date / time | E6: Dependency | F6: Current status | G6: Evidence / control
A7: ACT-01 | B7: Submit the reconciled recommendation and supporting option comparison for decision. | C7: Jelena Desrosiers, Wholesale account representative | D7: Thu 11 Apr 2030, 15:45 | E7: Reconciliation and recommendation complete | F7: Ready for approval review | G7: REV-01 / REV-02 / REV-04
A8: ACT-02 | B8: Record the approval decision for the recommended credit-and-replacement remedy. | C8: Gitta Rutkowski, Operations Manager | D8: Thu 11 Apr 2030, 16:00 | E8: ACT-01; approval record remains blank until decision | F8: Pending approval | G8: REV-04 / CT-8.2
A9: ACT-03 | B9: Place provisional inventory lock for 19 MD-ALP-8; 5 MD-VRT-1; 3 MD-NEX-4; prepare one EM-2 / EXP-12 dispatch and hold it. | C9: Ivo Novotny, Operations release | D9: Thu 11 Apr 2030, 15:00 | E9: Confirmed replacement schedule; no dispatch before ACT-02 | F9: Prepared / hold pending approval | G9: REV-03 / REV-06 / CT-6.3
A10: ACT-04 | B10: Set up and issue the £398.82 cash credit in GBP on the same day after approval. | C10: Credit Desk | D10: Thu 11 Apr 2030, same day after approval | E10: ACT-02 recorded approval; selected credit basis and cash-credit calculation | F10: Pending approval | G10: REV-05 / CT-7.1 / CT-8.2
A11: ACT-05 | B11: Send the approved revised outcome and release timing to Efua Calloway. | C11: Jelena Desrosiers, Wholesale account representative | D11: Thu 11 Apr 2030, immediately after ACT-02 | E11: ACT-02 recorded approval; ACT-04 credit reference available | F11: Pending approval | G11: REV-01 / REV-05 / CT-8.2
A12: ACT-06 | B12: Release the one consolidated replacement of 27 individual stands for dispatch. | C12: Ivo Novotny, Operations release | D12: Fri 12 Apr 2030, 09:00 | E12: ACT-02 recorded approval; ACT-03 lock; ACT-05 customer communication | F12: Pending approval | G12: REV-03 / REV-05 / REV-06 / CT-6.3 / CT-8.2
A14: Release gate | B14: No credit issue, customer communication, or dispatch is authorized before Gitta Rutkowski's recorded approval.
