Workbook

Sheet Decision
A1: Wexmoor Press - Returns Control Decision
A2: For Nadia Sepulveda | Retail-site pilot and future enterprise baseline | England and Wales | Legal and policy position as at 8 September 2025
A3: Decision | B3: Operating Procedure | C3: Comparison | D3: Change Log
A5: Recommendation
A6: Approve adoption of the portal-based returns control as the pilot and enterprise baseline, using bounded site-manager delegation for defined routine voluntary-policy cases and central triage for exceptions. Do not implement immediate portal-only central approval: the stronger portal framework is retained, but central-only approval cannot clear forecast peak demand without weakening service or control.
A8: This is an operational control recommendation, not legal advice. Staff must keep voluntary change-of-mind, distance-cancellation, and statutory-remedy assessments separate and escalate uncertainty.
A10: Decision Comparison
A11: Criterion | B11: Current cashier-led process | C11: Proposed portal-only central approval | D11: Approved controlled portal model
A12: Control consistency | B12: Quick, but staff use 'sale date' as payment or collection and there is no common exception log. | C12: One ruleset and central queue; consistent review logic, but every case waits for the sole reviewer. | D12: Portal rules, one case record and mandatory exception capture; local authority is limited to routine, verified voluntary-policy cases.
A13: Customer handling | B13: Immediate interaction, but outcomes can vary between cashiers and rights may be described inconsistently. | C13: Predictable handling, but a peak queue can delay an answer or refund for routine customers. | D13: Routine eligible cases can be resolved at site; exceptions receive a recorded hold, clear explanation and central review.
A14: Auditability | B14: Till evidence is available, but exceptions are not held in a common log and duplicate checks are weak. | C14: Portal record supports traceability, approval evidence and exception reporting. | D14: One Return Case ID or cross-reference, daily dual-system reconciliation and a defined audit record.
A15: Capacity | B15: Site capacity is available, but with unrestricted process variation rather than a controlled decision boundary. | C15: 35 central requests/day against a forecast 60/day peak leaves an unworkable 25 requests/day shortfall; no temporary-cover budget. | D15: Central capacity is reserved for legally sensitive, disputed, ambiguous or exceptional cases; no unrestricted cashier discretion.
A16: Transition feasibility | B16: Familiar today, but it would preserve the ambiguous date and missing-log weaknesses. | C16: Portal phases in 15 September-31 October while valid till slips remain evidence; central-only routing is infeasible at peak. | D16: Transition accepts till-slip and portal evidence, assigns one case ID and reconciles daily; portal is authoritative after 31 October.
A18: Formula-linked Evidence
A19: Measure | B19: Prior / capacity | C19: Current / peak | D19: Decision implication
A20: Central review flow | B20: =Comparison!B40 -> 35 | C20: =Comparison!B41 -> 60 | D20: =C20-B20 -> 25
A21: Confirmed lines | B21: =Comparison!B27 -> 1207 | C21: =Comparison!C27 -> 1311 | D21: =Comparison!D27 -> 104
A22: Confirmed value | B22: =Comparison!B28 -> 72880 | C22: =Comparison!C28 -> 85990 | D22: =Comparison!D28 -> 13110
A23: Exact-duplicate line rate | B23: =Comparison!B31 -> 0.022580645 | C23: =Comparison!C31 -> 0.051079137 | D23: =Comparison!D31 -> 2.8498492
A24: Raw vs confirmed value movement | B24: =Comparison!D29 -> 16660 | C24: =Comparison!D28 -> 13110 | D24: =Comparison!D32 -> 3550
A25: ="Comparison reading: confirmed activity grew (lines +"&TEXT(Comparison!D27,"#,##0")&" / "&TEXT(Comparison!E27,"0.0%")&"; value +£"&TEXT(Comparison!D28,"#,##0")&" / "&TEXT(Comparison!E28,"0.0%")&") while duplicate incidence worsened from "&TEXT(Comparison!B31,"0.0%")&" to "&TEXT(Comparison!C31,"0.0%")&" (+"&TEXT(Comparison!D31,"0.00")&" pp). Raw value rose £"&TEXT(Comparison!D29,"#,##0")&"; confirmed value rose £"&TEXT(Comparison!D28,"#,##0")&". The £"&TEXT(Comparison!D32,"#,##0")&" difference is the increased adjustment burden, not a substitute for confirmed growth." -> Comparison reading: confirmed activity grew (lines +104 / 8.6%; value +£13,110 / 18.0%) while duplicate incidence worsened from 2.3% to 5.1% (+2.85 pp). Raw value rose £16,660; confirmed value rose £13,110. The £3,550 difference is the increased adjustment burden, not a substitute for confirmed growth.
A26: Approval Call
A27: Approval sought this week: approve the controlled portal and triage model for the 15 September-31 October transition and its portal-authoritative end state from 1 November 2025. This replaces the unchanged cashier-led process and avoids infeasible immediate portal-only central approval; implementation remains subject to Nadia Sepulveda's approval of this draft.

Sheet Operating Procedure
A1: Wexmoor Press - Returns Operating Procedure
A2: Approval-ready draft | England and Wales | Legal and policy position as at 8 September 2025 | Applies to retail-site pilot and enterprise baseline
A3: Decision | B3: Operating Procedure | C3: Comparison | D3: Change Log
A4: Document owner | B4: Enterprise Retail Operations Manager, Vellumstone Associates | C4: Approver | D4: Nadia Sepulveda
A5: Version / status | B5: 0.9 | Draft - pending approval | C5: Intended dates | D5: Transition 15 September 2025 to 31 October 2025; end state 1 November 2025
A6: Purpose, scope and audience: control customer returns at Wexmoor Press's retail site during the pilot and as the future enterprise baseline. Used by frontline staff, site managers/delegated approvers, central review and compliance reviewers. It is operational guidance, not legal advice or a complete statement of consumer rights.
A7: Non-negotiable boundary: classify the customer's route before applying the house policy. The 30-day house rule is voluntary change-of-mind policy; statutory remedies and qualifying distance-sale cancellation rights are assessed separately and must not be narrowed by clearance, opening, a broken hygiene seal or expiry of the house-policy window.
A9: A. Classify the Route Before Any Eligibility Decision
A10: Route / check | B10: Staff action | C10: Control and legal qualification | D10: Record / escalation
A11: 1. Voluntary change of mind | B11: Use only where the customer seeks a discretionary return of satisfactory goods. Apply the house rule: verify timely return, credible purchase evidence, unopened goods, relevant product status and delegated authority. | C11: An in-store customer does not generally have a statutory right to return satisfactory goods merely for changing their mind. Apply any available house-policy entitlement, but do not describe it as the full measure of statutory rights. | D11: Record route as 'voluntary'. If the customer mentions a fault, description, fitness or quality issue, stop this route and use route 3.
A12: 2. Distance cancellation / click-and-collect | B12: For a qualifying distance contract, use the separate usual 14-day cancellation period measured from receipt of goods; do not apply it automatically to ordinary in-store sales. For click-and-collect, establish where and how the contract was concluded. | C12: Collection itself does not classify the contract. Distinguish an online purchase completed online from an online reservation completed in store. Escalate unclear channel or cancellation eligibility to central review. | D12: Record channel, contract-conclusion evidence and receipt/collection date. Keep cancellation route separate from voluntary and quality routes.
A13: 3. Quality / defect claim | B13: If goods are alleged faulty, not as described, unfit for purpose or of unsatisfactory quality, route to statutory-remedy assessment. Capture the allegation and any disclosed defect information without promising a remedy. | C13: Do not reject solely because goods are clearance, opened, hygiene-related, seal-broken or outside the voluntary 30-day window. Any Consumer Rights Act short-term right to reject concerns nonconforming goods, has its own conditions/timing and is not an unopened-goods rule or the house policy. | D13: Central review decides disputed, legally sensitive or exceptional statutory cases. Keep goods segregated where appropriate pending assessment.
A14: 4. Date, evidence and product checks | B14: House-policy eligibility date only: immediate in-store supply = date customer takes possession; advance-paid click-and-collect = collection date; delivered order = delivery date. Treat that event as day 0 and count day 1 from the following day through day 30. | C14: This day count is an internal voluntary-policy eligibility rule, not a clock for every statutory remedy. Ask for receipt, order record, payment record or till/order lookup; an original paper receipt is not the only credible evidence. | D14: If purchase evidence or transaction identity cannot be verified, record what was presented and escalate; do not promise approval. Record date basis and date used.
A15: 5. Clearance and hygiene rules | B15: For voluntary change-of-mind only, clearance goods are excluded. A relevant hygiene-sealed personal-care good is excluded only where a suitable hygiene/health-protection seal existed and has been broken. | C15: Do not treat every personal-care item, opened package or hygiene label as an automatic bar. A defect disclosed before sale differs from a different or undisclosed defect; statutory assessment remains available where raised. | D15: Record clearance status, seal presence/broken state and any disclosed-defect wording. Escalate disputed condition or disclosure.
A17: B. Execute, Record and Reconcile the Return
A18: Step / owner | B18: Action | C18: Authority / triage | D18: Record, customer and closure
A19: 1. Intake Frontline staff | B19: Acknowledge the request, inspect the item only as needed for route/condition, collect proportionate evidence and create one Return Case ID before any refund or refusal. Do not collect unnecessary sensitive personal data. | C19: Frontline staff may intake, inspect and record. They do not waive policy conditions, decide statutory disputes or finalise an exception. | D19: Capture original transaction reference, channel, date basis/date, route/reason, item, condition/seal where relevant, evidence source and intake timestamp.
A20: 2. Routine decision Site manager / delegated approver | B20: For a fully verified routine voluntary-policy case, test timeliness, credible proof, unopened condition, clearance/hygiene restriction and prior-refund search. Approve or refuse with a clear reason. | C20: May approve only a routine case that meets every documented house-policy test. Cannot waive time, condition or product exclusions; cannot determine a statutory, disputed, ambiguous or duplicate-risk case. | D20: Record decision, authority, value, refund/refusal outcome and timestamp. Explain the route and reason without suggesting policy removes statutory rights.
A21: 3. Central triage Central reviewer | B21: Queue legally sensitive, disputed, ambiguous or exceptional cases: unclear contract channel, disputed condition/disclosed defect, unresolved transaction identity, suspected duplicate refund, statutory-rights challenge or outside delegated authority. | C21: Central reviewer has final exception authority. Capacity is 35 requests/day against forecast peak 60; no temporary cover is assumed. Routine cases stay within the bounded local authority rather than recreating unrestricted cashier discretion. | D21: Record hold/escalation reason, queue status, reviewer decision and customer update. Do not make a final statutory refusal at site while review is pending.
A22: 4. Refund, stock and closure Approver / frontline | B22: Process approved refund through the controlled route, mark the case outcome, and prevent a second refund. Return only appropriate sellable goods to stock; segregate alleged faulty or uncertain goods pending the relevant assessment. | C22: No unlogged refund. A refusal must be evidence-based, use the correct route and identify escalation where applicable. | D22: Close only after outcome, value, authority and timestamps are recorded and the case is reconciled. Retain no unnecessary sensitive personal data.
A24: C. Migration, End State and Continuity
A25: Period / owner | B25: Required operating model | C25: Anti-duplication and authority control | D25: Record / completion
A26: 15 Sep-31 Oct 2025 Site manager | B26: Accept both valid till-slip and portal evidence while the portal is phased in. Allocate a portal Return Case ID where available; otherwise allocate a controlled transition-log ID and enter/cross-reference it when portal access is available. | C26: Search the portal, transition log and till/refund record before payment. The site manager reconciles Return Case IDs, till slips, refunds, pending central queue and portal entries each day; investigate and hold suspected duplicate payment. | D26: One return must have one case identifier or a documented cross-reference. Capture both evidence references where present and mark the final outcome in the authoritative case record.
A27: From 1 Nov 2025 Site manager / central review | B27: The portal is the authoritative returns register. Routine approvals remain limited to the defined delegated path and are entered in the portal; exception classes remain in the central-review queue. | C27: Do not revert to a silent till-only process. Continue duplicate search before refund and close cases only after portal record and outcome are complete. | D27: Use the portal record for audit reporting, exception review and reconciliation; retain supporting evidence reference rather than unnecessary personal data.
A28: Portal outage Site manager | B28: Use the controlled outage queue with a pre-assigned Return Case ID, full minimum record and evidence reference. Apply the same route and authority limits; no unlogged refund or exception waiver. | C28: On restoration, enter every queued record into the portal, cross-reference the outage ID and reconcile any refund before closure. Escalate duplicate-risk or missing-identity cases. | D28: Record outage start/end, portal capture timestamp and reconciler. Keep the queue available for audit until reconciliation is complete.
A30: Minimum return record: Return Case ID; original transaction reference; channel and contract/date basis; route/reason; item and relevant seal/condition; purchase evidence reference; decision and authority; value; refund/refusal/hold outcome; intake, decision and closure timestamps; transition/outage cross-reference where used. Keep data proportionate and do not solicit unnecessary sensitive personal data.
A32: Escalation destination and holding action: central review for unclear channel, disputed condition or disclosed defect, unresolved transaction identity, suspected duplicate refund, customer challenge involving statutory rights, or any case outside delegated authority. Record the hold and customer communication; do not leave the case at a dead end or present a policy refusal as a legal conclusion.

Sheet Comparison
A1: Wexmoor Press - Returns Comparison and Data Adjustment
A2: Recoverable period summaries | 1 Mar-31 May 2024 vs 1 Mar-31 May 2025 | Inputs are shaded yellow; editable formulas are shaded green
A3: Decision | B3: Operating Procedure | C3: Comparison | D3: Change Log
A4: Method: remove each exact duplicate once. Duplicate and malformed-ID groups are non-overlapping. Unambiguously linked malformed-ID records remain in the confirmed population; unresolved malformed-ID records remain visible but are excluded from confirmed figures without being treated as proven invalid transactions.
A5: Scope limitation: no line-level re-export was available before sign-off. These summaries do not support invented transaction-level facts, product, customer, reason, channel or approval conclusions. England and Wales operational context as at 8 September 2025.
A7: A. Supplied Summary Inputs and Reconciliation
A8: Component | B8: 2024 lines | C8: 2024 value | D8: 2025 lines | E8: 2025 value | F8: Treatment / trace
A9: Raw recoverable comparison population | B9: 1240 | C9: 74880 | D9: 1390 | E9: 91540 | F9: Starting population in the recoverable comparison summary.
A10: Exact duplicate lines | B10: 28 | C10: 1680 | D10: 71 | E10: 4870 | F10: Remove once from confirmed population. This group does not overlap with malformed IDs.
A11: Malformed-ID population | B11: 14 | C11: 910 | D11: 23 | E11: 1740 | F11: Reconciled below; malformed ID alone is not a reason to remove a linked record.
A12: Linked unambiguously | B12: 9 | C12: 590 | D12: 15 | E12: 1060 | F12: Retain in confirmed population; original ID was malformed but link is unambiguous.
A13: Unresolved | B13: 5 | C13: 320 | D13: 8 | E13: 680 | F13: Separate unresolved population. Exclude from confirmed figures, not proven invalid.
A14: Malformed-ID reconciliation check | B14: =B12+B13 -> 14 | C14: =C12+C13 -> 910 | D14: =D12+D13 -> 23 | E14: =E12+E13 -> 1740 | F14: Linked plus unresolved must equal the malformed-ID population.
A16: B. Formula-derived Confirmed Population
A17: Calculation | B17: 2024 lines | C17: 2024 value | D17: 2025 lines | E17: 2025 value | F17: Formula treatment
A18: Raw population | B18: =B9 -> 1240 | C18: =C9 -> 74880 | D18: =D9 -> 1390 | E18: =E9 -> 91540 | F18: Starting point.
A19: Less exact duplicates | B19: =B10 -> 28 | C19: =C10 -> 1680 | D19: =D10 -> 71 | E19: =E10 -> 4870 | F19: Deduct once only.
A20: Less unresolved malformed IDs | B20: =B13 -> 5 | C20: =C13 -> 320 | D20: =D13 -> 8 | E20: =E13 -> 680 | F20: Exclude from confirmed; keep visible as uncertainty.
A21: Confirmed population | B21: =B18-B19-B20 -> 1207 | C21: =C18-C19-C20 -> 72880 | D21: =D18-D19-D20 -> 1311 | E21: =E18-E19-E20 -> 85990 | F21: Raw less exact duplicates less unresolved malformed IDs.
A22: Linked malformed IDs retained | B22: =B12 -> 9 | C22: =C12 -> 590 | D22: =D12 -> 15 | E22: =E12 -> 1060 | F22: Included within confirmed population; not a deduction.
A23: Total exclusions | B23: =B19+B20 -> 33 | C23: =C19+C20 -> 2000 | D23: =D19+D20 -> 79 | E23: =E19+E20 -> 5550 | F23: Duplicate plus unresolved-ID exclusion burden.
A25: C. Period Movement and Data-quality Signal
A26: Metric | B26: 2024 | C26: 2025 | D26: Movement | E26: % / pp | F26: Interpretation
A27: Confirmed line count | B27: =B21 -> 1207 | C27: =D21 -> 1311 | D27: =C27-B27 -> 104 | E27: =D27/B27 -> 0.086164043 | F27: Confirmed growth; percentage uses 2024 confirmed count.
A28: Confirmed value | B28: =C21 -> 72880 | C28: =E21 -> 85990 | D28: =C28-B28 -> 13110 | E28: =D28/B28 -> 0.17988474 | F28: Confirmed growth; percentage uses 2024 confirmed value.
A29: Raw value | B29: =C9 -> 74880 | C29: =E9 -> 91540 | D29: =C29-B29 -> 16660 | E29: =D29/B29 -> 0.22248932 | F29: Unadjusted movement before exclusions.
A30: Total exclusion burden | B30: =C23 -> 2000 | C30: =E23 -> 5550 | D30: =C30-B30 -> 3550 | F30: Increase in duplicate plus unresolved-ID adjustments.
A31: Exact-duplicate line rate | B31: =B10/B9 -> 0.022580645 | C31: =D10/D9 -> 0.051079137 | D31: =(C31-B31)*100 -> 2.8498492 | F31: Deterioration expressed as percentage points.
A32: Raw less confirmed value movement | D32: =D29-D28 -> 3550 | F32: Difference caused by higher period-on-period adjustment burden.
A34: ="Material change explanation: confirmed lines increased from "&TEXT(B21,"#,##0")&" to "&TEXT(D21,"#,##0")&" (+"&TEXT(D27,"#,##0")&"; "&TEXT(E27,"0.0%")&"). Confirmed value increased from £"&TEXT(C21,"#,##0")&" to £"&TEXT(E21,"#,##0")&" (+£"&TEXT(D28,"#,##0")&"; "&TEXT(E28,"0.0%")&"). This is genuine confirmed growth, alongside weaker data quality: exact-duplicate incidence rose from about "&TEXT(B31,"0.0%")&" to "&TEXT(C31,"0.0%")&" (+"&TEXT(D31,"0.00")&" pp). Raw value rose £"&TEXT(D29,"#,##0")&"; confirmed value rose £"&TEXT(D28,"#,##0")&". The £"&TEXT(D32,"#,##0")&" difference is the larger period-on-period adjustment burden (£"&TEXT(B30,"#,##0")&" in 2024 to £"&TEXT(C30,"#,##0")&" in 2025), not an assertion that unresolved lines are invalid." -> Material change explanation: confirmed lines increased from 1,207 to 1,311 (+104; 8.6%). Confirmed value increased from £72,880 to £85,990 (+£13,110; 18.0%). This is genuine confirmed growth, alongside weaker data quality: exact-duplicate incidence rose from about 2.3% to 5.1% (+2.85 pp). Raw value rose £16,660; confirmed value rose £13,110. The £3,550 difference is the larger period-on-period adjustment burden (£2,000 in 2024 to £5,550 in 2025), not an assertion that unresolved lines are invalid.
A38: D. Operational Capacity Inputs
A39: Control input | B39: Value | C39: Unit | D39: Use in decision
A40: Central reviewer capacity | B40: 35 | C40: requests/day | D40: Available capacity for central exception review.
A41: Forecast peak demand | B41: 60 | C41: requests/day | D41: Peak demand forecast for the promotion.
A42: Central-review shortfall | B42: =B41-B40 -> 25 | C42: requests/day | D42: Peak demand less capacity; supports bounded local routine authority.
A43: Temporary-cover budget | B43: 0 | C43: GBP | D43: No temporary cover is available in the stated scenario.
A45: Assumptions and limits: the comparison uses the recoverable summary only; no line-level re-export is available before sign-off. Exact duplicates and malformed-ID groups are stated to be non-overlapping. Each exact duplicate is removed once. Linked malformed records are retained because the linkage is unambiguous. Unresolved malformed records are excluded from confirmed figures but remain a visible uncertain population; they are not labelled duplicate, fraudulent or invalid. No transaction-level facts beyond the supplied summary have been inferred.

Sheet Change Log
A1: Wexmoor Press - Returns Control Change Log
A2: Document 0.9 | Draft - pending approval | Owner: Enterprise Retail Operations Manager, Vellumstone Associates | Approver: Nadia Sepulveda
A3: Decision | B3: Operating Procedure | C3: Comparison | D3: Change Log
A5: This log records substantive operating, policy-boundary and analytical judgments. Status is pending approval unless an approval trace says otherwise; this draft is not represented as already approved.
A7: Date / issue | B7: Change or judgment | C7: Rationale | D7: Status / approval trace
A8: 08 Sep 2025 0.9 / Decision | B8: Recommend the portal control framework with bounded delegation and central triage; do not implement immediate portal-only central approval. | C8: Central capacity is 35 requests/day against 60/day forecast peak, creating a 25/day shortfall; no temporary cover budget. | D8: Draft | Owner: Enterprise Retail Operations Manager | Pending Nadia Sepulveda approval; no approval recorded.
A9: 08 Sep 2025 0.9 / Procedure A4 | B9: Replace ambiguous 'sale date' with house-policy eligibility date: physical supply, collection or delivery; event is day 0 and count starts next day. | C9: Creates a consistent internal voluntary-policy window without asserting a statutory timing rule. | D9: Draft | Owner: Enterprise Retail Operations Manager | Pending Nadia Sepulveda approval.
A10: 08 Sep 2025 0.9 / Procedure A1-A5 | B10: Separate voluntary change-of-mind, distance cancellation and statutory quality/defect routes. Narrow hygiene and clearance exclusions to the voluntary path and preserve statutory assessment. | C10: Avoids treating house policy as the complete statement of customer rights or applying blanket exclusions. | D10: Draft | Owner: Enterprise Retail Operations Manager | Pending approval; operational guidance, not legal advice.
A11: 08 Sep 2025 0.9 / Procedure B | B11: Define frontline intake, site-manager routine approval boundary and central exception authority; record customer communication, stock disposition and closure. | C11: Allows routine service while reserving legally sensitive, disputed, ambiguous and exceptional cases for central review. | D11: Draft | Owner: Enterprise Retail Operations Manager | Pending Nadia Sepulveda approval.
A12: 08 Sep 2025 0.9 / Procedure C | B12: During 15 September-31 October accept valid till-slip and portal evidence, assign/cross-reference one Return Case ID and reconcile daily. From 1 November make portal authoritative; retain a controlled outage queue. | C12: Prevents duplicate refunds during dual running and preserves traceability when portal access is unavailable. | D12: Draft | Owner: Enterprise Retail Operations Manager | Pending Nadia Sepulveda approval.
A13: 08 Sep 2025 0.9 / Comparison A-B | B13: Remove each exact duplicate once. Retain unambiguously linked malformed IDs; display unresolved malformed IDs separately and exclude only those from confirmed totals. | C13: Provided groups do not overlap. This maintains a traceable confirmed population without treating unresolved records as proven invalid. | D13: Draft | Owner: Enterprise Retail Operations Manager | Pending approval; inputs and formulas remain editable.
A14: 08 Sep 2025 0.9 / Comparison C | B14: Document confirmed growth alongside deterioration in duplicate incidence and the higher adjustment burden. | C14: Raw value movement is GBP16,660; confirmed movement is GBP13,110; GBP3,550 is the increased exclusion burden. | D14: Draft | Owner: Enterprise Retail Operations Manager | Pending Nadia Sepulveda approval.
A15: 08 Sep 2025 0.9 / Document control | B15: Set owner, approver, draft status, intended transition dates and future end-state date. | C15: Makes the procedure approval-ready without claiming authorization before an approver decision. | D15: Draft | Owner: Enterprise Retail Operations Manager | Approval authority: Nadia Sepulveda; decision pending.
