Workbook

Sheet Start Here
A1: Pilot measurement instrument | Roth conversion review
A2: Version 1.0 • launch configuration • yellow = editable input / green = formula • no individual conversion advice
A4: Operating purpose | B4: Track the randomized proactive guided-review offer and produce the Dec 2026 assigned-group (intention-to-treat) readout. All eligible participants keep standard education and may decline a meeting.
A6: Control | B6: Configured standard | C6: How to use / source
A7: Analysis population | B7: 60 distinct eligible participants | C7: Derived from roster: Plan eligible Yes + Hourly + retirement date in 2026.
A8: Offer / comparison | B8: 30 guided offers / 30 standard education | C8: Offer count equals supplied Apr–Sep capacity; no hand-picking.
A9: Primary outcome | B9: Any confirmed Roth conversion by Dec 15, 2026 | C9: One binary participant event; all assigned eligible people remain in the denominator.
A10: Primary estimand | B10: Intention-to-treat: assigned-offer rate minus assigned-comparison rate | C10: Regardless of offer receipt, scheduling, attendance, refusal, crossover, or outside exposure.
A11: Missing status rule | B11: Unknown status remains distinct; primary readout counts it as no confirmed conversion | C11: Sensitivity bounds treat all unresolved status as no conversion / as conversion.
A12: How to operate | B12: Enter yellow participant-status fields; review QC before readout | C12: Do not alter Original assigned arm. Log any correction in Assignment Log.
A13: Source scope | B13: Supplied policy and jurisdiction language only | C13: Measurement and education governance, not a legal determination or individualized advice.

Sheet Participants
A1: Participant-level assignment and outcome entry
A2: One row per supplied participant key. Original assignment is fixed; enter yellow implementation/outcome fields only.
A4: Participant Key | B4: Eligible? | C4: Eligibility rule result | D4: Site | E4: Shift | F4: Retirement date | G4: Prior interest source | H4: Prior interest category | I4: Assignment block | J4: Random score | K4: Allocation quota | L4: Original assigned arm | M4: Offer delivery status | N4: Offer delivery date | O4: Scheduling status | P4: Scheduled date | Q4: Attendance status | R4: Attendance date | S4: Outside guided exposure | T4: Outside exposure date | U4: Primary outcome status | V4: Outcome date | W4: Conversion amount | X4: Record note
A5: PU-1001 | B5: Yes | C5: Meets supplied eligibility rule | D5: North Yard | E5: Day | F5: 46089 | G5: Interested | H5: Interested | I5: North Yard | Interested | J5: 137737511603094 | K5: 4 | L5: Standard education | M5: Not sent | O5: Not scheduled | Q5: Not attended | S5: No | U5: Unknown—unresolved
A6: PU-1002 | B6: Yes | C6: Meets supplied eligibility rule | D6: North Yard | E6: Swing | F6: 46123 | G6: Interested | H6: Interested | I6: North Yard | Interested | J6: 131099755127710 | K6: 4 | L6: Standard education | M6: Not sent | O6: Not scheduled | Q6: Not attended | S6: No | U6: Unknown—unresolved
A7: PU-1003 | B7: Yes | C7: Meets supplied eligibility rule | D7: North Yard | E7: Night | F7: 46156 | G7: Interested | H7: Interested | I7: North Yard | Interested | J7: 10621727917897 | K7: 4 | L7: Guided offer | M7: Not sent | O7: Not scheduled | Q7: Not attended | S7: No | U7: Unknown—unresolved
A8: PU-1004 | B8: Yes | C8: Meets supplied eligibility rule | D8: North Yard | E8: Day | F8: 46190 | G8: Interested | H8: Interested | I8: North Yard | Interested | J8: 225822471090875 | K8: 4 | L8: Standard education | M8: Not sent | O8: Not scheduled | Q8: Not attended | S8: No | U8: Unknown—unresolved
A9: PU-1005 | B9: Yes | C9: Meets supplied eligibility rule | D9: North Yard | E9: Swing | F9: 46223 | G9: Interested | H9: Interested | I9: North Yard | Interested | J9: 43752203397147 | K9: 4 | L9: Guided offer | M9: Not sent | O9: Not scheduled | Q9: Not attended | S9: No | U9: Unknown—unresolved
A10: PU-1006 | B10: Yes | C10: Meets supplied eligibility rule | D10: North Yard | E10: Night | F10: 46257 | G10: Interested | H10: Interested | I10: North Yard | Interested | J10: 65149256050649 | K10: 4 | L10: Guided offer | M10: Not sent | O10: Not scheduled | Q10: Not attended | S10: No | U10: Unknown—unresolved
A11: PU-1007 | B11: Yes | C11: Meets supplied eligibility rule | D11: North Yard | E11: Day | F11: 46291 | G11: Interested | H11: Interested | I11: North Yard | Interested | J11: 27552612692584 | K11: 4 | L11: Guided offer | M11: Not sent | O11: Not scheduled | Q11: Not attended | S11: No | U11: Unknown—unresolved
A12: PU-1008 | B12: Yes | C12: Meets supplied eligibility rule | D12: North Yard | E12: Swing | F12: 46305 | G12: Not interested | H12: Not interested | I12: North Yard | Not interested | J12: 60683451549020 | K12: 3 | L12: Guided offer | M12: Not sent | O12: Not scheduled | Q12: Not attended | S12: No | U12: Unknown—unresolved
A13: PU-1009 | B13: Yes | C13: Meets supplied eligibility rule | D13: North Yard | E13: Night | F13: 46339 | G13: Not interested | H13: Not interested | I13: North Yard | Not interested | J13: 179432734713592 | K13: 3 | L13: Standard education | M13: Not sent | O13: Not scheduled | Q13: Not attended | S13: No | U13: Unknown—unresolved
A14: PU-1010 | B14: Yes | C14: Meets supplied eligibility rule | D14: North Yard | E14: Day | F14: 46097 | G14: Not interested | H14: Not interested | I14: North Yard | Not interested | J14: 116953416753412 | K14: 3 | L14: Guided offer | M14: Not sent | O14: Not scheduled | Q14: Not attended | S14: No | U14: Unknown—unresolved
A15: PU-1011 | B15: Yes | C15: Meets supplied eligibility rule | D15: North Yard | E15: Swing | F15: 46131 | G15: Not interested | H15: Not interested | I15: North Yard | Not interested | J15: 117876754669293 | K15: 3 | L15: Standard education | M15: Not sent | O15: Not scheduled | Q15: Not attended | S15: No | U15: Unknown—unresolved
A16: PU-1012 | B16: Yes | C16: Meets supplied eligibility rule | D16: North Yard | E16: Night | F16: 46164 | G16: Not interested | H16: Not interested | I16: North Yard | Not interested | J16: 251634009081825 | K16: 3 | L16: Standard education | M16: Not sent | O16: Not scheduled | Q16: Not attended | S16: No | U16: Unknown—unresolved
... A18: PU-1014 | B18: Yes | C18: Meets supplied eligibility rule | D18: North Yard | E18: Swing | F18: 46212 | G18: Not interested | H18: Not interested | I18: North Yard | Not interested | J18: 6982505896046 | K18: 3 | L18: Guided offer | M18: Not sent | O18: Not scheduled | Q18: Not attended | S18: No | U18: Unknown—unresolved
A19: PU-1015 | B19: Yes | C19: Meets supplied eligibility rule | D19: North Yard | E19: Night | F19: 46246 | H19: Unknown | I19: North Yard | Unknown | J19: 23326490011888 | K19: 3 | L19: Guided offer | M19: Not sent | O19: Not scheduled | Q19: Not attended | S19: No | U19: Unknown—unresolved
A20: PU-1016 | B20: Yes | C20: Meets supplied eligibility rule | D20: North Yard | E20: Day | F20: 46280 | H20: Unknown | I20: North Yard | Unknown | J20: 65602187878132 | K20: 3 | L20: Standard education | M20: Not sent | O20: Not scheduled | Q20: Not attended | S20: No | U20: Unknown—unresolved
A21: PU-1017 | B21: Yes | C21: Meets supplied eligibility rule | D21: North Yard | E21: Swing | F21: 46313 | H21: Unknown | I21: North Yard | Unknown | J21: 63199732920604 | K21: 3 | L21: Guided offer | M21: Not sent | O21: Not scheduled | Q21: Not attended | S21: No | U21: Unknown—unresolved
A22: PU-1018 | B22: Yes | C22: Meets supplied eligibility rule | D22: North Yard | E22: Night | F22: 46347 | H22: Unknown | I22: North Yard | Unknown | J22: 230186501380851 | K22: 3 | L22: Standard education | M22: Not sent | O22: Not scheduled | Q22: Not attended | S22: No | U22: Unknown—unresolved
A23: PU-1019 | B23: Yes | C23: Meets supplied eligibility rule | D23: North Yard | E23: Day | F23: 46105 | H23: Unknown | I23: North Yard | Unknown | J23: 140500547380156 | K23: 3 | L23: Standard education | M23: Not sent | O23: Not scheduled | Q23: Not attended | S23: No | U23: Unknown—unresolved
A24: PU-1020 | B24: Yes | C24: Meets supplied eligibility rule | D24: North Yard | E24: Swing | F24: 46120 | H24: Unknown | I24: North Yard | Unknown | J24: 19349353598149 | K24: 3 | L24: Guided offer | M24: Not sent | O24: Not scheduled | Q24: Not attended | S24: No | U24: Unknown—unresolved
A25: PU-1021 | B25: Yes | C25: Meets supplied eligibility rule | D25: Central Plant | E25: Swing | F25: 46089 | G25: Interested | H25: Interested | I25: Central Plant | Interested | J25: 157474302047150 | K25: 3 | L25: Standard education | M25: Not sent | O25: Not scheduled | Q25: Not attended | S25: No | U25: Unknown—unresolved
A26: PU-1022 | B26: Yes | C26: Meets supplied eligibility rule | D26: Central Plant | E26: Night | F26: 46123 | G26: Interested | H26: Interested | I26: Central Plant | Interested | J26: 44066583038144 | K26: 3 | L26: Guided offer | M26: Not sent | O26: Not scheduled | Q26: Not attended | S26: No | U26: Unknown—unresolved
A27: PU-1023 | B27: Yes | C27: Meets supplied eligibility rule | D27: Central Plant | E27: Day | F27: 46156 | G27: Interested | H27: Interested | I27: Central Plant | Interested | J27: 1048032117521 | K27: 3 | L27: Guided offer | M27: Not sent | O27: Not scheduled | Q27: Not attended | S27: No | U27: Unknown—unresolved
A28: PU-1024 | B28: Yes | C28: Meets supplied eligibility rule | D28: Central Plant | E28: Swing | F28: 46190 | G28: Interested | H28: Interested | I28: Central Plant | Interested | J28: 206898379340112 | K28: 3 | L28: Standard education | M28: Not sent | O28: Not scheduled | Q28: Not attended | S28: No | U28: Unknown—unresolved
A29: PU-1025 | B29: Yes | C29: Meets supplied eligibility rule | D29: Central Plant | E29: Night | F29: 46223 | G29: Interested | H29: Interested | I29: Central Plant | Interested | J29: 265570218254206 | K29: 3 | L29: Standard education | M29: Not sent | O29: Not scheduled | Q29: Not attended | S29: No | U29: Unknown—unresolved
A30: PU-1026 | B30: Yes | C30: Meets supplied eligibility rule | D30: Central Plant | E30: Day | F30: 46257 | G30: Interested | H30: Interested | I30: Central Plant | Interested | J30: 149784490824154 | K30: 3 | L30: Standard education | M30: Not sent | O30: Not scheduled | Q30: Not attended | S30: No | U30: Unknown—unresolved
A31: PU-1027 | B31: Yes | C31: Meets supplied eligibility rule | D31: Central Plant | E31: Swing | F31: 46291 | G31: Interested | H31: Interested | I31: Central Plant | Interested | J31: 37910934208828 | K31: 3 | L31: Guided offer | M31: Not sent | O31: Not scheduled | Q31: Not attended | S31: No | U31: Unknown—unresolved
A32: PU-1028 | B32: Yes | C32: Meets supplied eligibility rule | D32: Central Plant | E32: Night | F32: 46305 | G32: Not interested | H32: Not interested | I32: Central Plant | Not interested | J32: 97349107930778 | K32: 4 | L32: Guided offer | M32: Not sent | O32: Not scheduled | Q32: Not attended | S32: No | U32: Unknown—unresolved
A33: PU-1029 | B33: Yes | C33: Meets supplied eligibility rule | D33: Central Plant | E33: Day | F33: 46339 | G33: Not interested | H33: Not interested | I33: Central Plant | Not interested | J33: 247155986992263 | K33: 4 | L33: Standard education | M33: Not sent | O33: Not scheduled | Q33: Not attended | S33: No | U33: Unknown—unresolved
A34: PU-1030 | B34: Yes | C34: Meets supplied eligibility rule | D34: Central Plant | E34: Swing | F34: 46097 | G34: Not interested | H34: Not interested | I34: Central Plant | Not interested | J34: 48867755265748 | K34: 4 | L34: Guided offer | M34: Not sent | O34: Not scheduled | Q34: Not attended | S34: No | U34: Unknown—unresolved
A35: PU-1031 | B35: Yes | C35: Meets supplied eligibility rule | D35: Central Plant | E35: Night | F35: 46131 | G35: Not interested | H35: Not interested | I35: Central Plant | Not interested | J35: 218441575224777 | K35: 4 | L35: Standard education | M35: Not sent | O35: Not scheduled | Q35: Not attended | S35: No | U35: Unknown—unresolved
A36: PU-1032 | B36: Yes | C36: Meets supplied eligibility rule | D36: Central Plant | E36: Day | F36: 46164 | G36: Not interested | H36: Not interested | I36: Central Plant | Not interested | J36: 17857276304710 | K36: 4 | L36: Guided offer | M36: Not sent | O36: Not scheduled | Q36: Not attended | S36: No | U36: Unknown—unresolved
... A38: PU-1034 | B38: Yes | C38: Meets supplied eligibility rule | D38: Central Plant | E38: Night | F38: 46212 | G38: Not interested | H38: Not interested | I38: Central Plant | Not interested | J38: 245196134462137 | K38: 4 | L38: Standard education | M38: Not sent | O38: Not scheduled | Q38: Not attended | S38: No | U38: Unknown—unresolved
A39: PU-1035 | B39: Yes | C39: Meets supplied eligibility rule | D39: Central Plant | E39: Day | F39: 46246 | H39: Unknown | I39: Central Plant | Unknown | J39: 203145074727104 | K39: 3 | L39: Standard education | M39: Not sent | O39: Not scheduled | Q39: Not attended | S39: No | U39: Unknown—unresolved
A40: PU-1036 | B40: Yes | C40: Meets supplied eligibility rule | D40: Central Plant | E40: Swing | F40: 46280 | H40: Unknown | I40: Central Plant | Unknown | J40: 94216147081047 | K40: 3 | L40: Guided offer | M40: Not sent | O40: Not scheduled | Q40: Not attended | S40: No | U40: Unknown—unresolved
A41: PU-1037 | B41: Yes | C41: Meets supplied eligibility rule | D41: Central Plant | E41: Night | F41: 46313 | H41: Unknown | I41: Central Plant | Unknown | J41: 22603268160579 | K41: 3 | L41: Guided offer | M41: Not sent | O41: Not scheduled | Q41: Not attended | S41: No | U41: Unknown—unresolved
A42: PU-1038 | B42: Yes | C42: Meets supplied eligibility rule | D42: Central Plant | E42: Day | F42: 46347 | H42: Unknown | I42: Central Plant | Unknown | J42: 190126255005578 | K42: 3 | L42: Standard education | M42: Not sent | O42: Not scheduled | Q42: Not attended | S42: No | U42: Unknown—unresolved
A43: PU-1039 | B43: Yes | C43: Meets supplied eligibility rule | D43: Central Plant | E43: Swing | F43: 46105 | H43: Unknown | I43: Central Plant | Unknown | J43: 88836480069598 | K43: 3 | L43: Guided offer | M43: Not sent | O43: Not scheduled | Q43: Not attended | S43: No | U43: Unknown—unresolved
A44: PU-1040 | B44: Yes | C44: Meets supplied eligibility rule | D44: Central Plant | E44: Night | F44: 46120 | H44: Unknown | I44: Central Plant | Unknown | J44: 168852981601719 | K44: 3 | L44: Standard education | M44: Not sent | O44: Not scheduled | Q44: Not attended | S44: No | U44: Unknown—unresolved
A45: PU-1041 | B45: Yes | C45: Meets supplied eligibility rule | D45: South Works | E45: Night | F45: 46089 | G45: Interested | H45: Interested | I45: South Works | Interested | J45: 46702423834866 | K45: 3 | L45: Guided offer | M45: Not sent | O45: Not scheduled | Q45: Not attended | S45: No | U45: Unknown—unresolved
A46: PU-1042 | B46: Yes | C46: Meets supplied eligibility rule | D46: South Works | E46: Day | F46: 46123 | G46: Interested | H46: Interested | I46: South Works | Interested | J46: 177268809934988 | K46: 3 | L46: Standard education | M46: Not sent | O46: Not scheduled | Q46: Not attended | S46: No | U46: Unknown—unresolved
A47: PU-1043 | B47: Yes | C47: Meets supplied eligibility rule | D47: South Works | E47: Swing | F47: 46156 | G47: Interested | H47: Interested | I47: South Works | Interested | J47: 14077069965488 | K47: 3 | L47: Guided offer | M47: Not sent | O47: Not scheduled | Q47: Not attended | S47: No | U47: Unknown—unresolved
A48: PU-1044 | B48: Yes | C48: Meets supplied eligibility rule | D48: South Works | E48: Night | F48: 46190 | G48: Interested | H48: Interested | I48: South Works | Interested | J48: 250131995406328 | K48: 3 | L48: Standard education | M48: Not sent | O48: Not scheduled | Q48: Not attended | S48: No | U48: Unknown—unresolved
A49: PU-1045 | B49: Yes | C49: Meets supplied eligibility rule | D49: South Works | E49: Day | F49: 46223 | G49: Interested | H49: Interested | I49: South Works | Interested | J49: 140083833596702 | K49: 3 | L49: Standard education | M49: Not sent | O49: Not scheduled | Q49: Not attended | S49: No | U49: Unknown—unresolved
A50: PU-1046 | B50: Yes | C50: Meets supplied eligibility rule | D50: South Works | E50: Swing | F50: 46257 | G50: Interested | H50: Interested | I50: South Works | Interested | J50: 66353400255363 | K50: 3 | L50: Standard education | M50: Not sent | O50: Not scheduled | Q50: Not attended | S50: No | U50: Unknown—unresolved
A51: PU-1047 | B51: Yes | C51: Meets supplied eligibility rule | D51: South Works | E51: Night | F51: 46291 | G51: Interested | H51: Interested | I51: South Works | Interested | J51: 42806420762908 | K51: 3 | L51: Guided offer | M51: Not sent | O51: Not scheduled | Q51: Not attended | S51: No | U51: Unknown—unresolved
A52: PU-1048 | B52: Yes | C52: Meets supplied eligibility rule | D52: South Works | E52: Day | F52: 46305 | G52: Not interested | H52: Not interested | I52: South Works | Not interested | J52: 140303440594243 | K52: 3 | L52: Standard education | M52: Not sent | O52: Not scheduled | Q52: Not attended | S52: No | U52: Unknown—unresolved
A53: PU-1049 | B53: Yes | C53: Meets supplied eligibility rule | D53: South Works | E53: Swing | F53: 46339 | G53: Not interested | H53: Not interested | I53: South Works | Not interested | J53: 178777119828249 | K53: 3 | L53: Standard education | M53: Not sent | O53: Not scheduled | Q53: Not attended | S53: No | U53: Unknown—unresolved
A54: PU-1050 | B54: Yes | C54: Meets supplied eligibility rule | D54: South Works | E54: Night | F54: 46097 | G54: Not interested | H54: Not interested | I54: South Works | Not interested | J54: 231378855205937 | K54: 3 | L54: Standard education | M54: Not sent | O54: Not scheduled | Q54: Not attended | S54: No | U54: Unknown—unresolved
A55: PU-1051 | B55: Yes | C55: Meets supplied eligibility rule | D55: South Works | E55: Day | F55: 46131 | G55: Not interested | H55: Not interested | I55: South Works | Not interested | J55: 89656577781269 | K55: 3 | L55: Guided offer | M55: Not sent | O55: Not scheduled | Q55: Not attended | S55: No | U55: Unknown—unresolved
A56: PU-1052 | B56: Yes | C56: Meets supplied eligibility rule | D56: South Works | E56: Swing | F56: 46164 | G56: Not interested | H56: Not interested | I56: South Works | Not interested | J56: 59397706210773 | K56: 3 | L56: Guided offer | M56: Not sent | O56: Not scheduled | Q56: Not attended | S56: No | U56: Unknown—unresolved
... A58: PU-1054 | B58: Yes | C58: Meets supplied eligibility rule | D58: South Works | E58: Day | F58: 46212 | G58: Not interested | H58: Not interested | I58: South Works | Not interested | J58: 242918872786842 | K58: 3 | L58: Standard education | M58: Not sent | O58: Not scheduled | Q58: Not attended | S58: No | U58: Unknown—unresolved
A59: PU-1055 | B59: Yes | C59: Meets supplied eligibility rule | D59: South Works | E59: Swing | F59: 46246 | H59: Unknown | I59: South Works | Unknown | J59: 147317013808670 | K59: 4 | L59: Guided offer | M59: Not sent | O59: Not scheduled | Q59: Not attended | S59: No | U59: Unknown—unresolved
A60: PU-1056 | B60: Yes | C60: Meets supplied eligibility rule | D60: South Works | E60: Night | F60: 46280 | H60: Unknown | I60: South Works | Unknown | J60: 280825105173875 | K60: 4 | L60: Standard education | M60: Not sent | O60: Not scheduled | Q60: Not attended | S60: No | U60: Unknown—unresolved
A61: PU-1057 | B61: Yes | C61: Meets supplied eligibility rule | D61: South Works | E61: Day | F61: 46313 | H61: Unknown | I61: South Works | Unknown | J61: 134737155661177 | K61: 4 | L61: Guided offer | M61: Not sent | O61: Not scheduled | Q61: Not attended | S61: No | U61: Unknown—unresolved
A62: PU-1058 | B62: Yes | C62: Meets supplied eligibility rule | D62: South Works | E62: Swing | F62: 46347 | H62: Unknown | I62: South Works | Unknown | J62: 123430877581688 | K62: 4 | L62: Guided offer | M62: Not sent | O62: Not scheduled | Q62: Not attended | S62: No | U62: Unknown—unresolved
A63: PU-1059 | B63: Yes | C63: Meets supplied eligibility rule | D63: South Works | E63: Night | F63: 46105 | H63: Unknown | I63: South Works | Unknown | J63: 190557480055099 | K63: 4 | L63: Guided offer | M63: Not sent | O63: Not scheduled | Q63: Not attended | S63: No | U63: Unknown—unresolved
A64: PU-1060 | B64: Yes | C64: Meets supplied eligibility rule | D64: South Works | E64: Day | F64: 46120 | H64: Unknown | I64: South Works | Unknown | J64: 209494090186923 | K64: 4 | L64: Standard education | M64: Not sent | O64: Not scheduled | Q64: Not attended | S64: No | U64: Unknown—unresolved

Sheet Readout
A1: Year-end causal readout
A2: Primary analysis is intention-to-treat (assigned offer group), regardless of attendance. Launch-stage statuses are unresolved until outcome capture.
A4: Metric | B4: Guided offer | C4: Standard education | D4: Difference / check | E4: Interpretation
A5: Eligible assigned denominator | B5: =COUNTIFS(Participants!$B$5:$B$64,"Yes",Participants!$L$5:$L$64,"Guided offer") -> 30 | C5: =COUNTIFS(Participants!$B$5:$B$64,"Yes",Participants!$L$5:$L$64,"Standard education") -> 30 | D5: =B5+C5 -> 60 | E5: All eligible assigned people; original arm controls.
A6: Confirmed conversion count | B6: =COUNTIFS(Participants!$B$5:$B$64,"Yes",Participants!$L$5:$L$64,"Guided offer",Participants!$U$5:$U$64,"Converted") -> 0 | C6: =COUNTIFS(Participants!$B$5:$B$64,"Yes",Participants!$L$5:$L$64,"Standard education",Participants!$U$5:$U$64,"Converted") -> 0 | D6: =B6-C6 -> 0 | E6: Participant-level numerator event by deadline.
A7: Primary rate (unknown = no confirmed conversion) | B7: =IFERROR(B6/B5,0) -> 0 | C7: =IFERROR(C6/C5,0) -> 0 | D7: =B7-C7 -> 0 | E7: Primary ITT rate difference, percentage points.
A8: 95% Wald CI — lower | D8: =D7-1.96*SQRT(B7*(1-B7)/B5+C7*(1-C7)/C5) -> 0 | E8: Binary-outcome uncertainty on the same pp scale.
A9: 95% Wald CI — upper | D9: =D7+1.96*SQRT(B7*(1-B7)/B5+C7*(1-C7)/C5) -> 0 | E9: Interpret with modest-pilot precision, not p-value alone.
A10: Unknown outcome status | B10: =COUNTIFS(Participants!$L$5:$L$64,"Guided offer",Participants!$U$5:$U$64,"Unknown—unresolved") -> 30 | C10: =COUNTIFS(Participants!$L$5:$L$64,"Standard education",Participants!$U$5:$U$64,"Unknown—unresolved") -> 30 | D10: =B10+C10 -> 60 | E10: Distinct from confirmed non-conversion; QC escalation at deadline.
A11: Sensitivity upper rate (all unknown = converted) | B11: =IFERROR((B6+B10)/B5,0) -> 1 | C11: =IFERROR((C6+C10)/C5,0) -> 1 | D11: =B11-C11 -> 0 | E11: Sensitivity range: lower bound is primary rate; upper bound assumes every unresolved record converted.
A12: Offer delivered | B12: =COUNTIFS(Participants!$L$5:$L$64,"Guided offer",Participants!$M$5:$M$64,"Sent") -> 0 | C12: =COUNTIFS(Participants!$L$5:$L$64,"Standard education",Participants!$M$5:$M$64,"Sent") -> 0 | D12: =B12/B5 -> 0 | E12: Implementation outcome; not a substitute for assignment.
A13: Attended guided review | B13: =COUNTIFS(Participants!$L$5:$L$64,"Guided offer",Participants!$Q$5:$Q$64,"Attended") -> 0 | C13: =COUNTIFS(Participants!$L$5:$L$64,"Standard education",Participants!$Q$5:$Q$64,"Attended") -> 0 | D13: =B13/B5 -> 0 | E13: Secondary/process measure only. Attendee comparisons are non-randomized and assumption-dependent.
A14: Outside guided exposure | B14: =COUNTIFS(Participants!$L$5:$L$64,"Guided offer",Participants!$S$5:$S$64,"Yes") -> 0 | C14: =COUNTIFS(Participants!$L$5:$L$64,"Standard education",Participants!$S$5:$S$64,"Yes") -> 0 | D14: =B14+C14 -> 0 | E14: Crossover retained in ITT denominator; changes learning about meeting receipt.
A17: Prospective precision (planning inputs — editable)
A18: Planning assumption | B18: Value | C18: Formula / result | D18: Use | E18: Owner
A19: Baseline conversion rate | B19: 0.2 | D19: Supplied-data gap: analyst planning assumption, not participant forecast. | E19: Mirela Danforth
A20: Planned offer n | B20: =B5 -> 30 | D20: Derived randomized group size. | E20: Benefits Analytics
A21: Planned comparison n | B21: =C5 -> 30 | D21: Derived randomized group size. | E21: Benefits Analytics
A22: Two-sided confidence level | B22: 0.95 | D22: Assumption for approximate precision. | E22: Benefits Analytics
A23: Approx. 95% half-width (pp) | C23: =1.96*SQRT(B19*(1-B19)/B20+B19*(1-B19)/B21) -> 0.20242793 | D23: Updates with n or planning rate; modest pilot likely wide. | E23: Benefits Analytics
A24: Approx. 80% MDE (pp) | C24: =(1.96+0.84)*SQRT(2*B19*(1-B19)/MIN(B20,B21)) -> 0.28918276 | D24: Screening-scale planning calculation, not a claim of power. | E24: Benefits Analytics
A27: Scenario context from supplied inputs
A28: Stable / market movement / bracket environment shift | B28: Report as shared 2026 context for both arms. Scenarios never generate conversions, forecast tax effects, or replace observed outcomes.

Sheet QC & Balance
A1: Quality controls and baseline balance
A2: Review before release. Any failure requires Benefits Analytics review; do not silently replace original assignments.
A4: Automated check | B4: Count / result | C4: Pass standard | D4: Action if failed | E4: Owner
A5: Duplicate participant keys | B5: =SUMPRODUCT(--(COUNTIF(Participants!$A$5:$A$64,Participants!$A$5:$A$64)>1)) -> 0 | C5: 0 | D5: Stop; deduplicate to supplied participant key before analysis. | E5: Benefits Analytics
A6: Invalid arm values | B6: =COUNTIFS(Participants!$L$5:$L$64,"<>Guided offer",Participants!$L$5:$L$64,"<>Standard education") -> 0 | C6: 0 | D6: Stop; Original assigned arm must be one configured code. | E6: Benefits Analytics
A7: Assignment-count reconciliation | B7: =ABS(COUNTIF(Participants!$L$5:$L$64,"Guided offer")+COUNTIF(Participants!$L$5:$L$64,"Standard education")-60) -> 0 | C7: 0 | D7: Stop; reconcile roster and allocation log. | E7: Benefits Analytics
A8: Capacity breach | B8: =MAX(0,COUNTIF(Participants!$L$5:$L$64,"Guided offer")-30) -> 0 | C8: 0 | D8: Stop; do not send excess offers. | E8: Advisor Operations
A9: Offer before allocation approval | B9: =COUNTIFS(Participants!$N$5:$N$64,"<"&DATE(2026,3,24)) -> 0 | C9: 0 | D9: Investigate chronology; preserve log. | E9: Benefits Operations
A10: Attendance before scheduled date | B10: =SUMPRODUCT(--(Participants!$R$5:$R$64<>""),--(Participants!$P$5:$P$64<>""),--(Participants!$R$5:$R$64<Participants!$P$5:$P$64)) -> 0 | C10: 0 | D10: Correct entry with dated reason in correction log. | E10: Advisor Operations
A11: Outcome after deadline | B11: =COUNTIFS(Participants!$V$5:$V$64,">"&DATE(2026,12,15)) -> 0 | C11: 0 | D11: Do not count in primary endpoint. | E11: Benefits Operations
A12: Unresolved primary status | B12: =COUNTIF(Participants!$U$5:$U$64,"Unknown—unresolved") -> 60 | C12: 0 at Dec 15 | D12: Escalate; retain as unknown and show sensitivity bounds. | E12: Benefits Operations
A15: Baseline arm balance (magnitude checks; no significance-test gate)
A16: Baseline category | B16: Guided offer n | C16: Standard education n | D16: Guided proportion | E16: Comparison proportion | F16: Absolute difference | G16: Review threshold
A17: Site: North Yard | B17: =COUNTIFS(Participants!$L$5:$L$64,"Guided offer",Participants!$D$5:$D$64,"North Yard") -> 10 | C17: =COUNTIFS(Participants!$L$5:$L$64,"Standard education",Participants!$D$5:$D$64,"North Yard") -> 10 | D17: =B17/30 -> 0.33333333 | E17: =C17/30 -> 0.33333333 | F17: =ABS(D17-E17) -> 0 | G17: Flag if >20 pp; explain, do not reassign
A18: Site: Central Plant | B18: =COUNTIFS(Participants!$L$5:$L$64,"Guided offer",Participants!$D$5:$D$64,"Central Plant") -> 10 | C18: =COUNTIFS(Participants!$L$5:$L$64,"Standard education",Participants!$D$5:$D$64,"Central Plant") -> 10 | D18: =B18/30 -> 0.33333333 | E18: =C18/30 -> 0.33333333 | F18: =ABS(D18-E18) -> 0 | G18: Flag if >20 pp; explain, do not reassign
A19: Site: South Works | B19: =COUNTIFS(Participants!$L$5:$L$64,"Guided offer",Participants!$D$5:$D$64,"South Works") -> 10 | C19: =COUNTIFS(Participants!$L$5:$L$64,"Standard education",Participants!$D$5:$D$64,"South Works") -> 10 | D19: =B19/30 -> 0.33333333 | E19: =C19/30 -> 0.33333333 | F19: =ABS(D19-E19) -> 0 | G19: Flag if >20 pp; explain, do not reassign
A20: Shift: Day | B20: =COUNTIFS(Participants!$L$5:$L$64,"Guided offer",Participants!$E$5:$E$64,"Day") -> 6 | C20: =COUNTIFS(Participants!$L$5:$L$64,"Standard education",Participants!$E$5:$E$64,"Day") -> 14 | D20: =B20/30 -> 0.2 | E20: =C20/30 -> 0.46666667 | F20: =ABS(D20-E20) -> 0.26666667 | G20: Flag if >20 pp; explain, do not reassign
A21: Shift: Swing | B21: =COUNTIFS(Participants!$L$5:$L$64,"Guided offer",Participants!$E$5:$E$64,"Swing") -> 14 | C21: =COUNTIFS(Participants!$L$5:$L$64,"Standard education",Participants!$E$5:$E$64,"Swing") -> 6 | D21: =B21/30 -> 0.46666667 | E21: =C21/30 -> 0.2 | F21: =ABS(D21-E21) -> 0.26666667 | G21: Flag if >20 pp; explain, do not reassign
A22: Shift: Night | B22: =COUNTIFS(Participants!$L$5:$L$64,"Guided offer",Participants!$E$5:$E$64,"Night") -> 10 | C22: =COUNTIFS(Participants!$L$5:$L$64,"Standard education",Participants!$E$5:$E$64,"Night") -> 10 | D22: =B22/30 -> 0.33333333 | E22: =C22/30 -> 0.33333333 | F22: =ABS(D22-E22) -> 0 | G22: Flag if >20 pp; explain, do not reassign
A23: Prior interest: Interested | B23: =COUNTIFS(Participants!$L$5:$L$64,"Guided offer",Participants!$H$5:$H$64,"Interested") -> 10 | C23: =COUNTIFS(Participants!$L$5:$L$64,"Standard education",Participants!$H$5:$H$64,"Interested") -> 11 | D23: =B23/30 -> 0.33333333 | E23: =C23/30 -> 0.36666667 | F23: =ABS(D23-E23) -> 0.033333333 | G23: Flag if >20 pp; explain, do not reassign
A24: Prior interest: Not interested | B24: =COUNTIFS(Participants!$L$5:$L$64,"Guided offer",Participants!$H$5:$H$64,"Not interested") -> 10 | C24: =COUNTIFS(Participants!$L$5:$L$64,"Standard education",Participants!$H$5:$H$64,"Not interested") -> 11 | D24: =B24/30 -> 0.33333333 | E24: =C24/30 -> 0.36666667 | F24: =ABS(D24-E24) -> 0.033333333 | G24: Flag if >20 pp; explain, do not reassign
A25: Prior interest: Unknown | B25: =COUNTIFS(Participants!$L$5:$L$64,"Guided offer",Participants!$H$5:$H$64,"Unknown") -> 10 | C25: =COUNTIFS(Participants!$L$5:$L$64,"Standard education",Participants!$H$5:$H$64,"Unknown") -> 8 | D25: =B25/30 -> 0.33333333 | E25: =C25/30 -> 0.26666667 | F25: =ABS(D25-E25) -> 0.066666667 | G25: Flag if >20 pp; explain, do not reassign

Sheet Data Dictionary
A1: Data dictionary
A2: Analysis-critical fields, allowed values, timing, and missing-value meaning.
A4: Field | B4: Allowed values / format | C4: Timing | D4: Missing value means | E4: Operational definition
A5: Participant Key | B5: Supplied key, unique | C5: Roster freeze | D5: Not permitted | E5: Assignment unit; one row per eligible person.
A6: Eligible? | B6: Yes / No | C6: At roster freeze | D6: Not eligible only if supplied rule fails | E6: Plan eligible Yes + Hourly + retirement date in 2026.
A7: Prior interest category | B7: Interested / Not interested / Unknown | C7: Baseline before allocation | D7: Unknown = source blank; not unwilling | E7: Blocking and balance variable; never exclusion.
A8: Original assigned arm | B8: Guided offer / Standard education | C8: Allocation, 24 Mar 2026 | D8: Not permitted | E8: Fixed randomized offer assignment; never overwrite.
A9: Offer delivery status | B9: Not sent / Sent / Undeliverable | C9: Apr–Sep 2026 | D9: Not sent = no recorded delivery | E9: Separate from assignment and attendance.
A10: Scheduling status | B10: Not scheduled / Scheduled / Declined | C10: Apr–Sep 2026 | D10: Not scheduled = no scheduling record | E10: Decline is permitted, not protocol failure.
A11: Attendance status | B11: Not attended / Attended / Declined / No-show | C11: Meeting window | D11: Not attended = no meeting recorded | E11: Secondary process outcome; no causal attendee analysis.
A12: Outside guided exposure | B12: No / Yes / Unknown | C12: Through Dec 15 | D12: Unknown = exposure not ascertained | E12: Capture crossover in either arm; retain ITT.
A13: Primary outcome status | B13: Converted / Not converted / Unknown—unresolved | C13: By Dec 15, 2026 | D13: Unknown is neither confirmed conversion nor non-conversion | E13: Any confirmed Roth conversion event by deadline.
A14: Outcome date | B14: m/d/yy | C14: By Dec 15, 2026 | D14: Blank when no confirmed event or status unresolved | E14: Date of confirmed conversion event.
A15: Conversion amount | B15: currency | C15: If conversion confirmed | D15: Blank means amount not captured; not zero | E15: Secondary, descriptive only; no advice.

Sheet Assumptions
A1: Assumptions, exclusions, approvals
A2: Supplied facts are distinct from analyst choices. Changes require documented governance approval before outcome review.
A4: Type | B4: Item | C4: Value / rule | D4: Rationale / source | E4: Owner | F4: Approval / status
A5: Supplied fact | B5: Eligibility | C5: Plan eligible Yes; Hourly; retirement date in 2026 | D5: Operating constraints | E5: Benefits Governance | F5: Freeze at 20 Mar 2026
A6: Supplied fact | B6: Capacity | C6: 30 proactive offers Apr–Sep 2026 | D6: Operating constraints | E6: Advisor Operations | F6: Configured
A7: Supplied fact | B7: Outcome deadline | C7: 15 Dec 2026 | D7: Operating constraints | E7: Benefits Operations | F7: Configured
A8: Analyst choice | B8: Random seed | C8: HPC-2026-PEATMOOR-041 | D8: Reproducible SHA-256 rank within Site × prior-interest category; quota 30 | E8: Benefits Analytics | F8: Approve 24 Mar 2026
A9: Analyst choice | B9: Missing prior interest | C9: Retain as Unknown | D9: Source has blanks; no basis to infer willingness | E9: Benefits Analytics | F9: Prespecified
A10: Analyst choice | B10: Missing outcome primary rule | C10: Unknown counts as no confirmed conversion; show upper sensitivity | D10: Preserves all eligible assigned denominators and distinguishes status | E10: Mirela Danforth | F10: Prespecified
A11: Exclusion | B11: Ineligible workforce records | C11: Excluded only if supplied eligibility rule fails | D11: No exclusion for missing prior interest | E11: Benefits Governance | F11: Documented
A12: Limitation | B12: Attendance effect | C12: Not primary causal result | D12: Voluntary attendance / crossover are non-randomized | E12: Mirela Danforth | F12: Readout label required
A13: Approval lock | B13: Prospective freeze | C13: Population, assignment, outcome, and interpretation standard | D13: Must occur before outcome observation | E13: Clara Almeida + Counsel | F13: Pending launch approval

Sheet Assignment Log
A1: Assignment provenance and correction log
A2: Original allocation is recorded below. Add a dated correction request; never overwrite Original assigned arm.
A4: Allocation run | B4: Roster freeze | C4: Allocation approval | D4: Random mechanism | E4: Seed / audit value | F4: Source roster count | G4: Eligible count | H4: Offer count
A5: ALLOC-2026-03-24-A | B5: 46101 | C5: 46105 | D5: SHA-256 rank within Site × prior-interest category; fixed quota | E5: HPC-2026-PEATMOOR-041 | F5: 72 | G5: 60 | H5: 30
A8: Correction requests (append-only)
A9: Request date | B9: Participant Key | C9: Field affected | D9: Original value | E9: Proposed value | F9: Reason | G9: Approved by | H9: Decision date
