Workbook

Sheet Read Me
A1: Ashcombe Council Frozen Call-off Model
A3: Authorized commercial model for Pembroke Supply | source cutoff 28 February 2027
A5: Operating use | B5: Use Reconciliation to authorize the cancellation reading; choose Base or Downside on Forecast; enter an additional April call-off only when authorized.
A7: Cell cue | B7: Amber = user control or future entry | Blue/grey = sourced or calculated | Friday Run Sheet manual fields begin blank.
A9: Commercial review | B9: Cecilia Asante
A10: Dispatch handoff | B10: Ludmila Havlicek
A11: Reusable owner | B11: Dmitri Radulescu
A13: Control | B13: Location | C13: Purpose
A14: Cancellation reading | B14: Reconciliation!C3 | C14: Sets cancellation allocation, contract price and April timing treatment
A15: Selected scenario | B15: Forecast!B3 | C15: Drives frontline cases, value and selected commercial output
A16: Additional April cases | B16: Forecast!B4 | C16: Blank provision; accepts authorized non-negative whole cases

Sheet Source Data
A1: Reconciled Call-off Source Data
A3: Cleaned source values retain raw labels and source-row lineage. Formula columns calculate only accepted commercial contribution. | AB3: Contract price reference | AF3: Frozen cost reference - 28 Feb
AB4: SKU | AC4: v1 through 28-Feb | AD4: v2 from 1-Mar | AF4: SKU | AG4: Cost GBP/case
A5: Source Row ID | B5: Client | C5: Jurisdiction | D5: Depot | E5: SKU | F5: Product | G5: Order ID | H5: Order Date | I5: Scheduled Date | J5: Contract Version | K5: Status | L5: Cases | M5: Unit Price GBP | N5: Data Quality Note | O5: Source Lineage | P5: Include in Analysis | Q5: Analysis Date | R5: Signed Cases | S5: Market Cost GBP | T5: Line Sales GBP | U5: Line Margin GBP | V5: Period | W5: Raw Client Label | X5: Raw Product Label | Y5: Raw Order Date | Z5: Raw Scheduled Date | AA5: Raw Cases | AB5: FSD-COD-5 | AC5: 72.35 | AD5: 75.1 | AF5: FSD-COD-5 | AG5: 49.375
A6: R-1001 | B6: Ashcombe Council | C6: England | D6: Midlands Hub | E6: FSD-COD-5 | F6: North Atlantic Cod Portions 5kg | G6: ACO-270129-01 | H6: 46416 | I6: 46423 | J6: =IF($P6="Yes",IF($Q6<DATE(2027,3,1),"PS-AC-FRZ v1","PS-AC-FRZ v2"),"") -> PS-AC-FRZ v1 | K6: Delivered | L6: 120 | M6: =IF($P6="Yes",IF($Q6<DATE(2027,3,1),SUMIF($AB$5:$AB$7,$E6,$AC$5:$AC$7),SUMIF($AB$5:$AB$7,$E6,$AD$5:$AD$7)),"") -> 72.35 | N6: Product label normalised | O6: R-1001 | P6: Yes | Q6: =IF($P6="Yes",IF($K6="Cancelled",IF(Cancellation_Reading="Order-date / lost demand",$H6,$I6),$I6),"") -> 46423 | R6: =IF($P6="Yes",IF($K6="Cancelled",-$L6,$L6),0) -> 120 | S6: =IF($P6="Yes",SUMIF($AF$5:$AF$7,$E6,$AG$5:$AG$7),"") -> 49.375 | T6: =IF($P6="Yes",$R6*$M6,0) -> 8682 | U6: =IF($P6="Yes",$T6-($R6*$S6),0) -> 2757 | V6: =IF($P6="Yes",TEXT($Q6,"mmm-yyyy"),"") -> Feb-2027 | W6: Ashcombe Council | X6: N Atlantic Cod Portions 5kg | Y6: 46416 | Z6: 46423 | AA6: 120 | AB6: FSD-SAL-10 | AC6: 64.8 | AD6: 66.25 | AF6: FSD-SAL-10 | AG6: 44.625
A7: R-1002 | B7: Ashcombe Council | C7: Wales | D7: Newport Crossdock | E7: FSD-SAL-10 | F7: Atlantic Salmon Portions 10kg | G7: ACO-270131-02 | H7: 46418 | I7: 46426 | J7: =IF($P7="Yes",IF($Q7<DATE(2027,3,1),"PS-AC-FRZ v1","PS-AC-FRZ v2"),"") -> PS-AC-FRZ v1 | K7: Delivered | L7: 80 | M7: =IF($P7="Yes",IF($Q7<DATE(2027,3,1),SUMIF($AB$5:$AB$7,$E7,$AC$5:$AC$7),SUMIF($AB$5:$AB$7,$E7,$AD$5:$AD$7)),"") -> 64.8 | N7: Product label normalised; Order date parsed; Scheduled date parsed; Cases parsed | O7: R-1002 | P7: Yes | Q7: =IF($P7="Yes",IF($K7="Cancelled",IF(Cancellation_Reading="Order-date / lost demand",$H7,$I7),$I7),"") -> 46426 | R7: =IF($P7="Yes",IF($K7="Cancelled",-$L7,$L7),0) -> 80 | S7: =IF($P7="Yes",SUMIF($AF$5:$AF$7,$E7,$AG$5:$AG$7),"") -> 44.625 | T7: =IF($P7="Yes",$R7*$M7,0) -> 5184 | U7: =IF($P7="Yes",$T7-($R7*$S7),0) -> 1614 | V7: =IF($P7="Yes",TEXT($Q7,"mmm-yyyy"),"") -> Feb-2027 | W7: Ashcombe Council | X7: Atlantic salmon portions 10kg | Y7: 31/01/2027 | Z7: 2027/02/08 | AA7: 80 cs | AB7: FSD-PEA-2 | AC7: 27.45 | AD7: 28.15 | AF7: FSD-PEA-2 | AG7: 17.825
A8: R-1003 | B8: Ashcombe Council | C8: Wales | D8: Newport Crossdock | E8: FSD-SAL-10 | F8: Atlantic Salmon Portions 10kg | G8: ACO-270131-02 | H8: 46418 | I8: 46426 | J8: =IF($P8="Yes",IF($Q8<DATE(2027,3,1),"PS-AC-FRZ v1","PS-AC-FRZ v2"),"") | K8: Delivered | L8: 80 | M8: =IF($P8="Yes",IF($Q8<DATE(2027,3,1),SUMIF($AB$5:$AB$7,$E8,$AC$5:$AC$7),SUMIF($AB$5:$AB$7,$E8,$AD$5:$AD$7)),"") | N8: Product label normalised; Order date parsed; Scheduled date parsed; Cases parsed; Migration copy of R-1002; Excluded from commercial totals | O8: R-1002; R-1003 | P8: No - migration copy | Q8: =IF($P8="Yes",IF($K8="Cancelled",IF(Cancellation_Reading="Order-date / lost demand",$H8,$I8),$I8),"") | R8: =IF($P8="Yes",IF($K8="Cancelled",-$L8,$L8),0) -> 0 | S8: =IF($P8="Yes",SUMIF($AF$5:$AF$7,$E8,$AG$5:$AG$7),"") | T8: =IF($P8="Yes",$R8*$M8,0) -> 0 | U8: =IF($P8="Yes",$T8-($R8*$S8),0) -> 0 | V8: =IF($P8="Yes",TEXT($Q8,"mmm-yyyy"),"") | W8: Ashcombe Council | X8: Atlantic salmon portions 10kg | Y8: 31/01/2027 | Z8: 2027/02/08 | AA8: 80 cs
A9: R-1004 | B9: Ashcombe Council | C9: England | D9: Midlands Hub | E9: FSD-PEA-2 | F9: Garden Peas 2kg | G9: ACO-270201-03 | H9: 46419 | I9: 46430 | J9: =IF($P9="Yes",IF($Q9<DATE(2027,3,1),"PS-AC-FRZ v1","PS-AC-FRZ v2"),"") -> PS-AC-FRZ v1 | K9: Delivered | L9: 100 | M9: =IF($P9="Yes",IF($Q9<DATE(2027,3,1),SUMIF($AB$5:$AB$7,$E9,$AC$5:$AC$7),SUMIF($AB$5:$AB$7,$E9,$AD$5:$AD$7)),"") -> 27.45 | N9: Client label normalised; Product label normalised; Order date parsed; Scheduled date parsed | O9: R-1004 | P9: Yes | Q9: =IF($P9="Yes",IF($K9="Cancelled",IF(Cancellation_Reading="Order-date / lost demand",$H9,$I9),$I9),"") -> 46430 | R9: =IF($P9="Yes",IF($K9="Cancelled",-$L9,$L9),0) -> 100 | S9: =IF($P9="Yes",SUMIF($AF$5:$AF$7,$E9,$AG$5:$AG$7),"") -> 17.825 | T9: =IF($P9="Yes",$R9*$M9,0) -> 2745 | U9: =IF($P9="Yes",$T9-($R9*$S9),0) -> 962.5 | V9: =IF($P9="Yes",TEXT($Q9,"mmm-yyyy"),"") -> Feb-2027 | W9: ASHCOMBE COUNCIL | X9: Garden peas 2 KG | Y9: 2027-02-01 | Z9: 2027-02-12 | AA9: 100
A10: R-1005 | B10: Ashcombe Council | C10: Wales | D10: Newport Crossdock | E10: FSD-COD-5 | F10: North Atlantic Cod Portions 5kg | G10: ACO-270202-04 | H10: 46420 | I10: 46434 | J10: =IF($P10="Yes",IF($Q10<DATE(2027,3,1),"PS-AC-FRZ v1","PS-AC-FRZ v2"),"") -> PS-AC-FRZ v1 | K10: Delivered | L10: 60 | M10: =IF($P10="Yes",IF($Q10<DATE(2027,3,1),SUMIF($AB$5:$AB$7,$E10,$AC$5:$AC$7),SUMIF($AB$5:$AB$7,$E10,$AD$5:$AD$7)),"") -> 72.35 | N10: Client label normalised; Product label normalised; Order date parsed; Cases parsed | O10: R-1005 | P10: Yes | Q10: =IF($P10="Yes",IF($K10="Cancelled",IF(Cancellation_Reading="Order-date / lost demand",$H10,$I10),$I10),"") -> 46434 | R10: =IF($P10="Yes",IF($K10="Cancelled",-$L10,$L10),0) -> 60 | S10: =IF($P10="Yes",SUMIF($AF$5:$AF$7,$E10,$AG$5:$AG$7),"") -> 49.375 | T10: =IF($P10="Yes",$R10*$M10,0) -> 4341 | U10: =IF($P10="Yes",$T10-($R10*$S10),0) -> 1378.5 | V10: =IF($P10="Yes",TEXT($Q10,"mmm-yyyy"),"") -> Feb-2027 | W10: Ashcombe Cncl | X10: COD PORTIONS - 5 KG | Y10: 02-02-27 | Z10: 46434 | AA10: 60CASE
A11: R-1006 | B11: Ashcombe Council | C11: England | D11: Midlands Hub | E11: FSD-SAL-10 | F11: Atlantic Salmon Portions 10kg | G11: ACO-270204-05 | H11: 46422 | I11: 46438 | J11: =IF($P11="Yes",IF($Q11<DATE(2027,3,1),"PS-AC-FRZ v1","PS-AC-FRZ v2"),"") -> PS-AC-FRZ v1 | K11: Delivered | L11: 50 | M11: =IF($P11="Yes",IF($Q11<DATE(2027,3,1),SUMIF($AB$5:$AB$7,$E11,$AC$5:$AC$7),SUMIF($AB$5:$AB$7,$E11,$AD$5:$AD$7)),"") -> 64.8 | N11: Client label normalised; Product label normalised; Scheduled date parsed | O11: R-1006 | P11: Yes | Q11: =IF($P11="Yes",IF($K11="Cancelled",IF(Cancellation_Reading="Order-date / lost demand",$H11,$I11),$I11),"") -> 46438 | R11: =IF($P11="Yes",IF($K11="Cancelled",-$L11,$L11),0) -> 50 | S11: =IF($P11="Yes",SUMIF($AF$5:$AF$7,$E11,$AG$5:$AG$7),"") -> 44.625 | T11: =IF($P11="Yes",$R11*$M11,0) -> 3240 | U11: =IF($P11="Yes",$T11-($R11*$S11),0) -> 1008.75 | V11: =IF($P11="Yes",TEXT($Q11,"mmm-yyyy"),"") -> Feb-2027 | W11: Ashcombe Council | X11: Atlantic Salmon 10kg | Y11: 46422 | Z11: 20-Feb-27 | AA11: 50
A12: R-1007 | B12: Ashcombe Council | C12: Wales | D12: Newport Crossdock | E12: FSD-PEA-2 | F12: Garden Peas 2kg | G12: ACO-270208-06 | H12: 46426 | I12: 46446 | J12: =IF($P12="Yes",IF($Q12<DATE(2027,3,1),"PS-AC-FRZ v1","PS-AC-FRZ v2"),"") -> PS-AC-FRZ v1 | K12: Delivered | L12: 45 | M12: =IF($P12="Yes",IF($Q12<DATE(2027,3,1),SUMIF($AB$5:$AB$7,$E12,$AC$5:$AC$7),SUMIF($AB$5:$AB$7,$E12,$AD$5:$AD$7)),"") -> 27.45 | N12: Client label normalised; Product label normalised; Order date parsed; Scheduled date parsed; Cases parsed | O12: R-1007 | P12: Yes | Q12: =IF($P12="Yes",IF($K12="Cancelled",IF(Cancellation_Reading="Order-date / lost demand",$H12,$I12),$I12),"") -> 46446 | R12: =IF($P12="Yes",IF($K12="Cancelled",-$L12,$L12),0) -> 45 | S12: =IF($P12="Yes",SUMIF($AF$5:$AF$7,$E12,$AG$5:$AG$7),"") -> 17.825 | T12: =IF($P12="Yes",$R12*$M12,0) -> 1235.25 | U12: =IF($P12="Yes",$T12-($R12*$S12),0) -> 433.125 | V12: =IF($P12="Yes",TEXT($Q12,"mmm-yyyy"),"") -> Feb-2027 | W12: ASHCOMBE Council | X12: GARDEN PEAS 2kg | Y12: 20270208 | Z12: 28.02.2027 | AA12: 45 cases
A13: R-1008 | B13: Ashcombe Council | C13: England | D13: Midlands Hub | E13: FSD-COD-5 | F13: North Atlantic Cod Portions 5kg | G13: ACO-270215-07 | H13: 46433 | I13: 46449 | J13: =IF($P13="Yes",IF($Q13<DATE(2027,3,1),"PS-AC-FRZ v1","PS-AC-FRZ v2"),"") -> PS-AC-FRZ v2 | K13: Delivered | L13: 140 | M13: =IF($P13="Yes",IF($Q13<DATE(2027,3,1),SUMIF($AB$5:$AB$7,$E13,$AC$5:$AC$7),SUMIF($AB$5:$AB$7,$E13,$AD$5:$AD$7)),"") -> 75.1 | N13: Product label normalised; Scheduled date parsed | O13: R-1008 | P13: Yes | Q13: =IF($P13="Yes",IF($K13="Cancelled",IF(Cancellation_Reading="Order-date / lost demand",$H13,$I13),$I13),"") -> 46449 | R13: =IF($P13="Yes",IF($K13="Cancelled",-$L13,$L13),0) -> 140 | S13: =IF($P13="Yes",SUMIF($AF$5:$AF$7,$E13,$AG$5:$AG$7),"") -> 49.375 | T13: =IF($P13="Yes",$R13*$M13,0) -> 10514 | U13: =IF($P13="Yes",$T13-($R13*$S13),0) -> 3601.5 | V13: =IF($P13="Yes",TEXT($Q13,"mmm-yyyy"),"") -> Mar-2027 | W13: Ashcombe Council | X13: Cod portions 5kg | Y13: 46433 | Z13: 03.03.2027 | AA13: 140
A14: R-1009 | B14: Ashcombe Council | C14: Wales | D14: Newport Crossdock | E14: FSD-COD-5 | F14: North Atlantic Cod Portions 5kg | G14: ACO-270216-08 | H14: 46434 | I14: 46451 | J14: =IF($P14="Yes",IF($Q14<DATE(2027,3,1),"PS-AC-FRZ v1","PS-AC-FRZ v2"),"") -> PS-AC-FRZ v2 | K14: Delivered | L14: 90 | M14: =IF($P14="Yes",IF($Q14<DATE(2027,3,1),SUMIF($AB$5:$AB$7,$E14,$AC$5:$AC$7),SUMIF($AB$5:$AB$7,$E14,$AD$5:$AD$7)),"") -> 75.1 | N14: Product label normalised; Order date parsed; Cases parsed | O14: R-1009 | P14: Yes | Q14: =IF($P14="Yes",IF($K14="Cancelled",IF(Cancellation_Reading="Order-date / lost demand",$H14,$I14),$I14),"") -> 46451 | R14: =IF($P14="Yes",IF($K14="Cancelled",-$L14,$L14),0) -> 90 | S14: =IF($P14="Yes",SUMIF($AF$5:$AF$7,$E14,$AG$5:$AG$7),"") -> 49.375 | T14: =IF($P14="Yes",$R14*$M14,0) -> 6759 | U14: =IF($P14="Yes",$T14-($R14*$S14),0) -> 2315.25 | V14: =IF($P14="Yes",TEXT($Q14,"mmm-yyyy"),"") -> Mar-2027 | W14: Ashcombe Council | X14: N. Atlantic cod 5kg | Y14: 16/02/2027 | Z14: 46451 | AA14: 90 cases
A15: R-1010 | B15: Ashcombe Council | C15: England | D15: Midlands Hub | E15: FSD-SAL-10 | F15: Atlantic Salmon Portions 10kg | G15: ACO-270218-09 | H15: 46436 | I15: 46456 | J15: =IF($P15="Yes",IF($Q15<DATE(2027,3,1),"PS-AC-FRZ v1","PS-AC-FRZ v2"),"") -> PS-AC-FRZ v2 | K15: Delivered | L15: 75 | M15: =IF($P15="Yes",IF($Q15<DATE(2027,3,1),SUMIF($AB$5:$AB$7,$E15,$AC$5:$AC$7),SUMIF($AB$5:$AB$7,$E15,$AD$5:$AD$7)),"") -> 66.25 | N15: Product label normalised; Scheduled date parsed | O15: R-1010 | P15: Yes | Q15: =IF($P15="Yes",IF($K15="Cancelled",IF(Cancellation_Reading="Order-date / lost demand",$H15,$I15),$I15),"") -> 46456 | R15: =IF($P15="Yes",IF($K15="Cancelled",-$L15,$L15),0) -> 75 | S15: =IF($P15="Yes",SUMIF($AF$5:$AF$7,$E15,$AG$5:$AG$7),"") -> 44.625 | T15: =IF($P15="Yes",$R15*$M15,0) -> 4968.75 | U15: =IF($P15="Yes",$T15-($R15*$S15),0) -> 1621.875 | V15: =IF($P15="Yes",TEXT($Q15,"mmm-yyyy"),"") -> Mar-2027 | W15: Ashcombe Council | X15: Atlantic salmon portions 10 kg | Y15: 46436 | Z15: 10-Mar-2027 | AA15: 75
A16: R-1011 | B16: Ashcombe Council | C16: Wales | D16: Newport Crossdock | E16: FSD-SAL-10 | F16: Atlantic Salmon Portions 10kg | G16: ACO-270219-10 | H16: 46437 | I16: 46463 | J16: =IF($P16="Yes",IF($Q16<DATE(2027,3,1),"PS-AC-FRZ v1","PS-AC-FRZ v2"),"") -> PS-AC-FRZ v2 | K16: Delivered | L16: 65 | M16: =IF($P16="Yes",IF($Q16<DATE(2027,3,1),SUMIF($AB$5:$AB$7,$E16,$AC$5:$AC$7),SUMIF($AB$5:$AB$7,$E16,$AD$5:$AD$7)),"") -> 66.25 | N16: Client label normalised; Product label normalised; Order date parsed; Scheduled date parsed; Cases parsed | O16: R-1011 | P16: Yes | Q16: =IF($P16="Yes",IF($K16="Cancelled",IF(Cancellation_Reading="Order-date / lost demand",$H16,$I16),$I16),"") -> 46463 | R16: =IF($P16="Yes",IF($K16="Cancelled",-$L16,$L16),0) -> 65 | S16: =IF($P16="Yes",SUMIF($AF$5:$AF$7,$E16,$AG$5:$AG$7),"") -> 44.625 | T16: =IF($P16="Yes",$R16*$M16,0) -> 4306.25 | U16: =IF($P16="Yes",$T16-($R16*$S16),0) -> 1405.625 | V16: =IF($P16="Yes",TEXT($Q16,"mmm-yyyy"),"") -> Mar-2027 | W16: Ashcombe Cncl | X16: ATLANTIC SALMON 10KG | Y16: 19-Feb-27 | Z16: 17/03/2027 | AA16: 65CS
A17: R-1012 | B17: Ashcombe Council | C17: England | D17: Midlands Hub | E17: FSD-PEA-2 | F17: Garden Peas 2kg | G17: ACO-270220-11 | H17: 46438 | I17: 46466 | J17: =IF($P17="Yes",IF($Q17<DATE(2027,3,1),"PS-AC-FRZ v1","PS-AC-FRZ v2"),"") -> PS-AC-FRZ v2 | K17: Delivered | L17: 120 | M17: =IF($P17="Yes",IF($Q17<DATE(2027,3,1),SUMIF($AB$5:$AB$7,$E17,$AC$5:$AC$7),SUMIF($AB$5:$AB$7,$E17,$AD$5:$AD$7)),"") -> 28.15 | N17: Product label normalised | O17: R-1012 | P17: Yes | Q17: =IF($P17="Yes",IF($K17="Cancelled",IF(Cancellation_Reading="Order-date / lost demand",$H17,$I17),$I17),"") -> 46466 | R17: =IF($P17="Yes",IF($K17="Cancelled",-$L17,$L17),0) -> 120 | S17: =IF($P17="Yes",SUMIF($AF$5:$AF$7,$E17,$AG$5:$AG$7),"") -> 17.825 | T17: =IF($P17="Yes",$R17*$M17,0) -> 3378 | U17: =IF($P17="Yes",$T17-($R17*$S17),0) -> 1239 | V17: =IF($P17="Yes",TEXT($Q17,"mmm-yyyy"),"") -> Mar-2027 | W17: Ashcombe Council | X17: Garden peas 2kg | Y17: 46438 | Z17: 46466 | AA17: 120
A18: R-1013 | B18: Ashcombe Council | C18: England | D18: Midlands Hub | E18: FSD-PEA-2 | F18: Garden Peas 2kg | G18: ACO-270220-11 | H18: 46438 | I18: 46466 | J18: =IF($P18="Yes",IF($Q18<DATE(2027,3,1),"PS-AC-FRZ v1","PS-AC-FRZ v2"),"") | K18: Delivered | L18: 120 | M18: =IF($P18="Yes",IF($Q18<DATE(2027,3,1),SUMIF($AB$5:$AB$7,$E18,$AC$5:$AC$7),SUMIF($AB$5:$AB$7,$E18,$AD$5:$AD$7)),"") | N18: Product label normalised; Migration copy of R-1012; Excluded from commercial totals | O18: R-1012; R-1013 | P18: No - migration copy | Q18: =IF($P18="Yes",IF($K18="Cancelled",IF(Cancellation_Reading="Order-date / lost demand",$H18,$I18),$I18),"") | R18: =IF($P18="Yes",IF($K18="Cancelled",-$L18,$L18),0) -> 0 | S18: =IF($P18="Yes",SUMIF($AF$5:$AF$7,$E18,$AG$5:$AG$7),"") | T18: =IF($P18="Yes",$R18*$M18,0) -> 0 | U18: =IF($P18="Yes",$T18-($R18*$S18),0) -> 0 | V18: =IF($P18="Yes",TEXT($Q18,"mmm-yyyy"),"") | W18: Ashcombe Council | X18: Garden peas 2kg | Y18: 46438 | Z18: 46466 | AA18: 120
A19: R-1014 | B19: Ashcombe Council | C19: Wales | D19: Newport Crossdock | E19: FSD-PEA-2 | F19: Garden Peas 2kg | G19: ACO-270221-12 | H19: 46439 | I19: 46470 | J19: =IF($P19="Yes",IF($Q19<DATE(2027,3,1),"PS-AC-FRZ v1","PS-AC-FRZ v2"),"") -> PS-AC-FRZ v2 | K19: Delivered | L19: 80 | M19: =IF($P19="Yes",IF($Q19<DATE(2027,3,1),SUMIF($AB$5:$AB$7,$E19,$AC$5:$AC$7),SUMIF($AB$5:$AB$7,$E19,$AD$5:$AD$7)),"") -> 28.15 | N19: Client label normalised; Product label normalised; Order date parsed; Scheduled date parsed | O19: R-1014 | P19: Yes | Q19: =IF($P19="Yes",IF($K19="Cancelled",IF(Cancellation_Reading="Order-date / lost demand",$H19,$I19),$I19),"") -> 46470 | R19: =IF($P19="Yes",IF($K19="Cancelled",-$L19,$L19),0) -> 80 | S19: =IF($P19="Yes",SUMIF($AF$5:$AF$7,$E19,$AG$5:$AG$7),"") -> 17.825 | T19: =IF($P19="Yes",$R19*$M19,0) -> 2252 | U19: =IF($P19="Yes",$T19-($R19*$S19),0) -> 826 | V19: =IF($P19="Yes",TEXT($Q19,"mmm-yyyy"),"") -> Mar-2027 | W19: ASHCOMBE COUNCIL | X19: Garden Peas 2 KG | Y19: 21/02/2027 | Z19: 24.03.2027 | AA19: 80
A20: R-1015 | B20: Ashcombe Council | C20: England | D20: Midlands Hub | E20: FSD-COD-5 | F20: North Atlantic Cod Portions 5kg | G20: INT-270222 | H20: 46440 | I20: 46441 | J20: =IF($P20="Yes",IF($Q20<DATE(2027,3,1),"PS-AC-FRZ v1","PS-AC-FRZ v2"),"") | K20: Internal sample | L20: 6 | M20: =IF($P20="Yes",IF($Q20<DATE(2027,3,1),SUMIF($AB$5:$AB$7,$E20,$AC$5:$AC$7),SUMIF($AB$5:$AB$7,$E20,$AD$5:$AD$7)),"") | N20: Product label normalised; Cases parsed; Excluded from commercial totals | O20: R-1015 | P20: No - internal sample | Q20: =IF($P20="Yes",IF($K20="Cancelled",IF(Cancellation_Reading="Order-date / lost demand",$H20,$I20),$I20),"") | R20: =IF($P20="Yes",IF($K20="Cancelled",-$L20,$L20),0) -> 0 | S20: =IF($P20="Yes",SUMIF($AF$5:$AF$7,$E20,$AG$5:$AG$7),"") | T20: =IF($P20="Yes",$R20*$M20,0) -> 0 | U20: =IF($P20="Yes",$T20-($R20*$S20),0) -> 0 | V20: =IF($P20="Yes",TEXT($Q20,"mmm-yyyy"),"") | W20: Ashcombe Council | X20: Cod Portions 5kg | Y20: 46440 | Z20: 46441 | AA20: 6 cs
A21: R-1016 | B21: Ashcombe Council | C21: Wales | D21: Newport Crossdock | E21: FRH-LAM-10 | F21: Fresh lamb portions 10kg | G21: ACO-270223-13 | H21: 46441 | I21: 46468 | J21: =IF($P21="Yes",IF($Q21<DATE(2027,3,1),"PS-AC-FRZ v1","PS-AC-FRZ v2"),"") | K21: Delivered | L21: 20 | M21: =IF($P21="Yes",IF($Q21<DATE(2027,3,1),SUMIF($AB$5:$AB$7,$E21,$AC$5:$AC$7),SUMIF($AB$5:$AB$7,$E21,$AD$5:$AD$7)),"") | N21: Excluded from commercial totals | O21: R-1016 | P21: No - non-frozen | Q21: =IF($P21="Yes",IF($K21="Cancelled",IF(Cancellation_Reading="Order-date / lost demand",$H21,$I21),$I21),"") | R21: =IF($P21="Yes",IF($K21="Cancelled",-$L21,$L21),0) -> 0 | S21: =IF($P21="Yes",SUMIF($AF$5:$AF$7,$E21,$AG$5:$AG$7),"") | T21: =IF($P21="Yes",$R21*$M21,0) -> 0 | U21: =IF($P21="Yes",$T21-($R21*$S21),0) -> 0 | V21: =IF($P21="Yes",TEXT($Q21,"mmm-yyyy"),"") | W21: Ashcombe Council | X21: Fresh lamb portions 10kg | Y21: 46441 | Z21: 46468 | AA21: 20
A22: R-1017 | B22: Breckland Borough | C22: England | D22: Midlands Hub | E22: FSD-COD-5 | F22: North Atlantic Cod Portions 5kg | G22: BBC-270224-01 | H22: 46442 | I22: 46458 | J22: =IF($P22="Yes",IF($Q22<DATE(2027,3,1),"PS-AC-FRZ v1","PS-AC-FRZ v2"),"") | K22: Delivered | L22: 70 | M22: =IF($P22="Yes",IF($Q22<DATE(2027,3,1),SUMIF($AB$5:$AB$7,$E22,$AC$5:$AC$7),SUMIF($AB$5:$AB$7,$E22,$AD$5:$AD$7)),"") | N22: Product label normalised; Excluded from commercial totals | O22: R-1017 | P22: No - other client | Q22: =IF($P22="Yes",IF($K22="Cancelled",IF(Cancellation_Reading="Order-date / lost demand",$H22,$I22),$I22),"") | R22: =IF($P22="Yes",IF($K22="Cancelled",-$L22,$L22),0) -> 0 | S22: =IF($P22="Yes",SUMIF($AF$5:$AF$7,$E22,$AG$5:$AG$7),"") | T22: =IF($P22="Yes",$R22*$M22,0) -> 0 | U22: =IF($P22="Yes",$T22-($R22*$S22),0) -> 0 | V22: =IF($P22="Yes",TEXT($Q22,"mmm-yyyy"),"") | W22: Breckland Borough | X22: N Atlantic Cod Portions 5kg | Y22: 46442 | Z22: 46458 | AA22: 70
A23: R-1018 | B23: Ashcombe Council | C23: England | D23: Midlands Hub | E23: FSD-SAL-10 | F23: Atlantic Salmon Portions 10kg | G23: ACO-270225-14 | H23: 46443 | I23: 46464 | J23: =IF($P23="Yes",IF($Q23<DATE(2027,3,1),"PS-AC-FRZ v1","PS-AC-FRZ v2"),"") -> PS-AC-FRZ v2 | K23: Delivered | L23: 55 | M23: =IF($P23="Yes",IF($Q23<DATE(2027,3,1),SUMIF($AB$5:$AB$7,$E23,$AC$5:$AC$7),SUMIF($AB$5:$AB$7,$E23,$AD$5:$AD$7)),"") -> 66.25 | N23: Product label normalised; Order date parsed | O23: R-1018 | P23: Yes | Q23: =IF($P23="Yes",IF($K23="Cancelled",IF(Cancellation_Reading="Order-date / lost demand",$H23,$I23),$I23),"") -> 46464 | R23: =IF($P23="Yes",IF($K23="Cancelled",-$L23,$L23),0) -> 55 | S23: =IF($P23="Yes",SUMIF($AF$5:$AF$7,$E23,$AG$5:$AG$7),"") -> 44.625 | T23: =IF($P23="Yes",$R23*$M23,0) -> 3643.75 | U23: =IF($P23="Yes",$T23-($R23*$S23),0) -> 1189.375 | V23: =IF($P23="Yes",TEXT($Q23,"mmm-yyyy"),"") -> Mar-2027 | W23: Ashcombe Council | X23: Atlantic salmon portions 10kg | Y23: 25/02/2027 | Z23: 46464 | AA23: 55
A24: R-1019 | B24: Ashcombe Council | C24: Wales | D24: Newport Crossdock | E24: FSD-COD-5 | F24: North Atlantic Cod Portions 5kg | G24: ACO-270226-15 | H24: 46444 | I24: 46472 | J24: =IF($P24="Yes",IF($Q24<DATE(2027,3,1),"PS-AC-FRZ v1","PS-AC-FRZ v2"),"") -> PS-AC-FRZ v2 | K24: Delivered | L24: 40 | M24: =IF($P24="Yes",IF($Q24<DATE(2027,3,1),SUMIF($AB$5:$AB$7,$E24,$AC$5:$AC$7),SUMIF($AB$5:$AB$7,$E24,$AD$5:$AD$7)),"") -> 75.1 | N24: Product label normalised; Scheduled date parsed; Cases parsed | O24: R-1019 | P24: Yes | Q24: =IF($P24="Yes",IF($K24="Cancelled",IF(Cancellation_Reading="Order-date / lost demand",$H24,$I24),$I24),"") -> 46472 | R24: =IF($P24="Yes",IF($K24="Cancelled",-$L24,$L24),0) -> 40 | S24: =IF($P24="Yes",SUMIF($AF$5:$AF$7,$E24,$AG$5:$AG$7),"") -> 49.375 | T24: =IF($P24="Yes",$R24*$M24,0) -> 3004 | U24: =IF($P24="Yes",$T24-($R24*$S24),0) -> 1029 | V24: =IF($P24="Yes",TEXT($Q24,"mmm-yyyy"),"") -> Mar-2027 | W24: Ashcombe Council | X24: COD portions 5 KG | Y24: 46444 | Z24: 26.03.2027 | AA24: 40.00*
A25: R-1020 | B25: Ashcombe Council | C25: England | D25: Midlands Hub | E25: FSD-PEA-2 | F25: Garden Peas 2kg | G25: ACO-270227-16 | H25: 46445 | I25: 46474 | J25: =IF($P25="Yes",IF($Q25<DATE(2027,3,1),"PS-AC-FRZ v1","PS-AC-FRZ v2"),"") -> PS-AC-FRZ v2 | K25: Delivered | L25: 35 | M25: =IF($P25="Yes",IF($Q25<DATE(2027,3,1),SUMIF($AB$5:$AB$7,$E25,$AC$5:$AC$7),SUMIF($AB$5:$AB$7,$E25,$AD$5:$AD$7)),"") -> 28.15 | N25: Product label normalised | O25: R-1020 | P25: Yes | Q25: =IF($P25="Yes",IF($K25="Cancelled",IF(Cancellation_Reading="Order-date / lost demand",$H25,$I25),$I25),"") -> 46474 | R25: =IF($P25="Yes",IF($K25="Cancelled",-$L25,$L25),0) -> 35 | S25: =IF($P25="Yes",SUMIF($AF$5:$AF$7,$E25,$AG$5:$AG$7),"") -> 17.825 | T25: =IF($P25="Yes",$R25*$M25,0) -> 985.25 | U25: =IF($P25="Yes",$T25-($R25*$S25),0) -> 361.375 | V25: =IF($P25="Yes",TEXT($Q25,"mmm-yyyy"),"") -> Mar-2027 | W25: Ashcombe Council | X25: Garden peas 2kg | Y25: 46445 | Z25: 46474 | AA25: 35
A26: R-1021 | B26: Ashcombe Council | C26: England | D26: Midlands Hub | E26: FSD-COD-5 | F26: North Atlantic Cod Portions 5kg | G26: ACO-270220-17 | H26: 46438 | I26: 46477 | J26: =IF($P26="Yes",IF($Q26<DATE(2027,3,1),"PS-AC-FRZ v1","PS-AC-FRZ v2"),"") -> PS-AC-FRZ v2 | K26: Cancelled | L26: 70 | M26: =IF($P26="Yes",IF($Q26<DATE(2027,3,1),SUMIF($AB$5:$AB$7,$E26,$AC$5:$AC$7),SUMIF($AB$5:$AB$7,$E26,$AD$5:$AD$7)),"") -> 75.1 | N26: Product label normalised; Order date parsed; Scheduled date parsed; Cases parsed | O26: R-1021 | P26: Yes | Q26: =IF($P26="Yes",IF($K26="Cancelled",IF(Cancellation_Reading="Order-date / lost demand",$H26,$I26),$I26),"") -> 46477 | R26: =IF($P26="Yes",IF($K26="Cancelled",-$L26,$L26),0) -> -70 | S26: =IF($P26="Yes",SUMIF($AF$5:$AF$7,$E26,$AG$5:$AG$7),"") -> 49.375 | T26: =IF($P26="Yes",$R26*$M26,0) -> -5257 | U26: =IF($P26="Yes",$T26-($R26*$S26),0) -> -1800.75 | V26: =IF($P26="Yes",TEXT($Q26,"mmm-yyyy"),"") -> Mar-2027 | W26: Ashcombe Council | X26: N Atlantic Cod Portions 5kg | Y26: 20/02/27 | Z26: 31-Mar-2027 | AA26: 70 cs

Sheet Reconciliation
A1: February to March Reconciliation
A3: Authorized cancellation treatment | B3: Cancellation reading | C3: Scheduled-delivery / one-week shift
B5: Commercial rationale | C5: =IF(Cancellation_Reading="Scheduled-delivery / one-week shift","Scheduled delivery on 31 March falls in PS-AC-FRZ v2. The 26 February wording says the requirement was revised one week later, so the 70-case cancellation is removed from March at v2 and carried into April as timing; demand is not treated as lost.","The 20 February order falls in PS-AC-FRZ v1. With no replacement call-off at cut-off, the 70-case cancellation is recorded against February as lost demand; no April volume is added.") -> Scheduled delivery on 31 March falls in PS-AC-FRZ v2. The 26 February wording says the requirement was revised one week later, so the 70-case cancellation is removed from March at v2 and carried into April as timing; demand is not treated as lost.
A10: Metric | B10: February 2027 | C10: March 2027 | D10: Absolute variance | E10: Variance %
A11: Volume (cases) | B11: =SUMIFS('Source Data'!$R$6:$R$26,'Source Data'!$Q$6:$Q$26,">="&DATE(2027,2,1),'Source Data'!$Q$6:$Q$26,"<"&DATE(2027,3,1)) -> 455 | C11: =SUMIFS('Source Data'!$R$6:$R$26,'Source Data'!$Q$6:$Q$26,">="&DATE(2027,3,1),'Source Data'!$Q$6:$Q$26,"<"&DATE(2027,4,1)) -> 630 | D11: =C11-B11 -> 175 | E11: =IFERROR(D11/B11,0) -> 0.38461538
A12: Sales value (GBP) | B12: =SUMIFS('Source Data'!$T$6:$T$26,'Source Data'!$Q$6:$Q$26,">="&DATE(2027,2,1),'Source Data'!$Q$6:$Q$26,"<"&DATE(2027,3,1)) -> 25427.25 | C12: =SUMIFS('Source Data'!$T$6:$T$26,'Source Data'!$Q$6:$Q$26,">="&DATE(2027,3,1),'Source Data'!$Q$6:$Q$26,"<"&DATE(2027,4,1)) -> 34554 | D12: =C12-B12 -> 9126.75 | E12: =IFERROR(D12/B12,0) -> 0.35893579
A13: Margin (GBP) | B13: =SUMIFS('Source Data'!$U$6:$U$26,'Source Data'!$Q$6:$Q$26,">="&DATE(2027,2,1),'Source Data'!$Q$6:$Q$26,"<"&DATE(2027,3,1)) -> 8153.875 | C13: =SUMIFS('Source Data'!$U$6:$U$26,'Source Data'!$Q$6:$Q$26,">="&DATE(2027,3,1),'Source Data'!$Q$6:$Q$26,"<"&DATE(2027,4,1)) -> 11788.25 | D13: =C13-B13 -> 3634.375 | E13: =IFERROR(D13/B13,0) -> 0.44572366
A16: Material-change narrative | B16: =IF(Cancellation_Reading="Scheduled-delivery / one-week shift","March is "&TEXT(D11,"0.0")&" cases and "&TEXT(D13,"£#,##0")&" margin versus February. The selected scheduled-delivery reading includes the 70-case Cod cancellation at v2 in March and carries that supported quantity into April. The remaining scheduled frozen line mix drives the comparison; no further demand or market cause is inferred.","March is "&TEXT(D11,"0.0")&" cases and "&TEXT(D13,"£#,##0")&" margin versus February. The selected order-date reading records the 70-case Cod cancellation in February at v1 as lost demand and adds no April replacement. The remaining scheduled frozen line mix drives the comparison; no further demand or market cause is inferred.") -> March is 175.0 cases and £3,634 margin versus February. The selected scheduled-delivery reading includes the 70-case Cod cancellation at v2 in March and carries that supported quantity into April. The remaining scheduled frozen line mix drives the comparison; no further demand or market cause is inferred.
A21: Source cutoff | B21: 28 February 2027 | D21: Contract reference | E21: PS-AC-FRZ v1 / v2

Sheet Forecast
A1: April Commercial Projection
A3: Selected frontline scenario | B3: Base | J3: Sourced April assumptions
A4: Additional April call-off (cases) | J4: Base volume factor | K4: 1.06
A5: Normal planning threshold | B5: =K8 -> 260 | J5: Downside volume factor | K5: 0.86
J6: Base cost adjustment | K6: 0
A7: Dispatch plan date | B7: =DATE(2027,4,9) -> 46486 | J7: Downside cost adjustment | K7: 0.035
J8: Normal planning threshold | K8: 260
J9: Source cutoff | K9: 28-Feb-2027
A11: SKU | B11: Product | C11: March delivered basis | D11: Timing shift cases | E11: April unit price | F11: Base cases | G11: Base sales | H11: Base cost | I11: Base margin | J11: Downside cases | K11: Downside sales | L11: Downside cost | M11: Downside margin | N11: Selected cases | O11: Selected sales | P11: Selected cost | Q11: Selected margin
A12: FSD-COD-5 | B12: North Atlantic Cod Portions 5kg | C12: =SUMIFS('Source Data'!$L$6:$L$26,'Source Data'!$E$6:$E$26,$A12,'Source Data'!$P$6:$P$26,"Yes",'Source Data'!$K$6:$K$26,"Delivered",'Source Data'!$I$6:$I$26,">="&DATE(2027,3,1),'Source Data'!$I$6:$I$26,"<"&DATE(2027,4,1)) -> 270 | D12: =IF(Cancellation_Reading="Scheduled-delivery / one-week shift",SUMIFS('Source Data'!$L$6:$L$26,'Source Data'!$E$6:$E$26,$A12,'Source Data'!$P$6:$P$26,"Yes",'Source Data'!$K$6:$K$26,"Cancelled"),0) -> 70 | E12: =SUMIF('Source Data'!$AB$5:$AB$7,$A12,'Source Data'!$AD$5:$AD$7) -> 75.1 | F12: =C12*$K$4+D12+IF($B$4="",0,$B$4)*IFERROR(C12/SUM($C$12:$C$14),0) -> 356.2 | G12: =F12*E12 -> 26750.62 | H12: =F12*SUMIF('Source Data'!$AF$5:$AF$7,$A12,'Source Data'!$AG$5:$AG$7)*(1+$K$6) -> 17587.375 | I12: =G12-H12 -> 9163.245 | J12: =C12*$K$5+D12+IF($B$4="",0,$B$4)*IFERROR(C12/SUM($C$12:$C$14),0) -> 302.2 | K12: =J12*E12 -> 22695.22 | L12: =J12*SUMIF('Source Data'!$AF$5:$AF$7,$A12,'Source Data'!$AG$5:$AG$7)*(1+$K$7) -> 15443.364 | M12: =K12-L12 -> 7251.8556 | N12: =IF(Selected_Scenario="Base",F12,J12) -> 356.2 | O12: =IF(Selected_Scenario="Base",G12,K12) -> 26750.62 | P12: =IF(Selected_Scenario="Base",H12,L12) -> 17587.375 | Q12: =IF(Selected_Scenario="Base",I12,M12) -> 9163.245
A13: FSD-SAL-10 | B13: Atlantic Salmon Portions 10kg | C13: =SUMIFS('Source Data'!$L$6:$L$26,'Source Data'!$E$6:$E$26,$A13,'Source Data'!$P$6:$P$26,"Yes",'Source Data'!$K$6:$K$26,"Delivered",'Source Data'!$I$6:$I$26,">="&DATE(2027,3,1),'Source Data'!$I$6:$I$26,"<"&DATE(2027,4,1)) -> 195 | D13: =IF(Cancellation_Reading="Scheduled-delivery / one-week shift",SUMIFS('Source Data'!$L$6:$L$26,'Source Data'!$E$6:$E$26,$A13,'Source Data'!$P$6:$P$26,"Yes",'Source Data'!$K$6:$K$26,"Cancelled"),0) -> 0 | E13: =SUMIF('Source Data'!$AB$5:$AB$7,$A13,'Source Data'!$AD$5:$AD$7) -> 66.25 | F13: =C13*$K$4+D13+IF($B$4="",0,$B$4)*IFERROR(C13/SUM($C$12:$C$14),0) -> 206.7 | G13: =F13*E13 -> 13693.875 | H13: =F13*SUMIF('Source Data'!$AF$5:$AF$7,$A13,'Source Data'!$AG$5:$AG$7)*(1+$K$6) -> 9223.9875 | I13: =G13-H13 -> 4469.8875 | J13: =C13*$K$5+D13+IF($B$4="",0,$B$4)*IFERROR(C13/SUM($C$12:$C$14),0) -> 167.7 | K13: =J13*E13 -> 11110.125 | L13: =J13*SUMIF('Source Data'!$AF$5:$AF$7,$A13,'Source Data'!$AG$5:$AG$7)*(1+$K$7) -> 7745.5389 | M13: =K13-L13 -> 3364.5861 | N13: =IF(Selected_Scenario="Base",F13,J13) -> 206.7 | O13: =IF(Selected_Scenario="Base",G13,K13) -> 13693.875 | P13: =IF(Selected_Scenario="Base",H13,L13) -> 9223.9875 | Q13: =IF(Selected_Scenario="Base",I13,M13) -> 4469.8875
A14: FSD-PEA-2 | B14: Garden Peas 2kg | C14: =SUMIFS('Source Data'!$L$6:$L$26,'Source Data'!$E$6:$E$26,$A14,'Source Data'!$P$6:$P$26,"Yes",'Source Data'!$K$6:$K$26,"Delivered",'Source Data'!$I$6:$I$26,">="&DATE(2027,3,1),'Source Data'!$I$6:$I$26,"<"&DATE(2027,4,1)) -> 235 | D14: =IF(Cancellation_Reading="Scheduled-delivery / one-week shift",SUMIFS('Source Data'!$L$6:$L$26,'Source Data'!$E$6:$E$26,$A14,'Source Data'!$P$6:$P$26,"Yes",'Source Data'!$K$6:$K$26,"Cancelled"),0) -> 0 | E14: =SUMIF('Source Data'!$AB$5:$AB$7,$A14,'Source Data'!$AD$5:$AD$7) -> 28.15 | F14: =C14*$K$4+D14+IF($B$4="",0,$B$4)*IFERROR(C14/SUM($C$12:$C$14),0) -> 249.1 | G14: =F14*E14 -> 7012.165 | H14: =F14*SUMIF('Source Data'!$AF$5:$AF$7,$A14,'Source Data'!$AG$5:$AG$7)*(1+$K$6) -> 4440.2075 | I14: =G14-H14 -> 2571.9575 | J14: =C14*$K$5+D14+IF($B$4="",0,$B$4)*IFERROR(C14/SUM($C$12:$C$14),0) -> 202.1 | K14: =J14*E14 -> 5689.115 | L14: =J14*SUMIF('Source Data'!$AF$5:$AF$7,$A14,'Source Data'!$AG$5:$AG$7)*(1+$K$7) -> 3728.5176 | M14: =K14-L14 -> 1960.5974 | N14: =IF(Selected_Scenario="Base",F14,J14) -> 249.1 | O14: =IF(Selected_Scenario="Base",G14,K14) -> 7012.165 | P14: =IF(Selected_Scenario="Base",H14,L14) -> 4440.2075 | Q14: =IF(Selected_Scenario="Base",I14,M14) -> 2571.9575
A15: TOTAL | C15: =SUM(C12:C14) -> 700 | D15: =SUM(D12:D14) -> 70 | F15: =SUM(F12:F14) -> 812 | G15: =SUM(G12:G14) -> 47456.66 | H15: =SUM(H12:H14) -> 31251.57 | I15: =SUM(I12:I14) -> 16205.09 | J15: =SUM(J12:J14) -> 672 | K15: =SUM(K12:K14) -> 39494.46 | L15: =SUM(L12:L14) -> 26917.421 | M15: =SUM(M12:M14) -> 12577.039 | ... Q15: =SUM(Q12:Q14) -> 16205.09
A18: Selected scenario output | B18: =Selected_Scenario -> Base
A19: Volume (cases) | B19: =N15 -> 812
A20: Sales value (GBP) | B20: =O15 -> 47456.66
A21: Cost (GBP) | B21: =P15 -> 31251.57
A22: Margin (GBP) | B22: =Q15 -> 16205.09
A25: Dispatch allocation - selected scenario
A26: SKU | B26: Product | C26: Depot | D26: Jurisdiction | E26: Allocation % | F26: Selected cases | G26: Unit price GBP | H26: Planned value GBP
A27: FSD-COD-5 | B27: North Atlantic Cod Portions 5kg | C27: Midlands Hub | D27: England | E27: 0.6 | F27: =SUMIF($A$12:$A$14,$A27,$N$12:$N$14)*$E27 -> 213.72 | G27: =SUMIF($A$12:$A$14,$A27,$E$12:$E$14) -> 75.1 | H27: =F27*G27 -> 16050.372
A28: FSD-COD-5 | B28: North Atlantic Cod Portions 5kg | C28: Newport Crossdock | D28: Wales | E28: 0.4 | F28: =SUMIF($A$12:$A$14,$A28,$N$12:$N$14)*$E28 -> 142.48 | G28: =SUMIF($A$12:$A$14,$A28,$E$12:$E$14) -> 75.1 | H28: =F28*G28 -> 10700.248
A29: FSD-SAL-10 | B29: Atlantic Salmon Portions 10kg | C29: Midlands Hub | D29: England | E29: 0.55 | F29: =SUMIF($A$12:$A$14,$A29,$N$12:$N$14)*$E29 -> 113.685 | G29: =SUMIF($A$12:$A$14,$A29,$E$12:$E$14) -> 66.25 | H29: =F29*G29 -> 7531.6313
A30: FSD-SAL-10 | B30: Atlantic Salmon Portions 10kg | C30: Newport Crossdock | D30: Wales | E30: 0.45 | F30: =SUMIF($A$12:$A$14,$A30,$N$12:$N$14)*$E30 -> 93.015 | G30: =SUMIF($A$12:$A$14,$A30,$E$12:$E$14) -> 66.25 | H30: =F30*G30 -> 6162.2437
A31: FSD-PEA-2 | B31: Garden Peas 2kg | C31: Midlands Hub | D31: England | E31: 0.65 | F31: =SUMIF($A$12:$A$14,$A31,$N$12:$N$14)*$E31 -> 161.915 | G31: =SUMIF($A$12:$A$14,$A31,$E$12:$E$14) -> 28.15 | H31: =F31*G31 -> 4557.9073
A32: FSD-PEA-2 | B32: Garden Peas 2kg | C32: Newport Crossdock | D32: Wales | E32: 0.35 | F32: =SUMIF($A$12:$A$14,$A32,$N$12:$N$14)*$E32 -> 87.185 | G32: =SUMIF($A$12:$A$14,$A32,$E$12:$E$14) -> 28.15 | H32: =F32*G32 -> 2454.2578
A33: Allocation total | F33: =SUM(F27:F32) -> 812 | H33: =SUM(H27:H32) -> 47456.66

Sheet Friday Run Sheet
A1: Ashcombe Council - Friday Dispatch Run Sheet
A2: April plan - use the selected commercial scenario; complete the blank shift fields at the depot.
A4: Selected scenario | B4: =Forecast!$B$3 -> Base | D4: Source snapshot | E4: 28-Feb-2027 | G4: Run-sheet value | H4: =H15 -> 47456.66 | J4: Scenario cases | K4: =F15 -> 812
A8: Line | B8: Jurisdiction | C8: Depot | D8: Scheduled date | E8: SKU | F8: Planned cases | G8: Unit GBP | H8: Planned GBP | I8: Label pack | J8: Actual cases | K8: Status | L8: Picker | M8: Exception note
A9: =ROW()-8 -> 1 | B9: =Forecast!$D$27 -> England | C9: =Forecast!$C$27 -> Midlands Hub | D9: =Forecast!$B$7 -> 46486 | E9: =Forecast!$A$27 -> FSD-COD-5 | F9: =Forecast!$F$27 -> 213.72 | G9: =Forecast!$G$27 -> 75.1 | H9: =Forecast!$H$27 -> 16050.372 | I9: =IF(B9="Wales","CY/EN","EN") -> EN
A10: =ROW()-8 -> 2 | B10: =Forecast!$D$28 -> Wales | C10: =Forecast!$C$28 -> Newport Crossdock | D10: =Forecast!$B$7 -> 46486 | E10: =Forecast!$A$28 -> FSD-COD-5 | F10: =Forecast!$F$28 -> 142.48 | G10: =Forecast!$G$28 -> 75.1 | H10: =Forecast!$H$28 -> 10700.248 | I10: =IF(B10="Wales","CY/EN","EN") -> CY/EN
A11: =ROW()-8 -> 3 | B11: =Forecast!$D$29 -> England | C11: =Forecast!$C$29 -> Midlands Hub | D11: =Forecast!$B$7 -> 46486 | E11: =Forecast!$A$29 -> FSD-SAL-10 | F11: =Forecast!$F$29 -> 113.685 | G11: =Forecast!$G$29 -> 66.25 | H11: =Forecast!$H$29 -> 7531.6313 | I11: =IF(B11="Wales","CY/EN","EN") -> EN
A12: =ROW()-8 -> 4 | B12: =Forecast!$D$30 -> Wales | C12: =Forecast!$C$30 -> Newport Crossdock | D12: =Forecast!$B$7 -> 46486 | E12: =Forecast!$A$30 -> FSD-SAL-10 | F12: =Forecast!$F$30 -> 93.015 | G12: =Forecast!$G$30 -> 66.25 | H12: =Forecast!$H$30 -> 6162.2437 | I12: =IF(B12="Wales","CY/EN","EN") -> CY/EN
A13: =ROW()-8 -> 5 | B13: =Forecast!$D$31 -> England | C13: =Forecast!$C$31 -> Midlands Hub | D13: =Forecast!$B$7 -> 46486 | E13: =Forecast!$A$31 -> FSD-PEA-2 | F13: =Forecast!$F$31 -> 161.915 | G13: =Forecast!$G$31 -> 28.15 | H13: =Forecast!$H$31 -> 4557.9073 | I13: =IF(B13="Wales","CY/EN","EN") -> EN
A14: =ROW()-8 -> 6 | B14: =Forecast!$D$32 -> Wales | C14: =Forecast!$C$32 -> Newport Crossdock | D14: =Forecast!$B$7 -> 46486 | E14: =Forecast!$A$32 -> FSD-PEA-2 | F14: =Forecast!$F$32 -> 87.185 | G14: =Forecast!$G$32 -> 28.15 | H14: =Forecast!$H$32 -> 2454.2578 | I14: =IF(B14="Wales","CY/EN","EN") -> CY/EN
A15: TOTAL | F15: =SUM(F9:F14) -> 812 | H15: =SUM(H9:H14) -> 47456.66
A18: Complete actual cases, choose a status, add picker initials and record a short exception. Use Held for any line that cannot dispatch and state why. | H18: Status: Not started | Picking | Loaded | Held Labels: EN = England English pack; CY/EN = Wales bilingual pack. Amber cells are blank shift-completion fields.
A23: Commercial approval - Cecilia Asante: ____________________ Dispatch handoff - Ludmila Havlicek: ____________________

Sheet Change Log
A1: Change Log
A4: Revision date | B4: Role | C4: Authorized by | D4: Cancellation reading | E4: Areas changed | F4: Source cutoff | G4: Record
A5: 28-Feb-2027 | B5: Model analyst | C5: Pending | D5: Pending | E5: Draft layout and controls | F5: 28-Feb-2027 | G5: Initial draft issued
A6: 09-Mar-2027 | B6: Sales Manager | C6: Hana Boateng | D6: Scheduled-delivery / one-week shift | E6: Reconciled duplicate, normalised and out-of-scope rows; completed February-March formulas, April scenarios, live controls, England/Wales run sheet, protections and validations. | F6: 28-Feb-2027 | G6: Authorized revision for dispatch review
