Workbook

Sheet Summary
A1: Saltmarsh Supplier-Quality Decision
A2: Ballantry Components Ltd. irrigation-emitter cartridges | Week ending 14-Feb-2029 | Payment hold: Brindlemere Advisory | Review-ready for Mahdi Lindqvist by 07:30, 16-Feb-2029
A3: Decision queue is ordered by immediate action need. Confirmed source facts and derived bounds support the current action; forecasts are bounded planning comparisons, not guarantees.
A5: Distinct physical runs | C5: Signed inspected (cartridges) | E5: Signed rejected (cartridges) | G5: ERP rejected (cartridges) | I5: Reject discrepancy signed - ERP | K5: ERP available stock (cartridges) | M5: Conditional release total (cartridges)
A6: =COUNT(Reconciliation!B7:B12) -> 0 | C6: =Reconciliation!M13 -> 9380 | E6: =Reconciliation!N13 -> 840 | G6: =Reconciliation!U13 -> 768 | I6: =Reconciliation!V13 -> 72 | K6: =Reconciliation!Y13 -> 8576 | M6: =Reconciliation!AD13 -> 7736
A8: Run decision queue
A9: Priority | B9: Current action | C9: Contract / Run ID | D9: Production date | E9: Line | F9: Cartridge model | G9: Lot | H9: Signed status | I9: Reject difference signed - ERP (cartridges) | J9: Release lower (cartridges) | K9: Release upper (cartridges) | L9: Conditional release qty (cartridges) | M9: Planning output release / reinspect / rework | N9: Planning scrap cost USD release / reinspect / rework | O9: Handoff rationale
A10: 1 | B10: Hold; assess rework | C10: =Reconciliation!B10 -> BRI-EM-2044 | D10: =Reconciliation!C10 -> 47160 | E10: =Reconciliation!D10 -> Line 1 | F10: =Reconciliation!E10 -> IE-32C | G10: =Reconciliation!F10 -> L9-8D | H10: =Reconciliation!P10 -> Hold - rework eligible | I10: =Reconciliation!V10 -> 60 | J10: =Reconciliation!AB10 -> 1044 | K10: =Reconciliation!AC10 -> 1140 | L10: =Reconciliation!AD10 -> 1044 | M10: =TEXT(Scenario_Forecast!R16,"#,##0")&" / "&TEXT(Scenario_Forecast!R17,"#,##0")&" / "&TEXT(Scenario_Forecast!R18,"#,##0") -> 1,044 / 0 / 1,305 | N10: =TEXT(Scenario_Forecast!U16,"$#,##0.00")&" / "&TEXT(Scenario_Forecast!U17,"$#,##0.00")&" / "&TEXT(Scenario_Forecast!U18,"$#,##0.00") -> $94.50 / $423.36 / $12.29 | O10: Signed hold remains controlling. Rework forecast is 1,305 cartridges with $12.29 scrap cost, versus lower-bound release at 1,044 / $94.50; the zero checked-sample makes reinspection a conservative 0-output forecast.
A11: 2 | B11: Reinspect before release | C11: =Reconciliation!B8 -> BRI-EM-2042 | D11: =Reconciliation!C8 -> 47159 | E11: =Reconciliation!D8 -> Line 3 | F11: =Reconciliation!E8 -> IE-24B | G11: =Reconciliation!F8 -> L9-4C | H11: =Reconciliation!P8 -> Hold - reinspection | I11: =Reconciliation!V8 -> -60 | J11: =Reconciliation!AB8 -> 1580 | K11: =Reconciliation!AC8 -> 1780 | L11: =Reconciliation!AD8 -> 1580 | M11: =TEXT(Scenario_Forecast!R10,"#,##0")&" / "&TEXT(Scenario_Forecast!R11,"#,##0")&" / "&TEXT(Scenario_Forecast!R12,"#,##0") -> 1,580 / 1,260 / 1,800 | N11: =TEXT(Scenario_Forecast!U10,"$#,##0.00")&" / "&TEXT(Scenario_Forecast!U11,"$#,##0.00")&" / "&TEXT(Scenario_Forecast!U12,"$#,##0.00") -> $52.25 / $128.25 / $0.00 | O11: Signed reinspection hold controls despite the -60 cartridge reject difference. Reinspection plans 1,260 / $128.25 versus rework 1,800 / $0.00; neither is a guarantee.
A12: 3 | B12: Hold; disposition review | C12: =Reconciliation!B12 -> BRI-EM-2046 | D12: =Reconciliation!C12 -> 47162 | E12: =Reconciliation!D12 -> Line 2 | F12: =Reconciliation!E12 -> IE-16A | G12: =Reconciliation!F12 -> L9-6G | H12: =Reconciliation!P12 -> Hold - disposition review | I12: =Reconciliation!V12 -> 48 | J12: =Reconciliation!AB12 -> 840 | K12: =Reconciliation!AC12 -> 912 | L12: =Reconciliation!AD12 -> 840 | M12: =TEXT(Scenario_Forecast!R22,"#,##0")&" / "&TEXT(Scenario_Forecast!R23,"#,##0")&" / "&TEXT(Scenario_Forecast!R24,"#,##0") -> 840 / 705 / 1,008 | N12: =TEXT(Scenario_Forecast!U22,"$#,##0.00")&" / "&TEXT(Scenario_Forecast!U23,"$#,##0.00")&" / "&TEXT(Scenario_Forecast!U24,"$#,##0.00") -> $31.08 / $56.06 / $0.00 | O12: Signed disposition review controls. Rework planning output is 1,008 cartridges with $0.00 scrap cost, versus lower-bound release at 840 / $31.08.
A13: 4 | B13: Release lower-bound quantity | C13: =Reconciliation!B7 -> BRI-EM-2041 | D13: =Reconciliation!C7 -> 47159 | E13: =Reconciliation!D7 -> Line 2 | F13: =Reconciliation!E7 -> IE-16A | G13: =Reconciliation!F7 -> L9-2A | H13: =Reconciliation!P7 -> Conditional release | I13: =Reconciliation!V7 -> 24 | J13: =Reconciliation!AB7 -> 1608 | K13: =Reconciliation!AC7 -> 1680 | L13: =Reconciliation!AD7 -> 1608 | M13: =TEXT(Scenario_Forecast!R7,"#,##0")&" / "&TEXT(Scenario_Forecast!R8,"#,##0")&" / "&TEXT(Scenario_Forecast!R9,"#,##0") -> 1,608 / 1,610 / 1,680 | N13: =TEXT(Scenario_Forecast!U7,"$#,##0.00")&" / "&TEXT(Scenario_Forecast!U8,"$#,##0.00")&" / "&TEXT(Scenario_Forecast!U9,"$#,##0.00") -> $13.32 / $12.95 / $0.00 | O13: Signed conditional-release status supports the policy lower bound of 1,608; retain the +24 cartridge ERP variance in the handoff. Release is 1,608 / $13.32; reinspection is 1,610 / $12.95 and remains a forecast.
A14: 5 | B14: Release lower-bound quantity | C14: =Reconciliation!B11 -> BRI-EM-2045 | D14: =Reconciliation!C11 -> 47161 | E14: =Reconciliation!D11 -> Line 3 | F14: =Reconciliation!E11 -> IE-24B | G14: =Reconciliation!F11 -> L9-1F | H14: =Reconciliation!P11 -> Accepted w/ inspection note | I14: =Reconciliation!V11 -> 0 | J14: =Reconciliation!AB11 -> 1320 | K14: =Reconciliation!AC11 -> 1400 | L14: =Reconciliation!AD11 -> 1320 | M14: =TEXT(Scenario_Forecast!R19,"#,##0")&" / "&TEXT(Scenario_Forecast!R20,"#,##0")&" / "&TEXT(Scenario_Forecast!R21,"#,##0") -> 1,320 / 1,330 / 1,400 | N14: =TEXT(Scenario_Forecast!U19,"$#,##0.00")&" / "&TEXT(Scenario_Forecast!U20,"$#,##0.00")&" / "&TEXT(Scenario_Forecast!U21,"$#,##0.00") -> $19.00 / $16.63 / $0.00 | O14: Signed accepted disposition and matching ERP reject posting support 1,320 cartridges. Release is 1,320 / $19.00; reinspection is 1,330 / $16.63, while rework remains planning information only.
A15: 6 | B15: Release lower-bound quantity | C15: =Reconciliation!B9 -> BRI-EM-2043 | D15: =Reconciliation!C9 -> 47160 | E15: =Reconciliation!D9 -> Line 2 | F15: =Reconciliation!E9 -> IE-16A | G15: =Reconciliation!F9 -> L9-3B | H15: =Reconciliation!P9 -> Accepted | I15: =Reconciliation!V9 -> 0 | J15: =Reconciliation!AB9 -> 1344 | K15: =Reconciliation!AC9 -> 1344 | L15: =Reconciliation!AD9 -> 1344 | M15: =TEXT(Scenario_Forecast!R13,"#,##0")&" / "&TEXT(Scenario_Forecast!R14,"#,##0")&" / "&TEXT(Scenario_Forecast!R15,"#,##0") -> 1,344 / 1,344 / 1,344 | N15: =TEXT(Scenario_Forecast!U13,"$#,##0.00")&" / "&TEXT(Scenario_Forecast!U14,"$#,##0.00")&" / "&TEXT(Scenario_Forecast!U15,"$#,##0.00") -> $0.00 / $0.00 / $0.00 | O15: Signed accepted disposition and no reject variance support release of 1,344 cartridges; release is 1,344 / $0.00, with reinspection 1,344 / $0.00 and no forecast advantage shown.
A18: Planning forecast totals - not guaranteed production
A19: Scenario | B19: Available output (cartridges) | C19: Scrap / unavailable (cartridges) | D19: Scrap cost (USD) | E19: Interpretation
A20: Release | B20: =Scenario_Forecast!C29 -> 7736 | C20: =Scenario_Forecast!D29 -> 840 | D20: =Scenario_Forecast!E29 -> 210.15 | E20: Policy-bound selected quantities; signed status still controls approval.
A21: Reinspection | B21: =Scenario_Forecast!C30 -> 6249 | C21: =Scenario_Forecast!D30 -> 2327 | D21: =Scenario_Forecast!E30 -> 637.25 | E21: Yield forecast from signed sample; zero denominator is conservatively zero output.
A22: Rework | B22: =Scenario_Forecast!C31 -> 8537 | C22: =Scenario_Forecast!D31 -> 39 | D22: =Scenario_Forecast!E31 -> 12.29 | E22: Recovery-rate forecast; recovery is not a confirmed result and output is stock-capped.

Sheet Reconciliation
A1: Run-Level Reconciliation
A2: Confirmed source quantities and policy-derived release bounds. Quantity basis: individual cartridges unless the heading says cartons.
A3: Reject discrepancy sign convention: signed rejected cartridges minus normalized ERP rejected cartridges. Signed inspection controls disposition; ERP remains visible as stock and audit evidence.
A4: Selected conservative release is the policy lower bound for planning and remains subject to the signed status / action gate shown for each run.
A6: Priority | B6: Contract / Run ID | C6: Production date | D6: Line | E6: Cartridge model | F6: Lot | G6: Composite run key | H6: Signed source record ID(s) | I6: ERP source record ID | J6: Contract pack size (cartridges/carton) | K6: Signed inspected cartons | L6: Signed rejected cartons | M6: Signed inspected cartridges | N6: Signed rejected cartridges | O6: Signed accepted cartridges | P6: Signed inspection status | Q6: Signed disposition | R6: ERP posted pack counts | S6: ERP posted cartridges | T6: ERP rejected pack counts | U6: ERP rejected cartridges | V6: Reject discrepancy: signed - ERP (cartridges) | W6: ERP receipt pack counts | X6: ERP outflow pack counts | Y6: ERP available stock (cartridges) | Z6: Contract rate raw (USD/cartridge) | AA6: Normalized rate used (USD/cartridge) | AB6: Release lower bound (cartridges) | AC6: Release upper bound (cartridges) | AD6: Selected conservative release (cartridges) | AE6: Signed reject scrap cost basis (USD) | AF6: Current action / decision gate | AG6: Evidence treatment
A7: 4 | B7: BRI-EM-2041 | C7: 47159 | D7: Line 2 | E7: IE-16A | F7: L9-2A | G7: BRI-EM-2041 | 10-Feb-2029 | Line 2 | IE-16A | L9-2A | H7: SQ-90211-17 | I7: ERP-709512 | J7: 24 | K7: 80 | L7: 3 | M7: =K7*J7 -> 1920 | N7: =L7*J7 -> 72 | O7: =M7-N7 -> 1848 | P7: Conditional release | Q7: Bounded release review | R7: 80 | S7: =R7*J7 -> 1920 | T7: 2 | U7: =T7*J7 -> 48 | V7: =N7-U7 -> 24 | W7: 80 | X7: 10 | Y7: =(W7-X7)*J7 -> 1680 | Z7: 0.185 | AA7: =ROUND(Z7,4) -> 0.185 | AB7: =MAX(0,Y7-N7) -> 1608 | AC7: =MIN(Y7,O7) -> 1680 | AD7: =AB7 -> 1608 | AE7: =ROUND(N7*AA7,2) -> 13.32 | AF7: Release lower-bound quantity | AG7: Signed source controls disposition; ERP comparison retained.
A8: 2 | B8: BRI-EM-2042 | C8: 47159 | D8: Line 3 | E8: IE-24B | F8: L9-4C | G8: BRI-EM-2042 | 10-Feb-2029 | Line 3 | IE-24B | L9-4C | H8: SQ-90211-18; SQ-90211-18A | I8: ERP-709513 | J8: 20 | K8: 100 | L8: 11 | M8: =K8*J8 -> 2000 | N8: =L8*J8 -> 220 | O8: =M8-N8 -> 1780 | P8: Hold - reinspection | Q8: QA reinspection pending | R8: 100 | S8: =R8*J8 -> 2000 | T8: 14 | U8: =T8*J8 -> 280 | V8: =N8-U8 -> -60 | W8: 99 | X8: 9 | Y8: =(W8-X8)*J8 -> 1800 | Z8: 0.2375 | AA8: =ROUND(Z8,4) -> 0.2375 | AB8: =MAX(0,Y8-N8) -> 1580 | AC8: =MIN(Y8,O8) -> 1780 | AD8: =AB8 -> 1580 | AE8: =ROUND(N8*AA8,2) -> 52.25 | AF8: Reinspect before release | AG8: Overlapping signed IDs retained in Evidence; counted once by composite run key.
A9: 6 | B9: BRI-EM-2043 | C9: 47160 | D9: Line 2 | E9: IE-16A | F9: L9-3B | G9: BRI-EM-2043 | 11-Feb-2029 | Line 2 | IE-16A | L9-3B | H9: SQ-90211-19 | I9: ERP-709514 | J9: 24 | K9: 60 | L9: 0 | M9: =K9*J9 -> 1440 | N9: =L9*J9 -> 0 | O9: =M9-N9 -> 1440 | P9: Accepted | Q9: Release on stock confirmation | R9: 60 | S9: =R9*J9 -> 1440 | T9: 0 | U9: =T9*J9 -> 0 | V9: =N9-U9 -> 0 | W9: 60 | X9: 4 | Y9: =(W9-X9)*J9 -> 1344 | Z9: 0.185 | AA9: =ROUND(Z9,4) -> 0.185 | AB9: =MAX(0,Y9-N9) -> 1344 | AC9: =MIN(Y9,O9) -> 1344 | AD9: =AB9 -> 1344 | AE9: =ROUND(N9*AA9,2) -> 0 | AF9: Release lower-bound quantity | AG9: Signed source controls disposition; ERP comparison retained.
A10: 1 | B10: BRI-EM-2044 | C10: 47160 | D10: Line 1 | E10: IE-32C | F10: L9-8D | G10: BRI-EM-2044 | 11-Feb-2029 | Line 1 | IE-32C | L9-8D | H10: SQ-90212-03 | I10: ERP-709515 | J10: 12 | K10: 120 | L10: 25 | M10: =K10*J10 -> 1440 | N10: =L10*J10 -> 300 | O10: =M10-N10 -> 1140 | P10: Hold - rework eligible | Q10: Rework assessment | R10: 120 | S10: =R10*J10 -> 1440 | T10: 20 | U10: =T10*J10 -> 240 | V10: =N10-U10 -> 60 | W10: 118 | X10: 6 | Y10: =(W10-X10)*J10 -> 1344 | Z10: 0.315 | AA10: =ROUND(Z10,4) -> 0.315 | AB10: =MAX(0,Y10-N10) -> 1044 | AC10: =MIN(Y10,O10) -> 1140 | AD10: =AB10 -> 1044 | AE10: =ROUND(N10*AA10,2) -> 94.5 | AF10: Hold; assess rework | AG10: Signed source controls disposition; ERP comparison retained.
A11: 5 | B11: BRI-EM-2045 | C11: 47161 | D11: Line 3 | E11: IE-24B | F11: L9-1F | G11: BRI-EM-2045 | 12-Feb-2029 | Line 3 | IE-24B | L9-1F | H11: SQ-90212-04 | I11: ERP-709516 | J11: 20 | K11: 75 | L11: 4 | M11: =K11*J11 -> 1500 | N11: =L11*J11 -> 80 | O11: =M11-N11 -> 1420 | P11: Accepted w/ inspection note | Q11: Bounded release | R11: 75 | S11: =R11*J11 -> 1500 | T11: 4 | U11: =T11*J11 -> 80 | V11: =N11-U11 -> 0 | W11: 75 | X11: 5 | Y11: =(W11-X11)*J11 -> 1400 | Z11: 0.2375 | AA11: =ROUND(Z11,4) -> 0.2375 | AB11: =MAX(0,Y11-N11) -> 1320 | AC11: =MIN(Y11,O11) -> 1400 | AD11: =AB11 -> 1320 | AE11: =ROUND(N11*AA11,2) -> 19 | AF11: Release lower-bound quantity | AG11: Signed source controls disposition; ERP comparison retained.
A12: 3 | B12: BRI-EM-2046 | C12: 47162 | D12: Line 2 | E12: IE-16A | F12: L9-6G | G12: BRI-EM-2046 | 13-Feb-2029 | Line 2 | IE-16A | L9-6G | H12: SQ-90213-08 | I12: ERP-709517 | J12: 24 | K12: 45 | L12: 7 | M12: =K12*J12 -> 1080 | N12: =L12*J12 -> 168 | O12: =M12-N12 -> 912 | P12: Hold - disposition review | Q12: Disposition review | R12: 45 | S12: =R12*J12 -> 1080 | T12: 5 | U12: =T12*J12 -> 120 | V12: =N12-U12 -> 48 | W12: 45 | X12: 3 | Y12: =(W12-X12)*J12 -> 1008 | Z12: 0.185 | AA12: =ROUND(Z12,4) -> 0.185 | AB12: =MAX(0,Y12-N12) -> 840 | AC12: =MIN(Y12,O12) -> 912 | AD12: =AB12 -> 840 | AE12: =ROUND(N12*AA12,2) -> 31.08 | AF12: Hold; disposition review | AG12: Signed source controls disposition; ERP comparison retained.
A13: TOTAL | B13: Distinct physical runs | G13: Deduplicated by supplied composite key | M13: =SUM(M7:M12) -> 9380 | N13: =SUM(N7:N12) -> 840 | O13: =SUM(O7:O12) -> 8540 | S13: =SUM(S7:S12) -> 9380 | U13: =SUM(U7:U12) -> 768 | V13: =SUM(V7:V12) -> 72 | Y13: =SUM(Y7:Y12) -> 8576 | AB13: =SUM(AB7:AB12) -> 7736 | AC13: =SUM(AC7:AC12) -> 8256 | AD13: =SUM(AD7:AD12) -> 7736 | AE13: =SUM(AE7:AE12) -> 210.15

Sheet Scenario_Forecast
A1: Scenario Forecast - Planning Comparison
A2: Forecast quantities are planning information, not confirmed production or quality outcomes. Stock base is ERP available stock in individual cartridges.
A3: Assumptions: reinspection applies signed sample pass / checked yield to the stock base and rounds output down. A zero checked-sample uses conservative 0% yield. Rework recovery uses the contract rate, rounds recovered units down, and caps output at available stock.
A4: For every scenario: Available output + scrap / unavailable = scenario stock base. All outputs are whole individual cartridges; costs are USD rounded to cents.
A6: Scenario | B6: Contract / Run ID | C6: Production date | D6: Line | E6: Cartridge model | F6: Lot | G6: Composite run key | H6: Classification | I6: Scenario stock base (cartridges) | J6: Signed accepted input (cartridges) | K6: Signed rejected input (cartridges) | L6: Selected release input (cartridges) | M6: Reinspect sample pass (cartridges) | N6: Reinspect sample checked (cartridges) | O6: Forecast yield (not confirmed) | P6: Contract recovery rate | Q6: Recovered rejected (cartridges) | R6: Available output (cartridges) | S6: Scrap / unavailable (cartridges) | T6: Normalized rate used (USD/cartridge) | U6: Scrap cost (USD) | V6: Assumption / uncertainty | W6: Source / calculation basis
A7: Release | B7: =Reconciliation!B7 -> BRI-EM-2041 | C7: =Reconciliation!C7 -> 47159 | D7: =Reconciliation!D7 -> Line 2 | E7: =Reconciliation!E7 -> IE-16A | F7: =Reconciliation!F7 -> L9-2A | G7: =Reconciliation!G7 -> BRI-EM-2041 | 10-Feb-2029 | Line 2 | IE-16A | L9-2A | H7: Forecast - planning only | I7: =Reconciliation!Y7 -> 1680 | J7: =Reconciliation!O7 -> 1848 | K7: =Reconciliation!N7 -> 72 | L7: =Reconciliation!AD7 -> 1608 | Q7: 0 | R7: =L7 -> 1608 | S7: =I7-R7 -> 72 | T7: =Reconciliation!AA7 -> 0.185 | U7: =ROUND(S7*T7,2) -> 13.32 | V7: Policy-bound selected release; remaining stock is unavailable under this planning scenario. | W7: Signed SQ-90211-17; ERP ERP-709512; contract term IE-16A.
A8: Reinspection | B8: =Reconciliation!B7 -> BRI-EM-2041 | C8: =Reconciliation!C7 -> 47159 | D8: =Reconciliation!D7 -> Line 2 | E8: =Reconciliation!E7 -> IE-16A | F8: =Reconciliation!F7 -> L9-2A | G8: =Reconciliation!G7 -> BRI-EM-2041 | 10-Feb-2029 | Line 2 | IE-16A | L9-2A | H8: Forecast - planning only | I8: =Reconciliation!Y7 -> 1680 | J8: =Reconciliation!O7 -> 1848 | K8: =Reconciliation!N7 -> 72 | L8: =Reconciliation!AD7 -> 1608 | M8: 46 | N8: 48 | O8: =IF(N8=0,0,M8/N8) -> 0.95833333 | Q8: 0 | R8: =ROUNDDOWN(I8*O8,0) -> 1610 | S8: =I8-R8 -> 70 | T8: =Reconciliation!AA7 -> 0.185 | U8: =ROUND(S8*T8,2) -> 12.95 | V8: Forecast yield = signed sample pass / checked; output rounded down to whole cartridges. | W8: Signed SQ-90211-17; ERP ERP-709512; contract term IE-16A.
A9: Rework | B9: =Reconciliation!B7 -> BRI-EM-2041 | C9: =Reconciliation!C7 -> 47159 | D9: =Reconciliation!D7 -> Line 2 | E9: =Reconciliation!E7 -> IE-16A | F9: =Reconciliation!F7 -> L9-2A | G9: =Reconciliation!G7 -> BRI-EM-2041 | 10-Feb-2029 | Line 2 | IE-16A | L9-2A | H9: Forecast - planning only | I9: =Reconciliation!Y7 -> 1680 | J9: =Reconciliation!O7 -> 1848 | K9: =Reconciliation!N7 -> 72 | L9: =Reconciliation!AD7 -> 1608 | P9: 0.6 | Q9: =ROUNDDOWN(K9*P9,0) -> 43 | R9: =MIN(I9,J9+Q9) -> 1680 | S9: =I9-R9 -> 0 | T9: =Reconciliation!AA7 -> 0.185 | U9: =ROUND(S9*T9,2) -> 0 | V9: Recovered rejects = signed rejects x contract recovery; output capped at ERP available stock. | W9: Signed SQ-90211-17; ERP ERP-709512; contract term IE-16A.
A10: Release | B10: =Reconciliation!B8 -> BRI-EM-2042 | C10: =Reconciliation!C8 -> 47159 | D10: =Reconciliation!D8 -> Line 3 | E10: =Reconciliation!E8 -> IE-24B | F10: =Reconciliation!F8 -> L9-4C | G10: =Reconciliation!G8 -> BRI-EM-2042 | 10-Feb-2029 | Line 3 | IE-24B | L9-4C | H10: Forecast - planning only | I10: =Reconciliation!Y8 -> 1800 | J10: =Reconciliation!O8 -> 1780 | K10: =Reconciliation!N8 -> 220 | L10: =Reconciliation!AD8 -> 1580 | Q10: 0 | R10: =L10 -> 1580 | S10: =I10-R10 -> 220 | T10: =Reconciliation!AA8 -> 0.2375 | U10: =ROUND(S10*T10,2) -> 52.25 | V10: Policy-bound selected release; remaining stock is unavailable under this planning scenario. | W10: Signed SQ-90211-18, SQ-90211-18A; ERP ERP-709513; contract term IE-24B.
A11: Reinspection | B11: =Reconciliation!B8 -> BRI-EM-2042 | C11: =Reconciliation!C8 -> 47159 | D11: =Reconciliation!D8 -> Line 3 | E11: =Reconciliation!E8 -> IE-24B | F11: =Reconciliation!F8 -> L9-4C | G11: =Reconciliation!G8 -> BRI-EM-2042 | 10-Feb-2029 | Line 3 | IE-24B | L9-4C | H11: Forecast - planning only | I11: =Reconciliation!Y8 -> 1800 | J11: =Reconciliation!O8 -> 1780 | K11: =Reconciliation!N8 -> 220 | L11: =Reconciliation!AD8 -> 1580 | M11: 28 | N11: 40 | O11: =IF(N11=0,0,M11/N11) -> 0.7 | Q11: 0 | R11: =ROUNDDOWN(I11*O11,0) -> 1260 | S11: =I11-R11 -> 540 | T11: =Reconciliation!AA8 -> 0.2375 | U11: =ROUND(S11*T11,2) -> 128.25 | V11: Forecast yield = signed sample pass / checked; output rounded down to whole cartridges. | W11: Signed SQ-90211-18, SQ-90211-18A; ERP ERP-709513; contract term IE-24B.
A12: Rework | B12: =Reconciliation!B8 -> BRI-EM-2042 | C12: =Reconciliation!C8 -> 47159 | D12: =Reconciliation!D8 -> Line 3 | E12: =Reconciliation!E8 -> IE-24B | F12: =Reconciliation!F8 -> L9-4C | G12: =Reconciliation!G8 -> BRI-EM-2042 | 10-Feb-2029 | Line 3 | IE-24B | L9-4C | H12: Forecast - planning only | I12: =Reconciliation!Y8 -> 1800 | J12: =Reconciliation!O8 -> 1780 | K12: =Reconciliation!N8 -> 220 | L12: =Reconciliation!AD8 -> 1580 | P12: 0.75 | Q12: =ROUNDDOWN(K12*P12,0) -> 165 | R12: =MIN(I12,J12+Q12) -> 1800 | S12: =I12-R12 -> 0 | T12: =Reconciliation!AA8 -> 0.2375 | U12: =ROUND(S12*T12,2) -> 0 | V12: Recovered rejects = signed rejects x contract recovery; output capped at ERP available stock. | W12: Signed SQ-90211-18, SQ-90211-18A; ERP ERP-709513; contract term IE-24B.
A13: Release | B13: =Reconciliation!B9 -> BRI-EM-2043 | C13: =Reconciliation!C9 -> 47160 | D13: =Reconciliation!D9 -> Line 2 | E13: =Reconciliation!E9 -> IE-16A | F13: =Reconciliation!F9 -> L9-3B | G13: =Reconciliation!G9 -> BRI-EM-2043 | 11-Feb-2029 | Line 2 | IE-16A | L9-3B | H13: Forecast - planning only | I13: =Reconciliation!Y9 -> 1344 | J13: =Reconciliation!O9 -> 1440 | K13: =Reconciliation!N9 -> 0 | L13: =Reconciliation!AD9 -> 1344 | Q13: 0 | R13: =L13 -> 1344 | S13: =I13-R13 -> 0 | T13: =Reconciliation!AA9 -> 0.185 | U13: =ROUND(S13*T13,2) -> 0 | V13: Policy-bound selected release; remaining stock is unavailable under this planning scenario. | W13: Signed SQ-90211-19; ERP ERP-709514; contract term IE-16A.
A14: Reinspection | B14: =Reconciliation!B9 -> BRI-EM-2043 | C14: =Reconciliation!C9 -> 47160 | D14: =Reconciliation!D9 -> Line 2 | E14: =Reconciliation!E9 -> IE-16A | F14: =Reconciliation!F9 -> L9-3B | G14: =Reconciliation!G9 -> BRI-EM-2043 | 11-Feb-2029 | Line 2 | IE-16A | L9-3B | H14: Forecast - planning only | I14: =Reconciliation!Y9 -> 1344 | J14: =Reconciliation!O9 -> 1440 | K14: =Reconciliation!N9 -> 0 | L14: =Reconciliation!AD9 -> 1344 | M14: 30 | N14: 30 | O14: =IF(N14=0,0,M14/N14) -> 1 | Q14: 0 | R14: =ROUNDDOWN(I14*O14,0) -> 1344 | S14: =I14-R14 -> 0 | T14: =Reconciliation!AA9 -> 0.185 | U14: =ROUND(S14*T14,2) -> 0 | V14: Forecast yield = signed sample pass / checked; output rounded down to whole cartridges. | W14: Signed SQ-90211-19; ERP ERP-709514; contract term IE-16A.
A15: Rework | B15: =Reconciliation!B9 -> BRI-EM-2043 | C15: =Reconciliation!C9 -> 47160 | D15: =Reconciliation!D9 -> Line 2 | E15: =Reconciliation!E9 -> IE-16A | F15: =Reconciliation!F9 -> L9-3B | G15: =Reconciliation!G9 -> BRI-EM-2043 | 11-Feb-2029 | Line 2 | IE-16A | L9-3B | H15: Forecast - planning only | I15: =Reconciliation!Y9 -> 1344 | J15: =Reconciliation!O9 -> 1440 | K15: =Reconciliation!N9 -> 0 | L15: =Reconciliation!AD9 -> 1344 | P15: 0.6 | Q15: =ROUNDDOWN(K15*P15,0) -> 0 | R15: =MIN(I15,J15+Q15) -> 1344 | S15: =I15-R15 -> 0 | T15: =Reconciliation!AA9 -> 0.185 | U15: =ROUND(S15*T15,2) -> 0 | V15: Recovered rejects = signed rejects x contract recovery; output capped at ERP available stock. | W15: Signed SQ-90211-19; ERP ERP-709514; contract term IE-16A.
A16: Release | B16: =Reconciliation!B10 -> BRI-EM-2044 | C16: =Reconciliation!C10 -> 47160 | D16: =Reconciliation!D10 -> Line 1 | E16: =Reconciliation!E10 -> IE-32C | F16: =Reconciliation!F10 -> L9-8D | G16: =Reconciliation!G10 -> BRI-EM-2044 | 11-Feb-2029 | Line 1 | IE-32C | L9-8D | H16: Forecast - planning only | I16: =Reconciliation!Y10 -> 1344 | J16: =Reconciliation!O10 -> 1140 | K16: =Reconciliation!N10 -> 300 | L16: =Reconciliation!AD10 -> 1044 | Q16: 0 | R16: =L16 -> 1044 | S16: =I16-R16 -> 300 | T16: =Reconciliation!AA10 -> 0.315 | U16: =ROUND(S16*T16,2) -> 94.5 | V16: Policy-bound selected release; remaining stock is unavailable under this planning scenario. | W16: Signed SQ-90212-03; ERP ERP-709515; contract term IE-32C.
A17: Reinspection | B17: =Reconciliation!B10 -> BRI-EM-2044 | C17: =Reconciliation!C10 -> 47160 | D17: =Reconciliation!D10 -> Line 1 | E17: =Reconciliation!E10 -> IE-32C | F17: =Reconciliation!F10 -> L9-8D | G17: =Reconciliation!G10 -> BRI-EM-2044 | 11-Feb-2029 | Line 1 | IE-32C | L9-8D | H17: Forecast - planning only | I17: =Reconciliation!Y10 -> 1344 | J17: =Reconciliation!O10 -> 1140 | K17: =Reconciliation!N10 -> 300 | L17: =Reconciliation!AD10 -> 1044 | M17: 0 | N17: 0 | O17: =IF(N17=0,0,M17/N17) -> 0 | Q17: 0 | R17: =ROUNDDOWN(I17*O17,0) -> 0 | S17: =I17-R17 -> 1344 | T17: =Reconciliation!AA10 -> 0.315 | U17: =ROUND(S17*T17,2) -> 423.36 | V17: Zero checked-sample: conservative 0% yield and 0 output; reinspection outcome is not quantifiable from the source. | W17: Signed SQ-90212-03; ERP ERP-709515; contract term IE-32C.
A18: Rework | B18: =Reconciliation!B10 -> BRI-EM-2044 | C18: =Reconciliation!C10 -> 47160 | D18: =Reconciliation!D10 -> Line 1 | E18: =Reconciliation!E10 -> IE-32C | F18: =Reconciliation!F10 -> L9-8D | G18: =Reconciliation!G10 -> BRI-EM-2044 | 11-Feb-2029 | Line 1 | IE-32C | L9-8D | H18: Forecast - planning only | I18: =Reconciliation!Y10 -> 1344 | J18: =Reconciliation!O10 -> 1140 | K18: =Reconciliation!N10 -> 300 | L18: =Reconciliation!AD10 -> 1044 | P18: 0.55 | Q18: =ROUNDDOWN(K18*P18,0) -> 165 | R18: =MIN(I18,J18+Q18) -> 1305 | S18: =I18-R18 -> 39 | T18: =Reconciliation!AA10 -> 0.315 | U18: =ROUND(S18*T18,2) -> 12.29 | V18: Recovered rejects = signed rejects x contract recovery; output capped at ERP available stock. | W18: Signed SQ-90212-03; ERP ERP-709515; contract term IE-32C.
A19: Release | B19: =Reconciliation!B11 -> BRI-EM-2045 | C19: =Reconciliation!C11 -> 47161 | D19: =Reconciliation!D11 -> Line 3 | E19: =Reconciliation!E11 -> IE-24B | F19: =Reconciliation!F11 -> L9-1F | G19: =Reconciliation!G11 -> BRI-EM-2045 | 12-Feb-2029 | Line 3 | IE-24B | L9-1F | H19: Forecast - planning only | I19: =Reconciliation!Y11 -> 1400 | J19: =Reconciliation!O11 -> 1420 | K19: =Reconciliation!N11 -> 80 | L19: =Reconciliation!AD11 -> 1320 | Q19: 0 | R19: =L19 -> 1320 | S19: =I19-R19 -> 80 | T19: =Reconciliation!AA11 -> 0.2375 | U19: =ROUND(S19*T19,2) -> 19 | V19: Policy-bound selected release; remaining stock is unavailable under this planning scenario. | W19: Signed SQ-90212-04; ERP ERP-709516; contract term IE-24B.
A20: Reinspection | B20: =Reconciliation!B11 -> BRI-EM-2045 | C20: =Reconciliation!C11 -> 47161 | D20: =Reconciliation!D11 -> Line 3 | E20: =Reconciliation!E11 -> IE-24B | F20: =Reconciliation!F11 -> L9-1F | G20: =Reconciliation!G11 -> BRI-EM-2045 | 12-Feb-2029 | Line 3 | IE-24B | L9-1F | H20: Forecast - planning only | I20: =Reconciliation!Y11 -> 1400 | J20: =Reconciliation!O11 -> 1420 | K20: =Reconciliation!N11 -> 80 | L20: =Reconciliation!AD11 -> 1320 | M20: 19 | N20: 20 | O20: =IF(N20=0,0,M20/N20) -> 0.95 | Q20: 0 | R20: =ROUNDDOWN(I20*O20,0) -> 1330 | S20: =I20-R20 -> 70 | T20: =Reconciliation!AA11 -> 0.2375 | U20: =ROUND(S20*T20,2) -> 16.63 | V20: Forecast yield = signed sample pass / checked; output rounded down to whole cartridges. | W20: Signed SQ-90212-04; ERP ERP-709516; contract term IE-24B.
A21: Rework | B21: =Reconciliation!B11 -> BRI-EM-2045 | C21: =Reconciliation!C11 -> 47161 | D21: =Reconciliation!D11 -> Line 3 | E21: =Reconciliation!E11 -> IE-24B | F21: =Reconciliation!F11 -> L9-1F | G21: =Reconciliation!G11 -> BRI-EM-2045 | 12-Feb-2029 | Line 3 | IE-24B | L9-1F | H21: Forecast - planning only | I21: =Reconciliation!Y11 -> 1400 | J21: =Reconciliation!O11 -> 1420 | K21: =Reconciliation!N11 -> 80 | L21: =Reconciliation!AD11 -> 1320 | P21: 0.75 | Q21: =ROUNDDOWN(K21*P21,0) -> 60 | R21: =MIN(I21,J21+Q21) -> 1400 | S21: =I21-R21 -> 0 | T21: =Reconciliation!AA11 -> 0.2375 | U21: =ROUND(S21*T21,2) -> 0 | V21: Recovered rejects = signed rejects x contract recovery; output capped at ERP available stock. | W21: Signed SQ-90212-04; ERP ERP-709516; contract term IE-24B.
A22: Release | B22: =Reconciliation!B12 -> BRI-EM-2046 | C22: =Reconciliation!C12 -> 47162 | D22: =Reconciliation!D12 -> Line 2 | E22: =Reconciliation!E12 -> IE-16A | F22: =Reconciliation!F12 -> L9-6G | G22: =Reconciliation!G12 -> BRI-EM-2046 | 13-Feb-2029 | Line 2 | IE-16A | L9-6G | H22: Forecast - planning only | I22: =Reconciliation!Y12 -> 1008 | J22: =Reconciliation!O12 -> 912 | K22: =Reconciliation!N12 -> 168 | L22: =Reconciliation!AD12 -> 840 | Q22: 0 | R22: =L22 -> 840 | S22: =I22-R22 -> 168 | T22: =Reconciliation!AA12 -> 0.185 | U22: =ROUND(S22*T22,2) -> 31.08 | V22: Policy-bound selected release; remaining stock is unavailable under this planning scenario. | W22: Signed SQ-90213-08; ERP ERP-709517; contract term IE-16A.
A23: Reinspection | B23: =Reconciliation!B12 -> BRI-EM-2046 | C23: =Reconciliation!C12 -> 47162 | D23: =Reconciliation!D12 -> Line 2 | E23: =Reconciliation!E12 -> IE-16A | F23: =Reconciliation!F12 -> L9-6G | G23: =Reconciliation!G12 -> BRI-EM-2046 | 13-Feb-2029 | Line 2 | IE-16A | L9-6G | H23: Forecast - planning only | I23: =Reconciliation!Y12 -> 1008 | J23: =Reconciliation!O12 -> 912 | K23: =Reconciliation!N12 -> 168 | L23: =Reconciliation!AD12 -> 840 | M23: 21 | N23: 30 | O23: =IF(N23=0,0,M23/N23) -> 0.7 | Q23: 0 | R23: =ROUNDDOWN(I23*O23,0) -> 705 | S23: =I23-R23 -> 303 | T23: =Reconciliation!AA12 -> 0.185 | U23: =ROUND(S23*T23,2) -> 56.06 | V23: Forecast yield = signed sample pass / checked; output rounded down to whole cartridges. | W23: Signed SQ-90213-08; ERP ERP-709517; contract term IE-16A.
A24: Rework | B24: =Reconciliation!B12 -> BRI-EM-2046 | C24: =Reconciliation!C12 -> 47162 | D24: =Reconciliation!D12 -> Line 2 | E24: =Reconciliation!E12 -> IE-16A | F24: =Reconciliation!F12 -> L9-6G | G24: =Reconciliation!G12 -> BRI-EM-2046 | 13-Feb-2029 | Line 2 | IE-16A | L9-6G | H24: Forecast - planning only | I24: =Reconciliation!Y12 -> 1008 | J24: =Reconciliation!O12 -> 912 | K24: =Reconciliation!N12 -> 168 | L24: =Reconciliation!AD12 -> 840 | P24: 0.6 | Q24: =ROUNDDOWN(K24*P24,0) -> 100 | R24: =MIN(I24,J24+Q24) -> 1008 | S24: =I24-R24 -> 0 | T24: =Reconciliation!AA12 -> 0.185 | U24: =ROUND(S24*T24,2) -> 0 | V24: Recovered rejects = signed rejects x contract recovery; output capped at ERP available stock. | W24: Signed SQ-90213-08; ERP ERP-709517; contract term IE-16A.
A27: Scenario totals - planning comparison (not a production commitment)
A28: Scenario | B28: Total stock base (cartridges) | C28: Total available output (cartridges) | D28: Total scrap / unavailable (cartridges) | E28: Total scrap cost (USD)
A29: Release | B29: =SUMIF($A$7:$A$24,A29,$I$7:$I$24) -> 8576 | C29: =SUMIF($A$7:$A$24,A29,$R$7:$R$24) -> 7736 | D29: =SUMIF($A$7:$A$24,A29,$S$7:$S$24) -> 840 | E29: =SUMIF($A$7:$A$24,A29,$U$7:$U$24) -> 210.15
A30: Reinspection | B30: =SUMIF($A$7:$A$24,A30,$I$7:$I$24) -> 8576 | C30: =SUMIF($A$7:$A$24,A30,$R$7:$R$24) -> 6249 | D30: =SUMIF($A$7:$A$24,A30,$S$7:$S$24) -> 2327 | E30: =SUMIF($A$7:$A$24,A30,$U$7:$U$24) -> 637.25
A31: Rework | B31: =SUMIF($A$7:$A$24,A31,$I$7:$I$24) -> 8576 | C31: =SUMIF($A$7:$A$24,A31,$R$7:$R$24) -> 8537 | D31: =SUMIF($A$7:$A$24,A31,$S$7:$S$24) -> 39 | E31: =SUMIF($A$7:$A$24,A31,$U$7:$U$24) -> 12.29

Sheet Method
A1: Method and Decision Conventions
A2: Confirmed source facts are separated from derived reconciliation values and forecast planning assumptions.
A4: Method notes used for this decision workbook
A5: Topic | B5: Method applied
A6: Source scope | B6: Confirmed inputs were read from signed_quality_records.xlsx (Signed Log) and erp_postings.xlsx (Postings Extract) for Ballantry Components Ltd. and the review week ending 14-Feb-2029.
A7: Cartridge-run key | B7: The complete physical-run key is Contract / Run ID + Production Date + Line + Cartridge Model + Lot. The same full key is shown in Reconciliation, Scenario_Forecast, and Evidence.
A8: Overlapping signed records | B8: Records sharing the full key were collapsed to one physical run before any quantity totals. SQ-90211-18 and SQ-90211-18A are retained as source IDs in Evidence, but their same inspection event contributes once to run-level quantities.
A9: Quantity convention | B9: Signed carton quantities and ERP PACK quantities were converted to individual cartridges using the applicable carton pack size from the Ballantry contract terms in signed_quality_records.xlsx. Source pack fields remain visible in their original convention.
A10: Signed-versus-ERP precedence | B10: When reject quantities disagree, the signed inspection reject quantity controls the selected quality disposition and release bounds. ERP reject postings were retained side by side as stock and audit evidence; they were not overwritten or concealed.
A11: Rate and currency | B11: Contract unit rates were used, not the ERP posting-control residual. Insignificant floating-point tails were neutralized by rounding the unit rate to four decimal USD per cartridge; displayed scrap costs are each run's scrap units times that normalized rate, rounded to cents.
A12: ERP stock | B12: ERP available stock is receipts less outflows from erp_postings.xlsx, then multiplied by the applicable contract pack size. The prior analyst residual formula error in the ERP export was excluded from all authoritative calculations, displayed results, and recommendations.
A13: Release bounds | B13: Lower bound = max(0, ERP available stock minus signed rejected cartridges). Upper bound = min(ERP available stock, signed accepted cartridges). The selected conservative release quantity equals the lower bound and remains subject to the signed status/action gate.
A14: Release forecast | B14: Release available output equals the selected conservative release quantity. Release scrap / unavailable units equal ERP available stock less that output; scrap cost uses the normalized contract rate.
A15: Reinspection forecast | B15: For a nonzero sample, forecast yield = signed sample pass cartridges divided by signed sample checked cartridges; forecast output = that yield times ERP available stock, rounded down to whole cartridges. Scrap / unavailable equals stock base less forecast output.
A16: Zero-denominator convention | B16: BRI-EM-2044 | 11-Feb-2029 | Line 1 | IE-32C | L9-8D has 0 sample pass and 0 sample checked. The zero reinspection denominator is handled as conservative 0% yield, reinspection output of 0 cartridges, and the entire stock base as forecast unavailable rather than calculating an ordinary rate.
... A18: Forecast status and display | B18: Signed records, ERP postings, contract terms, and stock movements are confirmed source facts. Reconciliation values are derived. Release, reinspection, and rework outputs/costs are planning forecasts, not guaranteed production or quality results. Quantities display as whole cartridges; USD costs display to cents.

Sheet Evidence
A1: Evidence Trail
A2: Source references preserve signed, ERP, and contract records needed to retrace each run-level conclusion.
A3: Raw signed carton quantities and ERP pack-count quantities are retained in their source convention here. The decision tabs normalize comparisons to individual cartridges using the contract pack size.
A5: Evidence class | B5: Source workbook | C5: Source sheet / row | D5: Source record / term ID | E5: Contract / Run ID | F5: Production date | G5: Line | H5: Cartridge model | I5: Lot | J5: Source quantity UOM | K5: Inspected / posted source packs | L5: Rejected source packs | M5: Receipt source packs | N5: Outflow source packs | O5: Net available source packs | P5: Contract pack size (cartridges/carton) | Q5: Rate raw USD/cartridge | R5: Reinspect sample pass (cartridges) | S5: Reinspect sample checked (cartridges) | T5: Signed status / ERP post state | U5: Contract recovery rate | V5: Audit treatment / trace note
A6: Signed inspection | B6: signed_quality_records.xlsx | C6: Signed Log / 6 | D6: SQ-90211-17 | E6: BRI-EM-2041 | F6: 47159 | G6: Line 2 | H6: IE-16A | I6: L9-2A | J6: Cartons | K6: 80 | L6: 3 | P6: 24 | Q6: 0.185 | R6: 46 | S6: 48 | T6: Conditional release | V6: Signed evidence; overlapping source IDs remain independently traceable by the full run key.
A7: Signed inspection | B7: signed_quality_records.xlsx | C7: Signed Log / 7 | D7: SQ-90211-18 | E7: BRI-EM-2042 | F7: 47159 | G7: Line 3 | H7: IE-24B | I7: L9-4C | J7: Cartons | K7: 100 | L7: 11 | P7: 20 | Q7: 0.2375 | R7: 28 | S7: 40 | T7: Hold - reinspection | V7: Signed evidence; overlapping source IDs remain independently traceable by the full run key.
A8: Signed inspection | B8: signed_quality_records.xlsx | C8: Signed Log / 8 | D8: SQ-90211-19 | E8: BRI-EM-2043 | F8: 47160 | G8: Line 2 | H8: IE-16A | I8: L9-3B | J8: Cartons | K8: 60 | L8: 0 | P8: 24 | Q8: 0.185 | R8: 30 | S8: 30 | T8: Accepted | V8: Signed evidence; overlapping source IDs remain independently traceable by the full run key.
A9: Signed inspection | B9: signed_quality_records.xlsx | C9: Signed Log / 9 | D9: SQ-90212-03 | E9: BRI-EM-2044 | F9: 47160 | G9: Line 1 | H9: IE-32C | I9: L9-8D | J9: Cartons | K9: 120 | L9: 25 | P9: 12 | Q9: 0.315 | R9: 0 | S9: 0 | T9: Hold - rework eligible | V9: Signed evidence; overlapping source IDs remain independently traceable by the full run key.
A10: Signed inspection | B10: signed_quality_records.xlsx | C10: Signed Log / 10 | D10: SQ-90212-04 | E10: BRI-EM-2045 | F10: 47161 | G10: Line 3 | H10: IE-24B | I10: L9-1F | J10: Cartons | K10: 75 | L10: 4 | P10: 20 | Q10: 0.2375 | R10: 19 | S10: 20 | T10: Accepted w/ inspection note | V10: Signed evidence; overlapping source IDs remain independently traceable by the full run key.
A11: Signed inspection | B11: signed_quality_records.xlsx | C11: Signed Log / 11 | D11: SQ-90213-08 | E11: BRI-EM-2046 | F11: 47162 | G11: Line 2 | H11: IE-16A | I11: L9-6G | J11: Cartons | K11: 45 | L11: 7 | P11: 24 | Q11: 0.185 | R11: 21 | S11: 30 | T11: Hold - disposition review | V11: Signed evidence; overlapping source IDs remain independently traceable by the full run key.
A12: Signed inspection | B12: signed_quality_records.xlsx | C12: Signed Log / 12 | D12: SQ-90211-18A | E12: BRI-EM-2042 | F12: 47159 | G12: Line 3 | H12: IE-24B | I12: L9-4C | J12: Cartons | K12: 100 | L12: 11 | P12: 20 | Q12: 0.2375 | R12: 28 | S12: 40 | T12: Hold - reinspection | V12: Signed evidence; overlapping source IDs remain independently traceable by the full run key.
A13: ERP posting / stock | B13: erp_postings.xlsx | C13: Postings Extract / 6 | D13: ERP-709512 | E13: BRI-EM-2041 | F13: 47159 | G13: Line 2 | H13: IE-16A | I13: L9-2A | J13: Pack counts (PACK) | K13: 80 | L13: 2 | M13: 80 | N13: 10 | O13: 70 | T13: Posted | V13: ERP comparison and stock evidence; ERP rejects do not replace signed disposition.
A14: ERP posting / stock | B14: erp_postings.xlsx | C14: Postings Extract / 7 | D14: ERP-709513 | E14: BRI-EM-2042 | F14: 47159 | G14: Line 3 | H14: IE-24B | I14: L9-4C | J14: Pack counts (PACK) | K14: 100 | L14: 14 | M14: 99 | N14: 9 | O14: 90 | T14: Posted | V14: ERP comparison and stock evidence; ERP rejects do not replace signed disposition.
A15: ERP posting / stock | B15: erp_postings.xlsx | C15: Postings Extract / 8 | D15: ERP-709514 | E15: BRI-EM-2043 | F15: 47160 | G15: Line 2 | H15: IE-16A | I15: L9-3B | J15: Pack counts (PACK) | K15: 60 | L15: 0 | M15: 60 | N15: 4 | O15: 56 | T15: Posted | V15: ERP comparison and stock evidence; ERP rejects do not replace signed disposition.
A16: ERP posting / stock | B16: erp_postings.xlsx | C16: Postings Extract / 9 | D16: ERP-709515 | E16: BRI-EM-2044 | F16: 47160 | G16: Line 1 | H16: IE-32C | I16: L9-8D | J16: Pack counts (PACK) | K16: 120 | L16: 20 | M16: 118 | N16: 6 | O16: 112 | T16: Held | V16: ERP comparison and stock evidence; ERP rejects do not replace signed disposition.
A17: ERP posting / stock | B17: erp_postings.xlsx | C17: Postings Extract / 10 | D17: ERP-709516 | E17: BRI-EM-2045 | F17: 47161 | G17: Line 3 | H17: IE-24B | I17: L9-1F | J17: Pack counts (PACK) | K17: 75 | L17: 4 | M17: 75 | N17: 5 | O17: 70 | T17: Posted | V17: ERP comparison and stock evidence; ERP rejects do not replace signed disposition.
A18: ERP posting / stock | B18: erp_postings.xlsx | C18: Postings Extract / 11 | D18: ERP-709517 | E18: BRI-EM-2046 | F18: 47162 | G18: Line 2 | H18: IE-16A | I18: L9-6G | J18: Pack counts (PACK) | K18: 45 | L18: 5 | M18: 45 | N18: 3 | O18: 42 | T18: Held | V18: ERP comparison and stock evidence; ERP rejects do not replace signed disposition.
A19: Contract term | B19: signed_quality_records.xlsx | C19: Signed Log / 17 | D19: BAL-IRR-2029 / IE-16A | H19: IE-16A | J19: Contract term | P19: 24 | Q19: 0.185 | T19: Ballantry Components Ltd. | U19: 0.6 | V19: Pack size, normalized rate source, and rework recovery input.
A20: Contract term | B20: signed_quality_records.xlsx | C20: Signed Log / 18 | D20: BAL-IRR-2029 / IE-24B | H20: IE-24B | J20: Contract term | P20: 20 | Q20: 0.2375 | T20: Ballantry Components Ltd. | U20: 0.75 | V20: Pack size, normalized rate source, and rework recovery input.
A21: Contract term | B21: signed_quality_records.xlsx | C21: Signed Log / 19 | D21: BAL-IRR-2029 / IE-32C | H21: IE-32C | J21: Contract term | P21: 12 | Q21: 0.315 | T21: Ballantry Components Ltd. | U21: 0.55 | V21: Pack size, normalized rate source, and rework recovery input.
A22: Excluded ERP control | B22: erp_postings.xlsx | C22: Postings Extract / Q14 | D22: Prior analyst residual | J22: Control cell | V22: Residual formula error outside authoritative quantities; deliberately excluded from all calculations.
A23: Policy reference | B23: signed_quality_records.xlsx | C23: Signed Log / 24-31 | D23: Supply Quality Memo SQ-28 | J23: Policy | V23: Defines the full run key, signed quality precedence, carton conversion, ERP stock basis, and bounded release formulas.
