Workbook

Sheet Board Brief
A1: Foxhollow Fisheries | Rookwood Quay renewal decision brief
A2: Prepared by Edith Lockhart, Pembroke Practice · for Camila Wolstenholme / Foxhollow board · valuation basis 30 June 2026
A4: Recommendation | B4: Negotiate the target package first; do not accept the quoted fixed term. A usable tenant break effective at the end of year 7 is a condition because the crane replacement decision occurs before then. If it cannot be secured, recommend Ferris rather than a superficially cheaper Rookwood rent.
A6: Decision item | B6: Amount | C6: Board reading
A7: Opening ask | B7: =Evidence!B21 -> 262700 | C7: £262,700 Y1 base (95% corrected benchmark); only with requested Y7 break package.
A8: Target package | B8: =Evidence!B22 -> 276500 | C8: £276,500 Y1 base; 10 years, break effective end Y7, six months’ notice, RPI-linked escalation capped 3.0%; no rent/charge after valid break.
A9: Economic walk-away | B9: =Economics!B8 -> 395758 | C9: Maximum Y1 base rent £395,758 for the same minimum Y7-break / 3.0%-cap package; derived at Ferris PV + permitted £80,000 premium.
A10: Delegated stopping rent | B10: =Economics!B10 -> 297300 | C10: £297,300: lower of economic walk-away and policy ceiling. Do not agree above it; no stop number applies without the Y7 right.
A11: Authority quoted renewal | B11: =Economics!C16 -> 307200 | C11: £307,200 Y1 base; 10 years, fixed 3.0% escalation and no tenant termination right — not acceptable.
A12: Ferris County alternative | B12: =Economics!B35 -> 2390327.3 | C12: Discounted 10-year occupancy cost, including supported move, fit-out, downtime, continuity and Notes overrides; no Rookwood charge.
A13: Economic comparison | B13: =Economics!B31 -> 1980812.4 | C13: Expected PV of target package with crane scenarios. Ferris is the fallback if the break is withheld or rent exceeds the stopping package.
A15: Why the Authority evidence should be challenged
A16: The cited schedule includes a conditional letting, an inland letting and an out-of-window letting that fail the written policy. Tideway Bay’s Notes override its main adjustment; the retired helper values are stale. Corrected eligible evidence supports the opening and target, not the quoted increase.
A18: Board approvals requested
A19: • | B19: Approve opening £262,700 and target £276,500 Y1 base, both contingent on the minimum Y7 break package.
A20: • | B20: Authorize Kamil to stop at £297,300 Y1 base only with that package; otherwise stop and recommend Ferris.
A21: • | B21: Confirm that Ferris may be progressed as fallback, subject to commercial availability and lease-documentation confirmation.
A22: • | B22: Approve conditional trades only as set out in the negotiation ladder; no unpriced landlord promise is assumed.

Sheet Negotiation Plan
A1: Negotiation Plan — live meeting ladder for Kamil Navarro
A2: Use in order. Figures are year-one base rent; all rent movement is conditional on the minimum package and evidence response.
A4: Step | B4: What Kamil says / asks | C4: Position | D4: Only move if | E4: Permitted exchange / evidence | F4: If Authority refuses
A5: 1 | B5: Ask Authority to reconcile its comparable schedule to its written eligibility and normalization policy before discussing price. | C5: No economic concession. | D5: They identify policy-eligible completed quayside records and apply Notes overrides. | E5: Point to C-04 conditional status, C-05 inland location, C-06 date window and C-02 Note-controlled adjustment. | F5: Keep opening position; do not validate the quoted £307,200.
A6: 2 | B6: Open at corrected policy position and state the condition. | C6: Opening ask =Evidence!B21 | D6: Authority accepts Y7 tenant break principle. | E6: £262,700 Y1 base; 10 years; break end Y7; six months’ notice; RPI cap 3%; no residual rent / charge after valid exercise. | F6: If break is not available, stop negotiating rent and recommend Ferris.
A7: 3 | B7: Move to target only after the break terms are agreed in principle. | C7: Target =Evidence!B22 | D7: Break effective end Y7 and post-break rent/charge treatment confirmed; escalation cap retained. | E7: £276,500 Y1 base. Ask for written confirmation that no Rookwood rent charge follows valid exercise. | F7: Do not release signage, term or index-form trades before this condition.
A8: 4 | B8: Trade, not gift: accept the 10-year term / estate signage / RPI wording within authority. | C8: Do not exceed =Economics!B10 | D8: Authority gives identified movement: break documentation, rent toward target or capped index. | E8: Term: no more than 10 years; signage: standard estate treatment; index: RPI-linked with 3.0% cap only. Each is conditional on the Y7 break already secured. | F8: No uncapped index; no extended term; no unconditional concession.
A9: 5 | B9: Final counter within delegated boundary. | C9: Stopping rent =Economics!B10 | D9: Every element of minimum package is documented. | E9: At or below £297,300 Y1 base, 3.0% capped RPI and valid Y7 break only. This is below the economic walk-away £395,758 because policy ceiling binds. | F9: If price exceeds £297,300, or break / post-break treatment is withheld, stop and recommend Ferris.
A10: 6 | B10: Close / escalate. | C10: No discretion above stop. | D10: Board approval for a package at or below stop. | E10: Record only offered terms; flag Ferris availability and lease documentation as confirmation items. | F10: Recommend Ferris County; do not substitute cheaper rent for usable Y7 exit.
A12: Non-negotiable stopping rule | B12: Stop and recommend Ferris if a usable break effective at the end of year 7 (with no rent or Rookwood charge after valid exercise) is absent, or if any otherwise-compliant package exceeds £297,300 Y1 base. Do not treat an unoffered landlord promise as a substitute.

Sheet Economics
A1: Economics — nominal annual occupancy cash flows and present values
A2: All amounts £; year-end timing; annual cash flows rounded to £1. Target / walk package assumes requested Y7 tenant break and RPI capped at 3.0%.
A4: Valuation date | B4: 30 June 2026
A5: Discount rate | B5: 0.08
A6: Rookwood charge rate (normal rounded) | B6: 0.0225
A7: Target first-year base rent | B7: 276500
A8: Economic walk-away first-year base rent | B8: 395758
A9: Authority delegated ceiling | B9: 297300
A10: Stopping rent (lower boundary) | B10: 297300
A11: Break transition cost at Y7 | B11: 90000
A12: Leave / retain probabilities | B12: 55% / 45%
A13: Ferris Notes treatment | B13: Fit-out £300,000 Y2; incentive £70,000 Y2; no Rookwood charge
A15: Yr | B15: DF | C15: Quoted base | D15: Quoted service | E15: Quoted Rwk charge | F15: Quoted total | G15: Target base | H15: Target service | I15: Target Rwk charge | J15: Target total | K15: Walk base | L15: Walk service | M15: Walk Rwk charge | N15: Walk total | O15: Ferris base | P15: Ferris site cost | Q15: Move | R15: Fit-out | S15: Downtime | T15: Continuity | U15: Incentive | V15: Ferris total
A16: 1 | B16: =1/(1+$B$5)^A16 -> 0.92592593 | C16: =ROUND(307200*(1+3%)^(A16-1),0) -> 307200 | D16: =ROUND(18000*(1+2%)^(A16-1),0) -> 18000 | E16: =ROUND(C16*$B$6,0) -> 6912 | F16: =SUM(C16:E16) -> 332112 | G16: =ROUND($B$7*(1+3%)^(A16-1),0) -> 276500 | H16: =ROUND(18000*(1+2%)^(A16-1),0) -> 18000 | I16: =ROUND(G16*$B$6,0) -> 6221 | J16: =SUM(G16:I16) -> 300721 | K16: =ROUND($B$8*(1+3%)^(A16-1),0) -> 395758 | L16: =ROUND(18000*(1+2%)^(A16-1),0) -> 18000 | M16: =ROUND(K16*$B$6,0) -> 8905 | N16: =SUM(K16:M16) -> 422663 | O16: =ROUND(230000*(1+2.5%)^(A16-1),0) -> 230000 | P16: =ROUND(30000*(1+2%)^(A16-1),0) -> 30000 | Q16: =IF(A16=1,150000,0) -> 150000 | R16: =IF(A16=2,300000,0) -> 0 | S16: =IF(A16=1,125000,0) -> 125000 | T16: =IF(A16=1,20000,0) -> 20000 | U16: =IF(A16=2,-70000,0) -> 0 | V16: =SUM(O16:U16) -> 555000
A17: 2 | B17: =1/(1+$B$5)^A17 -> 0.85733882 | C17: =ROUND(307200*(1+3%)^(A17-1),0) -> 316416 | D17: =ROUND(18000*(1+2%)^(A17-1),0) -> 18360 | E17: =ROUND(C17*$B$6,0) -> 7119 | F17: =SUM(C17:E17) -> 341895 | G17: =ROUND($B$7*(1+3%)^(A17-1),0) -> 284795 | H17: =ROUND(18000*(1+2%)^(A17-1),0) -> 18360 | I17: =ROUND(G17*$B$6,0) -> 6408 | J17: =SUM(G17:I17) -> 309563 | K17: =ROUND($B$8*(1+3%)^(A17-1),0) -> 407631 | L17: =ROUND(18000*(1+2%)^(A17-1),0) -> 18360 | M17: =ROUND(K17*$B$6,0) -> 9172 | N17: =SUM(K17:M17) -> 435163 | O17: =ROUND(230000*(1+2.5%)^(A17-1),0) -> 235750 | P17: =ROUND(30000*(1+2%)^(A17-1),0) -> 30600 | Q17: =IF(A17=1,150000,0) -> 0 | R17: =IF(A17=2,300000,0) -> 300000 | S17: =IF(A17=1,125000,0) -> 0 | T17: =IF(A17=1,20000,0) -> 0 | U17: =IF(A17=2,-70000,0) -> -70000 | V17: =SUM(O17:U17) -> 496350
A18: 3 | B18: =1/(1+$B$5)^A18 -> 0.79383224 | C18: =ROUND(307200*(1+3%)^(A18-1),0) -> 325908 | D18: =ROUND(18000*(1+2%)^(A18-1),0) -> 18727 | E18: =ROUND(C18*$B$6,0) -> 7333 | F18: =SUM(C18:E18) -> 351968 | G18: =ROUND($B$7*(1+3%)^(A18-1),0) -> 293339 | H18: =ROUND(18000*(1+2%)^(A18-1),0) -> 18727 | I18: =ROUND(G18*$B$6,0) -> 6600 | J18: =SUM(G18:I18) -> 318666 | K18: =ROUND($B$8*(1+3%)^(A18-1),0) -> 419860 | L18: =ROUND(18000*(1+2%)^(A18-1),0) -> 18727 | M18: =ROUND(K18*$B$6,0) -> 9447 | N18: =SUM(K18:M18) -> 448034 | O18: =ROUND(230000*(1+2.5%)^(A18-1),0) -> 241644 | P18: =ROUND(30000*(1+2%)^(A18-1),0) -> 31212 | Q18: =IF(A18=1,150000,0) -> 0 | R18: =IF(A18=2,300000,0) -> 0 | S18: =IF(A18=1,125000,0) -> 0 | T18: =IF(A18=1,20000,0) -> 0 | U18: =IF(A18=2,-70000,0) -> 0 | V18: =SUM(O18:U18) -> 272856
A19: 4 | B19: =1/(1+$B$5)^A19 -> 0.73502985 | C19: =ROUND(307200*(1+3%)^(A19-1),0) -> 335686 | D19: =ROUND(18000*(1+2%)^(A19-1),0) -> 19102 | E19: =ROUND(C19*$B$6,0) -> 7553 | F19: =SUM(C19:E19) -> 362341 | G19: =ROUND($B$7*(1+3%)^(A19-1),0) -> 302139 | H19: =ROUND(18000*(1+2%)^(A19-1),0) -> 19102 | I19: =ROUND(G19*$B$6,0) -> 6798 | J19: =SUM(G19:I19) -> 328039 | K19: =ROUND($B$8*(1+3%)^(A19-1),0) -> 432455 | L19: =ROUND(18000*(1+2%)^(A19-1),0) -> 19102 | M19: =ROUND(K19*$B$6,0) -> 9730 | N19: =SUM(K19:M19) -> 461287 | O19: =ROUND(230000*(1+2.5%)^(A19-1),0) -> 247685 | P19: =ROUND(30000*(1+2%)^(A19-1),0) -> 31836 | Q19: =IF(A19=1,150000,0) -> 0 | R19: =IF(A19=2,300000,0) -> 0 | S19: =IF(A19=1,125000,0) -> 0 | T19: =IF(A19=1,20000,0) -> 0 | U19: =IF(A19=2,-70000,0) -> 0 | V19: =SUM(O19:U19) -> 279521
A20: 5 | B20: =1/(1+$B$5)^A20 -> 0.6805832 | C20: =ROUND(307200*(1+3%)^(A20-1),0) -> 345756 | D20: =ROUND(18000*(1+2%)^(A20-1),0) -> 19484 | E20: =ROUND(C20*$B$6,0) -> 7780 | F20: =SUM(C20:E20) -> 373020 | G20: =ROUND($B$7*(1+3%)^(A20-1),0) -> 311203 | H20: =ROUND(18000*(1+2%)^(A20-1),0) -> 19484 | I20: =ROUND(G20*$B$6,0) -> 7002 | J20: =SUM(G20:I20) -> 337689 | K20: =ROUND($B$8*(1+3%)^(A20-1),0) -> 445429 | L20: =ROUND(18000*(1+2%)^(A20-1),0) -> 19484 | M20: =ROUND(K20*$B$6,0) -> 10022 | N20: =SUM(K20:M20) -> 474935 | O20: =ROUND(230000*(1+2.5%)^(A20-1),0) -> 253877 | P20: =ROUND(30000*(1+2%)^(A20-1),0) -> 32473 | Q20: =IF(A20=1,150000,0) -> 0 | R20: =IF(A20=2,300000,0) -> 0 | S20: =IF(A20=1,125000,0) -> 0 | T20: =IF(A20=1,20000,0) -> 0 | U20: =IF(A20=2,-70000,0) -> 0 | V20: =SUM(O20:U20) -> 286350
A21: 6 | B21: =1/(1+$B$5)^A21 -> 0.63016963 | C21: =ROUND(307200*(1+3%)^(A21-1),0) -> 356129 | D21: =ROUND(18000*(1+2%)^(A21-1),0) -> 19873 | E21: =ROUND(C21*$B$6,0) -> 8013 | F21: =SUM(C21:E21) -> 384015 | G21: =ROUND($B$7*(1+3%)^(A21-1),0) -> 320539 | H21: =ROUND(18000*(1+2%)^(A21-1),0) -> 19873 | I21: =ROUND(G21*$B$6,0) -> 7212 | J21: =SUM(G21:I21) -> 347624 | K21: =ROUND($B$8*(1+3%)^(A21-1),0) -> 458792 | L21: =ROUND(18000*(1+2%)^(A21-1),0) -> 19873 | M21: =ROUND(K21*$B$6,0) -> 10323 | N21: =SUM(K21:M21) -> 488988 | O21: =ROUND(230000*(1+2.5%)^(A21-1),0) -> 260224 | P21: =ROUND(30000*(1+2%)^(A21-1),0) -> 33122 | Q21: =IF(A21=1,150000,0) -> 0 | R21: =IF(A21=2,300000,0) -> 0 | S21: =IF(A21=1,125000,0) -> 0 | T21: =IF(A21=1,20000,0) -> 0 | U21: =IF(A21=2,-70000,0) -> 0 | V21: =SUM(O21:U21) -> 293346
A22: 7 | B22: =1/(1+$B$5)^A22 -> 0.5834904 | C22: =ROUND(307200*(1+3%)^(A22-1),0) -> 366813 | D22: =ROUND(18000*(1+2%)^(A22-1),0) -> 20271 | E22: =ROUND(C22*$B$6,0) -> 8253 | F22: =SUM(C22:E22) -> 395337 | G22: =ROUND($B$7*(1+3%)^(A22-1),0) -> 330155 | H22: =ROUND(18000*(1+2%)^(A22-1),0) -> 20271 | I22: =ROUND(G22*$B$6,0) -> 7428 | J22: =SUM(G22:I22) -> 357854 | K22: =ROUND($B$8*(1+3%)^(A22-1),0) -> 472556 | L22: =ROUND(18000*(1+2%)^(A22-1),0) -> 20271 | M22: =ROUND(K22*$B$6,0) -> 10633 | N22: =SUM(K22:M22) -> 503460 | O22: =ROUND(230000*(1+2.5%)^(A22-1),0) -> 266729 | P22: =ROUND(30000*(1+2%)^(A22-1),0) -> 33785 | Q22: =IF(A22=1,150000,0) -> 0 | R22: =IF(A22=2,300000,0) -> 0 | S22: =IF(A22=1,125000,0) -> 0 | T22: =IF(A22=1,20000,0) -> 0 | U22: =IF(A22=2,-70000,0) -> 0 | V22: =SUM(O22:U22) -> 300514
A23: 8 | B23: =1/(1+$B$5)^A23 -> 0.54026888 | C23: =ROUND(307200*(1+3%)^(A23-1),0) -> 377817 | D23: =ROUND(18000*(1+2%)^(A23-1),0) -> 20676 | E23: =ROUND(C23*$B$6,0) -> 8501 | F23: =SUM(C23:E23) -> 406994 | G23: =ROUND($B$7*(1+3%)^(A23-1),0) -> 340060 | H23: =ROUND(18000*(1+2%)^(A23-1),0) -> 20676 | I23: =ROUND(G23*$B$6,0) -> 7651 | J23: =SUM(G23:I23) -> 368387 | K23: =ROUND($B$8*(1+3%)^(A23-1),0) -> 486732 | L23: =ROUND(18000*(1+2%)^(A23-1),0) -> 20676 | M23: =ROUND(K23*$B$6,0) -> 10951 | N23: =SUM(K23:M23) -> 518359 | O23: =ROUND(230000*(1+2.5%)^(A23-1),0) -> 273398 | P23: =ROUND(30000*(1+2%)^(A23-1),0) -> 34461 | Q23: =IF(A23=1,150000,0) -> 0 | R23: =IF(A23=2,300000,0) -> 0 | S23: =IF(A23=1,125000,0) -> 0 | T23: =IF(A23=1,20000,0) -> 0 | U23: =IF(A23=2,-70000,0) -> 0 | V23: =SUM(O23:U23) -> 307859
A24: 9 | B24: =1/(1+$B$5)^A24 -> 0.50024897 | C24: =ROUND(307200*(1+3%)^(A24-1),0) -> 389152 | D24: =ROUND(18000*(1+2%)^(A24-1),0) -> 21090 | E24: =ROUND(C24*$B$6,0) -> 8756 | F24: =SUM(C24:E24) -> 418998 | G24: =ROUND($B$7*(1+3%)^(A24-1),0) -> 350262 | H24: =ROUND(18000*(1+2%)^(A24-1),0) -> 21090 | I24: =ROUND(G24*$B$6,0) -> 7881 | J24: =SUM(G24:I24) -> 379233 | K24: =ROUND($B$8*(1+3%)^(A24-1),0) -> 501334 | L24: =ROUND(18000*(1+2%)^(A24-1),0) -> 21090 | M24: =ROUND(K24*$B$6,0) -> 11280 | N24: =SUM(K24:M24) -> 533704 | O24: =ROUND(230000*(1+2.5%)^(A24-1),0) -> 280233 | P24: =ROUND(30000*(1+2%)^(A24-1),0) -> 35150 | Q24: =IF(A24=1,150000,0) -> 0 | R24: =IF(A24=2,300000,0) -> 0 | S24: =IF(A24=1,125000,0) -> 0 | T24: =IF(A24=1,20000,0) -> 0 | U24: =IF(A24=2,-70000,0) -> 0 | V24: =SUM(O24:U24) -> 315383
A25: 10 | B25: =1/(1+$B$5)^A25 -> 0.46319349 | C25: =ROUND(307200*(1+3%)^(A25-1),0) -> 400826 | D25: =ROUND(18000*(1+2%)^(A25-1),0) -> 21512 | E25: =ROUND(C25*$B$6,0) -> 9019 | F25: =SUM(C25:E25) -> 431357 | G25: =ROUND($B$7*(1+3%)^(A25-1),0) -> 360770 | H25: =ROUND(18000*(1+2%)^(A25-1),0) -> 21512 | I25: =ROUND(G25*$B$6,0) -> 8117 | J25: =SUM(G25:I25) -> 390399 | K25: =ROUND($B$8*(1+3%)^(A25-1),0) -> 516374 | L25: =ROUND(18000*(1+2%)^(A25-1),0) -> 21512 | M25: =ROUND(K25*$B$6,0) -> 11618 | N25: =SUM(K25:M25) -> 549504 | O25: =ROUND(230000*(1+2.5%)^(A25-1),0) -> 287238 | P25: =ROUND(30000*(1+2%)^(A25-1),0) -> 35853 | Q25: =IF(A25=1,150000,0) -> 0 | R25: =IF(A25=2,300000,0) -> 0 | S25: =IF(A25=1,125000,0) -> 0 | T25: =IF(A25=1,20000,0) -> 0 | U25: =IF(A25=2,-70000,0) -> 0 | V25: =SUM(O25:U25) -> 323091
A27: Discounted totals / crane scenarios
A28: Quoted fixed-term renewal PV | B28: =SUMPRODUCT(B16:B25,F16:F25) -> 2502198.3
A29: Target renewal: replacement / leave at end Y7 PV | B29: =SUMPRODUCT(B16:B22,J16:J22)+$B$11*B22 -> 1748137.6
A30: Target renewal: retain crane PV | B30: =SUMPRODUCT(B16:B25,J16:J25) -> 2265192.7
A31: Target renewal expected PV | B31: =B29*55%+B30*45% -> 1980812.4
A32: Walk package: replacement / leave at end Y7 PV | B32: =SUMPRODUCT(B16:B22,N16:N22)+$B$11*B22 -> 2436816.7
A33: Walk package: retain crane PV | B33: =SUMPRODUCT(B16:B25,N16:N25) -> 3185867.3
A34: Walk package expected PV | B34: =B32*55%+B33*45% -> 2773889.5
A35: Ferris alternative PV | B35: =SUMPRODUCT(B16:B25,V16:V25) -> 2390327.3
A36: Ferris PV + permitted transition premium | B36: =B35+80000 -> 2470327.3
A37: Economic walk-away basis | B37: Walk expected PV must not exceed Ferris PV + £80,000 premium
A39: Scenario treatment | B39: Requested only: valid Y7 break ends rent and Rookwood charge after Y7. Replacement scenario adds supplied £90,000 transition in Y7. Without the break, both scenarios are the quoted full-term obligation.

Sheet Evidence
A1: Evidence — market test, policy application and model inputs
A2: Record current at 30 June 2026. Retired helper values are shown only to identify the Authority schedule weakness; they are not model inputs.
A4: Policy application
A5: Eligibility window | B5: 01 Jul 2024–30 Jun 2026; completed quayside industrial lettings; 20,000–45,000 sq ft; crane / heavy-goods compatible
A6: Normalization | B6: (base rent − incentive) / area + access adjustment; Notes replacement controls
A7: Benchmark | B7: Simple average of eligible live adjusted unit rents; carry precision, display £0.01/sq ft
A8: Negotiation authority | B8: Opening 95.0%; target 100.0%; ceiling 107.5% of benchmark rent; positions rounded £100
A9: Minimum package | B9: 10 years; Y7 tenant break; six months’ notice; RPI-linked escalation capped 3.0%; no rent/charge after valid exercise
A11: Ref | B11: Property | C11: Area | D11: Base rent | E11: Incentive | F11: Main adj | G11: Live adj | H11: Live adjusted £/sq ft | I11: Eligible? | J11: Evidence / Note treatment
A12: C-01 | B12: Harbour Forge | C12: 30000 | D12: 285000 | E12: 15000 | F12: 0.1 | G12: 0.1 | H12: =(D12-E12)/C12+G12 -> 9.1 | I12: Yes | J12: Completed letting.
A13: C-02 | B13: Tideway Bay | C13: 28000 | D13: 260000 | E13: 0 | F13: -0.05 | G13: 0.15 | H13: =(D13-E13)/C13+G13 -> 9.4357143 | I13: Yes | J13: Use +£0.15/sq ft access adjustment, replacing the main-column amount. Live adjustment replaces main field.
A14: C-03 | B14: Narrow Quay Works | C14: 32000 | D14: 295000 | E14: 0 | F14: -0.1 | G14: -0.1 | H14: =(D14-E14)/C14+G14 -> 9.11875 | I14: Yes | J14: Completed letting.
A15: C-04 | B15: East Reach Shed | C15: 30000 | D15: 315000 | E15: 0 | F15: 0 | G15: 0 | H15: =(D15-E15)/C15+G15 -> 10.5 | I15: No | J15: Not eligible: agreement conditional and not completed.
A16: C-05 | B16: Mossfield Unit | C16: 26000 | D16: 205000 | E16: 0 | F16: 0 | G16: 0 | H16: =(D16-E16)/C16+G16 -> 7.8846154 | I16: No | J16: Inland; not a quayside letting.
A17: C-06 | B17: Old Slip Yard | C17: 30000 | D17: 270000 | E17: 0 | F17: 0 | G17: 0 | H17: =(D17-E17)/C17+G17 -> 9 | I17: No | J17: Outside policy date window.
A19: Corrected eligible benchmark (£/sq ft) | B19: =AVERAGE(H12:H14) -> 9.2181548 | D19: Authority comparable challenge
A20: Subject-area benchmark rent | B20: =B19*30000 -> 276544.64 | D20: C-04 | E20: Conditional / not completed, so fails policy requirement; must not support a market conclusion.
A21: Opening ask (95.0%, £100 rounding) | B21: =ROUND(B20*95%,-2) -> 262700 | D21: C-05 | E21: Inland location, so fails quayside condition.
A22: Target rent (100.0%, £100 rounding) | B22: =ROUND(B20,-2) -> 276500 | D22: C-06 | E22: Signed before policy window.
A23: Delegated ceiling (107.5%, £100 rounding) | B23: =ROUND(B20*107.5%,-2) -> 297300 | D23: C-02 | E23: Notes replace the main adjustment with +£0.15/sq ft; the retired helper is stale and cannot evidence current value.
A26: Jurisdiction / material input trail
A27: Rookwood charge | B27: 2.25% of base rent only; rate stored with harmless binary residue and applied at normal 2.25% rounding. Excludes service and one-time costs.
A28: Ferris charge | B28: None: Ferris County is outside the Rookwood charge jurisdiction.
A29: Quoted renewal | B29: £240,000 current base × 128.0% = £307,200 Y1; fixed 3.0% escalation, 10 years, no tenant break offered.
A30: Target / stop model | B30: Requested Y7 break package uses RPI capped at 3.0% modelled at cap, 6 months’ notice, and £90,000 Y7 transition only in leave scenario.
A31: Ferris Notes | B31: £300,000 fit-out paid Y2 (not Y1); incentive £70,000 received Y2 replacing £50,000 shown; rent, site cost, move, downtime and continuity as supplied.
A32: Unresolved | B32: Ferris commercial availability / lease documentation and Authority agreement to the requested break package require confirmation; neither is treated as offered.
