Workbook

Sheet Filing Note
A1: ANVILCROSS BUREAU | 2027 VENDOR COMMITMENT
A3: Filing note • Inglewood Board 31-store alliance • Prepared by Yolanda Adeyemi
A5: RECOMMENDATION • POOLED COMMITMENT
A6: Recommend one Board distribution-point delivery in whole pallets. Pooling reduces calculated excess from 1,550 units (direct-store) to 717 units while retaining the demand-fit plan for all 31 members. Lucia’s direct-delivery convenience is acknowledged; the lower avoidable excess is the controlling filing consideration. No supplier cost, freight, margin, or savings assumption is used.
A9: Decision metrics | F9: How to read this filing
A10: Alternative | B10: Cases | C10: Pallets | D10: Excess units | F10: Planning case equivalents are shown in whole- or half-case increments to fit network demand; they do not authorize physical split-case shipments. MSRP is suggested guidance shown for gross-retail comparison only; member retailers retain discretion over resale pricing. Gross retail at MSRP is not supplier cost, margin, profit, or freight savings.
A11: Direct-store | B11: 976.5 | C11: 96.875 | D11: 1550
A12: Pooled • recommended | B12: 906 | C12: 91 | D12: 717
A15: * Drop minimum: the minimum applies per SKU, per ship-to, per release. It is not a chain-wide annual minimum. For the direct-store alternative each member store is a separate ship-to; for the pooled alternative the Board distribution point is one ship-to. This vendor commitment is a planning submission only. It is not a purchase order, authorization to ship, or binding store order; release instructions remain subject to Board and supplier confirmation.

Sheet Commitment
A1: 2027 VENDOR COMMITMENT | COMPARISON
A3: Inglewood Board • 31 member stores • planning quantities in half-case increments
A5: DIRECT-STORE ALTERNATIVE | each member store is a ship-to; drop minimum applies per SKU / ship-to / release
A6: SKU | B6: Item | C6: Pack | D6: Cases/pallet | E6: MSRP† | F6: Drop minimum* | G6: Forecast units/store | H6: Demand-fit cases/store | I6: Direct cases/store | J6: Network cases | K6: Pallet equivalents | L6: Projected units | M6: Gross retail at MSRP | N6: Excess units
A7: BW-410 | B7: Hearth Cookware Set | C7: 6 | D7: 8 | E7: 84.99 | F7: 4 | G7: 29 | H7: =ROUNDUP((G7/C7)*2,0)/2 -> 5 | I7: =MAX(H7,F7) -> 5 | J7: =I7*31 -> 155 | K7: =J7/D7 -> 19.375 | L7: =J7*C7 -> 930 | M7: =L7*E7 -> 79040.7 | N7: =L7-(G7*31) -> 31
A8: BW-225 | B8: ClearNest Storage | C8: 8 | D8: 10 | E8: 39.99 | F8: 5 | G8: 37 | H8: =ROUNDUP((G8/C8)*2,0)/2 -> 5 | I8: =MAX(H8,F8) -> 5 | J8: =I8*31 -> 155 | K8: =J8/D8 -> 15.5 | L8: =J8*C8 -> 1240 | M8: =L8*E8 -> 49587.6 | N8: =L8-(G8*31) -> 93
A9: BW-318 | B9: Turnwell Caddy | C9: 12 | D9: 12 | E9: 24.99 | F9: 6 | G9: 40 | H9: =ROUNDUP((G9/C9)*2,0)/2 -> 3.5 | I9: =MAX(H9,F9) -> 6 | J9: =I9*31 -> 186 | K9: =J9/D9 -> 15.5 | L9: =J9*C9 -> 2232 | M9: =L9*E9 -> 55777.68 | N9: =L9-(G9*31) -> 992
A10: BW-144 | B10: Grainline Board | C10: 10 | D10: 9 | E10: 29.99 | F10: 4.5 | G10: 43 | H10: =ROUNDUP((G10/C10)*2,0)/2 -> 4.5 | I10: =MAX(H10,F10) -> 4.5 | J10: =I10*31 -> 139.5 | K10: =J10/D10 -> 15.5 | L10: =J10*C10 -> 1395 | M10: =L10*E10 -> 41836.05 | N10: =L10-(G10*31) -> 62
A11: BW-507 | B11: Northcoil Kettle | C11: 6 | D11: 8 | E11: 54.99 | F11: 4 | G11: 20 | H11: =ROUNDUP((G11/C11)*2,0)/2 -> 3.5 | I11: =MAX(H11,F11) -> 4 | J11: =I11*31 -> 124 | K11: =J11/D11 -> 15.5 | L11: =J11*C11 -> 744 | M11: =L11*E11 -> 40912.56 | N11: =L11-(G11*31) -> 124
A12: BW-612 | B12: Loomridge Towels | C12: 12 | D12: 14 | E12: 19.99 | F12: 7 | G12: 76 | H12: =ROUNDUP((G12/C12)*2,0)/2 -> 6.5 | I12: =MAX(H12,F12) -> 7 | J12: =I12*31 -> 217 | K12: =J12/D12 -> 15.5 | L12: =J12*C12 -> 2604 | M12: =L12*E12 -> 52053.96 | N12: =L12-(G12*31) -> 248
A13: TOTAL | J13: =SUM(J7:J12) -> 976.5 | K13: =SUM(K7:K12) -> 96.875 | L13: =SUM(L7:L12) -> 9145 | M13: =SUM(M7:M12) -> 319208.55 | N13: =SUM(N7:N12) -> 1550
A15: POOLED ALTERNATIVE | one Board distribution point; committed cases round up to whole pallets
A16: SKU | B16: Item | C16: Pack | D16: Cases/pallet | E16: MSRP† | F16: Forecast units/store | G16: Demand-fit cases/store | H16: Network demand-fit cases | I16: Committed cases | J16: Whole pallets | K16: Projected units | L16: Gross retail at MSRP | M16: Excess units | N16: Selection
A17: BW-410 | B17: Hearth Cookware Set | C17: 6 | D17: 8 | E17: 84.99 | F17: 29 | G17: =ROUNDUP((F17/C17)*2,0)/2 -> 5 | H17: =G17*31 -> 155 | I17: =ROUNDUP(H17/D17,0)*D17 -> 160 | J17: =I17/D17 -> 20 | K17: =I17*C17 -> 960 | L17: =K17*E17 -> 81590.4 | M17: =K17-(F17*31) -> 61 | N17: RECOMMENDED
A18: BW-225 | B18: ClearNest Storage | C18: 8 | D18: 10 | E18: 39.99 | F18: 37 | G18: =ROUNDUP((F18/C18)*2,0)/2 -> 5 | H18: =G18*31 -> 155 | I18: =ROUNDUP(H18/D18,0)*D18 -> 160 | J18: =I18/D18 -> 16 | K18: =I18*C18 -> 1280 | L18: =K18*E18 -> 51187.2 | M18: =K18-(F18*31) -> 133 | N18: RECOMMENDED
A19: BW-318 | B19: Turnwell Caddy | C19: 12 | D19: 12 | E19: 24.99 | F19: 40 | G19: =ROUNDUP((F19/C19)*2,0)/2 -> 3.5 | H19: =G19*31 -> 108.5 | I19: =ROUNDUP(H19/D19,0)*D19 -> 120 | J19: =I19/D19 -> 10 | K19: =I19*C19 -> 1440 | L19: =K19*E19 -> 35985.6 | M19: =K19-(F19*31) -> 200 | N19: RECOMMENDED
A20: BW-144 | B20: Grainline Board | C20: 10 | D20: 9 | E20: 29.99 | F20: 43 | G20: =ROUNDUP((F20/C20)*2,0)/2 -> 4.5 | H20: =G20*31 -> 139.5 | I20: =ROUNDUP(H20/D20,0)*D20 -> 144 | J20: =I20/D20 -> 16 | K20: =I20*C20 -> 1440 | L20: =K20*E20 -> 43185.6 | M20: =K20-(F20*31) -> 107 | N20: RECOMMENDED
A21: BW-507 | B21: Northcoil Kettle | C21: 6 | D21: 8 | E21: 54.99 | F21: 20 | G21: =ROUNDUP((F21/C21)*2,0)/2 -> 3.5 | H21: =G21*31 -> 108.5 | I21: =ROUNDUP(H21/D21,0)*D21 -> 112 | J21: =I21/D21 -> 14 | K21: =I21*C21 -> 672 | L21: =K21*E21 -> 36953.28 | M21: =K21-(F21*31) -> 52 | N21: RECOMMENDED
A22: BW-612 | B22: Loomridge Towels | C22: 12 | D22: 14 | E22: 19.99 | F22: 76 | G22: =ROUNDUP((F22/C22)*2,0)/2 -> 6.5 | H22: =G22*31 -> 201.5 | I22: =ROUNDUP(H22/D22,0)*D22 -> 210 | J22: =I22/D22 -> 15 | K22: =I22*C22 -> 2520 | L22: =K22*E22 -> 50374.8 | M22: =K22-(F22*31) -> 164 | N22: RECOMMENDED
A23: TOTAL | H23: =SUM(H17:H22) -> 868 | I23: =SUM(I17:I22) -> 906 | J23: =SUM(J17:J22) -> 91 | K23: =SUM(K17:K22) -> 8312 | L23: =SUM(L17:L22) -> 299276.88 | M23: =SUM(M17:M22) -> 717
A25: † MSRP is manufacturer's suggested retail guidance for comparison only; it is not a required resale price, and member retailers retain resale-pricing discretion.

Sheet Store Detail
A1: STORE DETAIL | POOLED COMMITMENT CARRY-THROUGH
A3: Recommended option: pooled delivery to one Board distribution point • 31 member planning allocations + visible reserve
A6: Store / reserve | B6: Allocation basis | C6: BW-410 | D6: BW-225 | E6: BW-318 | F6: BW-144 | G6: BW-507 | H6: BW-612
A7: 01 | B7: Demand-fit plan | C7: =Commitment!G17 -> 5 | D7: =Commitment!G18 -> 5 | E7: =Commitment!G19 -> 3.5 | F7: =Commitment!G20 -> 4.5 | G7: =Commitment!G21 -> 3.5 | H7: =Commitment!G22 -> 6.5
A8: 02 | B8: Demand-fit plan | C8: =Commitment!G17 -> 5 | D8: =Commitment!G18 -> 5 | E8: =Commitment!G19 -> 3.5 | F8: =Commitment!G20 -> 4.5 | G8: =Commitment!G21 -> 3.5 | H8: =Commitment!G22 -> 6.5
A9: 03 | B9: Demand-fit plan | C9: =Commitment!G17 -> 5 | D9: =Commitment!G18 -> 5 | E9: =Commitment!G19 -> 3.5 | F9: =Commitment!G20 -> 4.5 | G9: =Commitment!G21 -> 3.5 | H9: =Commitment!G22 -> 6.5
A10: 04 | B10: Demand-fit plan | C10: =Commitment!G17 -> 5 | D10: =Commitment!G18 -> 5 | E10: =Commitment!G19 -> 3.5 | F10: =Commitment!G20 -> 4.5 | G10: =Commitment!G21 -> 3.5 | H10: =Commitment!G22 -> 6.5
A11: 05 | B11: Demand-fit plan | C11: =Commitment!G17 -> 5 | D11: =Commitment!G18 -> 5 | E11: =Commitment!G19 -> 3.5 | F11: =Commitment!G20 -> 4.5 | G11: =Commitment!G21 -> 3.5 | H11: =Commitment!G22 -> 6.5
A12: 06 | B12: Demand-fit plan | C12: =Commitment!G17 -> 5 | D12: =Commitment!G18 -> 5 | E12: =Commitment!G19 -> 3.5 | F12: =Commitment!G20 -> 4.5 | G12: =Commitment!G21 -> 3.5 | H12: =Commitment!G22 -> 6.5
A13: 07 | B13: Demand-fit plan | C13: =Commitment!G17 -> 5 | D13: =Commitment!G18 -> 5 | E13: =Commitment!G19 -> 3.5 | F13: =Commitment!G20 -> 4.5 | G13: =Commitment!G21 -> 3.5 | H13: =Commitment!G22 -> 6.5
A14: 08 | B14: Demand-fit plan | C14: =Commitment!G17 -> 5 | D14: =Commitment!G18 -> 5 | E14: =Commitment!G19 -> 3.5 | F14: =Commitment!G20 -> 4.5 | G14: =Commitment!G21 -> 3.5 | H14: =Commitment!G22 -> 6.5
A15: 09 | B15: Demand-fit plan | C15: =Commitment!G17 -> 5 | D15: =Commitment!G18 -> 5 | E15: =Commitment!G19 -> 3.5 | F15: =Commitment!G20 -> 4.5 | G15: =Commitment!G21 -> 3.5 | H15: =Commitment!G22 -> 6.5
A16: 10 | B16: Demand-fit plan | C16: =Commitment!G17 -> 5 | D16: =Commitment!G18 -> 5 | E16: =Commitment!G19 -> 3.5 | F16: =Commitment!G20 -> 4.5 | G16: =Commitment!G21 -> 3.5 | H16: =Commitment!G22 -> 6.5
A17: 11 | B17: Demand-fit plan | C17: =Commitment!G17 -> 5 | D17: =Commitment!G18 -> 5 | E17: =Commitment!G19 -> 3.5 | F17: =Commitment!G20 -> 4.5 | G17: =Commitment!G21 -> 3.5 | H17: =Commitment!G22 -> 6.5
A18: 12 | B18: Demand-fit plan | C18: =Commitment!G17 -> 5 | D18: =Commitment!G18 -> 5 | E18: =Commitment!G19 -> 3.5 | F18: =Commitment!G20 -> 4.5 | G18: =Commitment!G21 -> 3.5 | H18: =Commitment!G22 -> 6.5
A19: 13 | B19: Demand-fit plan | C19: =Commitment!G17 -> 5 | D19: =Commitment!G18 -> 5 | E19: =Commitment!G19 -> 3.5 | F19: =Commitment!G20 -> 4.5 | G19: =Commitment!G21 -> 3.5 | H19: =Commitment!G22 -> 6.5
A20: 14 | B20: Demand-fit plan | C20: =Commitment!G17 -> 5 | D20: =Commitment!G18 -> 5 | E20: =Commitment!G19 -> 3.5 | F20: =Commitment!G20 -> 4.5 | G20: =Commitment!G21 -> 3.5 | H20: =Commitment!G22 -> 6.5
A21: 15 | B21: Demand-fit plan | C21: =Commitment!G17 -> 5 | D21: =Commitment!G18 -> 5 | E21: =Commitment!G19 -> 3.5 | F21: =Commitment!G20 -> 4.5 | G21: =Commitment!G21 -> 3.5 | H21: =Commitment!G22 -> 6.5
A22: 16 | B22: Demand-fit plan | C22: =Commitment!G17 -> 5 | D22: =Commitment!G18 -> 5 | E22: =Commitment!G19 -> 3.5 | F22: =Commitment!G20 -> 4.5 | G22: =Commitment!G21 -> 3.5 | H22: =Commitment!G22 -> 6.5
A23: 17 | B23: Demand-fit plan | C23: =Commitment!G17 -> 5 | D23: =Commitment!G18 -> 5 | E23: =Commitment!G19 -> 3.5 | F23: =Commitment!G20 -> 4.5 | G23: =Commitment!G21 -> 3.5 | H23: =Commitment!G22 -> 6.5
A24: 18 | B24: Demand-fit plan | C24: =Commitment!G17 -> 5 | D24: =Commitment!G18 -> 5 | E24: =Commitment!G19 -> 3.5 | F24: =Commitment!G20 -> 4.5 | G24: =Commitment!G21 -> 3.5 | H24: =Commitment!G22 -> 6.5
A25: 19 | B25: Demand-fit plan | C25: =Commitment!G17 -> 5 | D25: =Commitment!G18 -> 5 | E25: =Commitment!G19 -> 3.5 | F25: =Commitment!G20 -> 4.5 | G25: =Commitment!G21 -> 3.5 | H25: =Commitment!G22 -> 6.5
A26: 20 | B26: Demand-fit plan | C26: =Commitment!G17 -> 5 | D26: =Commitment!G18 -> 5 | E26: =Commitment!G19 -> 3.5 | F26: =Commitment!G20 -> 4.5 | G26: =Commitment!G21 -> 3.5 | H26: =Commitment!G22 -> 6.5
A27: 21 | B27: Demand-fit plan | C27: =Commitment!G17 -> 5 | D27: =Commitment!G18 -> 5 | E27: =Commitment!G19 -> 3.5 | F27: =Commitment!G20 -> 4.5 | G27: =Commitment!G21 -> 3.5 | H27: =Commitment!G22 -> 6.5
A28: 22 | B28: Demand-fit plan | C28: =Commitment!G17 -> 5 | D28: =Commitment!G18 -> 5 | E28: =Commitment!G19 -> 3.5 | F28: =Commitment!G20 -> 4.5 | G28: =Commitment!G21 -> 3.5 | H28: =Commitment!G22 -> 6.5
A29: 23 | B29: Demand-fit plan | C29: =Commitment!G17 -> 5 | D29: =Commitment!G18 -> 5 | E29: =Commitment!G19 -> 3.5 | F29: =Commitment!G20 -> 4.5 | G29: =Commitment!G21 -> 3.5 | H29: =Commitment!G22 -> 6.5
A30: 24 | B30: Demand-fit plan | C30: =Commitment!G17 -> 5 | D30: =Commitment!G18 -> 5 | E30: =Commitment!G19 -> 3.5 | F30: =Commitment!G20 -> 4.5 | G30: =Commitment!G21 -> 3.5 | H30: =Commitment!G22 -> 6.5
A31: 25 | B31: Demand-fit plan | C31: =Commitment!G17 -> 5 | D31: =Commitment!G18 -> 5 | E31: =Commitment!G19 -> 3.5 | F31: =Commitment!G20 -> 4.5 | G31: =Commitment!G21 -> 3.5 | H31: =Commitment!G22 -> 6.5
A32: 26 | B32: Demand-fit plan | C32: =Commitment!G17 -> 5 | D32: =Commitment!G18 -> 5 | E32: =Commitment!G19 -> 3.5 | F32: =Commitment!G20 -> 4.5 | G32: =Commitment!G21 -> 3.5 | H32: =Commitment!G22 -> 6.5
A33: 27 | B33: Demand-fit plan | C33: =Commitment!G17 -> 5 | D33: =Commitment!G18 -> 5 | E33: =Commitment!G19 -> 3.5 | F33: =Commitment!G20 -> 4.5 | G33: =Commitment!G21 -> 3.5 | H33: =Commitment!G22 -> 6.5
A34: 28 | B34: Demand-fit plan | C34: =Commitment!G17 -> 5 | D34: =Commitment!G18 -> 5 | E34: =Commitment!G19 -> 3.5 | F34: =Commitment!G20 -> 4.5 | G34: =Commitment!G21 -> 3.5 | H34: =Commitment!G22 -> 6.5
A35: 29 | B35: Demand-fit plan | C35: =Commitment!G17 -> 5 | D35: =Commitment!G18 -> 5 | E35: =Commitment!G19 -> 3.5 | F35: =Commitment!G20 -> 4.5 | G35: =Commitment!G21 -> 3.5 | H35: =Commitment!G22 -> 6.5
A36: 30 | B36: Demand-fit plan | C36: =Commitment!G17 -> 5 | D36: =Commitment!G18 -> 5 | E36: =Commitment!G19 -> 3.5 | F36: =Commitment!G20 -> 4.5 | G36: =Commitment!G21 -> 3.5 | H36: =Commitment!G22 -> 6.5
A37: 31 | B37: Demand-fit plan | C37: =Commitment!G17 -> 5 | D37: =Commitment!G18 -> 5 | E37: =Commitment!G19 -> 3.5 | F37: =Commitment!G20 -> 4.5 | G37: =Commitment!G21 -> 3.5 | H37: =Commitment!G22 -> 6.5
A38: Board distribution-point reserve | B38: Pooled residual | C38: =Commitment!I17-SUM(C7:C37) -> 5 | D38: =Commitment!I18-SUM(D7:D37) -> 5 | E38: =Commitment!I19-SUM(E7:E37) -> 11.5 | F38: =Commitment!I20-SUM(F7:F37) -> 4.5 | G38: =Commitment!I21-SUM(G7:G37) -> 3.5 | H38: =Commitment!I22-SUM(H7:H37) -> 8.5
A39: TOTAL COMMITTED | B39: ties to Commitment pooled cases | C39: =SUM(C7:C38) -> 160 | D39: =SUM(D7:D38) -> 160 | E39: =SUM(E7:E38) -> 120 | F39: =SUM(F7:F38) -> 144 | G39: =SUM(G7:G38) -> 112 | H39: =SUM(H7:H38) -> 210
A41: Store rows are planning allocations in whole- or half-case equivalents. The reserve remains at the Board distribution point until release instructions are confirmed; it is not a physical split-case authorization.
